Workbook

Sheet Sheet1
A1: University | B1: University2 | C1: unitid | D1: GeoFips | E1: Season | F1: Total Revenue | G1: Lagged Total Revenue | H1: Winpct | I1: Attendance | J1: Population | K1: PCI | L1: Stadium Capacity
A2: A&M-Corpus Christi | B2: A&M-Corpus Christi | C2: 224147 | D2: 18580 | E2: 2015 | F2: =IFERROR(IF(VLOOKUP(C2,TotalRev1!A:C,3,FALSE)="","",VLOOKUP(C2,TotalRev1!A:C,3,FALSE)),"") -> 577051 | G2: =IFERROR(IF(VLOOKUP(C2,TotalRevL!A:C,3,FALSE)="","",VLOOKUP(C2,TotalRevL!A:C,3,FALSE)),"") -> 561786 | H2: =IFERROR(IFERROR(VLOOKUP($A2,Winpct1!$A:$K,9,FALSE),VLOOKUP($B2,Winpct1!$A:$K,9,FALSE)),"") -> 0.543 | I2: =IFERROR(IFERROR(VLOOKUP($A2,Attendance1!$B:$H,3,FALSE),VLOOKUP($B2,Attendance1!$B:$H,3,FALSE)),"") -> 6833 | J2: =IFERROR(VLOOKUP(D2,'Pop-Metro'!A:R,E2-2005,FALSE),VLOOKUP(D2,'Pop-Micro'!A:R,E2-2005,FALSE)) -> 423451 | K2: =IFERROR(VLOOKUP(D2,'PCI-Metro'!A:R,E2-2005,FALSE),VLOOKUP(D2,'PCI-Micro'!A:R,E2-2005,FALSE)) -> 42801 | L2: =IFERROR(IF(IFERROR(VLOOKUP($A2,Attendance1!$B:$H,5,FALSE),VLOOKUP($B2,Attendance1!$B:$H,5,FALSE))="","",IFERROR(VLOOKUP($A2,Attendance1!$B:$H,5,FALSE),VLOOKUP($B2,Attendance1!$B:$H,5,FALSE))),"") -> 1200
A3: Abilene Christian | B3: Abilene Christian | C3: 222178 | D3: 10180 | E3: =E$2 -> 2015 | F3: =IFERROR(IF(VLOOKUP(C3,TotalRev1!A:C,3,FALSE)="","",VLOOKUP(C3,TotalRev1!A:C,3,FALSE)),"") | G3: =IFERROR(IF(VLOOKUP(C3,TotalRevL!A:C,3,FALSE)="","",VLOOKUP(C3,TotalRevL!A:C,3,FALSE)),"") | H3: =IFERROR(IFERROR(VLOOKUP($A3,Winpct1!$A:$K,9,FALSE),VLOOKUP($B3,Winpct1!$A:$K,9,FALSE)),"") | I3: =IFERROR(IFERROR(VLOOKUP($A3,Attendance1!$B:$H,3,FALSE),VLOOKUP($B3,Attendance1!$B:$H,3,FALSE)),"") -> 3859 | J3: =IFERROR(VLOOKUP(D3,'Pop-Metro'!A:R,E3-2005,FALSE),VLOOKUP(D3,'Pop-Micro'!A:R,E3-2005,FALSE)) -> 171579 | K3: =IFERROR(VLOOKUP(D3,'PCI-Metro'!A:R,E3-2005,FALSE),VLOOKUP(D3,'PCI-Micro'!A:R,E3-2005,FALSE)) -> 39866 | L3: =IFERROR(IF(IFERROR(VLOOKUP($A3,Attendance1!$B:$H,5,FALSE),VLOOKUP($B3,Attendance1!$B:$H,5,FALSE))="","",IFERROR(VLOOKUP($A3,Attendance1!$B:$H,5,FALSE),VLOOKUP($B3,Attendance1!$B:$H,5,FALSE))),"") -> 4600
A4: Air Force | B4: Air Force | C4: 500002 | D4: 17820 | E4: =E$2 -> 2015 | F4: =IFERROR(IF(VLOOKUP(C4,TotalRev1!A:C,3,FALSE)="","",VLOOKUP(C4,TotalRev1!A:C,3,FALSE)),"") | G4: =IFERROR(IF(VLOOKUP(C4,TotalRevL!A:C,3,FALSE)="","",VLOOKUP(C4,TotalRevL!A:C,3,FALSE)),"") | H4: =IFERROR(IFERROR(VLOOKUP($A4,Winpct1!$A:$K,9,FALSE),VLOOKUP($B4,Winpct1!$A:$K,9,FALSE)),"") -> 0.406 | I4: =IFERROR(IFERROR(VLOOKUP($A4,Attendance1!$B:$H,3,FALSE),VLOOKUP($B4,Attendance1!$B:$H,3,FALSE)),"") -> 5422 | J4: =IFERROR(VLOOKUP(D4,'Pop-Metro'!A:R,E4-2005,FALSE),VLOOKUP(D4,'Pop-Micro'!A:R,E4-2005,FALSE)) -> 698671 | K4: =IFERROR(VLOOKUP(D4,'PCI-Metro'!A:R,E4-2005,FALSE),VLOOKUP(D4,'PCI-Micro'!A:R,E4-2005,FALSE)) -> 44235 | L4: =IFERROR(IF(IFERROR(VLOOKUP($A4,Attendance1!$B:$H,5,FALSE),VLOOKUP($B4,Attendance1!$B:$H,5,FALSE))="","",IFERROR(VLOOKUP($A4,Attendance1!$B:$H,5,FALSE),VLOOKUP($B4,Attendance1!$B:$H,5,FALSE))),"") -> 1000
A5: Akron | B5: Akron | C5: 200800 | D5: 10420 | E5: =E$2 -> 2015 | F5: =IFERROR(IF(VLOOKUP(C5,TotalRev1!A:C,3,FALSE)="","",VLOOKUP(C5,TotalRev1!A:C,3,FALSE)),"") -> 38063 | G5: =IFERROR(IF(VLOOKUP(C5,TotalRevL!A:C,3,FALSE)="","",VLOOKUP(C5,TotalRevL!A:C,3,FALSE)),"") -> 41564 | H5: =IFERROR(IFERROR(VLOOKUP($A5,Winpct1!$A:$K,9,FALSE),VLOOKUP($B5,Winpct1!$A:$K,9,FALSE)),"") -> 0.258 | I5: =IFERROR(IFERROR(VLOOKUP($A5,Attendance1!$B:$H,3,FALSE),VLOOKUP($B5,Attendance1!$B:$H,3,FALSE)),"") -> 2889 | J5: =IFERROR(VLOOKUP(D5,'Pop-Metro'!A:R,E5-2005,FALSE),VLOOKUP(D5,'Pop-Micro'!A:R,E5-2005,FALSE)) -> 704664 | K5: =IFERROR(VLOOKUP(D5,'PCI-Metro'!A:R,E5-2005,FALSE),VLOOKUP(D5,'PCI-Micro'!A:R,E5-2005,FALSE)) -> 44674 | L5: =IFERROR(IF(IFERROR(VLOOKUP($A5,Attendance1!$B:$H,5,FALSE),VLOOKUP($B5,Attendance1!$B:$H,5,FALSE))="","",IFERROR(VLOOKUP($A5,Attendance1!$B:$H,5,FALSE),VLOOKUP($B5,Attendance1!$B:$H,5,FALSE))),"") -> 5500
A6: Alabama | B6: Alabama | C6: 100751 | D6: 46220 | E6: =E$2 -> 2015 | F6: =IFERROR(IF(VLOOKUP(C6,TotalRev1!A:C,3,FALSE)="","",VLOOKUP(C6,TotalRev1!A:C,3,FALSE)),"") -> 677222 | G6: =IFERROR(IF(VLOOKUP(C6,TotalRevL!A:C,3,FALSE)="","",VLOOKUP(C6,TotalRevL!A:C,3,FALSE)),"") -> 627654 | H6: =IFERROR(IFERROR(VLOOKUP($A6,Winpct1!$A:$K,9,FALSE),VLOOKUP($B6,Winpct1!$A:$K,9,FALSE)),"") -> 0.765 | I6: =IFERROR(IFERROR(VLOOKUP($A6,Attendance1!$B:$H,3,FALSE),VLOOKUP($B6,Attendance1!$B:$H,3,FALSE)),"") -> 12289 | J6: =IFERROR(VLOOKUP(D6,'Pop-Metro'!A:R,E6-2005,FALSE),VLOOKUP(D6,'Pop-Micro'!A:R,E6-2005,FALSE)) -> 256895 | K6: =IFERROR(VLOOKUP(D6,'PCI-Metro'!A:R,E6-2005,FALSE),VLOOKUP(D6,'PCI-Micro'!A:R,E6-2005,FALSE)) -> 34113 | L6: =IFERROR(IF(IFERROR(VLOOKUP($A6,Attendance1!$B:$H,5,FALSE),VLOOKUP($B6,Attendance1!$B:$H,5,FALSE))="","",IFERROR(VLOOKUP($A6,Attendance1!$B:$H,5,FALSE),VLOOKUP($B6,Attendance1!$B:$H,5,FALSE))),"") -> 3800
A7: Alabama A&M | B7: Alabama A&M | C7: 100654 | D7: 26620 | E7: =E$2 -> 2015 | F7: =IFERROR(IF(VLOOKUP(C7,TotalRev1!A:C,3,FALSE)="","",VLOOKUP(C7,TotalRev1!A:C,3,FALSE)),"") | G7: =IFERROR(IF(VLOOKUP(C7,TotalRevL!A:C,3,FALSE)="","",VLOOKUP(C7,TotalRevL!A:C,3,FALSE)),"") | H7: =IFERROR(IFERROR(VLOOKUP($A7,Winpct1!$A:$K,9,FALSE),VLOOKUP($B7,Winpct1!$A:$K,9,FALSE)),"") -> 0.394 | I7: =IFERROR(IFERROR(VLOOKUP($A7,Attendance1!$B:$H,3,FALSE),VLOOKUP($B7,Attendance1!$B:$H,3,FALSE)),"") -> 1335 | J7: =IFERROR(VLOOKUP(D7,'Pop-Metro'!A:R,E7-2005,FALSE),VLOOKUP(D7,'Pop-Micro'!A:R,E7-2005,FALSE)) -> 450781 | K7: =IFERROR(VLOOKUP(D7,'PCI-Metro'!A:R,E7-2005,FALSE),VLOOKUP(D7,'PCI-Micro'!A:R,E7-2005,FALSE)) -> 44403 | L7: =IFERROR(IF(IFERROR(VLOOKUP($A7,Attendance1!$B:$H,5,FALSE),VLOOKUP($B7,Attendance1!$B:$H,5,FALSE))="","",IFERROR(VLOOKUP($A7,Attendance1!$B:$H,5,FALSE),VLOOKUP($B7,Attendance1!$B:$H,5,FALSE))),"") -> 5500
A8: Alabama St. | B8: Alabama St. | C8: 100724 | D8: 33860 | E8: =E$2 -> 2015 | F8: =IFERROR(IF(VLOOKUP(C8,TotalRev1!A:C,3,FALSE)="","",VLOOKUP(C8,TotalRev1!A:C,3,FALSE)),"") | G8: =IFERROR(IF(VLOOKUP(C8,TotalRevL!A:C,3,FALSE)="","",VLOOKUP(C8,TotalRevL!A:C,3,FALSE)),"") -> 21370 | H8: =IFERROR(IFERROR(VLOOKUP($A8,Winpct1!$A:$K,9,FALSE),VLOOKUP($B8,Winpct1!$A:$K,9,FALSE)),"") -> 0.513 | I8: =IFERROR(IFERROR(VLOOKUP($A8,Attendance1!$B:$H,3,FALSE),VLOOKUP($B8,Attendance1!$B:$H,3,FALSE)),"") -> 3495 | J8: =IFERROR(VLOOKUP(D8,'Pop-Metro'!A:R,E8-2005,FALSE),VLOOKUP(D8,'Pop-Micro'!A:R,E8-2005,FALSE)) -> 380358 | K8: =IFERROR(VLOOKUP(D8,'PCI-Metro'!A:R,E8-2005,FALSE),VLOOKUP(D8,'PCI-Micro'!A:R,E8-2005,FALSE)) -> 38885 | L8: =IFERROR(IF(IFERROR(VLOOKUP($A8,Attendance1!$B:$H,5,FALSE),VLOOKUP($B8,Attendance1!$B:$H,5,FALSE))="","",IFERROR(VLOOKUP($A8,Attendance1!$B:$H,5,FALSE),VLOOKUP($B8,Attendance1!$B:$H,5,FALSE))),"") -> 700
A9: Alcorn | B9: Alcorn | C9: 175342 | D9: 35020 | E9: =E$2 -> 2015 | F9: =IFERROR(IF(VLOOKUP(C9,TotalRev1!A:C,3,FALSE)="","",VLOOKUP(C9,TotalRev1!A:C,3,FALSE)),"") | G9: =IFERROR(IF(VLOOKUP(C9,TotalRevL!A:C,3,FALSE)="","",VLOOKUP(C9,TotalRevL!A:C,3,FALSE)),"") | H9: =IFERROR(IFERROR(VLOOKUP($A9,Winpct1!$A:$K,9,FALSE),VLOOKUP($B9,Winpct1!$A:$K,9,FALSE)),"") -> 0.286 | I9: =IFERROR(IFERROR(VLOOKUP($A9,Attendance1!$B:$H,3,FALSE),VLOOKUP($B9,Attendance1!$B:$H,3,FALSE)),"") -> 1053 | J9: =IFERROR(VLOOKUP(D9,'Pop-Metro'!A:R,E9-2005,FALSE),VLOOKUP(D9,'Pop-Micro'!A:R,E9-2005,FALSE)) -> 51163 | K9: =IFERROR(VLOOKUP(D9,'PCI-Metro'!A:R,E9-2005,FALSE),VLOOKUP(D9,'PCI-Micro'!A:R,E9-2005,FALSE)) -> 31235 | L9: =IFERROR(IF(IFERROR(VLOOKUP($A9,Attendance1!$B:$H,5,FALSE),VLOOKUP($B9,Attendance1!$B:$H,5,FALSE))="","",IFERROR(VLOOKUP($A9,Attendance1!$B:$H,5,FALSE),VLOOKUP($B9,Attendance1!$B:$H,5,FALSE))),"") -> 10000
A10: American | B10: American | C10: 131159 | D10: 47900 | E10: =E$2 -> 2015 | F10: =IFERROR(IF(VLOOKUP(C10,TotalRev1!A:C,3,FALSE)="","",VLOOKUP(C10,TotalRev1!A:C,3,FALSE)),"") | G10: =IFERROR(IF(VLOOKUP(C10,TotalRevL!A:C,3,FALSE)="","",VLOOKUP(C10,TotalRevL!A:C,3,FALSE)),"") | H10: =IFERROR(IFERROR(VLOOKUP($A10,Winpct1!$A:$K,9,FALSE),VLOOKUP($B10,Winpct1!$A:$K,9,FALSE)),"") -> 0.788 | I10: =IFERROR(IFERROR(VLOOKUP($A10,Attendance1!$B:$H,3,FALSE),VLOOKUP($B10,Attendance1!$B:$H,3,FALSE)),"") -> 7923 | J10: =IFERROR(VLOOKUP(D10,'Pop-Metro'!A:R,E10-2005,FALSE),VLOOKUP(D10,'Pop-Micro'!A:R,E10-2005,FALSE)) -> 6131237 | K10: =IFERROR(VLOOKUP(D10,'PCI-Metro'!A:R,E10-2005,FALSE),VLOOKUP(D10,'PCI-Micro'!A:R,E10-2005,FALSE)) -> 64476 | L10: =IFERROR(IF(IFERROR(VLOOKUP($A10,Attendance1!$B:$H,5,FALSE),VLOOKUP($B10,Attendance1!$B:$H,5,FALSE))="","",IFERROR(VLOOKUP($A10,Attendance1!$B:$H,5,FALSE),VLOOKUP($B10,Attendance1!$B:$H,5,FALSE))),"") -> 2000
A11: App State | B11: Appalachian St. | C11: 197869 | D11: 14380 | E11: =E$2 -> 2015 | F11: =IFERROR(IF(VLOOKUP(C11,TotalRev1!A:C,3,FALSE)="","",VLOOKUP(C11,TotalRev1!A:C,3,FALSE)),"") -> 29840 | G11: =IFERROR(IF(VLOOKUP(C11,TotalRevL!A:C,3,FALSE)="","",VLOOKUP(C11,TotalRevL!A:C,3,FALSE)),"") -> 22400 | H11: =IFERROR(IFERROR(VLOOKUP($A11,Winpct1!$A:$K,9,FALSE),VLOOKUP($B11,Winpct1!$A:$K,9,FALSE)),"") -> 0.677 | I11: =IFERROR(IFERROR(VLOOKUP($A11,Attendance1!$B:$H,3,FALSE),VLOOKUP($B11,Attendance1!$B:$H,3,FALSE)),"") -> 5174 | J11: =IFERROR(VLOOKUP(D11,'Pop-Metro'!A:R,E11-2005,FALSE),VLOOKUP(D11,'Pop-Micro'!A:R,E11-2005,FALSE)) -> 51985 | K11: =IFERROR(VLOOKUP(D11,'PCI-Metro'!A:R,E11-2005,FALSE),VLOOKUP(D11,'PCI-Micro'!A:R,E11-2005,FALSE)) -> 33170 | L11: =IFERROR(IF(IFERROR(VLOOKUP($A11,Attendance1!$B:$H,5,FALSE),VLOOKUP($B11,Attendance1!$B:$H,5,FALSE))="","",IFERROR(VLOOKUP($A11,Attendance1!$B:$H,5,FALSE),VLOOKUP($B11,Attendance1!$B:$H,5,FALSE))),"") -> 8325
A12: Arizona | B12: Arizona | C12: 104179 | D12: 46060 | E12: =E$2 -> 2015 | F12: =IFERROR(IF(VLOOKUP(C12,TotalRev1!A:C,3,FALSE)="","",VLOOKUP(C12,TotalRev1!A:C,3,FALSE)),"") -> 485291 | G12: =IFERROR(IF(VLOOKUP(C12,TotalRevL!A:C,3,FALSE)="","",VLOOKUP(C12,TotalRevL!A:C,3,FALSE)),"") -> 451431 | H12: =IFERROR(IFERROR(VLOOKUP($A12,Winpct1!$A:$K,9,FALSE),VLOOKUP($B12,Winpct1!$A:$K,9,FALSE)),"") -> 0.706 | I12: =IFERROR(IFERROR(VLOOKUP($A12,Attendance1!$B:$H,3,FALSE),VLOOKUP($B12,Attendance1!$B:$H,3,FALSE)),"") -> 27266 | J12: =IFERROR(VLOOKUP(D12,'Pop-Metro'!A:R,E12-2005,FALSE),VLOOKUP(D12,'Pop-Micro'!A:R,E12-2005,FALSE)) -> 1001271 | K12: =IFERROR(VLOOKUP(D12,'PCI-Metro'!A:R,E12-2005,FALSE),VLOOKUP(D12,'PCI-Micro'!A:R,E12-2005,FALSE)) -> 38571 | L12: =IFERROR(IF(IFERROR(VLOOKUP($A12,Attendance1!$B:$H,5,FALSE),VLOOKUP($B12,Attendance1!$B:$H,5,FALSE))="","",IFERROR(VLOOKUP($A12,Attendance1!$B:$H,5,FALSE),VLOOKUP($B12,Attendance1!$B:$H,5,FALSE))),"") -> 14545
A13: Arizona St. | B13: Arizona St. | C13: 104151 | D13: 38060 | E13: =E$2 -> 2015 | F13: =IFERROR(IF(VLOOKUP(C13,TotalRev1!A:C,3,FALSE)="","",VLOOKUP(C13,TotalRev1!A:C,3,FALSE)),"") -> 248561 | G13: =IFERROR(IF(VLOOKUP(C13,TotalRevL!A:C,3,FALSE)="","",VLOOKUP(C13,TotalRevL!A:C,3,FALSE)),"") -> 146802 | H13: =IFERROR(IFERROR(VLOOKUP($A13,Winpct1!$A:$K,9,FALSE),VLOOKUP($B13,Winpct1!$A:$K,9,FALSE)),"") -> 0.588 | I13: =IFERROR(IFERROR(VLOOKUP($A13,Attendance1!$B:$H,3,FALSE),VLOOKUP($B13,Attendance1!$B:$H,3,FALSE)),"") -> 22373 | J13: =IFERROR(VLOOKUP(D13,'Pop-Metro'!A:R,E13-2005,FALSE),VLOOKUP(D13,'Pop-Micro'!A:R,E13-2005,FALSE)) -> 4488678 | K13: =IFERROR(VLOOKUP(D13,'PCI-Metro'!A:R,E13-2005,FALSE),VLOOKUP(D13,'PCI-Micro'!A:R,E13-2005,FALSE)) -> 41828 | L13: =IFERROR(IF(IFERROR(VLOOKUP($A13,Attendance1!$B:$H,5,FALSE),VLOOKUP($B13,Attendance1!$B:$H,5,FALSE))="","",IFERROR(VLOOKUP($A13,Attendance1!$B:$H,5,FALSE),VLOOKUP($B13,Attendance1!$B:$H,5,FALSE))),"") -> 10734
A14: Ark.-Pine Bluff | B14: Ark.-Pine Bluff | C14: 106412 | D14: 38220 | E14: =E$2 -> 2015 | F14: =IFERROR(IF(VLOOKUP(C14,TotalRev1!A:C,3,FALSE)="","",VLOOKUP(C14,TotalRev1!A:C,3,FALSE)),"") -> 250 | G14: =IFERROR(IF(VLOOKUP(C14,TotalRevL!A:C,3,FALSE)="","",VLOOKUP(C14,TotalRevL!A:C,3,FALSE)),"") -> 0 | H14: =IFERROR(IFERROR(VLOOKUP($A14,Winpct1!$A:$K,9,FALSE),VLOOKUP($B14,Winpct1!$A:$K,9,FALSE)),"") -> 0.355 | I14: =IFERROR(IFERROR(VLOOKUP($A14,Attendance1!$B:$H,3,FALSE),VLOOKUP($B14,Attendance1!$B:$H,3,FALSE)),"") -> 774 | J14: =IFERROR(VLOOKUP(D14,'Pop-Metro'!A:R,E14-2005,FALSE),VLOOKUP(D14,'Pop-Micro'!A:R,E14-2005,FALSE)) -> 94630 | K14: =IFERROR(VLOOKUP(D14,'PCI-Metro'!A:R,E14-2005,FALSE),VLOOKUP(D14,'PCI-Micro'!A:R,E14-2005,FALSE)) -> 31002 | L14: =IFERROR(IF(IFERROR(VLOOKUP($A14,Attendance1!$B:$H,5,FALSE),VLOOKUP($B14,Attendance1!$B:$H,5,FALSE))="","",IFERROR(VLOOKUP($A14,Attendance1!$B:$H,5,FALSE),VLOOKUP($B14,Attendance1!$B:$H,5,FALSE))),"") -> 4500
... A353: Youngstown St. | B353: Youngstown St. | C353: 206695 | D353: 49660 | E353: =E$2 -> 2015 | F353: =IFERROR(IF(VLOOKUP(C353,TotalRev1!A:C,3,FALSE)="","",VLOOKUP(C353,TotalRev1!A:C,3,FALSE)),"") -> 94975 | G353: =IFERROR(IF(VLOOKUP(C353,TotalRevL!A:C,3,FALSE)="","",VLOOKUP(C353,TotalRevL!A:C,3,FALSE)),"") -> 62487 | H353: =IFERROR(IFERROR(VLOOKUP($A353,Winpct1!$A:$K,9,FALSE),VLOOKUP($B353,Winpct1!$A:$K,9,FALSE)),"") -> 0.548 | I353: =IFERROR(IFERROR(VLOOKUP($A353,Attendance1!$B:$H,3,FALSE),VLOOKUP($B353,Attendance1!$B:$H,3,FALSE)),"") -> 1100 | J353: =IFERROR(VLOOKUP(D353,'Pop-Metro'!A:R,E353-2005,FALSE),VLOOKUP(D353,'Pop-Micro'!A:R,E353-2005,FALSE)) -> 553591 | K353: =IFERROR(VLOOKUP(D353,'PCI-Metro'!A:R,E353-2005,FALSE),VLOOKUP(D353,'PCI-Micro'!A:R,E353-2005,FALSE)) -> 38143 | L353: =IFERROR(IF(IFERROR(VLOOKUP($A353,Attendance1!$B:$H,5,FALSE),VLOOKUP($B353,Attendance1!$B:$H,5,FALSE))="","",IFERROR(VLOOKUP($A353,Attendance1!$B:$H,5,FALSE),VLOOKUP($B353,Attendance1!$B:$H,5,FALSE))),"") -> 6000
A354: A&M-Corpus Christi | B354: A&M-Corpus Christi | C354: 224147 | D354: 18580 | E354: =E353+1 -> 2016 | F354: =IFERROR(IF(VLOOKUP(C354,TotalRev2!A:C,3,FALSE)="","",VLOOKUP(C354,TotalRev2!A:C,3,FALSE)),"") -> 565073 | G354: =IFERROR(IF(VLOOKUP(C354,TotalRev1!A:C,3,FALSE)="","",VLOOKUP(C354,TotalRev1!A:C,3,FALSE)),"") -> 577051 | H354: =IFERROR(IFERROR(VLOOKUP($A354,Winpct2!$A:$K,9,FALSE),VLOOKUP($B354,Winpct2!$A:$K,9,FALSE)),"") -> 0.861 | I354: =IFERROR(IFERROR(VLOOKUP($A354,Attendance2!$B:$H,3,FALSE),VLOOKUP($B354,Attendance2!$B:$H,3,FALSE)),"") -> 9856 | J354: =IFERROR(VLOOKUP(D354,'Pop-Metro'!A:R,E354-2005,FALSE),VLOOKUP(D354,'Pop-Micro'!A:R,E354-2005,FALSE)) -> 423993 | K354: =IFERROR(VLOOKUP(D354,'PCI-Metro'!A:R,E354-2005,FALSE),VLOOKUP(D354,'PCI-Micro'!A:R,E354-2005,FALSE)) -> 40817 | L354: =IFERROR(IF(IFERROR(VLOOKUP($A354,Attendance2!$B:$H,5,FALSE),VLOOKUP($B354,Attendance2!$B:$H,5,FALSE))="","",IFERROR(VLOOKUP($A354,Attendance2!$B:$H,5,FALSE),VLOOKUP($B354,Attendance2!$B:$H,5,FALSE))),"") -> 1200
A355: Abilene Christian | B355: Abilene Christian | C355: 222178 | D355: 10180 | E355: =E354 -> 2016 | F355: =IFERROR(IF(VLOOKUP(C355,TotalRev2!A:C,3,FALSE)="","",VLOOKUP(C355,TotalRev2!A:C,3,FALSE)),"") | G355: =IFERROR(IF(VLOOKUP(C355,TotalRev1!A:C,3,FALSE)="","",VLOOKUP(C355,TotalRev1!A:C,3,FALSE)),"") | H355: =IFERROR(IFERROR(VLOOKUP($A355,Winpct2!$A:$K,9,FALSE),VLOOKUP($B355,Winpct2!$A:$K,9,FALSE)),"") | I355: =IFERROR(IFERROR(VLOOKUP($A355,Ra2W!$A:$K,6,FALSE),VLOOKUP($B355,Ra2W!$A:$K,6,FALSE)),"") -> 2972 | J355: =IFERROR(VLOOKUP(D355,'Pop-Metro'!A:R,E355-2005,FALSE),VLOOKUP(D355,'Pop-Micro'!A:R,E355-2005,FALSE)) -> 172242 | K355: =IFERROR(VLOOKUP(D355,'PCI-Metro'!A:R,E355-2005,FALSE),VLOOKUP(D355,'PCI-Micro'!A:R,E355-2005,FALSE)) -> 39163 | L355: =IFERROR(IF(IFERROR(VLOOKUP($A355,Attendance2!$B:$H,5,FALSE),VLOOKUP($B355,Attendance2!$B:$H,5,FALSE))="","",IFERROR(VLOOKUP($A355,Attendance2!$B:$H,5,FALSE),VLOOKUP($B355,Attendance2!$B:$H,5,FALSE))),"") -> 4600
A356: Air Force | B356: Air Force | C356: 500002 | D356: 17820 | E356: =E355 -> 2016 | F356: =IFERROR(IF(VLOOKUP(C356,TotalRev2!A:C,3,FALSE)="","",VLOOKUP(C356,TotalRev2!A:C,3,FALSE)),"") | G356: =IFERROR(IF(VLOOKUP(C356,TotalRev1!A:C,3,FALSE)="","",VLOOKUP(C356,TotalRev1!A:C,3,FALSE)),"") | H356: =IFERROR(IFERROR(VLOOKUP($A356,Winpct2!$A:$K,9,FALSE),VLOOKUP($B356,Winpct2!$A:$K,9,FALSE)),"") -> 0.364 | I356: =IFERROR(IFERROR(VLOOKUP($A356,Ra2W!$A:$K,6,FALSE),VLOOKUP($B356,Ra2W!$A:$K,6,FALSE)),"") -> 4884 | J356: =IFERROR(VLOOKUP(D356,'Pop-Metro'!A:R,E356-2005,FALSE),VLOOKUP(D356,'Pop-Micro'!A:R,E356-2005,FALSE)) -> 714179 | K356: =IFERROR(VLOOKUP(D356,'PCI-Metro'!A:R,E356-2005,FALSE),VLOOKUP(D356,'PCI-Micro'!A:R,E356-2005,FALSE)) -> 44612 | L356: =IFERROR(IF(IFERROR(VLOOKUP($A356,Attendance2!$B:$H,5,FALSE),VLOOKUP($B356,Attendance2!$B:$H,5,FALSE))="","",IFERROR(VLOOKUP($A356,Attendance2!$B:$H,5,FALSE),VLOOKUP($B356,Attendance2!$B:$H,5,FALSE))),"") -> 1000
A357: Akron | B357: Akron | C357: 200800 | D357: 10420 | E357: =E356 -> 2016 | F357: =IFERROR(IF(VLOOKUP(C357,TotalRev2!A:C,3,FALSE)="","",VLOOKUP(C357,TotalRev2!A:C,3,FALSE)),"") -> 27194 | G357: =IFERROR(IF(VLOOKUP(C357,TotalRev1!A:C,3,FALSE)="","",VLOOKUP(C357,TotalRev1!A:C,3,FALSE)),"") -> 38063 | H357: =IFERROR(IFERROR(VLOOKUP($A357,Winpct2!$A:$K,9,FALSE),VLOOKUP($B357,Winpct2!$A:$K,9,FALSE)),"") -> 0.276 | I357: =IFERROR(IFERROR(VLOOKUP($A357,Ra2W!$A:$K,6,FALSE),VLOOKUP($B357,Ra2W!$A:$K,6,FALSE)),"") -> 4186 | J357: =IFERROR(VLOOKUP(D357,'Pop-Metro'!A:R,E357-2005,FALSE),VLOOKUP(D357,'Pop-Micro'!A:R,E357-2005,FALSE)) -> 703862 | K357: =IFERROR(VLOOKUP(D357,'PCI-Metro'!A:R,E357-2005,FALSE),VLOOKUP(D357,'PCI-Micro'!A:R,E357-2005,FALSE)) -> 45463 | L357: =IFERROR(IF(IFERROR(VLOOKUP($A357,Attendance2!$B:$H,5,FALSE),VLOOKUP($B357,Attendance2!$B:$H,5,FALSE))="","",IFERROR(VLOOKUP($A357,Attendance2!$B:$H,5,FALSE),VLOOKUP($B357,Attendance2!$B:$H,5,FALSE))),"") -> 5500
A358: Alabama | B358: Alabama | C358: 100751 | D358: 46220 | E358: =E357 -> 2016 | F358: =IFERROR(IF(VLOOKUP(C358,TotalRev2!A:C,3,FALSE)="","",VLOOKUP(C358,TotalRev2!A:C,3,FALSE)),"") -> 661383 | G358: =IFERROR(IF(VLOOKUP(C358,TotalRev1!A:C,3,FALSE)="","",VLOOKUP(C358,TotalRev1!A:C,3,FALSE)),"") -> 677222 | H358: =IFERROR(IFERROR(VLOOKUP($A358,Winpct2!$A:$K,9,FALSE),VLOOKUP($B358,Winpct2!$A:$K,9,FALSE)),"") -> 0.531 | I358: =IFERROR(IFERROR(VLOOKUP($A358,Ra2W!$A:$K,6,FALSE),VLOOKUP($B358,Ra2W!$A:$K,6,FALSE)),"") -> 15003 | J358: =IFERROR(VLOOKUP(D358,'Pop-Metro'!A:R,E358-2005,FALSE),VLOOKUP(D358,'Pop-Micro'!A:R,E358-2005,FALSE)) -> 259612 | K358: =IFERROR(VLOOKUP(D358,'PCI-Metro'!A:R,E358-2005,FALSE),VLOOKUP(D358,'PCI-Micro'!A:R,E358-2005,FALSE)) -> 34178 | L358: =IFERROR(IF(IFERROR(VLOOKUP($A358,Attendance2!$B:$H,5,FALSE),VLOOKUP($B358,Attendance2!$B:$H,5,FALSE))="","",IFERROR(VLOOKUP($A358,Attendance2!$B:$H,5,FALSE),VLOOKUP($B358,Attendance2!$B:$H,5,FALSE))),"") -> 3800
A359: Alabama A&M | B359: Alabama A&M | C359: 100654 | D359: 26620 | E359: =E358 -> 2016 | F359: =IFERROR(IF(VLOOKUP(C359,TotalRev2!A:C,3,FALSE)="","",VLOOKUP(C359,TotalRev2!A:C,3,FALSE)),"") | G359: =IFERROR(IF(VLOOKUP(C359,TotalRev1!A:C,3,FALSE)="","",VLOOKUP(C359,TotalRev1!A:C,3,FALSE)),"") | H359: =IFERROR(IFERROR(VLOOKUP($A359,Winpct2!$A:$K,9,FALSE),VLOOKUP($B359,Winpct2!$A:$K,9,FALSE)),"") -> 0.342 | I359: =IFERROR(IFERROR(VLOOKUP($A359,Ra2W!$A:$K,6,FALSE),VLOOKUP($B359,Ra2W!$A:$K,6,FALSE)),"") -> 1360 | J359: =IFERROR(VLOOKUP(D359,'Pop-Metro'!A:R,E359-2005,FALSE),VLOOKUP(D359,'Pop-Micro'!A:R,E359-2005,FALSE)) -> 457090 | K359: =IFERROR(VLOOKUP(D359,'PCI-Metro'!A:R,E359-2005,FALSE),VLOOKUP(D359,'PCI-Micro'!A:R,E359-2005,FALSE)) -> 45464 | L359: =IFERROR(IF(IFERROR(VLOOKUP($A359,Attendance2!$B:$H,5,FALSE),VLOOKUP($B359,Attendance2!$B:$H,5,FALSE))="","",IFERROR(VLOOKUP($A359,Attendance2!$B:$H,5,FALSE),VLOOKUP($B359,Attendance2!$B:$H,5,FALSE))),"") -> 5500
A360: Alabama St. | B360: Alabama St. | C360: 100724 | D360: 33860 | E360: =E359 -> 2016 | F360: =IFERROR(IF(VLOOKUP(C360,TotalRev2!A:C,3,FALSE)="","",VLOOKUP(C360,TotalRev2!A:C,3,FALSE)),"") | G360: =IFERROR(IF(VLOOKUP(C360,TotalRev1!A:C,3,FALSE)="","",VLOOKUP(C360,TotalRev1!A:C,3,FALSE)),"") | H360: =IFERROR(IFERROR(VLOOKUP($A360,Winpct2!$A:$K,9,FALSE),VLOOKUP($B360,Winpct2!$A:$K,9,FALSE)),"") -> 0.583 | I360: =IFERROR(IFERROR(VLOOKUP($A360,Ra2W!$A:$K,6,FALSE),VLOOKUP($B360,Ra2W!$A:$K,6,FALSE)),"") -> 805 | J360: =IFERROR(VLOOKUP(D360,'Pop-Metro'!A:R,E360-2005,FALSE),VLOOKUP(D360,'Pop-Micro'!A:R,E360-2005,FALSE)) -> 382309 | K360: =IFERROR(VLOOKUP(D360,'PCI-Metro'!A:R,E360-2005,FALSE),VLOOKUP(D360,'PCI-Micro'!A:R,E360-2005,FALSE)) -> 39809 | L360: =IFERROR(IF(IFERROR(VLOOKUP($A360,Attendance2!$B:$H,5,FALSE),VLOOKUP($B360,Attendance2!$B:$H,5,FALSE))="","",IFERROR(VLOOKUP($A360,Attendance2!$B:$H,5,FALSE),VLOOKUP($B360,Attendance2!$B:$H,5,FALSE))),"") -> 500
A361: Alcorn | B361: Alcorn | C361: 175342 | D361: 35020 | E361: =E360 -> 2016 | F361: =IFERROR(IF(VLOOKUP(C361,TotalRev2!A:C,3,FALSE)="","",VLOOKUP(C361,TotalRev2!A:C,3,FALSE)),"") | G361: =IFERROR(IF(VLOOKUP(C361,TotalRev1!A:C,3,FALSE)="","",VLOOKUP(C361,TotalRev1!A:C,3,FALSE)),"") | H361: =IFERROR(IFERROR(VLOOKUP($A361,Winpct2!$A:$K,9,FALSE),VLOOKUP($B361,Winpct2!$A:$K,9,FALSE)),"") -> 0.353 | I361: =IFERROR(IFERROR(VLOOKUP($A361,Ra2W!$A:$K,6,FALSE),VLOOKUP($B361,Ra2W!$A:$K,6,FALSE)),"") -> 1077 | J361: =IFERROR(VLOOKUP(D361,'Pop-Metro'!A:R,E361-2005,FALSE),VLOOKUP(D361,'Pop-Micro'!A:R,E361-2005,FALSE)) -> 50811 | K361: =IFERROR(VLOOKUP(D361,'PCI-Metro'!A:R,E361-2005,FALSE),VLOOKUP(D361,'PCI-Micro'!A:R,E361-2005,FALSE)) -> 31281 | L361: =IFERROR(IF(IFERROR(VLOOKUP($A361,Attendance2!$B:$H,5,FALSE),VLOOKUP($B361,Attendance2!$B:$H,5,FALSE))="","",IFERROR(VLOOKUP($A361,Attendance2!$B:$H,5,FALSE),VLOOKUP($B361,Attendance2!$B:$H,5,FALSE))),"") -> 10000
A362: American | B362: American | C362: 131159 | D362: 47900 | E362: =E361 -> 2016 | F362: =IFERROR(IF(VLOOKUP(C362,TotalRev2!A:C,3,FALSE)="","",VLOOKUP(C362,TotalRev2!A:C,3,FALSE)),"") | G362: =IFERROR(IF(VLOOKUP(C362,TotalRev1!A:C,3,FALSE)="","",VLOOKUP(C362,TotalRev1!A:C,3,FALSE)),"") | H362: =IFERROR(IFERROR(VLOOKUP($A362,Winpct2!$A:$K,9,FALSE),VLOOKUP($B362,Winpct2!$A:$K,9,FALSE)),"") -> 0.8 | I362: =IFERROR(IFERROR(VLOOKUP($A362,Ra2W!$A:$K,6,FALSE),VLOOKUP($B362,Ra2W!$A:$K,6,FALSE)),"") -> 6366 | J362: =IFERROR(VLOOKUP(D362,'Pop-Metro'!A:R,E362-2005,FALSE),VLOOKUP(D362,'Pop-Micro'!A:R,E362-2005,FALSE)) -> 6193671 | K362: =IFERROR(VLOOKUP(D362,'PCI-Metro'!A:R,E362-2005,FALSE),VLOOKUP(D362,'PCI-Micro'!A:R,E362-2005,FALSE)) -> 66189 | L362: =IFERROR(IF(IFERROR(VLOOKUP($A362,Attendance2!$B:$H,5,FALSE),VLOOKUP($B362,Attendance2!$B:$H,5,FALSE))="","",IFERROR(VLOOKUP($A362,Attendance2!$B:$H,5,FALSE),VLOOKUP($B362,Attendance2!$B:$H,5,FALSE))),"") -> 2000
A363: Appalachian St. | B363: App State | C363: 197869 | D363: 14380 | E363: =E362 -> 2016 | F363: =IFERROR(IF(VLOOKUP(C363,TotalRev2!A:C,3,FALSE)="","",VLOOKUP(C363,TotalRev2!A:C,3,FALSE)),"") -> 7562 | G363: =IFERROR(IF(VLOOKUP(C363,TotalRev1!A:C,3,FALSE)="","",VLOOKUP(C363,TotalRev1!A:C,3,FALSE)),"") -> 29840 | H363: =IFERROR(IFERROR(VLOOKUP($A363,Winpct2!$A:$K,9,FALSE),VLOOKUP($B363,Winpct2!$A:$K,9,FALSE)),"") -> 0.733 | I363: =IFERROR(IFERROR(VLOOKUP($A363,Ra2W!$A:$K,6,FALSE),VLOOKUP($B363,Ra2W!$A:$K,6,FALSE)),"") -> 5894 | J363: =IFERROR(VLOOKUP(D363,'Pop-Metro'!A:R,E363-2005,FALSE),VLOOKUP(D363,'Pop-Micro'!A:R,E363-2005,FALSE)) -> 52785 | K363: =IFERROR(VLOOKUP(D363,'PCI-Metro'!A:R,E363-2005,FALSE),VLOOKUP(D363,'PCI-Micro'!A:R,E363-2005,FALSE)) -> 34422 | L363: =IFERROR(IF(IFERROR(VLOOKUP($A363,Attendance2!$B:$H,5,FALSE),VLOOKUP($B363,Attendance2!$B:$H,5,FALSE))="","",IFERROR(VLOOKUP($A363,Attendance2!$B:$H,5,FALSE),VLOOKUP($B363,Attendance2!$B:$H,5,FALSE))),"") -> 8325
A364: Arizona | B364: Arizona | C364: 104179 | D364: 46060 | E364: =E363 -> 2016 | F364: =IFERROR(IF(VLOOKUP(C364,TotalRev2!A:C,3,FALSE)="","",VLOOKUP(C364,TotalRev2!A:C,3,FALSE)),"") -> 466246 | G364: =IFERROR(IF(VLOOKUP(C364,TotalRev1!A:C,3,FALSE)="","",VLOOKUP(C364,TotalRev1!A:C,3,FALSE)),"") -> 485291 | H364: =IFERROR(IFERROR(VLOOKUP($A364,Winpct2!$A:$K,9,FALSE),VLOOKUP($B364,Winpct2!$A:$K,9,FALSE)),"") -> 0.576 | I364: =IFERROR(IFERROR(VLOOKUP($A364,Ra2W!$A:$K,6,FALSE),VLOOKUP($B364,Ra2W!$A:$K,6,FALSE)),"") -> 23391 | J364: =IFERROR(VLOOKUP(D364,'Pop-Metro'!A:R,E364-2005,FALSE),VLOOKUP(D364,'Pop-Micro'!A:R,E364-2005,FALSE)) -> 1007258 | K364: =IFERROR(VLOOKUP(D364,'PCI-Metro'!A:R,E364-2005,FALSE),VLOOKUP(D364,'PCI-Micro'!A:R,E364-2005,FALSE)) -> 39723 | L364: =IFERROR(IF(IFERROR(VLOOKUP($A364,Attendance2!$B:$H,5,FALSE),VLOOKUP($B364,Attendance2!$B:$H,5,FALSE))="","",IFERROR(VLOOKUP($A364,Attendance2!$B:$H,5,FALSE),VLOOKUP($B364,Attendance2!$B:$H,5,FALSE))),"") -> 14545
A365: Arizona St. | B365: Arizona St. | C365: 104151 | D365: 38060 | E365: =E364 -> 2016 | F365: =IFERROR(IF(VLOOKUP(C365,TotalRev2!A:C,3,FALSE)="","",VLOOKUP(C365,TotalRev2!A:C,3,FALSE)),"") -> 411288 | G365: =IFERROR(IF(VLOOKUP(C365,TotalRev1!A:C,3,FALSE)="","",VLOOKUP(C365,TotalRev1!A:C,3,FALSE)),"") -> 248561 | H365: =IFERROR(IFERROR(VLOOKUP($A365,Winpct2!$A:$K,9,FALSE),VLOOKUP($B365,Winpct2!$A:$K,9,FALSE)),"") -> 0.594 | I365: =IFERROR(IFERROR(VLOOKUP($A365,Ra2W!$A:$K,6,FALSE),VLOOKUP($B365,Ra2W!$A:$K,6,FALSE)),"") -> 28182 | J365: =IFERROR(VLOOKUP(D365,'Pop-Metro'!A:R,E365-2005,FALSE),VLOOKUP(D365,'Pop-Micro'!A:R,E365-2005,FALSE)) -> 4564173 | K365: =IFERROR(VLOOKUP(D365,'PCI-Metro'!A:R,E365-2005,FALSE),VLOOKUP(D365,'PCI-Micro'!A:R,E365-2005,FALSE)) -> 43196 | L365: =IFERROR(IF(IFERROR(VLOOKUP($A365,Attendance2!$B:$H,5,FALSE),VLOOKUP($B365,Attendance2!$B:$H,5,FALSE))="","",IFERROR(VLOOKUP($A365,Attendance2!$B:$H,5,FALSE),VLOOKUP($B365,Attendance2!$B:$H,5,FALSE))),"") -> 10734
A366: Ark.-Pine Bluff | B366: Ark.-Pine Bluff | C366: 106412 | D366: 38220 | E366: =E365 -> 2016 | F366: =IFERROR(IF(VLOOKUP(C366,TotalRev2!A:C,3,FALSE)="","",VLOOKUP(C366,TotalRev2!A:C,3,FALSE)),"") -> 4000 | G366: =IFERROR(IF(VLOOKUP(C366,TotalRev1!A:C,3,FALSE)="","",VLOOKUP(C366,TotalRev1!A:C,3,FALSE)),"") -> 250 | H366: =IFERROR(IFERROR(VLOOKUP($A366,Winpct2!$A:$K,9,FALSE),VLOOKUP($B366,Winpct2!$A:$K,9,FALSE)),"") -> 0.206 | I366: =IFERROR(IFERROR(VLOOKUP($A366,Ra2W!$A:$K,6,FALSE),VLOOKUP($B366,Ra2W!$A:$K,6,FALSE)),"") -> 902 | J366: =IFERROR(VLOOKUP(D366,'Pop-Metro'!A:R,E366-2005,FALSE),VLOOKUP(D366,'Pop-Micro'!A:R,E366-2005,FALSE)) -> 93144 | K366: =IFERROR(VLOOKUP(D366,'PCI-Metro'!A:R,E366-2005,FALSE),VLOOKUP(D366,'PCI-Micro'!A:R,E366-2005,FALSE)) -> 31376 | L366: =IFERROR(IF(IFERROR(VLOOKUP($A366,Attendance2!$B:$H,5,FALSE),VLOOKUP($B366,Attendance2!$B:$H,5,FALSE))="","",IFERROR(VLOOKUP($A366,Attendance2!$B:$H,5,FALSE),VLOOKUP($B366,Attendance2!$B:$H,5,FALSE))),"") -> 4500
... A705: Youngstown St. | B705: Youngstown St. | C705: 206695 | D705: 49660 | E705: =E704 -> 2016 | F705: =IFERROR(IF(VLOOKUP(C705,TotalRev2!A:C,3,FALSE)="","",VLOOKUP(C705,TotalRev2!A:C,3,FALSE)),"") -> 116847 | G705: =IFERROR(IF(VLOOKUP(C705,TotalRev1!A:C,3,FALSE)="","",VLOOKUP(C705,TotalRev1!A:C,3,FALSE)),"") -> 94975 | H705: =IFERROR(IFERROR(VLOOKUP($A705,Winpct2!$A:$K,9,FALSE),VLOOKUP($B705,Winpct2!$A:$K,9,FALSE)),"") -> 0.323 | I705: =IFERROR(IFERROR(VLOOKUP($A705,Ra2W!$A:$K,6,FALSE),VLOOKUP($B705,Ra2W!$A:$K,6,FALSE)),"") -> 2193 | J705: =IFERROR(VLOOKUP(D705,'Pop-Metro'!A:R,E705-2005,FALSE),VLOOKUP(D705,'Pop-Micro'!A:R,E705-2005,FALSE)) -> 550063 | K705: =IFERROR(VLOOKUP(D705,'PCI-Metro'!A:R,E705-2005,FALSE),VLOOKUP(D705,'PCI-Micro'!A:R,E705-2005,FALSE)) -> 38564 | L705: =IFERROR(IF(IFERROR(VLOOKUP($A705,Attendance2!$B:$H,5,FALSE),VLOOKUP($B705,Attendance2!$B:$H,5,FALSE))="","",IFERROR(VLOOKUP($A705,Attendance2!$B:$H,5,FALSE),VLOOKUP($B705,Attendance2!$B:$H,5,FALSE))),"") -> 6000

Sheet TotalRev1
A1: unitid | B1: University | C1: Total Revenue
A2: 200800 | B2: Akron | C2: 38063
A3: 100751 | B3: Alabama | C3: 677222
A4: 197869 | B4: Appalachian State | C4: 29840
A5: 104179 | B5: Arizona | C5: 485291
A6: 104151 | B6: Arizona State | C6: 248561
A7: 106397 | B7: Arkansas | C7: 26259
A8: 106245 | B8: Arkansas Little Rock | C8: 107642
A9: 106412 | B9: Arkansas Pine Bluff | C9: 250
A10: 106458 | B10: Arkansas State | C10: 381665
A11: 500001 | B11: Army | C11: 352123
A12: 100858 | B12: Auburn | C12: 133233
A13: 219602 | B13: Austin Peay State | C13: 8424
... A27: 199139 | B27: Charlotte | C27: 692855
A28: 144005 | B28: Chicago State
A29: 201885 | B29: Cincinnati | C29: 12143
A30: 217864 | B30: Citadel | C30: 503916
A31: 217882 | B31: Clemson | C31: 686221
A32: 202134 | B32: Cleveland State | C32: 522299
A33: 218724 | B33: Coastal Carolina | C33: 976071
A34: 217819 | B34: College Of Charleston | C34: 37158
A35: 126614 | B35: Colorado | C35: 485792
A36: 126818 | B36: Colorado State | C36: 813329
A37: 129020 | B37: Connecticut | C37: 11691
A38: 162283 | B38: Coppin State | C38: 51700
A39: 198464 | B39: East Carolina | C39: 8980
A40: 144892 | B40: Eastern Illinois | C40: 1177
A41: 156620 | B41: Eastern Kentucky
A42: 169798 | B42: Eastern Michigan | C42: 856585
A43: 235097 | B43: Eastern Washington | C43: 774442
A44: 134130 | B44: Florida | C44: 1476057
A45: 133669 | B45: Florida Atlantic | C45: 499887
A46: 433660 | B46: Florida Gulf Coast | C46: 219598
A47: 133951 | B47: Florida International | C47: 563136
A48: 134097 | B48: Florida State | C48: 912544
A49: 110556 | B49: Fresno State | C49: 725503
A50: 139959 | B50: Georgia | C50: 214103
A51: 139931 | B51: Georgia Southern | C51: 2007
A52: 139940 | B52: Georgia State | C52: 230987
A53: 139755 | B53: Georgia Tech | C53: 200624
A54: 159009 | B54: Grambling State
A55: 141574 | B55: Hawaii | C55: 1471393
A56: 225511 | B56: Houston | C56: 14935
A57: 142285 | B57: Idaho | C57: 801555
A58: 142276 | B58: Idaho State | C58: 343710
A59: 145637 | B59: Illinois | C59: 809829
A60: 145600 | B60: Illinois Chicago | C60: 147328
A61: 145813 | B61: Illinois State | C61: 323431
A62: 151351 | B62: Indiana | C62: 55558
A63: 151324 | B63: Indiana State | C63: 416021
A64: 153658 | B64: Iowa | C64: 262021
A65: 153603 | B65: Iowa State | C65: 236645
A66: 151102 | B66: Purdue Fort Wayne | C66: 457664
... A203: 206695 | B203: Youngstown State | C203: 94975

Sheet TotalRev2
A1: unitid | B1: University | C1: Total Revenue
A2: 200800 | B2: Akron | C2: 27194
A3: 100751 | B3: Alabama | C3: 661383
A4: 196060 | B4: Albany | C4: 155396
A5: 196060 | B5: Albany | C5: 155396
A6: 197869 | B6: Appalachian State | C6: 7562
A7: 104179 | B7: Arizona | C7: 466246
A8: 104151 | B8: Arizona State | C8: 411288
A9: 106397 | B9: Arkansas | C9: 32096
A10: 106245 | B10: Arkansas Little Rock | C10: 125794
A11: 106412 | B11: Arkansas Pine Bluff | C11: 4000
A12: 500001 | B12: Army | C12: 487483
A13: 100858 | B13: Auburn | C13: 110791
... A24: 110635 | B24: California | C24: 279155
A25: 106704 | B25: Central Arkansas
A26: 128771 | B26: Central Connecticut State | C26: 732361
A27: 169248 | B27: Central Michigan | C27: 71421
A28: 199139 | B28: Charlotte | C28: 788033
A29: 144005 | B29: Chicago State | C29: 521869
A30: 201885 | B30: Cincinnati | C30: 16512
A31: 217864 | B31: Citadel | C31: 569305
A32: 217882 | B32: Clemson | C32: 890642
A33: 202134 | B33: Cleveland State | C33: 569633
A34: 218724 | B34: Coastal Carolina | C34: 1010358
A35: 217819 | B35: College Of Charleston | C35: 50244
A36: 126614 | B36: Colorado | C36: 555413
A37: 126818 | B37: Colorado State | C37: 630996
... A41: 144892 | B41: Eastern Illinois | C41: 241533
A42: 156620 | B42: Eastern Kentucky
A43: 169798 | B43: Eastern Michigan | C43: 770664
A44: 235097 | B44: Eastern Washington | C44: 762348
A45: 134130 | B45: Florida
A46: 133669 | B46: Florida Atlantic | C46: 394163
A47: 433660 | B47: Florida Gulf Coast | C47: 268224
A48: 133951 | B48: Florida International | C48: 732177
A49: 134097 | B49: Florida State | C49: 1048495
A50: 110556 | B50: Fresno State | C50: 440254
A51: 139959 | B51: Georgia | C51: 209075
A52: 139931 | B52: Georgia Southern | C52: 63673
A53: 139940 | B53: Georgia State | C53: 216489
A54: 139755 | B54: Georgia Tech | C54: 247615
A55: 159009 | B55: Grambling State | C55: 73111
A56: 141574 | B56: Hawaii | C56: 1572495
A57: 225511 | B57: Houston | C57: 30927
... A68: 151111 | B68: IUPUI | C68: 3149
A69: 175856 | B69: Jackson State
A70: 232423 | B70: James Madison | C70: 42571
A71: 155317 | B71: Kansas | C71: 111745
A72: 155399 | B72: Kansas State | C72: 52116
A73: 486840 | B73: Kennesaw State | C73: 134744
A74: 203517 | B74: Kent State | C74: 88430
A75: 157085 | B75: Kentucky | C75: 329896
A76: 226091 | B76: Lamar | C76: 547824
A77: 110583 | B77: Long Beach State | C77: 806948
A78: 160658 | B78: Louisiana Lafayette | C78: 652023
A79: 159993 | B79: Louisiana Monroe | C79: 30887
A80: 159647 | B80: Louisiana Tech | C80: 669262
A81: 159647 | B81: Louisiana Tech | C81: 669262
... A113: 159966 | B113: Nicholls State | C113: 455776
A114: 185828 | B114: NJIT
A115: 199120 | B115: North Carolina | C115: 683750
A116: 199102 | B116: North Carolina A&T | C116: 371074
A117: 199157 | B117: North Carolina Central | C117: 499
A118: 199148 | B118: North Carolina Greensboro
A119: 199193 | B119: North Carolina State | C119: 661431
A120: 199218 | B120: North Carolina Wilmington | C120: 35932
A121: 200280 | B121: North Dakota | C121: 165967
A122: 200332 | B122: North Dakota State | C122: 370919
A123: 136172 | B123: North Florida | C123: 88129
A124: 227216 | B124: North Texas | C124: 412525
A125: 227216 | B125: North Texas | C125: 412525
A126: 105330 | B126: Northern Arizona | C126: 901547
A127: 127741 | B127: Northern Colorado | C127: 912739
A128: 147703 | B128: Northern Illinois | C128: 148410
A129: 154095 | B129: Northern Iowa | C129: 608344
A130: 160038 | B130: Northwestern State | C130: 415830
... A144: 217484 | B144: Rhode Island | C144: 810403
A145: 186380 | B145: Rutgers
A146: 110617 | B146: Sacramento State | C146: 346976
A147: 227881 | B147: Sam Houston State | C147: 23236
A148: 122409 | B148: San Diego State | C148: 943696
A149: 122409 | B149: San Diego State | C149: 943696
A150: 122755 | B150: San Jose State | C150: 37041
A151: 140960 | B151: Savannah State | C151: 163104
A152: 218663 | B152: South Carolina | C152: 131737
A153: 218663 | B153: South Carolina | C153: 131737
A154: 218742 | B154: South Carolina Upstate | C154: 364530
A155: 219471 | B155: South Dakota | C155: 313427
A156: 219356 | B156: South Dakota State | C156: 14019
A157: 137351 | B157: South Florida | C157: 129889
A158: 179557 | B158: Southeast Missouri State | C158: 285026
A159: 160621 | B159: Southern
A160: 149222 | B160: Southern Illinois | C160: 193491
A161: 149231 | B161: Southern Illinois Edwardsville | C161: 444097
A162: 176372 | B162: Southern Mississippi | C162: 41410
A163: 230603 | B163: Southern Utah | C163: 532910
A164: 228431 | B164: Stephen F. Austin | C164: 543747
A165: 196097 | B165: Stony Brook | C165: 526932
A166: 221759 | B166: Tennessee | C166: 193598
A167: 221740 | B167: Tennessee Chattanooga | C167: 657507
...

Sheet TotalRevL
A1: unitid | B1: University | C1: Total Revenue
A2: 200800 | B2: Akron | C2: 41564
A3: 100751 | B3: Alabama | C3: 627654
A4: 100724 | B4: Alabama State | C4: 21370
A5: 196060 | B5: Albany | C5: 155156
A6: 175342 | B6: Alcorn State
A7: 197869 | B7: Appalachian State | C7: 22400
A8: 104179 | B8: Arizona | C8: 451431
A9: 104151 | B9: Arizona State | C9: 146802
A10: 106397 | B10: Arkansas | C10: 206965
A11: 106245 | B11: Arkansas Little Rock | C11: 62579
A12: 106412 | B12: Arkansas Pine Bluff | C12: 0
A13: 106458 | B13: Arkansas State | C13: 388553
A14: 100858 | B14: Auburn | C14: 4599
A15: 219602 | B15: Austin Peay State | C15: 8217
A16: 150136 | B16: Ball State | C16: 102331
A17: 196079 | B17: Binghamton | C17: 558956
A18: 142115 | B18: Boise State | C18: 412975
... A56: 139755 | B56: Georgia Tech | C56: 286669
A57: 159009 | B57: Grambling State
A58: 141574 | B58: Hawaii | C58: 1579035
A59: 225511 | B59: Houston | C59: 22185
A60: 142285 | B60: Idaho | C60: 517524
A61: 142276 | B61: Idaho State | C61: 319042
A62: 145637 | B62: Illinois | C62: 1338993
A63: 145600 | B63: Illinois Chicago | C63: 428628
A64: 145813 | B64: Illinois State | C64: 347732
A65: 151351 | B65: Indiana | C65: 63573
A66: 151324 | B66: Indiana State | C66: 460106
A67: 153658 | B67: Iowa | C67: 165628
A68: 153603 | B68: Iowa State | C68: 251376
A69: 151111 | B69: IUPUI | C69: 10526
... A208: 206695 | B208: Youngstown State | C208: 62487

Sheet Attendance1
A1: Rank | B1: Institution | C1: Conference | D1: Accum Attendance | E1: Avg Attendance | F1: Stadium Capacity | G1: Pct Capacity | H1: Games
A2: 1 | B2: Nebraska | C2: Big Ten | D2: 145493 | E2: 8083 | F2: 7907 | G2: 102.23 | H2: 18
A3: 2 | B3: Hawaii | C3: Big West | D3: 120776 | E3: 6357 | F3: 10300 | G3: 61.71 | H3: 19
A4: 3 | B4: Wisconsin | C4: Big Ten | D4: 73999 | E4: 4933 | F4: 6000 | G4: 82.22 | H4: 15
A5: 4 | B5: Washington | C5: Pac-12 | D5: 60829 | E5: 3379 | F5: 10000 | G5: 33.79 | H5: 18
A6: 5 | B6: Penn St. | C6: Big Ten | D6: 56977 | E6: 2999 | F6: 5812 | G6: 51.6 | H6: 19
A7: 6 | B7: Colorado St. | C7: Mountain West | D7: 54926 | E7: 3231 | F7: 8745 | G7: 36.95 | H7: 17
A8: 7 | B8: Minnesota | C8: Big Ten | D8: 50149 | E8: 3343 | F8: 5840 | G8: 57.25 | H8: 15
A9: 8 | B9: Illinois | C9: Big Ten | D9: 45410 | E9: 3027 | F9: 4536 | G9: 66.74 | H9: 15
A10: 9 | B10: Michigan St. | C10: Big Ten | D10: 43918 | E10: 2928 | F10: 5017 | G10: 58.36 | H10: 15
A11: 10 | B11: Florida | C11: SEC | D11: 40833 | E11: 2402 | F11: 9777 | G11: 24.57 | H11: 17
A12: 11 | B12: UNI | C12: MVC | D12: 40537 | E12: 3118 | F12: 6650 | G12: 46.89 | H12: 13
A13: 12 | B13: Texas | C13: Big 12 | D13: 40378 | E13: 2884 | F13: 4000 | G13: 72.1 | H13: 14
... A27: 26 | B27: Arizona St. | C27: Pac-12 | D27: 22373 | E27: 1398 | F27: 10734 | G27: 13.03 | H27: 16
A28: 27 | B28: New Mexico | C28: Mountain West | D28: 21085 | E28: 1318 | F28: 0 | G28: Inf | H28: 16
A29: 28 | B29: BYU | C29: WCC | D29: 20649 | E29: 1588 | F29: 5000 | G29: 31.77 | H29: 13
A30: 29 | B30: Duke | C30: ACC | D30: 19943 | E30: 1330 | F30: 9314 | G30: 14.27 | H30: 15
A31: 30 | B31: Texas A&M | C31: SEC | D31: 19635 | E31: 1309 | F31: 12989 | G31: 10.08 | H31: 15
A32: 31 | B32: Kansas | C32: Big 12 | D32: 19283 | E32: 1205 | F32: 1300 | G32: 92.71 | H32: 16
A33: 32 | B33: Creighton | C33: Big East | D33: 19239 | E33: 1283 | F33: 2500 | G33: 51.3 | H33: 15
A34: 33 | B34: Michigan | C34: Big Ten | D34: 19040 | E34: 1269 | F34: 1850 | G34: 68.61 | H34: 15
A35: 34 | B35: South Carolina | C35: SEC | D35: 18581 | E35: 1239 | F35: 1200 | G35: 103.23 | H35: 15
A36: 35 | B36: Colorado | C36: Pac-12 | D36: 18378 | E36: 1149 | F36: 11196 | G36: 10.26 | H36: 16
A37: 36 | B37: Long Beach St. | C37: Big West | D37: 17708 | E37: 1107 | F37: 4200 | G37: 26.35 | H37: 16
A38: 37 | B38: TCU | C38: Big 12 | D38: 16856 | E38: 1054 | F38: 1350 | G38: 78.04 | H38: 16
A39: 38 | B39: Notre Dame | C39: ACC | D39: 16483 | E39: 1099 | F39: 9149 | G39: 12.01 | H39: 15
A40: 39 | B40: Florida St. | C40: ACC | D40: 16268 | E40: 957 | F40: 1162 | G40: 82.35 | H40: 17
... A76: 75 | B76: Morehead St. | C76: OVC | D76: 8974 | E76: 641 | F76: 3500 | G76: 18.31 | H76: 14
A77: 76 | B77: Idaho St. | C77: Big Sky | D77: 8859 | E77: 738 | F77: 0 | G77: Inf | H77: 12
A78: 77 | B78: Washington St. | C78: Pac-12 | D78: 8740 | E78: 672 | F78: 3000 | G78: 22.41 | H78: 13
A79: 78 | B79: West Virginia | C79: Big 12 | D79: 8714 | E79: 581 | F79: 14000 | G79: 4.15 | H79: 15
A80: 79 | B80: Xavier | C80: Big East | D80: 8681 | E80: 543 | F80: 10250 | G80: 5.29 | H80: 16
A81: 80 | B81: Pacific | C81: WCC | D81: 8626 | E81: 719 | F81: 6150 | G81: 11.69 | H81: 12
A82: 81 | B82: SMU | C82: American | D82: 8625 | E82: 539 | F82: 8998 | G82: 5.99 | H82: 16
A83: 82 | B83: Pittsburgh | C83: ACC | D83: 8528 | E83: 533 | F83: 6798 | G83: 7.84 | H83: 16
A84: 83 | B84: Western Mich. | C84: MAC | D84: 8342 | E84: 758 | F84: 5421 | G84: 13.99 | H84: 11
A85: 84 | B85: Ole Miss | C85: SEC | D85: 8289 | E85: 518 | F85: 1000 | G85: 51.81 | H85: 16
A86: 85 | B86: Mississippi St. | C86: SEC | D86: 8112 | E86: 477 | F86: 2000 | G86: 23.86 | H86: 17
A87: 86 | B87: Virginia Tech | C87: ACC | D87: 7954 | E87: 663 | F87: 10052 | G87: 6.59 | H87: 12
A88: 87 | B88: American | C88: Patriot | D88: 7923 | E88: 495 | F88: 2000 | G88: 24.76 | H88: 16
A89: 88 | B89: Missouri St. | C89: MVC | D89: 7804 | E89: 600 | F89: 8846 | G89: 6.79 | H89: 13
... A140: 139 | B140: Gardner-Webb | C140: Big South | D140: 5229 | E140: 475 | F140: 3500 | G140: 13.58 | H140: 11
A141: 140 | B141: Kennesaw St. | C141: ASUN | D141: 5176 | E141: 518 | F141: 0 | G141: Inf | H141: 10
A142: 141 | B142: App State | C142: Sun Belt | D142: 5174 | E142: 323 | F142: 8325 | G142: 3.88 | H142: 16
A143: 142 | B143: CSUN | C143: Big West | D143: 5134 | E143: 642 | F143: 1600 | G143: 40.11 | H143: 8
A144: 143 | B144: Cal St. Fullerton | C144: Big West | D144: 5110 | E144: 365 | F144: 4000 | G144: 9.13 | H144: 14
A145: 144 | B145: Louisiana | C145: Sun Belt | D145: 5060 | E145: 337 | F145: 1121 | G145: 30.09 | H145: 15
A146: 145 | B146: Troy | C146: Sun Belt | D146: 4989 | E146: 356 | F146: 5200 | G146: 6.85 | H146: 14
A147: 146 | B147: Belmont | C147: OVC | D147: 4978 | E147: 356 | F147: 5000 | G147: 7.11 | H147: 14
A148: 147 | B148: Tulsa | C148: American | D148: 4947 | E148: 412 | F148: 26 | G148: 1585.58 | H148: 12
A149: 148 | B149: Tennessee Tech | C149: OVC | D149: 4917 | E149: 615 | F149: 9282 | G149: 6.62 | H149: 8
A150: 149 | B150: IU Indy | C150: Summit League | D150: 4902 | E150: 409 | F150: 0 | G150: Inf | H150: 12
A151: 150 | B151: Milwaukee | C151: Horizon | D151: 4883 | E151: 407 | F151: 2500 | G151: 16.28 | H151: 12
A152: 151 | B152: Central Ark. | C152: Southland | D152: 4821 | E152: 344 | F152: 350 | G152: 98.39 | H152: 14
A153: 152 | B153: Middle Tenn. | C153: CUSA | D153: 4800 | E153: 400 | F153: 2000 | G153: 20 | H153: 12
A154: 153 | B154: San Diego St. | C154: Mountain West | D154: 4794 | E154: 342 | F154: 2500 | G154: 13.7 | H154: 14
A155: 154 | B155: LMU (CA) | C155: WCC | D155: 4708 | E155: 336 | F155: 4156 | G155: 8.09 | H155: 14
A156: 155 | B156: Liberty | C156: Big South | D156: 4678 | E156: 360 | F156: 9443 | G156: 3.81 | H156: 13
A157: 156 | B157: Evansville | C157: MVC | D157: 4666 | E157: 333 | F157: 1000 | G157: 33.33 | H157: 14
A158: 157 | B158: Villanova | C158: Big East | D158: 4660 | E158: 333 | F158: 1500 | G158: 22.19 | H158: 14
A159: 158 | B159: Little Rock | C159: Sun Belt | D159: 4634 | E159: 421 | F159: 0 | G159: Inf | H159: 11
A160: 159 | B160: Southern Ill. | C160: MVC | D160: 4592 | E160: 383 | F160: 1250 | G160: 30.61 | H160: 12
A161: 160 | B161: Radford | C161: Big South | D161: 4538 | E161: 504 | F161: 3215 | G161: 15.68 | H161: 9
A162: 161 | B162: Wofford | C162: SoCon | D162: 4531 | E162: 378 | F162: 3000 | G162: 12.59 | H162: 12
A163: 162 | B163: DePaul | C163: Big East | D163: 4520 | E163: 377 | F163: 3000 | G163: 12.56 | H163: 12
A164: 163 | B164: Northern Ariz. | C164: Big Sky | D164: 4505 | E164: 410 | F164: 1210 | G164: 33.85 | H164: 11
A165: 164 | B165: Yale | C165: Ivy League | D165: 4479 | E165: 407 | F165: 2532 | G165: 16.08 | H165: 11
A166: 165 | B166: Nevada | C166: Mountain West | D166: 4382 | E166: 438 | F166: 1800 | G166: 24.34 | H166: 10
A167: 166 | B167: UT Martin | C167: OVC | D167: 4359 | E167: 335 | F167: 3000 | G167: 11.18 | H167: 13
A168: 167 | B168: Butler | C168: Big East | D168: 4356 | E168: 484 | F168: 10000 | G168: 4.84 | H168: 9
A169: 168 | B169: James Madison | C169: CAA | D169: 4338 | E169: 289 | F169: 5000 | G169: 5.78 | H169: 15
A170: 169 | B170: Davidson | C170: Atlantic 10 | D170: 4320 | E170: 432 | F170: 0 | G170: Inf | H170: 10
A171: 170 | B171: Seton Hall | C171: Big East | D171: 4250 | E171: 250 | F171: 2600 | G171: 9.62 | H171: 17
A172: 171 | B172: Rhode Island | C172: Atlantic 10 | D172: 4161 | E172: 416 | F172: 5000 | G172: 8.32 | H172: 10
A173: 172 | B173: Sam Houston | C173: Southland | D173: 4158 | E173: 347 | F173: 6100 | G173: 5.68 | H173: 12
A174: 173 | B174: Bryant | C174: NEC | D174: 4157 | E174: 297 | F174: 2800 | G174: 10.6 | H174: 14
A175: 174 | B175: North Florida | C175: ASUN | D175: 4119 | E175: 275 | F175: 0 | G175: Inf | H175: 15
A176: 175 | B176: Bradley | C176: MVC | D176: 4115 | E176: 343 | F176: 4200 | G176: 8.16 | H176: 12
A177: 176 | B177: New Orleans | C177: Southland | D177: 4106 | E177: 342 | F177: 10000 | G177: 3.42 | H177: 12
A178: 177 | B178: Harvard | C178: Ivy League | D178: 4101 | E178: 342 | F178: 1000 | G178: 34.18 | H178: 12
A179: 178 | B179: Portland St. | C179: Big Sky | D179: 4082 | E179: 454 | F179: 1500 | G179: 30.24 | H179: 9
A180: 179 | B180: UC Irvine | C180: Big West | D180: 4071 | E180: 339 | F180: 5000 | G180: 6.78 | H180: 12
A181: 180 | B181: VCU | C181: Atlantic 10 | D181: 4024 | E181: 402 | F181: 7500 | G181: 5.37 | H181: 10
A182: 181 | B182: Furman | C182: SoCon | D182: 4004 | E182: 445 | F182: 1000 | G182: 44.49 | H182: 9
A183: 182 | B183: UConn | C183: American | D183: 3997 | E183: 250 | F183: 10241 | G183: 2.44 | H183: 16
A184: 182 | B184: Coastal Carolina | C184: Big South | D184: 3997 | E184: 266 | F184: 3212 | G184: 8.3 | H184: 15
A185: 184 | B185: Kent St. | C185: MAC | D185: 3968 | E185: 331 | F185: 6327 | G185: 5.23 | H185: 12
A186: 185 | B186: Boston College | C186: ACC | D186: 3921 | E186: 327 | F186: 1000 | G186: 32.68 | H186: 12
A187: 186 | B187: Hofstra | C187: CAA | D187: 3887 | E187: 229 | F187: 1200 | G187: 19.05 | H187: 17
... A270: 269 | B270: Louisiana Tech | C270: CUSA | D270: 2314 | E270: 193 | F270: 8000 | G270: 2.41 | H270: 12
A271: 270 | B271: Lehigh | C271: Patriot | D271: 2293 | E271: 191 | F271: 0 | G271: Inf | H271: 12
A272: 271 | B272: Bethune-Cookman | C272: MEAC | D272: 2281 | E272: 253 | F272: 3000 | G272: 8.45 | H272: 9
A273: 272 | B273: Princeton | C273: Ivy League | D273: 2257 | E273: 322 | F273: 1500 | G273: 21.5 | H273: 7
A274: 273 | B274: William & Mary | C274: CAA | D274: 2209 | E274: 221 | F274: 8600 | G274: 2.57 | H274: 10
A275: 274 | B275: Southern U. | C275: SWAC | D275: 2194 | E275: 244 | F275: 800 | G275: 30.47 | H275: 9
A276: 275 | B276: Sacred Heart | C276: NEC | D276: 2181 | E276: 198 | F276: 2100 | G276: 9.44 | H276: 11
A277: 276 | B277: Lamar University | C277: Southland | D277: 2167 | E277: 271 | F277: 500 | G277: 54.18 | H277: 8
A278: 277 | B278: Mississippi Val. | C278: SWAC | D278: 2152 | E278: 269 | F278: 6000 | G278: 4.48 | H278: 8
A279: 278 | B279: Iona | C279: MAAC | D279: 2139 | E279: 165 | F279: 2611 | G279: 6.3 | H279: 13
A280: 279 | B280: Jacksonville | C280: ASUN | D280: 2075 | E280: 148 | F280: 0 | G280: Inf | H280: 14
...

Sheet Attendance2
A1: Rank | B1: Institution | C1: Conference | D1: Accum Attendance | E1: Avg Attendance | F1: Stadium Capacity | G1: Pct Capacity | H1: Games
A2: 1 | B2: Nebraska | C2: Big Ten | D2: 147714 | E2: 8206 | F2: 7907 | G2: 103.79 | H2: 18
A3: 2 | B3: Hawaii | C3: Big West | D3: 131187 | E3: 6905 | F3: 10300 | G3: 67.03 | H3: 19
A4: 3 | B4: Wisconsin | C4: Big Ten | D4: 85774 | E4: 5046 | F4: 6000 | G4: 84.09 | H4: 17
A5: 4 | B5: Penn St. | C5: Big Ten | D5: 66672 | E5: 3922 | F5: 5812 | G5: 67.48 | H5: 17
A6: 5 | B6: Minnesota | C6: Big Ten | D6: 62574 | E6: 4172 | F6: 5840 | G6: 71.43 | H6: 15
A7: 6 | B7: Texas | C7: Big 12 | D7: 56257 | E7: 2813 | F7: 4000 | G7: 70.32 | H7: 20
A8: 7 | B8: Washington | C8: Pac-12 | D8: 44680 | E8: 2628 | F8: 10000 | G8: 26.28 | H8: 17
A9: 8 | B9: Purdue | C9: Big Ten | D9: 40379 | E9: 2524 | F9: 2288 | G9: 110.3 | H9: 16
A10: 9 | B10: Illinois | C10: Big Ten | D10: 39260 | E10: 3020 | F10: 4536 | G10: 66.58 | H10: 13
A11: 10 | B11: Colorado St. | C11: Mountain West | D11: 38584 | E11: 2270 | F11: 8745 | G11: 25.95 | H11: 17
A12: 11 | B12: Michigan St. | C12: Big Ten | D12: 37333 | E12: 2872 | F12: 5017 | G12: 57.24 | H12: 13
A13: 12 | B13: Louisville | C13: ACC | D13: 34334 | E13: 2020 | F13: 950 | G13: 212.59 | H13: 17
... A40: 39 | B40: Long Beach St. | C40: Big West | D40: 17291 | E40: 910 | F40: 4200 | G40: 21.67 | H40: 19
A41: 40 | B41: New Mexico | C41: Mountain West | D41: 16494 | E41: 1100 | F41: 0 | G41: Inf | H41: 15
A42: 41 | B42: Oregon | C42: Pac-12 | D42: 15874 | E42: 1587 | F42: 12541 | G42: 12.66 | H42: 10
A43: 42 | B43: Wyoming | C43: Mountain West | D43: 15500 | E43: 861 | F43: 1200 | G43: 71.76 | H43: 18
A44: 43 | B44: Georgia | C44: SEC | D44: 15472 | E44: 967 | F44: 1925 | G44: 50.23 | H44: 16
A45: 44 | B45: New Mexico St. | C45: WAC | D45: 15299 | E45: 1093 | F45: 13007 | G45: 8.4 | H45: 14
A46: 45 | B46: Alabama | C46: SEC | D46: 15003 | E46: 883 | F46: 3800 | G46: 23.22 | H46: 17
A47: 46 | B47: Arkansas | C47: SEC | D47: 14697 | E47: 980 | F47: 8500 | G47: 11.53 | H47: 15
A48: 47 | B48: Notre Dame | C48: ACC | D48: 14002 | E48: 1077 | F48: 9149 | G48: 11.77 | H48: 13
A49: 48 | B49: Utah | C49: Pac-12 | D49: 13917 | E49: 994 | F49: 15000 | G49: 6.63 | H49: 14
A50: 49 | B50: North Dakota | C50: Big Sky | D50: 13562 | E50: 969 | F50: 3800 | G50: 25.49 | H50: 14
A51: 50 | B51: Florida St. | C51: ACC | D51: 13076 | E51: 1006 | F51: 1250 | G51: 80.47 | H51: 13
A52: 51 | B52: LSU | C52: SEC | D52: 12673 | E52: 1152 | F52: 13215 | G52: 8.72 | H52: 11
A53: 52 | B53: Utah St. | C53: Mountain West | D53: 12569 | E53: 898 | F53: 1400 | G53: 64.13 | H53: 14
... A104: 103 | B104: Montana St. | C104: Big Sky | D104: 7044 | E104: 881 | F104: 2000 | G104: 44.03 | H104: 8
A105: 104 | B105: Kennesaw St. | C105: ASUN | D105: 7023 | E105: 585 | F105: 0 | G105: Inf | H105: 12
A106: 105 | B106: Troy | C106: Sun Belt | D106: 7015 | E106: 468 | F106: 5200 | G106: 8.99 | H106: 15
A107: 106 | B107: East Carolina | C107: American | D107: 6987 | E107: 537 | F107: 8000 | G107: 6.72 | H107: 13
A108: 107 | B108: UNLV | C108: Mountain West | D108: 6870 | E108: 458 | F108: 2500 | G108: 18.32 | H108: 15
A109: 108 | B109: Gardner-Webb | C109: Big South | D109: 6825 | E109: 525 | F109: 3500 | G109: 15 | H109: 13
A110: 109 | B110: High Point | C110: Big South | D110: 6769 | E110: 423 | F110: 1750 | G110: 24.18 | H110: 16
A111: 110 | B111: NIU | C111: MAC | D111: 6704 | E111: 447 | F111: 800 | G111: 55.87 | H111: 15
A112: 111 | B112: Houston Christian | C112: Southland | D112: 6686 | E112: 514 | F112: 1000 | G112: 51.43 | H112: 13
A113: 112 | B113: Liberty | C113: Big South | D113: 6625 | E113: 602 | F113: 9443 | G113: 6.38 | H113: 11
A114: 113 | B114: Arkansas St. | C114: Sun Belt | D114: 6600 | E114: 825 | F114: 10563 | G114: 7.81 | H114: 8
A115: 114 | B115: Sam Houston | C115: Southland | D115: 6589 | E115: 507 | F115: 6100 | G115: 8.31 | H115: 13
A116: 115 | B116: Pittsburgh | C116: ACC | D116: 6528 | E116: 435 | F116: 6798 | G116: 6.4 | H116: 15
A117: 116 | B117: Morehead St. | C117: OVC | D117: 6393 | E117: 492 | F117: 3500 | G117: 14.05 | H117: 13
A118: 117 | B118: Idaho St. | C118: Big Sky | D118: 6392 | E118: 710 | F118: 0 | G118: Inf | H118: 9
A119: 118 | B119: American | C119: Patriot | D119: 6366 | E119: 398 | F119: 2000 | G119: 19.89 | H119: 16
A120: 119 | B120: Valparaiso | C120: Horizon | D120: 6328 | E120: 422 | F120: 5000 | G120: 8.44 | H120: 15
A121: 120 | B121: Oral Roberts | C121: Summit League | D121: 6300 | E121: 630 | F121: 500 | G121: 126 | H121: 10
A122: 121 | B122: New Hampshire | C122: America East | D122: 6282 | E122: 524 | F122: 3500 | G122: 14.96 | H122: 12
A123: 122 | B123: UNCW | C123: CAA | D123: 6239 | E123: 567 | F123: 1000 | G123: 56.72 | H123: 11
A124: 123 | B124: Utah Valley | C124: WAC | D124: 6222 | E124: 778 | F124: 2000 | G124: 38.89 | H124: 8
A125: 123 | B125: SMU | C125: American | D125: 6222 | E125: 389 | F125: 8998 | G125: 4.32 | H125: 16
A126: 125 | B126: Southern Utah | C126: Big Sky | D126: 6165 | E126: 771 | F126: 5300 | G126: 14.54 | H126: 8
A127: 126 | B127: Purdue Fort Wayne | C127: Summit League | D127: 6144 | E127: 512 | F127: 1800 | G127: 28.44 | H127: 12
A128: 127 | B128: George Washington | C128: Atlantic 10 | D128: 6104 | E128: 436 | F128: 4338 | G128: 10.05 | H128: 14
A129: 128 | B129: Texas Tech | C129: Big 12 | D129: 5901 | E129: 422 | F129: 15050 | G129: 2.8 | H129: 14
A130: 129 | B130: App State | C130: Sun Belt | D130: 5894 | E130: 453 | F130: 8325 | G130: 5.45 | H130: 13
... A160: 159 | B160: Omaha | C160: Summit League | D160: 4579 | E160: 382 | F160: 2500 | G160: 15.26 | H160: 12
A161: 160 | B161: North Florida | C161: ASUN | D161: 4517 | E161: 411 | F161: 0 | G161: Inf | H161: 11
A162: 161 | B162: Delaware | C162: CAA | D162: 4498 | E162: 409 | F162: 5000 | G162: 8.18 | H162: 11
A163: 162 | B163: Davidson | C163: Atlantic 10 | D163: 4471 | E163: 406 | F163: 0 | G163: Inf | H163: 11
A164: 163 | B164: San Francisco | C164: WCC | D164: 4462 | E164: 297 | F164: 5300 | G164: 5.61 | H164: 15
A165: 164 | B165: Rice | C165: CUSA | D165: 4455 | E165: 371 | F165: 5750 | G165: 6.46 | H165: 12
A166: 165 | B166: Wright St. | C166: Horizon | D166: 4426 | E166: 277 | F166: 500 | G166: 55.33 | H166: 16
A167: 166 | B167: VCU | C167: Atlantic 10 | D167: 4424 | E167: 442 | F167: 7500 | G167: 5.9 | H167: 10
A168: 167 | B168: Middle Tenn. | C168: CUSA | D168: 4400 | E168: 275 | F168: 2000 | G168: 13.75 | H168: 16
A169: 168 | B169: UNC Asheville | C169: Big South | D169: 4399 | E169: 367 | F169: 1100 | G169: 33.33 | H169: 12
A170: 169 | B170: Central Ark. | C170: Southland | D170: 4299 | E170: 391 | F170: 350 | G170: 111.66 | H170: 11
A171: 170 | B171: Towson | C171: CAA | D171: 4274 | E171: 329 | F171: 5200 | G171: 6.32 | H171: 13
A172: 171 | B172: Nevada | C172: Mountain West | D172: 4268 | E172: 356 | F172: 1800 | G172: 19.76 | H172: 12
A173: 172 | B173: Southern Miss. | C173: CUSA | D173: 4256 | E173: 304 | F173: 8095 | G173: 3.76 | H173: 14
A174: 173 | B174: West Virginia | C174: Big 12 | D174: 4254 | E174: 473 | F174: 14000 | G174: 3.38 | H174: 9
A175: 174 | B175: Marshall | C175: CUSA | D175: 4204 | E175: 467 | F175: 9043 | G175: 5.17 | H175: 9
... A213: 212 | B213: Tennessee Tech | C213: OVC | D213: 3532 | E213: 321 | F213: 9282 | G213: 3.46 | H213: 11
A214: 213 | B214: IU Indy | C214: Summit League | D214: 3499 | E214: 292 | F214: 0 | G214: Inf | H214: 12
A215: 214 | B215: Santa Clara | C215: WCC | D215: 3484 | E215: 290 | F215: 4200 | G215: 6.91 | H215: 12
A216: 215 | B216: South Alabama | C216: Sun Belt | D216: 3480 | E216: 290 | F216: 800 | G216: 36.25 | H216: 12
A217: 216 | B217: UIC | C217: Horizon | D217: 3463 | E217: 266 | F217: 500 | G217: 53.28 | H217: 13
A218: 217 | B218: Green Bay | C218: Horizon | D218: 3447 | E218: 383 | F218: 4018 | G218: 9.53 | H218: 9
A219: 218 | B219: Georgia St. | C219: Sun Belt | D219: 3396 | E219: 283 | F219: 3800 | G219: 7.45 | H219: 12
A220: 219 | B220: Lamar University | C220: Southland | D220: 3380 | E220: 241 | F220: 500 | G220: 48.29 | H220: 14
A221: 220 | B221: Cal St. Fullerton | C221: Big West | D221: 3321 | E221: 302 | F221: 4000 | G221: 7.55 | H221: 11
A222: 221 | B222: Ga. Southern | C222: Sun Belt | D222: 3261 | E222: 233 | F222: 4358 | G222: 5.34 | H222: 14
A223: 222 | B223: Saint Mary's (CA) | C223: WCC | D223: 3249 | E223: 250 | F223: 3500 | G223: 7.14 | H223: 13
A224: 223 | B224: SIUE | C224: OVC | D224: 3240 | E224: 295 | F224: 4000 | G224: 7.36 | H224: 11
A225: 224 | B225: McNeese | C225: Southland | D225: 3224 | E225: 269 | F225: 315 | G225: 85.29 | H225: 12
A226: 225 | B226: William & Mary | C226: CAA | D226: 3218 | E226: 293 | F226: 8600 | G226: 3.4 | H226: 11
... A255: 254 | B255: UC Santa Barbara | C255: Big West | D255: 2599 | E255: 200 | F255: 6000 | G255: 3.33 | H255: 13
A256: 255 | B256: Lehigh | C256: Patriot | D256: 2561 | E256: 197 | F256: 0 | G256: Inf | H256: 13
A257: 256 | B257: George Mason | C257: Atlantic 10 | D257: 2558 | E257: 284 | F257: 1500 | G257: 18.95 | H257: 9
A258: 257 | B258: FIU | C258: CUSA | D258: 2497 | E258: 166 | F258: 5000 | G258: 3.33 | H258: 15
A259: 258 | B259: Bryant | C259: NEC | D259: 2460 | E259: 176 | F259: 2800 | G259: 6.28 | H259: 14
A260: 259 | B260: Buffalo | C260: MAC | D260: 2435 | E260: 304 | F260: 6100 | G260: 4.99 | H260: 8
A261: 260 | B261: Campbell | C261: Big South | D261: 2402 | E261: 218 | F261: 3095 | G261: 7.06 | H261: 11
A262: 261 | B262: Rider | C262: MAAC | D262: 2374 | E262: 264 | F262: 1650 | G262: 15.99 | H262: 9
A263: 262 | B263: Marist | C263: MAAC | D263: 2343 | E263: 180 | F263: 3200 | G263: 5.63 | H263: 13
A264: 263 | B264: Robert Morris | C264: NEC | D264: 2316 | E264: 211 | F264: 3056 | G264: 6.89 | H264: 11
A265: 264 | B265: Manhattan | C265: MAAC | D265: 2310 | E265: 210 | F265: 2500 | G265: 8.4 | H265: 11
A266: 265 | B266: Evansville | C266: MVC | D266: 2300 | E266: 192 | F266: 1000 | G266: 19.17 | H266: 12
A267: 266 | B267: Jacksonville | C267: ASUN | D267: 2288 | E267: 327 | F267: 0 | G267: Inf | H267: 7
A268: 267 | B268: ULM | C268: Sun Belt | D268: 2284 | E268: 228 | F268: 7000 | G268: 3.26 | H268: 10
A269: 268 | B269: Samford | C269: SoCon | D269: 2279 | E269: 253 | F269: 5000 | G269: 5.06 | H269: 9
A270: 269 | B270: Princeton | C270: Ivy League | D270: 2268 | E270: 324 | F270: 1500 | G270: 21.6 | H270: 7
...

Sheet Winpct1
A1: A&M-Corpus Christi | B1: A&M-Corpus Christi | C1: 224147 | D1: 18580 | E1: 2015 | F1: 6833 | G1: 9115 | H1: 13 | I1: 0.543 | J1: 0.625 | K1: 423386
A2: Abilene Christian | B2: Abilene Christian | C2: 222178 | D2: 10180 | E2: 2015 | F2: 3859 | G2: 3992 | H2: 9 | K2: 171666
A3: Air Force | B3: Air Force | C3: 500002 | D3: 17820 | E3: 2015 | F3: 5422 | G3: 6002 | H3: 17 | I3: 0.406 | J3: 0.25 | K3: 698874
A4: Akron | B4: Akron | C4: 200800 | D4: 10420 | E4: 2015 | F4: 2889 | G4: 2933 | H4: 13 | I4: 0.258 | J4: 0.296 | K4: 704604
A5: Alabama | B5: Alabama | C5: 100751 | D5: 46220 | E5: 2015 | F5: 12289 | G5: 12376 | H5: 13 | I5: 0.765 | J5: 0.706 | K5: 257358
A6: Alabama A&M | B6: Alabama A&M | C6: 100654 | D6: 26620 | E6: 2015 | F6: 1335 | G6: 1146 | H6: 9 | I6: 0.394 | J6: 0.344 | K6: 451269
A7: Alabama St. | B7: Alabama St. | C7: 100724 | D7: 33860 | E7: 2015 | F7: 3495 | G7: 1804 | H7: 16 | I7: 0.513 | J7: 0.61 | K7: 380447
A8: Alcorn | B8: Alcorn | C8: 175342 | D8: 35020 | E8: 2015 | F8: 1053 | G8: 612 | H8: 9 | I8: 0.286 | K8: 51163
A9: American | B9: American | C9: 131159 | D9: 47900 | E9: 2015 | F9: 7923 | G9: 5700 | H9: 16 | I9: 0.788 | J9: 0.919 | K9: 6132190
A10: App State | B10: Appalachian St. | C10: 197869 | D10: 14380 | E10: 2015 | F10: 5174 | G10: 4432 | H10: 16 | I10: 0.677 | J10: 0.594 | K10: 51985
A11: Arizona | B11: Arizona | C11: 104179 | D11: 46060 | E11: 2015 | F11: 27266 | G11: 19887 | H11: 18 | I11: 0.706 | J11: 0.618 | K11: 1001320
A12: Arizona St. | B12: Arizona St. | C12: 104151 | D12: 38060 | E12: 2015 | F12: 22373 | G12: 17544 | H12: 16 | I12: 0.588 | J12: 0.576 | K12: 4480231
A13: Ark.-Pine Bluff | B13: Ark.-Pine Bluff | C13: 106412 | D13: 38220 | E13: 2015 | F13: 774 | G13: 911 | H13: 7 | I13: 0.355 | J13: 0.361 | K13: 94570
A14: Arkansas | B14: Arkansas | C14: 106397 | D14: 22220 | E14: 2015 | F14: 15265 | G14: 12395 | H14: 16 | I14: 0.484 | J14: 0.533 | K14: 492646
A15: Arkansas St. | B15: Arkansas St. | C15: 106458 | D15: 27860 | E15: 2015 | F15: 3742 | G15: 4137 | H15: 10 | I15: 0.677 | J15: 0.429 | K15: 127954
A16: Army West Point | B16: Army West Point | C16: 500001 | D16: 35620 | E16: 2015 | F16: 1921 | G16: 3909 | H16: 12 | I16: 0.467 | J16: 0.519 | K16: 19833335
A17: Auburn | B17: Auburn | C17: 100858 | D17: 12220 | E17: 2015 | F17: 11835 | G17: 8694 | H17: 15 | I17: 0.419 | J17: 0.633 | K17: 161247
A18: Austin Peay | B18: Austin Peay | C18: 219602 | D18: 17300 | E18: 2015 | F18: 2860 | G18: 3066 | H18: 9 | I18: 0.424 | J18: 0.371 | K18: 297187
A19: Ball St. | B19: Ball St. | C19: 150136 | D19: 34620 | E19: 2015 | F19: 6403 | G19: 8288 | H19: 11 | I19: 0.567 | J19: 0.75 | K19: 114923
A20: Baylor | B20: Baylor | C20: 223232 | D20: 47380 | E20: 2015 | F20: 9660 | G20: 11470 | H20: 14 | I20: 0.452 | J20: 0.375 | K20: 263235
... A25: Boston College | B25: Boston College | C25: 164924 | D25: 14460 | E25: 2015 | F25: 3921 | G25: 4311 | H25: 12 | I25: 0.379 | J25: 0.281 | K25: 4812849
A26: Boston U. | B26: Boston U. | C26: 164988 | D26: 14380 | E26: 2015 | K26: 51985
A27: Bowling Green | B27: Bowling Green | C27: 201441 | D27: 45780 | E27: 2015 | F27: 7651 | G27: 9115 | H27: 11 | I27: 0.25 | J27: 0.467 | K27: 648620
A28: Bradley | B28: Bradley | C28: 143358 | D28: 37900 | E28: 2015 | F28: 4115 | G28: 5533 | H28: 12 | I28: 0.071 | J28: 0.464 | K28: 415361
A29: Brown | B29: Brown | C29: 217156 | D29: 39300 | E29: 2015 | F29: 1631 | G29: 1343 | H29: 12 | I29: 0.462 | J29: 0.48 | K29: 1641256
A30: Bryant | B30: Bryant | C30: 217165 | D30: 39300 | E30: 2015 | F30: 4157 | G30: 1522 | H30: 14 | I30: 0.353 | J30: 0.242 | K30: 1641256
A31: Bucknell | B31: Bucknell | C31: 211291 | D31: 30260 | E31: 2015 | F31: 1800 | G31: 3480 | H31: 11 | I31: 0.28 | J31: 0.385 | K31: 44700
A32: Buffalo | B32: Buffalo | C32: 196088 | D32: 15380 | E32: 2015 | F32: 3338 | G32: 6145 | H32: 14 | I32: 0.531 | J32: 0.6 | K32: 1154207
A33: Butler | B33: Butler | C33: 150163 | D33: 26900 | E33: 2015 | F33: 4356 | G33: 9951 | H33: 9 | I33: 0.667 | J33: 0.75 | K33: 1999191
A34: BYU | B34: BYU | C34: 230038 | D34: 39340 | E34: 2015 | F34: 20649 | G34: 12157 | H34: 13 | I34: 0.857 | J34: 0.774 | K34: 589961
A35: Cal Poly | B35: Cal Poly | C35: 110422 | D35: 42020 | E35: 2015 | F35: 6217 | G35: 7125 | H35: 13 | I35: 0.346 | J35: 0.414 | K35: 280062
A36: Cal St. Fullerton | B36: Cal St. Fullerton | C36: 110565 | D36: 31080 | E36: 2015 | F36: 5110 | G36: 4558 | H36: 14 | I36: 0.276 | J36: 0.393 | K36: 13258364
A37: California | B37: California | C37: 110635 | D37: 41860 | E37: 2015 | F37: 9197 | G37: 11376 | H37: 13 | I37: 0.333 | J37: 0.581 | K37: 4669540
A38: California Baptist | B38: California Baptist | C38: 110361 | D38: 40140 | E38: 2015 | K38: 4420560
A39: Campbell | B39: Campbell | C39: 198136 | D39: 15820 | E39: 2015 | F39: 5375 | G39: 2949 | H39: 12 | I39: 0.438 | J39: 0.452 | K39: 36763
A40: Canisius | B40: Canisius | C40: 189705 | D40: 15380 | E40: 2015 | F40: 1888 | G40: 4345 | H40: 9 | I40: 0.375 | J40: 0.379 | K40: 1154207
A41: Central Ark. | B41: Central Ark. | C41: 106704 | D41: 30780 | E41: 2015 | F41: 4821 | G41: 4186 | H41: 14 | I41: 0.625 | J41: 0.879 | K41: 732412
A42: Central Conn. St. | B42: Central Conn. St. | C42: 128771 | D42: 25540 | E42: 2015 | F42: 1580 | G42: 1874 | H42: 10 | I42: 0.407 | J42: 0.7 | K42: 1217677
A43: Central Mich. | B43: Central Mich. | C43: 169248 | D43: 34380 | E43: 2015 | F43: 3540 | G43: 4687 | H43: 11 | I43: 0.357 | J43: 0.393 | K43: 68141
A44: Charleston So. | B44: Charleston So. | C44: 217688 | D44: 16700 | E44: 2015 | F44: 3413 | G44: 2364 | H44: 14 | I44: 0.333 | J44: 0.2 | K44: 737259
A45: Charlotte | B45: Charlotte | C45: 199139 | D45: 16740 | E45: 2015 | F45: 6439 | G45: 6581 | H45: 13 | I45: 0.5 | J45: 0.414 | K45: 2442023
A46: Chattanooga | B46: Chattanooga | C46: 221740 | D46: 16860 | E46: 2015 | F46: 2625 | G46: 3900 | H46: 15 | I46: 0.406 | J46: 0.129 | K46: 544285
A47: Chicago St. | B47: Chicago St. | C47: 144005 | D47: 16980 | E47: 2015 | F47: 1988 | G47: 3352 | H47: 19 | I47: 0.2 | J47: 0.065 | K47: 9654044
A48: Cincinnati | B48: Cincinnati | C48: 201885 | D48: 17140 | E48: 2015 | F48: 6470 | G48: 5870 | H48: 15 | I48: 0.469 | J48: 0.094 | K48: 2196029
A49: Clemson | B49: Clemson | C49: 217882 | D49: 42860 | E49: 2015 | F49: 14559 | G49: 14708 | H49: 17 | I49: 0.563 | J49: 0.484 | K49: 75212
A50: Cleveland St. | B50: Cleveland St. | C50: 202134 | D50: 17460 | E50: 2015 | F50: 3266 | G50: 2535 | H50: 11 | I50: 0.5 | J50: 0.552 | K50: 2086587
... A68: DePaul | B68: DePaul | C68: 144740 | D68: 16980 | E68: 2015 | F68: 4520 | G68: 6167 | H68: 12 | I68: 0.1 | J68: 0.533 | K68: 9654044
A69: Detroit Mercy | B69: Detroit Mercy | C69: 169716 | D69: 19820 | E69: 2015 | K69: 4352979
A70: Drake | B70: Drake | C70: 153269 | D70: 19780 | E70: 2015 | F70: 3542 | G70: 3713 | H70: 10 | I70: 0.379 | J70: 0.067 | K70: 661440
A71: Drexel | B71: Drexel | C71: 212054 | D71: 37980 | E71: 2015 | K71: 6130446
A72: Duke | B72: Duke | C72: 198419 | D72: 20500 | E72: 2015 | F72: 19943 | G72: 29723 | H72: 15 | I72: 0.733 | J72: 0.848 | K72: 607517
A73: Duquesne | B73: Duquesne | C73: 212106 | D73: 38300 | E73: 2015 | F73: 1762 | G73: 1632 | H73: 11 | I73: 0.571 | J73: 0.667 | K73: 2379296
A74: East Carolina | B74: East Carolina | C74: 198464 | D74: 24780 | E74: 2015 | F74: 5546 | G74: 3281 | H74: 16 | I74: 0.484 | J74: 0.406 | K74: 169708
A75: Eastern Ill. | B75: Eastern Ill. | C75: 144892 | D75: 16660 | E75: 2015 | F75: 2471 | G75: 3794 | H75: 8 | I75: 0.484 | J75: 0.6 | K75: 61011
A76: Eastern Ky. | B76: Eastern Ky. | C76: 156620 | D76: 40080 | E76: 2015 | F76: 1510 | G76: 1820 | H76: 11 | I76: 0.6 | J76: 0.529 | K76: 102037
A77: Eastern Mich. | B77: Eastern Mich. | C77: 169798 | D77: 11460 | E77: 2015 | F77: 2072 | G77: 2630 | H77: 10 | I77: 0.581 | J77: 0.529 | K77: 366258
A78: Eastern Wash. | B78: Eastern Wash. | C78: 235097 | D78: 44060 | E78: 2015 | F78: 5568 | G78: 5302 | H78: 9 | I78: 0.31 | J78: 0.323 | K78: 539167
A79: Elon | B79: Elon | C79: 198516 | D79: 24660 | E79: 2015 | F79: 1795 | G79: 2402 | H79: 13 | I79: 0.188 | J79: 0.485 | K79: 751915
A80: ETSU | B80: ETSU | C80: 220075 | D80: 27740 | E80: 2015 | F80: 3149 | G80: 3531 | H80: 10 | I80: 0.515 | J80: 0.71 | K80: 201923
A81: Evansville | B81: Evansville | C81: 150534 | D81: 21780 | E81: 2015 | F81: 4666 | G81: 3476 | H81: 14 | I81: 0.267 | J81: 0.31 | K81: 314321
A82: Fairfield | B82: Fairfield | C82: 129242 | D82: 35620 | E82: 2015 | F82: 1672 | G82: 1348 | H82: 9 | I82: 0.613 | J82: 0.594 | K82: 19833335
A83: FDU | B83: Fairleigh Dickinson | C83: 184603 | D83: 35620 | E83: 2015 | F83: 1828 | G83: 1155 | H83: 9 | I83: 0.207 | J83: 0.172 | K83: 19833335
... A102: Grambling | B102: Grambling | C102: 159009 | D102: 33740 | E102: 2015 | F102: 1583 | G102: 1781 | H102: 10 | I102: 0.115 | J102: 0.167 | K102: 209816
A103: Grand Canyon | B103: Grand Canyon | C103: 104717 | D103: 38060 | E103: 2015 | F103: 3779 | G103: 4652 | H103: 13 | K103: 4480231
A104: Green Bay | B104: Green Bay | C104: 240277 | D104: 24580 | E104: 2015 | F104: 3484 | G104: 3825 | H104: 10 | I104: 0.192 | J104: 0.5 | K104: 318318
A105: Hampton | B105: Hampton | C105: 232265 | D105: 47260 | E105: 2015 | F105: 3220 | G105: 2140 | H105: 10 | I105: 0.656 | J105: 0.633 | K105: 1768553
A106: Hartford | B106: Hartford | C106: 129525 | D106: 25540 | E106: 2015 | F106: 1935 | G106: 1413 | H106: 8 | I106: 0.567 | J106: 0.4 | K106: 1217677
A107: Harvard | B107: Harvard | C107: 166027 | D107: 14460 | E107: 2015 | F107: 4101 | G107: 3193 | H107: 12 | I107: 0.792 | J107: 0.609 | K107: 4812849
A108: Hawaii | B108: Hawaii | C108: 141574 | D108: 46520 | E108: 2015 | F108: 120776 | G108: 144235 | H108: 19 | I108: 0.759 | J108: 0.833 | K108: 1017588
A109: High Point | B109: High Point | C109: 198695 | D109: 24660 | E109: 2015 | F109: 6450 | G109: 5384 | H109: 10 | I109: 0.448 | J109: 0.516 | K109: 751915
A110: Hofstra | B110: Hofstra | C110: 191649 | D110: 35620 | E110: 2015 | F110: 3887 | G110: 2290 | H110: 17 | I110: 0.824 | J110: 0.531 | K110: 19833335
A111: Holy Cross | B111: Holy Cross | C111: 166124 | D111: 49340 | E111: 2015 | F111: 1800 | G111: 1639 | H111: 10 | I111: 0.259 | J111: 0.25 | K111: 951907
A112: Houston | B112: Houston | C112: 225511 | D112: 26420 | E112: 2015 | F112: 5973 | G112: 7922 | H112: 16 | I112: 0.438 | J112: 0.545 | K112: 6663204
A113: Houston Christian | B113: Houston Baptist | C113: 225399 | D113: 26420 | E113: 2015 | F113: 5678 | G113: 4889 | H113: 12 | I113: 0.469 | J113: 0.455 | K113: 6663204
A114: Howard | B114: Howard | C114: 131520 | D114: 47900 | E114: 2015 | F114: 939 | G114: 895 | H114: 7 | I114: 0.645 | J114: 0.656 | K114: 6132190
A115: Idaho | B115: Idaho | C115: 142285 | D115: 34140 | E115: 2015 | F115: 7499 | G115: 5157 | H115: 11 | I115: 0.517 | J115: 0.633 | K115: 38271
... A123: Iowa St. | B123: Iowa St. | C123: 153603 | D123: 11180 | E123: 2015 | F123: 34172 | G123: 29703 | H123: 14 | I123: 0.655 | J123: 0.643 | K123: 123658
A124: IUPUI | B124: IUPUI | C124: 151111 | D124: 26900 | E124: 2015 | K124: 1999191
A125: Jackson St. | B125: Jackson St. | C125: 175856 | D125: 27140 | E125: 2015 | F125: 3291 | G125: 2650 | H125: 7 | I125: 0.344 | J125: 0.344 | K125: 598752
A126: Jacksonville | B126: Jacksonville | C126: 134945 | D126: 27260 | E126: 2015 | F126: 2075 | G126: 2542 | H126: 14 | I126: 0.559 | J126: 0.882 | K126: 1457992
A127: Jacksonville St. | B127: Jacksonville St. | C127: 101480 | D127: 11500 | E127: 2015 | F127: 3384 | G127: 1617 | H127: 10 | I127: 0.529 | J127: 0.419 | K127: 116986
A128: James Madison | B128: James Madison | C128: 232423 | D128: 25500 | E128: 2015 | F128: 4338 | G128: 4423 | H128: 15 | I128: 0.548 | J128: 0.464 | K128: 131186
A129: Kansas | B129: Kansas | C129: 155317 | D129: 29940 | E129: 2015 | F129: 19283 | G129: 24733 | H129: 16 | I129: 0.71 | J129: 0.758 | K129: 116291
A130: Kansas City | B130: UMKC | C130: 178402 | D130: 28140 | E130: 2015 | F130: 3796 | G130: 3637 | H130: 9 | I130: 0.8 | J130: 0.517 | K130: 2098230
A131: Kansas St. | B131: Kansas St. | C131: 155399 | D131: 31740 | E131: 2015 | F131: 30759 | G131: 26573 | H131: 13 | I131: 0.71 | J131: 0.621 | K131: 139373
A132: Kennesaw St. | B132: Kennesaw St. | C132: 486840 | D132: 12060 | E132: 2015 | F132: 5176 | G132: 5325 | H132: 10 | I132: 0.345 | J132: 0.433 | K132: 5695668
A133: Kent St. | B133: Kent St. | C133: 203517 | D133: 10420 | E133: 2015 | F133: 3968 | G133: 3972 | H133: 12 | I133: 0.548 | J133: 0.4 | K133: 704604
A134: Kentucky | B134: Kentucky | C134: 157085 | D134: 30460 | E134: 2015 | F134: 30453 | G134: 26806 | H134: 20 | I134: 0.818 | J134: 0.71 | K134: 500115
A135: La Salle | B135: La Salle | C135: 213367 | D135: 37980 | E135: 2015 | F135: 1184 | G135: 1021 | H135: 13 | I135: 0.323 | J135: 0.031 | K135: 6130446
A136: Lafayette | B136: Lafayette | C136: 213385 | D136: 10900 | E136: 2015 | F136: 1710 | G136: 1887 | H136: 13 | I136: 0.214 | J136: 0.407 | K136: 838657
A137: Lamar University | B137: Lamar University | C137: 226091 | D137: 13140 | E137: 2015 | F137: 2167 | G137: 3963 | H137: 8 | I137: 0.179 | J137: 0.3 | K137: 397955
A138: Lehigh | B138: Lehigh | C138: 213543 | D138: 10900 | E138: 2015 | F138: 2293 | H138: 12 | I138: 0.688 | J138: 0.69 | K138: 838657
A139: Liberty | B139: Liberty | C139: 232557 | D139: 31340 | E139: 2015 | F139: 4678 | G139: 5814 | H139: 13 | I139: 0.697 | J139: 0.379 | K139: 258067
A140: Lipscomb | B140: Lipscomb | C140: 219976 | D140: 34980 | E140: 2015 | F140: 3410 | G140: 3959 | H140: 12 | I140: 0.7 | J140: 0.742 | K140: 1824091
A141: Little Rock | B141: Little Rock | C141: 106245 | D141: 30780 | E141: 2015 | F141: 4634 | G141: 2864 | H141: 11 | I141: 0.857 | J141: 0.645 | K141: 732412
A142: LIU | B142: LIU Brooklyn | C142: 192448 | D142: 35620 | E142: 2015 | F142: 2705 | G142: 2112 | H142: 13 | I142: 0.781 | J142: 0.742 | K142: 19833335
A143: LMU (CA) | B143: LMU (CA) | C143: 117946 | D143: 31080 | E143: 2015 | F143: 4708 | G143: 4010 | H143: 14 | I143: 0.742 | J143: 0.5 | K143: 13258364
A144: Long Beach St. | B144: Long Beach St. | C144: 110583 | D144: 31080 | E144: 2015 | F144: 17708 | G144: 18006 | H144: 16 | I144: 0.844 | J144: 0.621 | K144: 13258364
A145: Longwood | B145: Longwood | C145: 232566 | D145: 40060 | E145: 2015 | K145: 1254013
A146: Louisiana | B146: Louisiana | C146: 160658 | D146: 29180 | E146: 2015 | F146: 5060 | G146: 4834 | H146: 15 | I146: 0.606 | J146: 0.576 | K146: 483623
...

Sheet Winpct2
A1: A&M-Corpus Christi | B1: A&M-Corpus Christi | C1: 224147 | D1: 18580 | E1: 2016 | F1: 9856 | G1: 6833 | H1: 14 | I1: 0.861 | J1: 0.543 | K1: 423932
A2: Abilene Christian | B2: Abilene Christian | C2: 222178 | D2: 10180 | E2: 2016 | F2: 2972 | G2: 3859 | H2: 8 | K2: 172344
A3: Air Force | B3: Air Force | C3: 500002 | D3: 17820 | E3: 2016 | F3: 4884 | G3: 5422 | H3: 16 | I3: 0.364 | J3: 0.406 | K3: 714386
A4: Akron | B4: Akron | C4: 200800 | D4: 10420 | E4: 2016 | F4: 4186 | G4: 2889 | H4: 12 | I4: 0.276 | J4: 0.258 | K4: 703787
A5: Alabama | B5: Alabama | C5: 100751 | D5: 46220 | E5: 2016 | F5: 15003 | G5: 12289 | H5: 17 | I5: 0.531 | J5: 0.765 | K5: 260042
A6: Alabama A&M | B6: Alabama A&M | C6: 100654 | D6: 26620 | E6: 2016 | F6: 1360 | G6: 1335 | H6: 7 | I6: 0.342 | J6: 0.394 | K6: 457597
A7: Alabama St. | B7: Alabama St. | C7: 100724 | D7: 33860 | E7: 2016 | F7: 805 | G7: 3495 | H7: 4 | I7: 0.583 | J7: 0.513 | K7: 382383
A8: Alcorn | B8: Alcorn | C8: 175342 | D8: 35020 | E8: 2016 | F8: 1077 | G8: 1053 | H8: 11 | I8: 0.353 | J8: 0.286 | K8: 50811
A9: American | B9: American | C9: 131159 | D9: 47900 | E9: 2016 | F9: 6366 | G9: 7923 | H9: 16 | I9: 0.8 | J9: 0.788 | K9: 6194690
A10: Appalachian St. | B10: App State | C10: 197869 | D10: 14380 | E10: 2016 | F10: 5894 | G10: 5174 | H10: 13 | I10: 0.733 | J10: 0.677 | K10: 52785
A11: Arizona | B11: Arizona | C11: 104179 | D11: 46060 | E11: 2016 | F11: 23391 | G11: 27266 | H11: 16 | I11: 0.576 | J11: 0.706 | K11: 1007353
A12: Arizona St. | B12: Arizona St. | C12: 104151 | D12: 38060 | E12: 2016 | F12: 28182 | G12: 22373 | H12: 15 | I12: 0.594 | J12: 0.588 | K12: 4556103
A13: Ark.-Pine Bluff | B13: Ark.-Pine Bluff | C13: 106412 | D13: 38220 | E13: 2016 | F13: 902 | G13: 774 | H13: 7 | I13: 0.206 | J13: 0.355 | K13: 93091
A14: Arkansas | B14: Arkansas | C14: 106397 | D14: 22220 | E14: 2016 | F14: 14697 | G14: 15265 | H14: 15 | I14: 0.567 | J14: 0.484 | K14: 504921
... A25: Boston College | B25: Boston College | C25: 164924 | D25: 14460 | E25: 2016 | F25: 4847 | G25: 3921 | H25: 14 | I25: 0.375 | J25: 0.379 | K25: 4850147
A26: Boston U. | B26: Boston U. | C26: 164988 | D26: 14380 | E26: 2016 | K26: 52785
A27: Bowling Green | B27: Bowling Green | C27: 201441 | D27: 45780 | E27: 2016 | F27: 5614 | G27: 7651 | H27: 11 | I27: 0.241 | J27: 0.25 | K27: 648677
A28: Bradley | B28: Bradley | C28: 143358 | D28: 37900 | E28: 2016 | F28: 5705 | G28: 4115 | H28: 15 | I28: 0.2 | J28: 0.071 | K28: 413782
A29: Brown | B29: Brown | C29: 217156 | D29: 39300 | E29: 2016 | F29: 1793 | G29: 1631 | H29: 8 | I29: 0.385 | J29: 0.462 | K29: 1648701
A30: Bryant | B30: Bryant | C30: 217165 | D30: 39300 | E30: 2016 | F30: 2460 | G30: 4157 | H30: 14 | I30: 0.576 | J30: 0.353 | K30: 1648701
A31: Bucknell | B31: Bucknell | C31: 211291 | D31: 30260 | E31: 2016 | F31: 1936 | G31: 1800 | H31: 10 | I31: 0.538 | J31: 0.28 | K31: 44489
A32: Buffalo | B32: Buffalo | C32: 196088 | D32: 15380 | E32: 2016 | F32: 2435 | G32: 3338 | H32: 8 | I32: 0.241 | J32: 0.531 | K32: 1155507
A33: Butler | B33: Butler | C33: 150163 | D33: 26900 | E33: 2016 | F33: 7804 | G33: 4356 | H33: 16 | I33: 0.387 | J33: 0.667 | K33: 2022451
A34: BYU | B34: BYU | C34: 230038 | D34: 39340 | E34: 2016 | F34: 26205 | G34: 20649 | H34: 14 | I34: 0.875 | J34: 0.857 | K34: 609431
A35: Cal Poly | B35: Cal Poly | C35: 110422 | D35: 42020 | E35: 2016 | F35: 7218 | G35: 6217 | H35: 10 | I35: 0.704 | J35: 0.346 | K35: 281794
A36: Cal St. Fullerton | B36: Cal St. Fullerton | C36: 110565 | D36: 31080 | E36: 2016 | F36: 3321 | G36: 5110 | H36: 11 | J36: 0.276 | K36: 13297429
A37: California | B37: California | C37: 110635 | D37: 41860 | E37: 2016 | F37: 9642 | G37: 9197 | H37: 15 | I37: 0.29 | J37: 0.333 | K37: 4713476
A38: California Baptist | B38: California Baptist | C38: 110361 | D38: 40140 | E38: 2016 | K38: 4463228
A39: Campbell | B39: Campbell | C39: 198136 | D39: 15820 | E39: 2016 | F39: 2402 | G39: 5375 | H39: 11 | I39: 0.452 | J39: 0.438 | K39: 36677
A40: Canisius | B40: Canisius | C40: 189705 | D40: 15380 | E40: 2016 | F40: 2837 | G40: 1888 | H40: 11 | I40: 0.367 | J40: 0.375 | K40: 1155507
A41: Central Ark. | B41: Central Ark. | C41: 106704 | D41: 30780 | E41: 2016 | F41: 4299 | G41: 4821 | H41: 11 | I41: 0.552 | J41: 0.625 | K41: 735686
A42: Central Conn. St. | B42: Central Conn. St. | C42: 128771 | D42: 25540 | E42: 2016 | F42: 1993 | G42: 1580 | H42: 13 | I42: 0.407 | J42: 0.407 | K42: 1215446
A43: Central Mich. | B43: Central Mich. | C43: 169248 | D43: 34380 | E43: 2016 | F43: 4928 | G43: 3540 | H43: 11 | I43: 0.379 | J43: 0.357 | K43: 68075
A44: Charleston So. | B44: Charleston So. | C44: 217688 | D44: 16700 | E44: 2016 | F44: 2754 | G44: 3413 | H44: 10 | I44: 0.303 | J44: 0.333 | K44: 752067
A45: Charlotte | B45: Charlotte | C45: 199139 | D45: 16740 | E45: 2016 | F45: 7765 | G45: 6439 | H45: 12 | I45: 0.296 | J45: 0.5 | K45: 2492928
A46: Chattanooga | B46: Chattanooga | C46: 221740 | D46: 16860 | E46: 2016 | F46: 4192 | G46: 2625 | H46: 15 | I46: 0.813 | J46: 0.406 | K46: 548385
A47: Chicago St. | B47: Chicago St. | C47: 144005 | D47: 16980 | E47: 2016 | F47: 1026 | G47: 1988 | H47: 8 | I47: 0.036 | J47: 0.2 | K47: 9654839
A48: Cincinnati | B48: Cincinnati | C48: 201885 | D48: 17140 | E48: 2016 | F48: 7538 | G48: 6470 | H48: 15 | I48: 0.677 | J48: 0.469 | K48: 2209105
A49: Clemson | B49: Clemson | C49: 217882 | D49: 42860 | E49: 2016 | F49: 11735 | G49: 14559 | H49: 16 | I49: 0.188 | J49: 0.563 | K49: 75676
A50: Cleveland St. | B50: Cleveland St. | C50: 202134 | D50: 17460 | E50: 2016 | F50: 3924 | G50: 3266 | H50: 13 | I50: 0.788 | J50: 0.5 | K50: 2087581
... A68: DePaul | B68: DePaul | C68: 144740 | D68: 16980 | E68: 2016 | F68: 4031 | G68: 4520 | H68: 13 | I68: 0.516 | J68: 0.1 | K68: 9654839
A69: Detroit Mercy | B69: Detroit Mercy | C69: 169716 | D69: 19820 | E69: 2016 | K69: 4368028
A70: Drake | B70: Drake | C70: 153269 | D70: 19780 | E70: 2016 | F70: 4079 | G70: 3542 | H70: 10 | I70: 0.429 | J70: 0.379 | K70: 673388
A71: Drexel | B71: Drexel | C71: 212054 | D71: 37980 | E71: 2016 | K71: 6153898
A72: Duke | B72: Duke | C72: 198419 | D72: 20500 | E72: 2016 | F72: 18318 | G72: 19943 | H72: 14 | I72: 0.567 | J72: 0.733 | K72: 617871
A73: Duquesne | B73: Duquesne | C73: 212106 | D73: 38300 | E73: 2016 | F73: 1828 | G73: 1762 | H73: 10 | I73: 0.483 | J73: 0.571 | K73: 2377735
A74: East Carolina | B74: East Carolina | C74: 198464 | D74: 24780 | E74: 2016 | F74: 6987 | G74: 5546 | H74: 13 | I74: 0.387 | J74: 0.484 | K74: 169586
A75: Eastern Ill. | B75: Eastern Ill. | C75: 144892 | D75: 16660 | E75: 2016 | F75: 3733 | G75: 2471 | H75: 9 | I75: 0.516 | J75: 0.484 | K75: 60259
A76: Eastern Ky. | B76: Eastern Ky. | C76: 156620 | D76: 40080 | E76: 2016 | F76: 1179 | G76: 1510 | H76: 9 | I76: 0.303 | J76: 0.6 | K76: 103239
A77: Eastern Mich. | B77: Eastern Mich. | C77: 169798 | D77: 11460 | E77: 2016 | F77: 2191 | G77: 2072 | H77: 8 | I77: 0.467 | J77: 0.581 | K77: 370179
A78: Eastern Wash. | B78: Eastern Wash. | C78: 235097 | D78: 44060 | E78: 2016 | F78: 2677 | G78: 5568 | H78: 9 | I78: 0.5 | J78: 0.31 | K78: 549234
A79: Elon | B79: Elon | C79: 198516 | D79: 24660 | E79: 2016 | F79: 2828 | G79: 1795 | H79: 14 | I79: 0.233 | J79: 0.188 | K79: 759364
A80: ETSU | B80: ETSU | C80: 220075 | D80: 27740 | E80: 2016 | F80: 2013 | G80: 3149 | H80: 9 | I80: 0.613 | J80: 0.515 | K80: 203406
A81: Evansville | B81: Evansville | C81: 150534 | D81: 21780 | E81: 2016 | F81: 2300 | G81: 4666 | H81: 12 | I81: 0.25 | J81: 0.267 | K81: 314463
A82: Fairfield | B82: Fairfield | C82: 129242 | D82: 35620 | E82: 2016 | F82: 1781 | G82: 1672 | H82: 13 | I82: 0.677 | J82: 0.613 | K82: 19945132
A83: Fairleigh Dickinson | B83: FDU | C83: 184603 | D83: 35620 | E83: 2016 | F83: 1824 | G83: 1828 | H83: 11 | I83: 0.345 | J83: 0.207 | K83: 19945132
... A102: Grambling | B102: Grambling | C102: 159009 | D102: 33740 | E102: 2016 | F102: 1853 | G102: 1583 | H102: 9 | I102: 0.265 | J102: 0.115 | K102: 210259
A103: Grand Canyon | B103: Grand Canyon | C103: 104717 | D103: 38060 | E103: 2016 | F103: 7814 | G103: 3779 | H103: 15 | K103: 4556103
A104: Green Bay | B104: Green Bay | C104: 240277 | D104: 24580 | E104: 2016 | F104: 3447 | G104: 3484 | H104: 9 | I104: 0.567 | J104: 0.192 | K104: 320537
A105: Hampton | B105: Hampton | C105: 232265 | D105: 47260 | E105: 2016 | F105: 1400 | G105: 3220 | H105: 6 | I105: 0.12 | J105: 0.656 | K105: 1773787
A106: Hartford | B106: Hartford | C106: 129525 | D106: 25540 | E106: 2016 | F106: 3023 | G106: 1935 | H106: 11 | I106: 0.069 | J106: 0.567 | K106: 1215446
A107: Harvard | B107: Harvard | C107: 166027 | D107: 14460 | E107: 2016 | F107: 4011 | G107: 4101 | H107: 15 | I107: 0.577 | J107: 0.792 | K107: 4850147
A108: Hawaii | B108: Hawaii | C108: 141574 | D108: 46520 | E108: 2016 | F108: 131187 | G108: 120776 | H108: 19 | I108: 0.935 | J108: 0.759 | K108: 1023810
A109: High Point | B109: High Point | C109: 198695 | D109: 24660 | E109: 2016 | F109: 6769 | G109: 6450 | H109: 16 | I109: 0.677 | J109: 0.448 | K109: 759364
A110: Hofstra | B110: Hofstra | C110: 191649 | D110: 35620 | E110: 2016 | F110: 2123 | G110: 3887 | H110: 12 | I110: 0.656 | J110: 0.824 | K110: 19945132
A111: Holy Cross | B111: Holy Cross | C111: 166124 | D111: 49340 | E111: 2016 | F111: 962 | G111: 1800 | H111: 8 | I111: 0.241 | J111: 0.259 | K111: 956771
A112: Houston | B112: Houston | C112: 225511 | D112: 26420 | E112: 2016 | F112: 4591 | G112: 5973 | H112: 13 | I112: 0.594 | J112: 0.438 | K112: 6797263
A113: Houston Baptist | B113: Houston Christian | C113: 225399 | D113: 26420 | E113: 2016 | F113: 6686 | G113: 5678 | H113: 13 | I113: 0.5 | J113: 0.469 | K113: 6797263
A114: Howard | B114: Howard | C114: 131520 | D114: 47900 | E114: 2016 | F114: 1222 | G114: 939 | H114: 9 | I114: 0.563 | J114: 0.645 | K114: 6194690
A115: Idaho | B115: Idaho | C115: 142285 | D115: 34140 | E115: 2016 | F115: 4938 | G115: 7499 | H115: 11 | I115: 0.467 | J115: 0.517 | K115: 38448
... A123: Iowa St. | B123: Iowa St. | C123: 153603 | D123: 11180 | E123: 2016 | F123: 34113 | G123: 34172 | H123: 13 | I123: 0.633 | J123: 0.655 | K123: 123978
A124: IUPUI | B124: IUPUI | C124: 151111 | D124: 26900 | E124: 2016 | K124: 2022451
A125: Jackson St. | B125: Jackson St. | C125: 175856 | D125: 27140 | E125: 2016 | F125: 3086 | G125: 3291 | H125: 13 | I125: 0.405 | J125: 0.344 | K125: 600631
A126: Jacksonville | B126: Jacksonville | C126: 134945 | D126: 27260 | E126: 2016 | F126: 2288 | G126: 2075 | H126: 7 | I126: 0.429 | J126: 0.559 | K126: 1492438
A127: Jacksonville St. | B127: Jacksonville St. | C127: 101480 | D127: 11500 | E127: 2016 | F127: 3731 | G127: 3384 | H127: 11 | I127: 0.412 | J127: 0.529 | K127: 116746
A128: James Madison | B128: James Madison | C128: 232423 | D128: 25500 | E128: 2016 | F128: 3694 | G128: 4338 | H128: 16 | I128: 0.733 | J128: 0.548 | K128: 133060
A129: Kansas | B129: Kansas | C129: 155317 | D129: 29940 | E129: 2016 | F129: 22324 | G129: 19283 | H129: 16 | I129: 0.909 | J129: 0.71 | K129: 117526
A130: UMKC | B130: Kansas City | C130: 178402 | D130: 28140 | E130: 2016 | F130: 2893 | G130: 3796 | H130: 12 | I130: 0.536 | J130: 0.8 | K130: 2121656
A131: Kansas St. | B131: Kansas St. | C131: 155399 | D131: 31740 | E131: 2016 | F131: 22362 | G131: 30759 | H131: 11 | I131: 0.586 | J131: 0.71 | K131: 136983
A132: Kennesaw St. | B132: Kennesaw St. | C132: 486840 | D132: 12060 | E132: 2016 | F132: 7023 | G132: 5176 | H132: 12 | I132: 0.679 | J132: 0.345 | K132: 5800308
A133: Kent St. | B133: Kent St. | C133: 203517 | D133: 10420 | E133: 2016 | F133: 4849 | G133: 3968 | H133: 11 | I133: 0.667 | J133: 0.548 | K133: 703787
A134: Kentucky | B134: Kentucky | C134: 157085 | D134: 30460 | E134: 2016 | F134: 24334 | G134: 30453 | H134: 14 | I134: 0.677 | J134: 0.818 | K134: 504058
A135: La Salle | B135: La Salle | C135: 213367 | D135: 37980 | E135: 2016 | F135: 1026 | G135: 1184 | H135: 10 | I135: 0.194 | J135: 0.323 | K135: 6153898
A136: Lafayette | B136: Lafayette | C136: 213385 | D136: 10900 | E136: 2016 | F136: 1851 | G136: 1710 | H136: 15 | I136: 0.407 | J136: 0.214 | K136: 843356
... A144: Long Beach St. | B144: Long Beach St. | C144: 110583 | D144: 31080 | E144: 2016 | F144: 17291 | G144: 17708 | H144: 19 | I144: 0.806 | J144: 0.844 | K144: 13297429
A145: Longwood | B145: Longwood | C145: 232566 | D145: 40060 | E145: 2016 | K145: 1267408
A146: Louisiana | B146: Louisiana | C146: 160658 | D146: 29180 | E146: 2016 | F146: 3785 | G146: 5060 | H146: 12 | I146: 0.207 | J146: 0.606 | K146: 483889
A147: Louisiana Tech | B147: Louisiana Tech | C147: 159647 | D147: 40820 | E147: 2016 | F147: 2747 | G147: 2314 | H147: 12 | I147: 0.333 | J147: 0.3 | K147: 48584
A148: Louisville | B148: Louisville | C148: 157289 | D148: 31140 | E148: 2016 | F148: 34334 | G148: 26352 | H148: 17 | I148: 0.781 | J148: 0.5 | K148: 1263416
A149: Loyola Chicago | B149: Loyola Chicago | C149: 146719 | D149: 16980 | E149: 2016 | F149: 4144 | G149: 2772 | H149: 12 | I149: 0.625 | J149: 0.321 | K149: 9654839
A150: Loyola Maryland | B150: Loyola Maryland | C150: 163046 | D150: 12580 | E150: 2016 | F150: 1894 | G150: 1558 | H150: 10 | I150: 0.194 | J150: 0.069 | K150: 2821292
A151: LSU | B151: LSU | C151: 159391 | D151: 12940 | E151: 2016 | F151: 12673 | G151: 9027 | H151: 11 | I151: 0.31 | J151: 0.69 | K151: 864779
A152: Maine | B152: Maine | C152: 161253 | D152: 12620 | E152: 2016 | K152: 151714
A153: Manhattan | B153: Manhattan | C153: 192703 | D153: 35620 | E153: 2016 | F153: 2310 | G153: 1966 | H153: 11 | I153: 0.588 | J153: 0.618 | K153: 19945132
A154: Marist | B154: Marist | C154: 192819 | D154: 39100 | E154: 2016 | F154: 2343 | G154: 2472 | H154: 13 | I154: 0.677 | J154: 0.806 | K154: 682352
A155: Marquette | B155: Marquette | C155: 239105 | D155: 33340 | E155: 2016 | F155: 7579 | G155: 10487 | H155: 13 | I155: 0.647 | J155: 0.727 | K155: 1574201
A156: Marshall | B156: Marshall | C156: 237525 | D156: 26580 | E156: 2016 | F156: 4204 | G156: 6642 | H156: 9 | I156: 0.533 | J156: 0.5 | K156: 368494
A157: Maryland | B157: Maryland | C157: 163286 | D157: 47900 | E157: 2016 | F157: 20027 | G157: 15387 | H157: 16 | I157: 0.441 | J157: 0.323 | K157: 6194690
A158: Massachusetts | B158: Massachusetts | C158: 166629 | D158: 44140 | E158: 2016 | K158: 701824
A159: McNeese | B159: McNeese | C159: 159717 | D159: 29340 | E159: 2016 | F159: 3224 | G159: 2825 | H159: 12 | I159: 0.455 | J159: 0.469 | K159: 215028
...

Sheet Pop-Metro
A1: GeoFips | B1: GeoName | C1: LineCode | D1: Description | E1: 2010 | F1: 2011 | G1: 2012 | H1: 2013 | I1: 2014 | J1: 2015 | K1: 2016 | L1: 2017 | M1: 2018 | N1: 2019 | O1: 2020 | P1: 2021 | Q1: 2022 | R1: 2023
A2: 998 | B2: United States (Metropolitan Portion) | C2: 2 | D2: Population (persons) 1 | E2: 263718787 | F2: 266205658 | G2: 268779366 | H2: 271230523 | I2: 273817755 | J2: 276425937 | K2: 278995907 | L2: 281262885 | M2: 283180665 | N2: 284873351 | O2: 286193652 | P2: 286656077 | Q2: 287835880 | R2: 289370890
A3: 10180 | B3: Abilene, TX (Metropolitan Statistical Area) | C3: 2 | D3: Population (persons) 1 | E3: 165673 | F3: 167069 | G3: 168246 | H3: 168614 | I3: 169859 | J3: 171579 | K3: 172242 | L3: 172915 | M3: 174005 | N3: 175187 | O3: 176883 | P3: 177831 | Q3: 179665 | R3: 181591
A4: 10420 | B4: Akron, OH (Metropolitan Statistical Area) | C4: 2 | D4: Population (persons) 1 | E4: 703057 | F4: 703272 | G4: 702245 | H4: 703809 | I4: 705134 | J4: 704664 | K4: 703862 | L4: 704229 | M4: 703925 | N4: 703361 | O4: 701674 | P4: 696512 | Q4: 697511 | R4: 698398
A5: 10500 | B5: Albany, GA (Metropolitan Statistical Area) | C5: 2 | D5: Population (persons) 1 | E5: 154227 | F5: 154933 | G5: 154669 | H5: 153680 | I5: 153263 | J5: 152018 | K5: 151044 | L5: 150387 | M5: 150440 | N5: 149530 | O5: 148249 | P5: 144933 | Q5: 145796 | R5: 145508
A6: 10540 | B6: Albany-Lebanon, OR (Metropolitan Statistical Area) | C6: 2 | D6: Population (persons) 1 | E6: 116840 | F6: 117938 | G6: 117865 | H6: 117822 | I6: 118285 | J6: 119295 | K6: 121648 | L6: 123657 | M6: 125788 | N6: 127700 | O6: 128981 | P6: 130120 | Q6: 130622 | R6: 131496
A7: 10580 | B7: Albany-Schenectady-Troy, NY (Metropolitan Statistical Area) | C7: 2 | D7: Population (persons) 1 | E7: 871603 | F7: 875387 | G7: 879397 | H7: 883854 | I7: 886981 | J7: 889918 | K7: 892762 | L7: 897172 | M7: 899605 | N7: 898791 | O7: 899724 | P7: 904824 | Q7: 903595 | R7: 904682
A8: 10740 | B8: Albuquerque, NM (Metropolitan Statistical Area) * | C8: 2 | D8: Population (persons) 1 | E8: 889434 | F8: 897378 | G8: 900747 | H8: 903185 | I8: 902178 | J8: 903085 | K8: 905774 | L8: 908217 | M8: 910284 | N8: 913231 | O8: 917579 | P8: 919392 | Q8: 920138 | R8: 922296
A9: 10780 | B9: Alexandria, LA (Metropolitan Statistical Area) | C9: 2 | D9: Population (persons) 1 | E9: 154112 | F9: 154538 | G9: 154643 | H9: 154972 | I9: 155021 | J9: 154658 | K9: 154763 | L9: 154292 | M9: 153614 | N9: 153019 | O9: 151800 | P9: 150882 | Q9: 149068 | R9: 148171
A10: 10900 | B10: Allentown-Bethlehem-Easton, PA-NJ (Metropolitan Statistical Area) | C10: 2 | D10: Population (persons) 1 | E10: 822144 | F10: 826750 | G10: 829566 | H10: 830735 | I10: 835077 | J10: 838490 | K10: 843181 | L10: 849703 | M10: 855983 | N10: 858656 | O10: 861557 | P10: 870135 | Q10: 870570 | R10: 873555
A11: 11020 | B11: Altoona, PA (Metropolitan Statistical Area) | C11: 2 | D11: Population (persons) 1 | E11: 127089 | F11: 127192 | G11: 126931 | H11: 126389 | I11: 125986 | J11: 125469 | K11: 124764 | L11: 124310 | M11: 123854 | N11: 123376 | O11: 122666 | P11: 122150 | Q11: 120734 | R11: 120273
A12: 11100 | B12: Amarillo, TX (Metropolitan Statistical Area) | C12: 2 | D12: Population (persons) 1 | E12: 252739 | F12: 256366 | G12: 258511 | H12: 259908 | I12: 262135 | J12: 263232 | K12: 264785 | L12: 266308 | M12: 266497 | N12: 267174 | O12: 269029 | P12: 269804 | Q12: 270589 | R12: 272395
A13: 11180 | B13: Ames, IA (Metropolitan Statistical Area) | C13: 2 | D13: Population (persons) 1 | E13: 115952 | F13: 117552 | G13: 118366 | H13: 120499 | I13: 122552 | J13: 123653 | K13: 123972 | L13: 124446 | M13: 123798 | N13: 124556 | O13: 125347 | P13: 126440 | Q13: 124836 | R13: 125156
... A386: 49740 | B386: Yuma, AZ (Metropolitan Statistical Area) * | C386: 2 | D386: Population (persons) 1 | E386: 196839 | F386: 201291 | G386: 199666 | H386: 198339 | I386: 198670 | J386: 198510 | K386: 199165 | L386: 199915 | M386: 200572 | N386: 202099 | O386: 205659 | P386: 207284 | Q386: 208874 | R386: 213221

Sheet Pop-Micro
A1: GeoFips | B1: GeoName | C1: LineCode | D1: Description | E1: 2010 | F1: 2011 | G1: 2012 | H1: 2013 | I1: 2014 | J1: 2015 | K1: 2016 | L1: 2017 | M1: 2018 | N1: 2019 | O1: 2020 | P1: 2021 | Q1: 2022 | R1: 2023
A2: 10100 | B2: Aberdeen, SD (Micropolitan Statistical Area) | C2: 2 | D2: Population (persons) 1 | E2: 40715 | F2: 40940 | G2: 41526 | H2: 42080 | I2: 42123 | J2: 42275 | K2: 42626 | L2: 43011 | M2: 42686 | N2: 42436 | O2: 42213 | P2: 42151 | Q2: 41972 | R2: 41790
A3: 10140 | B3: Aberdeen, WA (Micropolitan Statistical Area) | C3: 2 | D3: Population (persons) 1 | E3: 72847 | F3: 72361 | G3: 71761 | H3: 71025 | I3: 70751 | J3: 70971 | K3: 71489 | L3: 72430 | M3: 73697 | N3: 74944 | O3: 75855 | P3: 76838 | Q3: 77041 | R3: 77290
A4: 10220 | B4: Ada, OK (Micropolitan Statistical Area) | C4: 2 | D4: Population (persons) 1 | E4: 37587 | F4: 37718 | G4: 38001 | H4: 38070 | I4: 38169 | J4: 38188 | K4: 38311 | L4: 38130 | M4: 38077 | N4: 38067 | O4: 38095 | P4: 38184 | Q4: 38032 | R4: 38396
A5: 10300 | B5: Adrian, MI (Micropolitan Statistical Area) | C5: 2 | D5: Population (persons) 1 | E5: 99678 | F5: 99545 | G5: 99356 | H5: 99304 | I5: 99368 | J5: 99164 | K5: 99470 | L5: 99526 | M5: 99268 | N5: 99816 | O5: 99325 | P5: 99100 | Q5: 98280 | R5: 97520
A6: 10460 | B6: Alamogordo, NM (Micropolitan Statistical Area) | C6: 2 | D6: Population (persons) 1 | E6: 64404 | F6: 65650 | G6: 66223 | H6: 66321 | I6: 65359 | J6: 64792 | K6: 65669 | L6: 66097 | M6: 66528 | N6: 67489 | O6: 67862 | P6: 68486 | Q6: 68517 | R6: 68835
A7: 10620 | B7: Albemarle, NC (Micropolitan Statistical Area) | C7: 2 | D7: Population (persons) 1 | E7: 60564 | F7: 60464 | G7: 60341 | H7: 60455 | I7: 60383 | J7: 60326 | K7: 60467 | L7: 61028 | M7: 61578 | N7: 62073 | O7: 62642 | P7: 63100 | Q7: 64231 | R7: 65699
A8: 10660 | B8: Albert Lea, MN (Micropolitan Statistical Area) | C8: 2 | D8: Population (persons) 1 | E8: 31216 | F8: 31135 | G8: 31144 | H8: 31095 | I8: 30964 | J8: 30791 | K8: 30764 | L8: 30961 | M8: 30981 | N8: 30863 | O8: 30896 | P8: 30803 | Q8: 30683 | R8: 30515
A9: 10700 | B9: Albertville, AL (Micropolitan Statistical Area) | C9: 2 | D9: Population (persons) 1 | E9: 93136 | F9: 93984 | G9: 94416 | H9: 94575 | I9: 94544 | J9: 94935 | K9: 95535 | L9: 96066 | M9: 96774 | N9: 97362 | O9: 97702 | P9: 98286 | Q9: 99428 | R9: 100756
A10: 10760 | B10: Alexander City, AL (Micropolitan Statistical Area) | C10: 2 | D10: Population (persons) 1 | E10: 53280 | F10: 53004 | G10: 52595 | H10: 52568 | I10: 52297 | J10: 52007 | K10: 51950 | L10: 51964 | M10: 51870 | N10: 51794 | O10: 51619 | P10: 51413 | Q10: 51220 | R10: 50945
A11: 10820 | B11: Alexandria, MN (Micropolitan Statistical Area) | C11: 2 | D11: Population (persons) 1 | E11: 36007 | F11: 36273 | G11: 36455 | H11: 36578 | I11: 36880 | J11: 37170 | K11: 37612 | L11: 38076 | M11: 38596 | N11: 38755 | O11: 39087 | P11: 39298 | Q11: 39684 | R11: 39953
A12: 10860 | B12: Alice, TX (Micropolitan Statistical Area) | C12: 2 | D12: Population (persons) 1 | E12: 52544 | F12: 52646 | G12: 52562 | H12: 52298 | I12: 51753 | J12: 51312 | K12: 50789 | L12: 50097 | M12: 49564 | N12: 49083 | O12: 48689 | P12: 48891 | Q12: 48435 | R12: 48266
A13: 10940 | B13: Alma, MI (Micropolitan Statistical Area) | C13: 2 | D13: Population (persons) 1 | E13: 42466 | F13: 42295 | G13: 42288 | H13: 42390 | I13: 42054 | J13: 42056 | K13: 41792 | L13: 41972 | M13: 41703 | N13: 41943 | O13: 41683 | P13: 41286 | Q13: 41104 | R13: 41368
... A544: 49820 | B544: Zapata, TX (Micropolitan Statistical Area) | C544: 2 | D544: Population (persons) 1 | E544: 14079 | F544: 14187 | G544: 14204 | H544: 14283 | I544: 14238 | J544: 14324 | K544: 14242 | L544: 14047 | M544: 13919 | N544: 13960 | O544: 13875 | P544: 13875 | Q544: 13838 | R544: 13736

Sheet PCI-Metro
A1: GeoFips | B1: GeoName | C1: LineCode | D1: Description | E1: 2010 | F1: 2011 | G1: 2012 | H1: 2013 | I1: 2014 | J1: 2015 | K1: 2016 | L1: 2017 | M1: 2018 | N1: 2019 | O1: 2020 | P1: 2021 | Q1: 2022 | R1: 2023
A2: 998 | B2: United States (Metropolitan Portion) | C2: 3 | D2: Per capita personal income (dollars) 2 | E2: 41994 | F2: 44112 | G2: 45779 | H2: 45845 | I2: 47836 | J2: 49741 | K2: 50756 | L2: 52884 | M2: 55293 | N2: 57621 | O2: 61179 | P2: 66663 | Q2: 68517 | R2: 72275
A3: 10180 | B3: Abilene, TX (Metropolitan Statistical Area) | C3: 3 | D3: Per capita personal income (dollars) 2 | E3: 34935 | F3: 36812 | G3: 38138 | H3: 39123 | I3: 41461 | J3: 39866 | K3: 39163 | L3: 40384 | M3: 42781 | N3: 45075 | O3: 47854 | P3: 51995 | Q3: 53514 | R3: 56034
A4: 10420 | B4: Akron, OH (Metropolitan Statistical Area) | C4: 3 | D4: Per capita personal income (dollars) 2 | E4: 38080 | F4: 39794 | G4: 41099 | H4: 41643 | I4: 43331 | J4: 44674 | K4: 45463 | L4: 47163 | M4: 49091 | N4: 50905 | O4: 54376 | P4: 59583 | Q4: 59609 | R4: 62904
A5: 10500 | B5: Albany, GA (Metropolitan Statistical Area) | C5: 3 | D5: Per capita personal income (dollars) 2 | E5: 30317 | F5: 32256 | G5: 32379 | H5: 32211 | I5: 33110 | J5: 33868 | K5: 34476 | L5: 35338 | M5: 36158 | N5: 37940 | O5: 42071 | P5: 46969 | Q5: 46754 | R5: 48546
A6: 10540 | B6: Albany-Lebanon, OR (Metropolitan Statistical Area) | C6: 3 | D6: Per capita personal income (dollars) 2 | E6: 31609 | F6: 32316 | G6: 33264 | H6: 33705 | I6: 35888 | J6: 37940 | K6: 38991 | L6: 40571 | M6: 43056 | N6: 44286 | O6: 48033 | P6: 52230 | Q6: 54123 | R6: 57016
A7: 10580 | B7: Albany-Schenectady-Troy, NY (Metropolitan Statistical Area) | C7: 3 | D7: Per capita personal income (dollars) 2 | E7: 44146 | F7: 45558 | G7: 46708 | H7: 47434 | I7: 48762 | J7: 51103 | K7: 51996 | L7: 54685 | M7: 56159 | N7: 58330 | O7: 62728 | P7: 66929 | Q7: 67884 | R7: 71972
A8: 10740 | B8: Albuquerque, NM (Metropolitan Statistical Area) * | C8: 3 | D8: Per capita personal income (dollars) 2 | E8: 34521 | F8: 35720 | G8: 35918 | H8: 35330 | I8: 37284 | J8: 38644 | K8: 40050 | L8: 40802 | M8: 42178 | N8: 44597 | O8: 48463 | P8: 52372 | Q8: 54687 | R8: 57278
A9: 10780 | B9: Alexandria, LA (Metropolitan Statistical Area) | C9: 3 | D9: Per capita personal income (dollars) 2 | E9: 34936 | F9: 36684 | G9: 38264 | H9: 38257 | I9: 38665 | J9: 39271 | K9: 39871 | L9: 40302 | M9: 41876 | N9: 43558 | O9: 47669 | P9: 51240 | Q9: 51601 | R9: 53765
A10: 10900 | B10: Allentown-Bethlehem-Easton, PA-NJ (Metropolitan Statistical Area) | C10: 3 | D10: Per capita personal income (dollars) 2 | E10: 42274 | F10: 43509 | G10: 43937 | H10: 44324 | I10: 45795 | J10: 47682 | K10: 48896 | L10: 50135 | M10: 52126 | N10: 54962 | O10: 58589 | P10: 61836 | Q10: 62900 | R10: 66493
A11: 11020 | B11: Altoona, PA (Metropolitan Statistical Area) | C11: 3 | D11: Per capita personal income (dollars) 2 | E11: 35024 | F11: 36961 | G11: 37573 | H11: 37498 | I11: 38992 | J11: 40944 | K11: 41604 | L11: 42754 | M11: 44979 | N11: 46381 | O11: 50793 | P11: 54826 | Q11: 55071 | R11: 57782
A12: 11100 | B12: Amarillo, TX (Metropolitan Statistical Area) | C12: 3 | D12: Per capita personal income (dollars) 2 | E12: 38036 | F12: 40070 | G12: 40669 | H12: 41108 | I12: 42723 | J12: 42750 | K12: 42505 | L12: 44042 | M12: 45765 | N12: 48397 | O12: 51696 | P12: 55923 | Q12: 56643 | R12: 60182
A13: 11180 | B13: Ames, IA (Metropolitan Statistical Area) | C13: 3 | D13: Per capita personal income (dollars) 2 | E13: 34741 | F13: 36877 | G13: 39708 | H13: 38100 | I13: 39053 | J13: 39817 | K13: 39977 | L13: 40705 | M13: 42839 | N13: 44054 | O13: 45990 | P13: 49396 | Q13: 54141 | R13: 55770
... A386: 49740 | B386: Yuma, AZ (Metropolitan Statistical Area) * | C386: 3 | D386: Per capita personal income (dollars) 2 | E386: 27791 | F386: 28558 | G386: 28301 | H386: 30017 | I386: 29745 | J386: 31949 | K386: 33033 | L386: 34809 | M386: 35266 | N386: 36928 | O386: 41995 | P386: 44461 | Q386: 45028 | R386: 46441

Sheet PCI-Micro
A1: GeoFips | B1: GeoName | C1: LineCode | D1: Description | E1: 2010 | F1: 2011 | G1: 2012 | H1: 2013 | I1: 2014 | J1: 2015 | K1: 2016 | L1: 2017 | M1: 2018 | N1: 2019 | O1: 2020 | P1: 2021 | Q1: 2022 | R1: 2023
A2: 10100 | B2: Aberdeen, SD (Micropolitan Statistical Area) | C2: 3 | D2: Per capita personal income (dollars) 2 | E2: 41076 | F2: 47333 | G2: 47939 | H2: 50744 | I2: 50512 | J2: 51514 | K2: 49821 | L2: 49475 | M2: 53295 | N2: 54143 | O2: 61400 | P2: 72304 | Q2: 76672 | R2: 77242
A3: 10140 | B3: Aberdeen, WA (Micropolitan Statistical Area) | C3: 3 | D3: Per capita personal income (dollars) 2 | E3: 30223 | F3: 30888 | G3: 31806 | H3: 31979 | I3: 34277 | J3: 34894 | K3: 36023 | L3: 37512 | M3: 38982 | N3: 40452 | O3: 43601 | P3: 47004 | Q3: 47232 | R3: 49968
A4: 10220 | B4: Ada, OK (Micropolitan Statistical Area) | C4: 3 | D4: Per capita personal income (dollars) 2 | E4: 34526 | F4: 36192 | G4: 36300 | H4: 36380 | I4: 38682 | J4: 38776 | K4: 39222 | L4: 40988 | M4: 42881 | N4: 45099 | O4: 48275 | P4: 51729 | Q4: 53531 | R4: 56112
A5: 10300 | B5: Adrian, MI (Micropolitan Statistical Area) | C5: 3 | D5: Per capita personal income (dollars) 2 | E5: 30552 | F5: 32182 | G5: 33032 | H5: 32631 | I5: 33710 | J5: 35560 | K5: 36484 | L5: 37025 | M5: 38918 | N5: 40110 | O5: 44127 | P5: 47735 | Q5: 48611 | R5: 51391
A6: 10460 | B6: Alamogordo, NM (Micropolitan Statistical Area) | C6: 3 | D6: Per capita personal income (dollars) 2 | E6: 31474 | F6: 31979 | G6: 31760 | H6: 30598 | I6: 31617 | J6: 32587 | K6: 33105 | L6: 33240 | M6: 34474 | N6: 35119 | O6: 38834 | P6: 41855 | Q6: 42490 | R6: 43353
A7: 10620 | B7: Albemarle, NC (Micropolitan Statistical Area) | C7: 3 | D7: Per capita personal income (dollars) 2 | E7: 29239 | F7: 29917 | G7: 31500 | H7: 31786 | I7: 33292 | J7: 34639 | K7: 36109 | L7: 37585 | M7: 38705 | N7: 40254 | O7: 43148 | P7: 47770 | Q7: 48450 | R7: 50394
A8: 10660 | B8: Albert Lea, MN (Micropolitan Statistical Area) | C8: 3 | D8: Per capita personal income (dollars) 2 | E8: 34935 | F8: 37669 | G8: 38862 | H8: 40443 | I8: 39579 | J8: 40839 | K8: 40117 | L8: 42361 | M8: 43490 | N8: 44518 | O8: 48857 | P8: 54489 | Q8: 55432 | R8: 56100
A9: 10700 | B9: Albertville, AL (Micropolitan Statistical Area) | C9: 3 | D9: Per capita personal income (dollars) 2 | E9: 29709 | F9: 29648 | G9: 30789 | H9: 31076 | I9: 32093 | J9: 34050 | K9: 33615 | L9: 34556 | M9: 35648 | N9: 37673 | O9: 41120 | P9: 45985 | Q9: 47142 | R9: 48602
A10: 10760 | B10: Alexander City, AL (Micropolitan Statistical Area) | C10: 3 | D10: Per capita personal income (dollars) 2 | E10: 30699 | F10: 31202 | G10: 32129 | H10: 32452 | I10: 32782 | J10: 35019 | K10: 35889 | L10: 36506 | M10: 37885 | N10: 40125 | O10: 42533 | P10: 46781 | Q10: 46972 | R10: 49396
A11: 10820 | B11: Alexandria, MN (Micropolitan Statistical Area) | C11: 3 | D11: Per capita personal income (dollars) 2 | E11: 43255 | F11: 45281 | G11: 49625 | H11: 48494 | I11: 46179 | J11: 49126 | K11: 50091 | L11: 49167 | M11: 50088 | N11: 51196 | O11: 55839 | P11: 61686 | Q11: 63755 | R11: 65827
A12: 10860 | B12: Alice, TX (Micropolitan Statistical Area) | C12: 3 | D12: Per capita personal income (dollars) 2 | E12: 33147 | F12: 37523 | G12: 40161 | H12: 41830 | I12: 43500 | J12: 39914 | K12: 37538 | L12: 39904 | M12: 41376 | N12: 43314 | O12: 46340 | P12: 48074 | Q12: 48839 | R12: 51699
A13: 10940 | B13: Alma, MI (Micropolitan Statistical Area) | C13: 3 | D13: Per capita personal income (dollars) 2 | E13: 28766 | F13: 31142 | G13: 31475 | H13: 31558 | I13: 31831 | J13: 33200 | K13: 33620 | L13: 34369 | M13: 35625 | N13: 36073 | O13: 41228 | P13: 44174 | Q13: 44050 | R13: 45517
... A544: 49820 | B544: Zapata, TX (Micropolitan Statistical Area) | C544: 3 | D544: Per capita personal income (dollars) 2 | E544: 24492 | F544: 27827 | G544: 31077 | H544: 32417 | I544: 33646 | J544: 29177 | K544: 24981 | L544: 27377 | M544: 29102 | N544: 29731 | O544: 29730 | P544: 33375 | Q544: 32715 | R544: 34154

Sheet Stadium Capacity

Sheet Ra2W
A1: A&M-Corpus Christi | B1: A&M-Corpus Christi | C1: 224147 | D1: 18580 | E1: 2016 | F1: 9856 | G1: 6833 | H1: 14 | I1: 0.861 | J1: 0.543 | K1: 423932
A2: Abilene Christian | B2: Abilene Christian | C2: 222178 | D2: 10180 | E2: 2016 | F2: 2972 | G2: 3859 | H2: 8 | K2: 172344
A3: Air Force | B3: Air Force | C3: 500002 | D3: 17820 | E3: 2016 | F3: 4884 | G3: 5422 | H3: 16 | I3: 0.364 | J3: 0.406 | K3: 714386
A4: Akron | B4: Akron | C4: 200800 | D4: 10420 | E4: 2016 | F4: 4186 | G4: 2889 | H4: 12 | I4: 0.276 | J4: 0.258 | K4: 703787
A5: Alabama | B5: Alabama | C5: 100751 | D5: 46220 | E5: 2016 | F5: 15003 | G5: 12289 | H5: 17 | I5: 0.531 | J5: 0.765 | K5: 260042
A6: Alabama A&M | B6: Alabama A&M | C6: 100654 | D6: 26620 | E6: 2016 | F6: 1360 | G6: 1335 | H6: 7 | I6: 0.342 | J6: 0.394 | K6: 457597
A7: Alabama St. | B7: Alabama St. | C7: 100724 | D7: 33860 | E7: 2016 | F7: 805 | G7: 3495 | H7: 4 | I7: 0.583 | J7: 0.513 | K7: 382383
A8: Alcorn | B8: Alcorn | C8: 175342 | D8: 35020 | E8: 2016 | F8: 1077 | G8: 1053 | H8: 11 | I8: 0.353 | J8: 0.286 | K8: 50811
A9: American | B9: American | C9: 131159 | D9: 47900 | E9: 2016 | F9: 6366 | G9: 7923 | H9: 16 | I9: 0.8 | J9: 0.788 | K9: 6194690
A10: Appalachian St. | B10: App State | C10: 197869 | D10: 14380 | E10: 2016 | F10: 5894 | G10: 5174 | H10: 13 | I10: 0.733 | J10: 0.677 | K10: 52785
A11: Arizona | B11: Arizona | C11: 104179 | D11: 46060 | E11: 2016 | F11: 23391 | G11: 27266 | H11: 16 | I11: 0.576 | J11: 0.706 | K11: 1007353
A12: Arizona St. | B12: Arizona St. | C12: 104151 | D12: 38060 | E12: 2016 | F12: 28182 | G12: 22373 | H12: 15 | I12: 0.594 | J12: 0.588 | K12: 4556103
A13: Ark.-Pine Bluff | B13: Ark.-Pine Bluff | C13: 106412 | D13: 38220 | E13: 2016 | F13: 902 | G13: 774 | H13: 7 | I13: 0.206 | J13: 0.355 | K13: 93091
A14: Arkansas | B14: Arkansas | C14: 106397 | D14: 22220 | E14: 2016 | F14: 14697 | G14: 15265 | H14: 15 | I14: 0.567 | J14: 0.484 | K14: 504921
... A25: Boston College | B25: Boston College | C25: 164924 | D25: 14460 | E25: 2016 | F25: 4847 | G25: 3921 | H25: 14 | I25: 0.375 | J25: 0.379 | K25: 4850147
A26: Boston U. | B26: Boston U. | C26: 164988 | D26: 14380 | E26: 2016 | K26: 52785
A27: Bowling Green | B27: Bowling Green | C27: 201441 | D27: 45780 | E27: 2016 | F27: 5614 | G27: 7651 | H27: 11 | I27: 0.241 | J27: 0.25 | K27: 648677
A28: Bradley | B28: Bradley | C28: 143358 | D28: 37900 | E28: 2016 | F28: 5705 | G28: 4115 | H28: 15 | I28: 0.2 | J28: 0.071 | K28: 413782
A29: Brown | B29: Brown | C29: 217156 | D29: 39300 | E29: 2016 | F29: 1793 | G29: 1631 | H29: 8 | I29: 0.385 | J29: 0.462 | K29: 1648701
A30: Bryant | B30: Bryant | C30: 217165 | D30: 39300 | E30: 2016 | F30: 2460 | G30: 4157 | H30: 14 | I30: 0.576 | J30: 0.353 | K30: 1648701
A31: Bucknell | B31: Bucknell | C31: 211291 | D31: 30260 | E31: 2016 | F31: 1936 | G31: 1800 | H31: 10 | I31: 0.538 | J31: 0.28 | K31: 44489
A32: Buffalo | B32: Buffalo | C32: 196088 | D32: 15380 | E32: 2016 | F32: 2435 | G32: 3338 | H32: 8 | I32: 0.241 | J32: 0.531 | K32: 1155507
A33: Butler | B33: Butler | C33: 150163 | D33: 26900 | E33: 2016 | F33: 7804 | G33: 4356 | H33: 16 | I33: 0.387 | J33: 0.667 | K33: 2022451
A34: BYU | B34: BYU | C34: 230038 | D34: 39340 | E34: 2016 | F34: 26205 | G34: 20649 | H34: 14 | I34: 0.875 | J34: 0.857 | K34: 609431
A35: Cal Poly | B35: Cal Poly | C35: 110422 | D35: 42020 | E35: 2016 | F35: 7218 | G35: 6217 | H35: 10 | I35: 0.704 | J35: 0.346 | K35: 281794
A36: Cal St. Fullerton | B36: Cal St. Fullerton | C36: 110565 | D36: 31080 | E36: 2016 | F36: 3321 | G36: 5110 | H36: 11 | J36: 0.276 | K36: 13297429
A37: California | B37: California | C37: 110635 | D37: 41860 | E37: 2016 | F37: 9642 | G37: 9197 | H37: 15 | I37: 0.29 | J37: 0.333 | K37: 4713476
A38: California Baptist | B38: California Baptist | C38: 110361 | D38: 40140 | E38: 2016 | K38: 4463228
A39: Campbell | B39: Campbell | C39: 198136 | D39: 15820 | E39: 2016 | F39: 2402 | G39: 5375 | H39: 11 | I39: 0.452 | J39: 0.438 | K39: 36677
A40: Canisius | B40: Canisius | C40: 189705 | D40: 15380 | E40: 2016 | F40: 2837 | G40: 1888 | H40: 11 | I40: 0.367 | J40: 0.375 | K40: 1155507
A41: Central Ark. | B41: Central Ark. | C41: 106704 | D41: 30780 | E41: 2016 | F41: 4299 | G41: 4821 | H41: 11 | I41: 0.552 | J41: 0.625 | K41: 735686
A42: Central Conn. St. | B42: Central Conn. St. | C42: 128771 | D42: 25540 | E42: 2016 | F42: 1993 | G42: 1580 | H42: 13 | I42: 0.407 | J42: 0.407 | K42: 1215446
A43: Central Mich. | B43: Central Mich. | C43: 169248 | D43: 34380 | E43: 2016 | F43: 4928 | G43: 3540 | H43: 11 | I43: 0.379 | J43: 0.357 | K43: 68075
A44: Charleston So. | B44: Charleston So. | C44: 217688 | D44: 16700 | E44: 2016 | F44: 2754 | G44: 3413 | H44: 10 | I44: 0.303 | J44: 0.333 | K44: 752067
A45: Charlotte | B45: Charlotte | C45: 199139 | D45: 16740 | E45: 2016 | F45: 7765 | G45: 6439 | H45: 12 | I45: 0.296 | J45: 0.5 | K45: 2492928
A46: Chattanooga | B46: Chattanooga | C46: 221740 | D46: 16860 | E46: 2016 | F46: 4192 | G46: 2625 | H46: 15 | I46: 0.813 | J46: 0.406 | K46: 548385
A47: Chicago St. | B47: Chicago St. | C47: 144005 | D47: 16980 | E47: 2016 | F47: 1026 | G47: 1988 | H47: 8 | I47: 0.036 | J47: 0.2 | K47: 9654839
A48: Cincinnati | B48: Cincinnati | C48: 201885 | D48: 17140 | E48: 2016 | F48: 7538 | G48: 6470 | H48: 15 | I48: 0.677 | J48: 0.469 | K48: 2209105
A49: Clemson | B49: Clemson | C49: 217882 | D49: 42860 | E49: 2016 | F49: 11735 | G49: 14559 | H49: 16 | I49: 0.188 | J49: 0.563 | K49: 75676
A50: Cleveland St. | B50: Cleveland St. | C50: 202134 | D50: 17460 | E50: 2016 | F50: 3924 | G50: 3266 | H50: 13 | I50: 0.788 | J50: 0.5 | K50: 2087581
... A68: DePaul | B68: DePaul | C68: 144740 | D68: 16980 | E68: 2016 | F68: 4031 | G68: 4520 | H68: 13 | I68: 0.516 | J68: 0.1 | K68: 9654839
A69: Detroit Mercy | B69: Detroit Mercy | C69: 169716 | D69: 19820 | E69: 2016 | K69: 4368028
A70: Drake | B70: Drake | C70: 153269 | D70: 19780 | E70: 2016 | F70: 4079 | G70: 3542 | H70: 10 | I70: 0.429 | J70: 0.379 | K70: 673388
A71: Drexel | B71: Drexel | C71: 212054 | D71: 37980 | E71: 2016 | K71: 6153898
A72: Duke | B72: Duke | C72: 198419 | D72: 20500 | E72: 2016 | F72: 18318 | G72: 19943 | H72: 14 | I72: 0.567 | J72: 0.733 | K72: 617871
A73: Duquesne | B73: Duquesne | C73: 212106 | D73: 38300 | E73: 2016 | F73: 1828 | G73: 1762 | H73: 10 | I73: 0.483 | J73: 0.571 | K73: 2377735
A74: East Carolina | B74: East Carolina | C74: 198464 | D74: 24780 | E74: 2016 | F74: 6987 | G74: 5546 | H74: 13 | I74: 0.387 | J74: 0.484 | K74: 169586
A75: Eastern Ill. | B75: Eastern Ill. | C75: 144892 | D75: 16660 | E75: 2016 | F75: 3733 | G75: 2471 | H75: 9 | I75: 0.516 | J75: 0.484 | K75: 60259
A76: Eastern Ky. | B76: Eastern Ky. | C76: 156620 | D76: 40080 | E76: 2016 | F76: 1179 | G76: 1510 | H76: 9 | I76: 0.303 | J76: 0.6 | K76: 103239
A77: Eastern Mich. | B77: Eastern Mich. | C77: 169798 | D77: 11460 | E77: 2016 | F77: 2191 | G77: 2072 | H77: 8 | I77: 0.467 | J77: 0.581 | K77: 370179
A78: Eastern Wash. | B78: Eastern Wash. | C78: 235097 | D78: 44060 | E78: 2016 | F78: 2677 | G78: 5568 | H78: 9 | I78: 0.5 | J78: 0.31 | K78: 549234
A79: Elon | B79: Elon | C79: 198516 | D79: 24660 | E79: 2016 | F79: 2828 | G79: 1795 | H79: 14 | I79: 0.233 | J79: 0.188 | K79: 759364
A80: ETSU | B80: ETSU | C80: 220075 | D80: 27740 | E80: 2016 | F80: 2013 | G80: 3149 | H80: 9 | I80: 0.613 | J80: 0.515 | K80: 203406
A81: Evansville | B81: Evansville | C81: 150534 | D81: 21780 | E81: 2016 | F81: 2300 | G81: 4666 | H81: 12 | I81: 0.25 | J81: 0.267 | K81: 314463
A82: Fairfield | B82: Fairfield | C82: 129242 | D82: 35620 | E82: 2016 | F82: 1781 | G82: 1672 | H82: 13 | I82: 0.677 | J82: 0.613 | K82: 19945132
A83: Fairleigh Dickinson | B83: FDU | C83: 184603 | D83: 35620 | E83: 2016 | F83: 1824 | G83: 1828 | H83: 11 | I83: 0.345 | J83: 0.207 | K83: 19945132
... A102: Grambling | B102: Grambling | C102: 159009 | D102: 33740 | E102: 2016 | F102: 1853 | G102: 1583 | H102: 9 | I102: 0.265 | J102: 0.115 | K102: 210259
A103: Grand Canyon | B103: Grand Canyon | C103: 104717 | D103: 38060 | E103: 2016 | F103: 7814 | G103: 3779 | H103: 15 | K103: 4556103
A104: Green Bay | B104: Green Bay | C104: 240277 | D104: 24580 | E104: 2016 | F104: 3447 | G104: 3484 | H104: 9 | I104: 0.567 | J104: 0.192 | K104: 320537
A105: Hampton | B105: Hampton | C105: 232265 | D105: 47260 | E105: 2016 | F105: 1400 | G105: 3220 | H105: 6 | I105: 0.12 | J105: 0.656 | K105: 1773787
A106: Hartford | B106: Hartford | C106: 129525 | D106: 25540 | E106: 2016 | F106: 3023 | G106: 1935 | H106: 11 | I106: 0.069 | J106: 0.567 | K106: 1215446
A107: Harvard | B107: Harvard | C107: 166027 | D107: 14460 | E107: 2016 | F107: 4011 | G107: 4101 | H107: 15 | I107: 0.577 | J107: 0.792 | K107: 4850147
A108: Hawaii | B108: Hawaii | C108: 141574 | D108: 46520 | E108: 2016 | F108: 131187 | G108: 120776 | H108: 19 | I108: 0.935 | J108: 0.759 | K108: 1023810
A109: High Point | B109: High Point | C109: 198695 | D109: 24660 | E109: 2016 | F109: 6769 | G109: 6450 | H109: 16 | I109: 0.677 | J109: 0.448 | K109: 759364
A110: Hofstra | B110: Hofstra | C110: 191649 | D110: 35620 | E110: 2016 | F110: 2123 | G110: 3887 | H110: 12 | I110: 0.656 | J110: 0.824 | K110: 19945132
A111: Holy Cross | B111: Holy Cross | C111: 166124 | D111: 49340 | E111: 2016 | F111: 962 | G111: 1800 | H111: 8 | I111: 0.241 | J111: 0.259 | K111: 956771
A112: Houston | B112: Houston | C112: 225511 | D112: 26420 | E112: 2016 | F112: 4591 | G112: 5973 | H112: 13 | I112: 0.594 | J112: 0.438 | K112: 6797263
A113: Houston Baptist | B113: Houston Christian | C113: 225399 | D113: 26420 | E113: 2016 | F113: 6686 | G113: 5678 | H113: 13 | I113: 0.5 | J113: 0.469 | K113: 6797263
A114: Howard | B114: Howard | C114: 131520 | D114: 47900 | E114: 2016 | F114: 1222 | G114: 939 | H114: 9 | I114: 0.563 | J114: 0.645 | K114: 6194690
A115: Idaho | B115: Idaho | C115: 142285 | D115: 34140 | E115: 2016 | F115: 4938 | G115: 7499 | H115: 11 | I115: 0.467 | J115: 0.517 | K115: 38448
... A123: Iowa St. | B123: Iowa St. | C123: 153603 | D123: 11180 | E123: 2016 | F123: 34113 | G123: 34172 | H123: 13 | I123: 0.633 | J123: 0.655 | K123: 123978
A124: IUPUI | B124: IUPUI | C124: 151111 | D124: 26900 | E124: 2016 | K124: 2022451
A125: Jackson St. | B125: Jackson St. | C125: 175856 | D125: 27140 | E125: 2016 | F125: 3086 | G125: 3291 | H125: 13 | I125: 0.405 | J125: 0.344 | K125: 600631
A126: Jacksonville | B126: Jacksonville | C126: 134945 | D126: 27260 | E126: 2016 | F126: 2288 | G126: 2075 | H126: 7 | I126: 0.429 | J126: 0.559 | K126: 1492438
A127: Jacksonville St. | B127: Jacksonville St. | C127: 101480 | D127: 11500 | E127: 2016 | F127: 3731 | G127: 3384 | H127: 11 | I127: 0.412 | J127: 0.529 | K127: 116746
A128: James Madison | B128: James Madison | C128: 232423 | D128: 25500 | E128: 2016 | F128: 3694 | G128: 4338 | H128: 16 | I128: 0.733 | J128: 0.548 | K128: 133060
A129: Kansas | B129: Kansas | C129: 155317 | D129: 29940 | E129: 2016 | F129: 22324 | G129: 19283 | H129: 16 | I129: 0.909 | J129: 0.71 | K129: 117526
A130: UMKC | B130: Kansas City | C130: 178402 | D130: 28140 | E130: 2016 | F130: 2893 | G130: 3796 | H130: 12 | I130: 0.536 | J130: 0.8 | K130: 2121656
A131: Kansas St. | B131: Kansas St. | C131: 155399 | D131: 31740 | E131: 2016 | F131: 22362 | G131: 30759 | H131: 11 | I131: 0.586 | J131: 0.71 | K131: 136983
A132: Kennesaw St. | B132: Kennesaw St. | C132: 486840 | D132: 12060 | E132: 2016 | F132: 7023 | G132: 5176 | H132: 12 | I132: 0.679 | J132: 0.345 | K132: 5800308
A133: Kent St. | B133: Kent St. | C133: 203517 | D133: 10420 | E133: 2016 | F133: 4849 | G133: 3968 | H133: 11 | I133: 0.667 | J133: 0.548 | K133: 703787
A134: Kentucky | B134: Kentucky | C134: 157085 | D134: 30460 | E134: 2016 | F134: 24334 | G134: 30453 | H134: 14 | I134: 0.677 | J134: 0.818 | K134: 504058
A135: La Salle | B135: La Salle | C135: 213367 | D135: 37980 | E135: 2016 | F135: 1026 | G135: 1184 | H135: 10 | I135: 0.194 | J135: 0.323 | K135: 6153898
A136: Lafayette | B136: Lafayette | C136: 213385 | D136: 10900 | E136: 2016 | F136: 1851 | G136: 1710 | H136: 15 | I136: 0.407 | J136: 0.214 | K136: 843356
... A144: Long Beach St. | B144: Long Beach St. | C144: 110583 | D144: 31080 | E144: 2016 | F144: 17291 | G144: 17708 | H144: 19 | I144: 0.806 | J144: 0.844 | K144: 13297429
A145: Longwood | B145: Longwood | C145: 232566 | D145: 40060 | E145: 2016 | K145: 1267408
A146: Louisiana | B146: Louisiana | C146: 160658 | D146: 29180 | E146: 2016 | F146: 3785 | G146: 5060 | H146: 12 | I146: 0.207 | J146: 0.606 | K146: 483889
A147: Louisiana Tech | B147: Louisiana Tech | C147: 159647 | D147: 40820 | E147: 2016 | F147: 2747 | G147: 2314 | H147: 12 | I147: 0.333 | J147: 0.3 | K147: 48584
A148: Louisville | B148: Louisville | C148: 157289 | D148: 31140 | E148: 2016 | F148: 34334 | G148: 26352 | H148: 17 | I148: 0.781 | J148: 0.5 | K148: 1263416
A149: Loyola Chicago | B149: Loyola Chicago | C149: 146719 | D149: 16980 | E149: 2016 | F149: 4144 | G149: 2772 | H149: 12 | I149: 0.625 | J149: 0.321 | K149: 9654839
A150: Loyola Maryland | B150: Loyola Maryland | C150: 163046 | D150: 12580 | E150: 2016 | F150: 1894 | G150: 1558 | H150: 10 | I150: 0.194 | J150: 0.069 | K150: 2821292
A151: LSU | B151: LSU | C151: 159391 | D151: 12940 | E151: 2016 | F151: 12673 | G151: 9027 | H151: 11 | I151: 0.31 | J151: 0.69 | K151: 864779
A152: Maine | B152: Maine | C152: 161253 | D152: 12620 | E152: 2016 | K152: 151714
A153: Manhattan | B153: Manhattan | C153: 192703 | D153: 35620 | E153: 2016 | F153: 2310 | G153: 1966 | H153: 11 | I153: 0.588 | J153: 0.618 | K153: 19945132
A154: Marist | B154: Marist | C154: 192819 | D154: 39100 | E154: 2016 | F154: 2343 | G154: 2472 | H154: 13 | I154: 0.677 | J154: 0.806 | K154: 682352
A155: Marquette | B155: Marquette | C155: 239105 | D155: 33340 | E155: 2016 | F155: 7579 | G155: 10487 | H155: 13 | I155: 0.647 | J155: 0.727 | K155: 1574201
A156: Marshall | B156: Marshall | C156: 237525 | D156: 26580 | E156: 2016 | F156: 4204 | G156: 6642 | H156: 9 | I156: 0.533 | J156: 0.5 | K156: 368494
A157: Maryland | B157: Maryland | C157: 163286 | D157: 47900 | E157: 2016 | F157: 20027 | G157: 15387 | H157: 16 | I157: 0.441 | J157: 0.323 | K157: 6194690
A158: Massachusetts | B158: Massachusetts | C158: 166629 | D158: 44140 | E158: 2016 | K158: 701824
A159: McNeese | B159: McNeese | C159: 159717 | D159: 29340 | E159: 2016 | F159: 3224 | G159: 2825 | H159: 12 | I159: 0.455 | J159: 0.469 | K159: 215028
...

Sheet RA2L
A1: A&M-Corpus Christi | B1: A&M-Corpus Christi | C1: 224147 | D1: 18580 | E1: 2015 | F1: 6833 | G1: 9115 | H1: 13 | I1: 0.543 | J1: 0.625 | K1: 423386
A2: Abilene Christian | B2: Abilene Christian | C2: 222178 | D2: 10180 | E2: 2015 | F2: 3859 | G2: 3992 | H2: 9 | K2: 171666
A3: Air Force | B3: Air Force | C3: 500002 | D3: 17820 | E3: 2015 | F3: 5422 | G3: 6002 | H3: 17 | I3: 0.406 | J3: 0.25 | K3: 698874
A4: Akron | B4: Akron | C4: 200800 | D4: 10420 | E4: 2015 | F4: 2889 | G4: 2933 | H4: 13 | I4: 0.258 | J4: 0.296 | K4: 704604
A5: Alabama | B5: Alabama | C5: 100751 | D5: 46220 | E5: 2015 | F5: 12289 | G5: 12376 | H5: 13 | I5: 0.765 | J5: 0.706 | K5: 257358
A6: Alabama A&M | B6: Alabama A&M | C6: 100654 | D6: 26620 | E6: 2015 | F6: 1335 | G6: 1146 | H6: 9 | I6: 0.394 | J6: 0.344 | K6: 451269
A7: Alabama St. | B7: Alabama St. | C7: 100724 | D7: 33860 | E7: 2015 | F7: 3495 | G7: 1804 | H7: 16 | I7: 0.513 | J7: 0.61 | K7: 380447
A8: Alcorn | B8: Alcorn | C8: 175342 | D8: 35020 | E8: 2015 | F8: 1053 | G8: 612 | H8: 9 | I8: 0.286 | K8: 51163
A9: American | B9: American | C9: 131159 | D9: 47900 | E9: 2015 | F9: 7923 | G9: 5700 | H9: 16 | I9: 0.788 | J9: 0.919 | K9: 6132190
A10: App State | B10: Appalachian St. | C10: 197869 | D10: 14380 | E10: 2015 | F10: 5174 | G10: 4432 | H10: 16 | I10: 0.677 | J10: 0.594 | K10: 51985
A11: Arizona | B11: Arizona | C11: 104179 | D11: 46060 | E11: 2015 | F11: 27266 | G11: 19887 | H11: 18 | I11: 0.706 | J11: 0.618 | K11: 1001320
A12: Arizona St. | B12: Arizona St. | C12: 104151 | D12: 38060 | E12: 2015 | F12: 22373 | G12: 17544 | H12: 16 | I12: 0.588 | J12: 0.576 | K12: 4480231
A13: Ark.-Pine Bluff | B13: Ark.-Pine Bluff | C13: 106412 | D13: 38220 | E13: 2015 | F13: 774 | G13: 911 | H13: 7 | I13: 0.355 | J13: 0.361 | K13: 94570
A14: Arkansas | B14: Arkansas | C14: 106397 | D14: 22220 | E14: 2015 | F14: 15265 | G14: 12395 | H14: 16 | I14: 0.484 | J14: 0.533 | K14: 492646
A15: Arkansas St. | B15: Arkansas St. | C15: 106458 | D15: 27860 | E15: 2015 | F15: 3742 | G15: 4137 | H15: 10 | I15: 0.677 | J15: 0.429 | K15: 127954
A16: Army West Point | B16: Army West Point | C16: 500001 | D16: 35620 | E16: 2015 | F16: 1921 | G16: 3909 | H16: 12 | I16: 0.467 | J16: 0.519 | K16: 19833335
A17: Auburn | B17: Auburn | C17: 100858 | D17: 12220 | E17: 2015 | F17: 11835 | G17: 8694 | H17: 15 | I17: 0.419 | J17: 0.633 | K17: 161247
A18: Austin Peay | B18: Austin Peay | C18: 219602 | D18: 17300 | E18: 2015 | F18: 2860 | G18: 3066 | H18: 9 | I18: 0.424 | J18: 0.371 | K18: 297187
A19: Ball St. | B19: Ball St. | C19: 150136 | D19: 34620 | E19: 2015 | F19: 6403 | G19: 8288 | H19: 11 | I19: 0.567 | J19: 0.75 | K19: 114923
A20: Baylor | B20: Baylor | C20: 223232 | D20: 47380 | E20: 2015 | F20: 9660 | G20: 11470 | H20: 14 | I20: 0.452 | J20: 0.375 | K20: 263235
... A25: Boston College | B25: Boston College | C25: 164924 | D25: 14460 | E25: 2015 | F25: 3921 | G25: 4311 | H25: 12 | I25: 0.379 | J25: 0.281 | K25: 4812849
A26: Boston U. | B26: Boston U. | C26: 164988 | D26: 14380 | E26: 2015 | K26: 51985
A27: Bowling Green | B27: Bowling Green | C27: 201441 | D27: 45780 | E27: 2015 | F27: 7651 | G27: 9115 | H27: 11 | I27: 0.25 | J27: 0.467 | K27: 648620
A28: Bradley | B28: Bradley | C28: 143358 | D28: 37900 | E28: 2015 | F28: 4115 | G28: 5533 | H28: 12 | I28: 0.071 | J28: 0.464 | K28: 415361
A29: Brown | B29: Brown | C29: 217156 | D29: 39300 | E29: 2015 | F29: 1631 | G29: 1343 | H29: 12 | I29: 0.462 | J29: 0.48 | K29: 1641256
A30: Bryant | B30: Bryant | C30: 217165 | D30: 39300 | E30: 2015 | F30: 4157 | G30: 1522 | H30: 14 | I30: 0.353 | J30: 0.242 | K30: 1641256
A31: Bucknell | B31: Bucknell | C31: 211291 | D31: 30260 | E31: 2015 | F31: 1800 | G31: 3480 | H31: 11 | I31: 0.28 | J31: 0.385 | K31: 44700
A32: Buffalo | B32: Buffalo | C32: 196088 | D32: 15380 | E32: 2015 | F32: 3338 | G32: 6145 | H32: 14 | I32: 0.531 | J32: 0.6 | K32: 1154207
A33: Butler | B33: Butler | C33: 150163 | D33: 26900 | E33: 2015 | F33: 4356 | G33: 9951 | H33: 9 | I33: 0.667 | J33: 0.75 | K33: 1999191
A34: BYU | B34: BYU | C34: 230038 | D34: 39340 | E34: 2015 | F34: 20649 | G34: 12157 | H34: 13 | I34: 0.857 | J34: 0.774 | K34: 589961
A35: Cal Poly | B35: Cal Poly | C35: 110422 | D35: 42020 | E35: 2015 | F35: 6217 | G35: 7125 | H35: 13 | I35: 0.346 | J35: 0.414 | K35: 280062
A36: Cal St. Fullerton | B36: Cal St. Fullerton | C36: 110565 | D36: 31080 | E36: 2015 | F36: 5110 | G36: 4558 | H36: 14 | I36: 0.276 | J36: 0.393 | K36: 13258364
A37: California | B37: California | C37: 110635 | D37: 41860 | E37: 2015 | F37: 9197 | G37: 11376 | H37: 13 | I37: 0.333 | J37: 0.581 | K37: 4669540
A38: California Baptist | B38: California Baptist | C38: 110361 | D38: 40140 | E38: 2015 | K38: 4420560
A39: Campbell | B39: Campbell | C39: 198136 | D39: 15820 | E39: 2015 | F39: 5375 | G39: 2949 | H39: 12 | I39: 0.438 | J39: 0.452 | K39: 36763
A40: Canisius | B40: Canisius | C40: 189705 | D40: 15380 | E40: 2015 | F40: 1888 | G40: 4345 | H40: 9 | I40: 0.375 | J40: 0.379 | K40: 1154207
A41: Central Ark. | B41: Central Ark. | C41: 106704 | D41: 30780 | E41: 2015 | F41: 4821 | G41: 4186 | H41: 14 | I41: 0.625 | J41: 0.879 | K41: 732412
A42: Central Conn. St. | B42: Central Conn. St. | C42: 128771 | D42: 25540 | E42: 2015 | F42: 1580 | G42: 1874 | H42: 10 | I42: 0.407 | J42: 0.7 | K42: 1217677
A43: Central Mich. | B43: Central Mich. | C43: 169248 | D43: 34380 | E43: 2015 | F43: 3540 | G43: 4687 | H43: 11 | I43: 0.357 | J43: 0.393 | K43: 68141
A44: Charleston So. | B44: Charleston So. | C44: 217688 | D44: 16700 | E44: 2015 | F44: 3413 | G44: 2364 | H44: 14 | I44: 0.333 | J44: 0.2 | K44: 737259
A45: Charlotte | B45: Charlotte | C45: 199139 | D45: 16740 | E45: 2015 | F45: 6439 | G45: 6581 | H45: 13 | I45: 0.5 | J45: 0.414 | K45: 2442023
A46: Chattanooga | B46: Chattanooga | C46: 221740 | D46: 16860 | E46: 2015 | F46: 2625 | G46: 3900 | H46: 15 | I46: 0.406 | J46: 0.129 | K46: 544285
A47: Chicago St. | B47: Chicago St. | C47: 144005 | D47: 16980 | E47: 2015 | F47: 1988 | G47: 3352 | H47: 19 | I47: 0.2 | J47: 0.065 | K47: 9654044
A48: Cincinnati | B48: Cincinnati | C48: 201885 | D48: 17140 | E48: 2015 | F48: 6470 | G48: 5870 | H48: 15 | I48: 0.469 | J48: 0.094 | K48: 2196029
A49: Clemson | B49: Clemson | C49: 217882 | D49: 42860 | E49: 2015 | F49: 14559 | G49: 14708 | H49: 17 | I49: 0.563 | J49: 0.484 | K49: 75212
A50: Cleveland St. | B50: Cleveland St. | C50: 202134 | D50: 17460 | E50: 2015 | F50: 3266 | G50: 2535 | H50: 11 | I50: 0.5 | J50: 0.552 | K50: 2086587
... A68: DePaul | B68: DePaul | C68: 144740 | D68: 16980 | E68: 2015 | F68: 4520 | G68: 6167 | H68: 12 | I68: 0.1 | J68: 0.533 | K68: 9654044
A69: Detroit Mercy | B69: Detroit Mercy | C69: 169716 | D69: 19820 | E69: 2015 | K69: 4352979
A70: Drake | B70: Drake | C70: 153269 | D70: 19780 | E70: 2015 | F70: 3542 | G70: 3713 | H70: 10 | I70: 0.379 | J70: 0.067 | K70: 661440
A71: Drexel | B71: Drexel | C71: 212054 | D71: 37980 | E71: 2015 | K71: 6130446
A72: Duke | B72: Duke | C72: 198419 | D72: 20500 | E72: 2015 | F72: 19943 | G72: 29723 | H72: 15 | I72: 0.733 | J72: 0.848 | K72: 607517
A73: Duquesne | B73: Duquesne | C73: 212106 | D73: 38300 | E73: 2015 | F73: 1762 | G73: 1632 | H73: 11 | I73: 0.571 | J73: 0.667 | K73: 2379296
A74: East Carolina | B74: East Carolina | C74: 198464 | D74: 24780 | E74: 2015 | F74: 5546 | G74: 3281 | H74: 16 | I74: 0.484 | J74: 0.406 | K74: 169708
A75: Eastern Ill. | B75: Eastern Ill. | C75: 144892 | D75: 16660 | E75: 2015 | F75: 2471 | G75: 3794 | H75: 8 | I75: 0.484 | J75: 0.6 | K75: 61011
A76: Eastern Ky. | B76: Eastern Ky. | C76: 156620 | D76: 40080 | E76: 2015 | F76: 1510 | G76: 1820 | H76: 11 | I76: 0.6 | J76: 0.529 | K76: 102037
A77: Eastern Mich. | B77: Eastern Mich. | C77: 169798 | D77: 11460 | E77: 2015 | F77: 2072 | G77: 2630 | H77: 10 | I77: 0.581 | J77: 0.529 | K77: 366258
A78: Eastern Wash. | B78: Eastern Wash. | C78: 235097 | D78: 44060 | E78: 2015 | F78: 5568 | G78: 5302 | H78: 9 | I78: 0.31 | J78: 0.323 | K78: 539167
A79: Elon | B79: Elon | C79: 198516 | D79: 24660 | E79: 2015 | F79: 1795 | G79: 2402 | H79: 13 | I79: 0.188 | J79: 0.485 | K79: 751915
A80: ETSU | B80: ETSU | C80: 220075 | D80: 27740 | E80: 2015 | F80: 3149 | G80: 3531 | H80: 10 | I80: 0.515 | J80: 0.71 | K80: 201923
A81: Evansville | B81: Evansville | C81: 150534 | D81: 21780 | E81: 2015 | F81: 4666 | G81: 3476 | H81: 14 | I81: 0.267 | J81: 0.31 | K81: 314321
A82: Fairfield | B82: Fairfield | C82: 129242 | D82: 35620 | E82: 2015 | F82: 1672 | G82: 1348 | H82: 9 | I82: 0.613 | J82: 0.594 | K82: 19833335
A83: FDU | B83: Fairleigh Dickinson | C83: 184603 | D83: 35620 | E83: 2015 | F83: 1828 | G83: 1155 | H83: 9 | I83: 0.207 | J83: 0.172 | K83: 19833335
... A102: Grambling | B102: Grambling | C102: 159009 | D102: 33740 | E102: 2015 | F102: 1583 | G102: 1781 | H102: 10 | I102: 0.115 | J102: 0.167 | K102: 209816
A103: Grand Canyon | B103: Grand Canyon | C103: 104717 | D103: 38060 | E103: 2015 | F103: 3779 | G103: 4652 | H103: 13 | K103: 4480231
A104: Green Bay | B104: Green Bay | C104: 240277 | D104: 24580 | E104: 2015 | F104: 3484 | G104: 3825 | H104: 10 | I104: 0.192 | J104: 0.5 | K104: 318318
A105: Hampton | B105: Hampton | C105: 232265 | D105: 47260 | E105: 2015 | F105: 3220 | G105: 2140 | H105: 10 | I105: 0.656 | J105: 0.633 | K105: 1768553
A106: Hartford | B106: Hartford | C106: 129525 | D106: 25540 | E106: 2015 | F106: 1935 | G106: 1413 | H106: 8 | I106: 0.567 | J106: 0.4 | K106: 1217677
A107: Harvard | B107: Harvard | C107: 166027 | D107: 14460 | E107: 2015 | F107: 4101 | G107: 3193 | H107: 12 | I107: 0.792 | J107: 0.609 | K107: 4812849
A108: Hawaii | B108: Hawaii | C108: 141574 | D108: 46520 | E108: 2015 | F108: 120776 | G108: 144235 | H108: 19 | I108: 0.759 | J108: 0.833 | K108: 1017588
A109: High Point | B109: High Point | C109: 198695 | D109: 24660 | E109: 2015 | F109: 6450 | G109: 5384 | H109: 10 | I109: 0.448 | J109: 0.516 | K109: 751915
A110: Hofstra | B110: Hofstra | C110: 191649 | D110: 35620 | E110: 2015 | F110: 3887 | G110: 2290 | H110: 17 | I110: 0.824 | J110: 0.531 | K110: 19833335
A111: Holy Cross | B111: Holy Cross | C111: 166124 | D111: 49340 | E111: 2015 | F111: 1800 | G111: 1639 | H111: 10 | I111: 0.259 | J111: 0.25 | K111: 951907
A112: Houston | B112: Houston | C112: 225511 | D112: 26420 | E112: 2015 | F112: 5973 | G112: 7922 | H112: 16 | I112: 0.438 | J112: 0.545 | K112: 6663204
A113: Houston Christian | B113: Houston Baptist | C113: 225399 | D113: 26420 | E113: 2015 | F113: 5678 | G113: 4889 | H113: 12 | I113: 0.469 | J113: 0.455 | K113: 6663204
A114: Howard | B114: Howard | C114: 131520 | D114: 47900 | E114: 2015 | F114: 939 | G114: 895 | H114: 7 | I114: 0.645 | J114: 0.656 | K114: 6132190
A115: Idaho | B115: Idaho | C115: 142285 | D115: 34140 | E115: 2015 | F115: 7499 | G115: 5157 | H115: 11 | I115: 0.517 | J115: 0.633 | K115: 38271
... A123: Iowa St. | B123: Iowa St. | C123: 153603 | D123: 11180 | E123: 2015 | F123: 34172 | G123: 29703 | H123: 14 | I123: 0.655 | J123: 0.643 | K123: 123658
A124: IUPUI | B124: IUPUI | C124: 151111 | D124: 26900 | E124: 2015 | K124: 1999191
A125: Jackson St. | B125: Jackson St. | C125: 175856 | D125: 27140 | E125: 2015 | F125: 3291 | G125: 2650 | H125: 7 | I125: 0.344 | J125: 0.344 | K125: 598752
A126: Jacksonville | B126: Jacksonville | C126: 134945 | D126: 27260 | E126: 2015 | F126: 2075 | G126: 2542 | H126: 14 | I126: 0.559 | J126: 0.882 | K126: 1457992
A127: Jacksonville St. | B127: Jacksonville St. | C127: 101480 | D127: 11500 | E127: 2015 | F127: 3384 | G127: 1617 | H127: 10 | I127: 0.529 | J127: 0.419 | K127: 116986
A128: James Madison | B128: James Madison | C128: 232423 | D128: 25500 | E128: 2015 | F128: 4338 | G128: 4423 | H128: 15 | I128: 0.548 | J128: 0.464 | K128: 131186
A129: Kansas | B129: Kansas | C129: 155317 | D129: 29940 | E129: 2015 | F129: 19283 | G129: 24733 | H129: 16 | I129: 0.71 | J129: 0.758 | K129: 116291
A130: Kansas City | B130: UMKC | C130: 178402 | D130: 28140 | E130: 2015 | F130: 3796 | G130: 3637 | H130: 9 | I130: 0.8 | J130: 0.517 | K130: 2098230
A131: Kansas St. | B131: Kansas St. | C131: 155399 | D131: 31740 | E131: 2015 | F131: 30759 | G131: 26573 | H131: 13 | I131: 0.71 | J131: 0.621 | K131: 139373
A132: Kennesaw St. | B132: Kennesaw St. | C132: 486840 | D132: 12060 | E132: 2015 | F132: 5176 | G132: 5325 | H132: 10 | I132: 0.345 | J132: 0.433 | K132: 5695668
A133: Kent St. | B133: Kent St. | C133: 203517 | D133: 10420 | E133: 2015 | F133: 3968 | G133: 3972 | H133: 12 | I133: 0.548 | J133: 0.4 | K133: 704604
A134: Kentucky | B134: Kentucky | C134: 157085 | D134: 30460 | E134: 2015 | F134: 30453 | G134: 26806 | H134: 20 | I134: 0.818 | J134: 0.71 | K134: 500115
A135: La Salle | B135: La Salle | C135: 213367 | D135: 37980 | E135: 2015 | F135: 1184 | G135: 1021 | H135: 13 | I135: 0.323 | J135: 0.031 | K135: 6130446
A136: Lafayette | B136: Lafayette | C136: 213385 | D136: 10900 | E136: 2015 | F136: 1710 | G136: 1887 | H136: 13 | I136: 0.214 | J136: 0.407 | K136: 838657
A137: Lamar University | B137: Lamar University | C137: 226091 | D137: 13140 | E137: 2015 | F137: 2167 | G137: 3963 | H137: 8 | I137: 0.179 | J137: 0.3 | K137: 397955
A138: Lehigh | B138: Lehigh | C138: 213543 | D138: 10900 | E138: 2015 | F138: 2293 | H138: 12 | I138: 0.688 | J138: 0.69 | K138: 838657
A139: Liberty | B139: Liberty | C139: 232557 | D139: 31340 | E139: 2015 | F139: 4678 | G139: 5814 | H139: 13 | I139: 0.697 | J139: 0.379 | K139: 258067
A140: Lipscomb | B140: Lipscomb | C140: 219976 | D140: 34980 | E140: 2015 | F140: 3410 | G140: 3959 | H140: 12 | I140: 0.7 | J140: 0.742 | K140: 1824091
A141: Little Rock | B141: Little Rock | C141: 106245 | D141: 30780 | E141: 2015 | F141: 4634 | G141: 2864 | H141: 11 | I141: 0.857 | J141: 0.645 | K141: 732412
A142: LIU | B142: LIU Brooklyn | C142: 192448 | D142: 35620 | E142: 2015 | F142: 2705 | G142: 2112 | H142: 13 | I142: 0.781 | J142: 0.742 | K142: 19833335
A143: LMU (CA) | B143: LMU (CA) | C143: 117946 | D143: 31080 | E143: 2015 | F143: 4708 | G143: 4010 | H143: 14 | I143: 0.742 | J143: 0.5 | K143: 13258364
A144: Long Beach St. | B144: Long Beach St. | C144: 110583 | D144: 31080 | E144: 2015 | F144: 17708 | G144: 18006 | H144: 16 | I144: 0.844 | J144: 0.621 | K144: 13258364
A145: Longwood | B145: Longwood | C145: 232566 | D145: 40060 | E145: 2015 | K145: 1254013
A146: Louisiana | B146: Louisiana | C146: 160658 | D146: 29180 | E146: 2015 | F146: 5060 | G146: 4834 | H146: 15 | I146: 0.606 | J146: 0.576 | K146: 483623
...
