Workbook

Sheet Sheet1
A1: RA6 | B1: University | C1: unitid | D1: FY | E1: TotalConcessions | F1: RealTotalConcessions | G1: TotalAdRev | H1: RealTotalAdRev | I1: TotalAdExp | J1: RealTotalAdExp | K1: TotalAttendance
A2: 2 | B2: Arizona | C2: 104179 | D2: 2017 | E2: 2934038 | F2: =E2/VLOOKUP($D2,CPI!$P$16:$R$22,3,FALSE) -> 3623594 | G2: 9900132 | H2: =G2/VLOOKUP($D2,CPI!$P$16:$R$22,3,FALSE) -> 12226856 | I2: 1469240 | J2: =I2/VLOOKUP($D2,CPI!$P$16:$R$22,3,FALSE) -> 1814540 | K2: =VLOOKUP(C2,Total!A:O,8,FALSE) -> 551769
A3: =IF(ISBLANK(A$2),"",$A$2) -> 2 | B3: =B2 -> Arizona | C3: 104179 | D3: =IF(D2=2023,2017,D2+1) -> 2018 | E3: 2433487 | F3: =E3/VLOOKUP($D3,CPI!$P$16:$R$22,3,FALSE) -> 2939155 | G3: 8865761 | H3: =G3/VLOOKUP($D3,CPI!$P$16:$R$22,3,FALSE) -> 10708027 | I3: 1620431 | J3: =I3/VLOOKUP($D3,CPI!$P$16:$R$22,3,FALSE) -> 1957149.5 | K3: =VLOOKUP(C3,Total!A:O,9,FALSE) -> 455423
A4: =IF(ISBLANK(A$2),"",$A$2) -> 2 | B4: =B3 -> Arizona | C4: 104179 | D4: =IF(D3=2023,2017,D3+1) -> 2019 | E4: 2110407 | F4: =E4/VLOOKUP($D4,CPI!$P$16:$R$22,3,FALSE) -> 2497185.3 | G4: 8763036 | H4: =G4/VLOOKUP($D4,CPI!$P$16:$R$22,3,FALSE) -> 10369054 | I4: 1501762 | J4: =I4/VLOOKUP($D4,CPI!$P$16:$R$22,3,FALSE) -> 1776992.8 | K4: =VLOOKUP(C4,Total!A:O,10,FALSE) -> 522517
A5: =IF(ISBLANK(A$2),"",$A$2) -> 2 | B5: =B4 -> Arizona | C5: 104179 | D5: =IF(D4=2023,2017,D4+1) -> 2020 | E5: 1876754 | F5: =E5/VLOOKUP($D5,CPI!$P$16:$R$22,3,FALSE) -> 2186510 | G5: 8370957 | H5: =G5/VLOOKUP($D5,CPI!$P$16:$R$22,3,FALSE) -> 9752573.3 | I5: 1482270 | J5: =I5/VLOOKUP($D5,CPI!$P$16:$R$22,3,FALSE) -> 1726916.9 | K5: =VLOOKUP(C5,Total!A:O,11,FALSE) -> 441655
A6: =IF(ISBLANK(A$2),"",$A$2) -> 2 | B6: =B5 -> Arizona | C6: 104179 | D6: =IF(D5=2023,2017,D5+1) -> 2021 | E6: 563251 | F6: =E6/VLOOKUP($D6,CPI!$P$16:$R$22,3,FALSE) -> 641451.02 | G6: 6874440 | H6: =G6/VLOOKUP($D6,CPI!$P$16:$R$22,3,FALSE) -> 7828865.9 | I6: 369632 | J6: =I6/VLOOKUP($D6,CPI!$P$16:$R$22,3,FALSE) -> 420950.56 | K6: =VLOOKUP(C6,Total!A:O,12,FALSE) -> 106443
A7: =IF(ISBLANK(A$2),"",$A$2) -> 2 | B7: =B6 -> Arizona | C7: 104179 | D7: =IF(D6=2023,2017,D6+1) -> 2022 | E7: 2456996 | F7: =E7/VLOOKUP($D7,CPI!$P$16:$R$22,3,FALSE) -> 2610853.9 | G7: 9512261 | H7: =G7/VLOOKUP($D7,CPI!$P$16:$R$22,3,FALSE) -> 10107922 | I7: 1608565 | J7: =I7/VLOOKUP($D7,CPI!$P$16:$R$22,3,FALSE) -> 1709293.9 | K7: =VLOOKUP(C7,Total!A:O,13,FALSE) -> 514933
A8: =IF(ISBLANK(A$2),"",$A$2) -> 2 | B8: =B7 -> Arizona | C8: 104179 | D8: =IF(D7=2023,2017,D7+1) -> 2023 | E8: 3656522 | F8: =E8/VLOOKUP($D8,CPI!$P$16:$R$22,3,FALSE) -> 3656522 | G8: 12468828 | H8: =G8/VLOOKUP($D8,CPI!$P$16:$R$22,3,FALSE) -> 12468828 | I8: 1769772 | J8: =I8/VLOOKUP($D8,CPI!$P$16:$R$22,3,FALSE) -> 1769772 | K8: =VLOOKUP(C8,Total!A:O,14,FALSE) -> 515674
A9: =IF(ISBLANK(A$2),"",$A$2) -> 2 | B9: California | C9: 110635 | D9: =IF(D8=2023,2017,D8+1) -> 2017 | E9: 835280 | F9: =E9/VLOOKUP($D9,CPI!$P$16:$R$22,3,FALSE) -> 1031587.1 | G9: 12847555 | H9: =G9/VLOOKUP($D9,CPI!$P$16:$R$22,3,FALSE) -> 15866980 | I9: 4075181 | J9: =I9/VLOOKUP($D9,CPI!$P$16:$R$22,3,FALSE) -> 5032927.8 | K9: =VLOOKUP(C9,Total!A:O,8,FALSE) -> 370402
A10: =IF(ISBLANK(A$2),"",$A$2) -> 2 | B10: =B9 -> California | C10: 110635 | D10: =IF(D9=2023,2017,D9+1) -> 2018 | E10: 662604 | F10: =E10/VLOOKUP($D10,CPI!$P$16:$R$22,3,FALSE) -> 800290.22 | G10: 21490730 | H10: =G10/VLOOKUP($D10,CPI!$P$16:$R$22,3,FALSE) -> 25956410 | I10: 3922991 | J10: =I10/VLOOKUP($D10,CPI!$P$16:$R$22,3,FALSE) -> 4738171.4 | K10: =VLOOKUP(C10,Total!A:O,9,FALSE) -> 303448
A11: =IF(ISBLANK(A$2),"",$A$2) -> 2 | B11: =B10 -> California | C11: 110635 | D11: =IF(D10=2023,2017,D10+1) -> 2019 | E11: 867441 | F11: =E11/VLOOKUP($D11,CPI!$P$16:$R$22,3,FALSE) -> 1026418.6 | G11: 17201102 | H11: =G11/VLOOKUP($D11,CPI!$P$16:$R$22,3,FALSE) -> 20353581 | I11: 4802534 | J11: =I11/VLOOKUP($D11,CPI!$P$16:$R$22,3,FALSE) -> 5682703.5 | K11: =VLOOKUP(C11,Total!A:O,10,FALSE) -> 376515
A12: =IF(ISBLANK(A$2),"",$A$2) -> 2 | B12: =B11 -> California | C12: 110635 | D12: =IF(D11=2023,2017,D11+1) -> 2020 | E12: 812075 | F12: =E12/VLOOKUP($D12,CPI!$P$16:$R$22,3,FALSE) -> 946107 | G12: 17907314 | H12: =G12/VLOOKUP($D12,CPI!$P$16:$R$22,3,FALSE) -> 20862894 | I12: 4446741 | J12: =I12/VLOOKUP($D12,CPI!$P$16:$R$22,3,FALSE) -> 5180670.2 | K12: =VLOOKUP(C12,Total!A:O,11,FALSE) -> 310066
A13: =IF(ISBLANK(A$2),"",$A$2) -> 2 | B13: =B12 -> California | C13: 110635 | D13: =IF(D12=2023,2017,D12+1) -> 2021 | E13: 74025 | F13: =E13/VLOOKUP($D13,CPI!$P$16:$R$22,3,FALSE) -> 84302.402 | G13: 9202835 | H13: =G13/VLOOKUP($D13,CPI!$P$16:$R$22,3,FALSE) -> 10480528 | I13: 1890830 | J13: =I13/VLOOKUP($D13,CPI!$P$16:$R$22,3,FALSE) -> 2153347 | K13: =VLOOKUP(C13,Total!A:O,12,FALSE) -> 21102
A14: =IF(ISBLANK(A$2),"",$A$2) -> 2 | B14: =B13 -> California | C14: 110635 | D14: =IF(D13=2023,2017,D13+1) -> 2022 | E14: 602939 | F14: =E14/VLOOKUP($D14,CPI!$P$16:$R$22,3,FALSE) -> 640695.24 | G14: 13083897 | H14: =G14/VLOOKUP($D14,CPI!$P$16:$R$22,3,FALSE) -> 13903215 | I14: 4244985 | J14: =I14/VLOOKUP($D14,CPI!$P$16:$R$22,3,FALSE) -> 4510807.4 | K14: =VLOOKUP(C14,Total!A:O,13,FALSE) -> 288739
A15: =IF(ISBLANK(A$2),"",$A$2) -> 2 | B15: =B14 -> California | C15: 110635 | D15: =IF(D14=2023,2017,D14+1) -> 2023 | E15: 899070 | F15: =E15/VLOOKUP($D15,CPI!$P$16:$R$22,3,FALSE) -> 899070 | G15: 14449998 | H15: =G15/VLOOKUP($D15,CPI!$P$16:$R$22,3,FALSE) -> 14449998 | I15: 8105193 | J15: =I15/VLOOKUP($D15,CPI!$P$16:$R$22,3,FALSE) -> 8105193 | K15: =VLOOKUP(C15,Total!A:O,14,FALSE) -> 320988
A16: =IF(ISBLANK(A$2),"",$A$2) -> 2 | B16: Colorado | C16: 126614 | D16: =IF(D15=2023,2017,D15+1) -> 2017 | E16: 1617492 | F16: =E16/VLOOKUP($D16,CPI!$P$16:$R$22,3,FALSE) -> 1997634.1 | G16: 6416499 | H16: =G16/VLOOKUP($D16,CPI!$P$16:$R$22,3,FALSE) -> 7924501.1 | I16: 1885874 | J16: =I16/VLOOKUP($D16,CPI!$P$16:$R$22,3,FALSE) -> 2329091.1 | K16: =VLOOKUP(C16,Total!A:O,8,FALSE) -> 351226
A17: =IF(ISBLANK(A$2),"",$A$2) -> 2 | B17: =B16 -> Colorado | C17: 126614 | D17: =IF(D16=2023,2017,D16+1) -> 2018 | E17: 1638587 | F17: =E17/VLOOKUP($D17,CPI!$P$16:$R$22,3,FALSE) -> 1979078.2 | G17: 7281345 | H17: =G17/VLOOKUP($D17,CPI!$P$16:$R$22,3,FALSE) -> 8794376.7 | I17: 1854403 | J17: =I17/VLOOKUP($D17,CPI!$P$16:$R$22,3,FALSE) -> 2239739.9 | K17: =VLOOKUP(C17,Total!A:O,9,FALSE) -> 344020
A18: =IF(ISBLANK(A$2),"",$A$2) -> 2 | B18: =B17 -> Colorado | C18: 126614 | D18: =IF(D17=2023,2017,D17+1) -> 2019 | E18: 2307881 | F18: =E18/VLOOKUP($D18,CPI!$P$16:$R$22,3,FALSE) -> 2730850.7 | G18: 8742848 | H18: =G18/VLOOKUP($D18,CPI!$P$16:$R$22,3,FALSE) -> 10345166 | I18: 1782701 | J18: =I18/VLOOKUP($D18,CPI!$P$16:$R$22,3,FALSE) -> 2109420 | K18: =VLOOKUP(C18,Total!A:O,10,FALSE) -> 339747
A19: =IF(ISBLANK(A$2),"",$A$2) -> 2 | B19: =B18 -> Colorado | C19: 126614 | D19: =IF(D18=2023,2017,D18+1) -> 2020 | E19: 3868507 | F19: =E19/VLOOKUP($D19,CPI!$P$16:$R$22,3,FALSE) -> 4506999.4 | G19: 7105608 | H19: =G19/VLOOKUP($D19,CPI!$P$16:$R$22,3,FALSE) -> 8278380 | I19: 1007477 | J19: =I19/VLOOKUP($D19,CPI!$P$16:$R$22,3,FALSE) -> 1173759.9 | K19: =VLOOKUP(C19,Total!A:O,11,FALSE) -> 359954
A20: =IF(ISBLANK(A$2),"",$A$2) -> 2 | B20: =B19 -> Colorado | C20: 126614 | D20: =IF(D19=2023,2017,D19+1) -> 2021 | E20: 73564 | F20: =E20/VLOOKUP($D20,CPI!$P$16:$R$22,3,FALSE) -> 83777.398 | G20: 7578753 | H20: =G20/VLOOKUP($D20,CPI!$P$16:$R$22,3,FALSE) -> 8630963.6 | I20: 187544 | J20: =I20/VLOOKUP($D20,CPI!$P$16:$R$22,3,FALSE) -> 213582.03 | K20: =VLOOKUP(C20,Total!A:O,12,FALSE) -> 1588
A21: =IF(ISBLANK(A$2),"",$A$2) -> 2 | B21: =B20 -> Colorado | C21: 126614 | D21: =IF(D20=2023,2017,D20+1) -> 2022 | E21: 2722208 | F21: =E21/VLOOKUP($D21,CPI!$P$16:$R$22,3,FALSE) -> 2892673.6 | G21: 5911440 | H21: =G21/VLOOKUP($D21,CPI!$P$16:$R$22,3,FALSE) -> 6281616.4 | I21: 821185 | J21: =I21/VLOOKUP($D21,CPI!$P$16:$R$22,3,FALSE) -> 872607.88 | K21: =VLOOKUP(C21,Total!A:O,13,FALSE) -> 328750
A22: =IF(ISBLANK(A$2),"",$A$2) -> 2 | B22: =B21 -> Colorado | C22: 126614 | D22: =IF(D21=2023,2017,D21+1) -> 2023 | E22: 2249977 | F22: =E22/VLOOKUP($D22,CPI!$P$16:$R$22,3,FALSE) -> 2249977 | G22: 6674982 | H22: =G22/VLOOKUP($D22,CPI!$P$16:$R$22,3,FALSE) -> 6674982 | I22: 1187198 | J22: =I22/VLOOKUP($D22,CPI!$P$16:$R$22,3,FALSE) -> 1187198 | K22: =VLOOKUP(C22,Total!A:O,14,FALSE) -> 315103
A23: =IF(ISBLANK(A$2),"",$A$2) -> 2 | B23: Maryland Baltimore County | C23: 163268 | D23: =IF(D22=2023,2017,D22+1) -> 2017 | E23: 0 | F23: =E23/VLOOKUP($D23,CPI!$P$16:$R$22,3,FALSE) -> 0 | G23: 267785 | H23: =G23/VLOOKUP($D23,CPI!$P$16:$R$22,3,FALSE) -> 330719.69 | I23: 214800 | J23: =I23/VLOOKUP($D23,CPI!$P$16:$R$22,3,FALSE) -> 265282.18 | K23: =VLOOKUP(C23,Total!A:O,8,FALSE) -> 33569
A24: =IF(ISBLANK(A$2),"",$A$2) -> 2 | B24: =B23 -> Maryland Baltimore County | C24: 163268 | D24: =IF(D23=2023,2017,D23+1) -> 2018 | E24: 0 | F24: =E24/VLOOKUP($D24,CPI!$P$16:$R$22,3,FALSE) -> 0 | G24: 10408 | H24: =G24/VLOOKUP($D24,CPI!$P$16:$R$22,3,FALSE) -> 12570.737 | I24: 216275 | J24: =I24/VLOOKUP($D24,CPI!$P$16:$R$22,3,FALSE) -> 261216 | K24: =VLOOKUP(C24,Total!A:O,9,FALSE) -> 37456
A25: =IF(ISBLANK(A$2),"",$A$2) -> 2 | B25: =B24 -> Maryland Baltimore County | C25: 163268 | D25: =IF(D24=2023,2017,D24+1) -> 2019 | E25: 0 | F25: =E25/VLOOKUP($D25,CPI!$P$16:$R$22,3,FALSE) -> 0 | G25: 145623 | H25: =G25/VLOOKUP($D25,CPI!$P$16:$R$22,3,FALSE) -> 172311.6 | I25: 116822 | J25: =I25/VLOOKUP($D25,CPI!$P$16:$R$22,3,FALSE) -> 138232.19 | K25: =VLOOKUP(C25,Total!A:O,10,FALSE) -> 40248
A26: =IF(ISBLANK(A$2),"",$A$2) -> 2 | B26: =B25 -> Maryland Baltimore County | C26: 163268 | D26: =IF(D25=2023,2017,D25+1) -> 2020 | E26: 0 | F26: =E26/VLOOKUP($D26,CPI!$P$16:$R$22,3,FALSE) -> 0 | G26: 85087 | H26: =G26/VLOOKUP($D26,CPI!$P$16:$R$22,3,FALSE) -> 99130.506 | I26: 99303 | J26: =I26/VLOOKUP($D26,CPI!$P$16:$R$22,3,FALSE) -> 115692.84 | K26: =VLOOKUP(C26,Total!A:O,11,FALSE) -> 19692
A27: =IF(ISBLANK(A$2),"",$A$2) -> 2 | B27: =B26 -> Maryland Baltimore County | C27: 163268 | D27: =IF(D26=2023,2017,D26+1) -> 2021 | E27: 0 | F27: =E27/VLOOKUP($D27,CPI!$P$16:$R$22,3,FALSE) -> 0 | G27: 92788 | H27: =G27/VLOOKUP($D27,CPI!$P$16:$R$22,3,FALSE) -> 105670.4 | I27: 17092 | J27: =I27/VLOOKUP($D27,CPI!$P$16:$R$22,3,FALSE) -> 19465 | K27: =VLOOKUP(C27,Total!A:O,12,FALSE) -> 6144
A28: =IF(ISBLANK(A$2),"",$A$2) -> 2 | B28: =B27 -> Maryland Baltimore County | C28: 163268 | D28: =IF(D27=2023,2017,D27+1) -> 2022 | E28: 0 | F28: =E28/VLOOKUP($D28,CPI!$P$16:$R$22,3,FALSE) -> 0 | G28: 146229 | H28: =G28/VLOOKUP($D28,CPI!$P$16:$R$22,3,FALSE) -> 155385.91 | I28: 88199 | J28: =I28/VLOOKUP($D28,CPI!$P$16:$R$22,3,FALSE) -> 93722.051 | K28: =VLOOKUP(C28,Total!A:O,13,FALSE) -> 44218
A29: =IF(ISBLANK(A$2),"",$A$2) -> 2 | B29: =B28 -> Maryland Baltimore County | C29: 163268 | D29: =IF(D28=2023,2017,D28+1) -> 2023 | E29: 0 | F29: =E29/VLOOKUP($D29,CPI!$P$16:$R$22,3,FALSE) -> 0 | G29: 267593 | H29: =G29/VLOOKUP($D29,CPI!$P$16:$R$22,3,FALSE) -> 267593 | I29: 115335 | J29: =I29/VLOOKUP($D29,CPI!$P$16:$R$22,3,FALSE) -> 115335 | K29: =VLOOKUP(C29,Total!A:O,14,FALSE) -> 46741
A30: =IF(ISBLANK(A$2),"",$A$2) -> 2 | B30: North Carolina Wilmington | C30: 199218 | D30: 2017 | E30: 0 | F30: =E30/VLOOKUP($D30,CPI!$P$16:$R$22,3,FALSE) -> 0 | G30: 510225 | H30: =G30/VLOOKUP($D30,CPI!$P$16:$R$22,3,FALSE) -> 630137.8 | I30: 124676 | J30: =I30/VLOOKUP($D30,CPI!$P$16:$R$22,3,FALSE) -> 153977.29 | K30: =VLOOKUP(C30,Total!A:O,8,FALSE) -> 77225
A31: =IF(ISBLANK(A$2),"",$A$2) -> 2 | B31: =B30 -> North Carolina Wilmington | C31: 199218 | D31: =IF(D30=2023,2017,D30+1) -> 2018 | E31: 0 | F31: =E31/VLOOKUP($D31,CPI!$P$16:$R$22,3,FALSE) -> 0 | G31: 568950 | H31: =G31/VLOOKUP($D31,CPI!$P$16:$R$22,3,FALSE) -> 687175.33 | I31: 128120 | J31: =I31/VLOOKUP($D31,CPI!$P$16:$R$22,3,FALSE) -> 154742.78 | K31: =VLOOKUP(C31,Total!A:O,9,FALSE) -> 66942
A32: =IF(ISBLANK(A$2),"",$A$2) -> 2 | B32: =B31 -> North Carolina Wilmington | C32: 199218 | D32: =IF(D31=2023,2017,D31+1) -> 2019 | E32: 0 | F32: =E32/VLOOKUP($D32,CPI!$P$16:$R$22,3,FALSE) -> 0 | G32: 549897 | H32: =G32/VLOOKUP($D32,CPI!$P$16:$R$22,3,FALSE) -> 650677.67 | I32: 113372 | J32: =I32/VLOOKUP($D32,CPI!$P$16:$R$22,3,FALSE) -> 134149.9 | K32: =VLOOKUP(C32,Total!A:O,10,FALSE) -> 45082
A33: =IF(ISBLANK(A$2),"",$A$2) -> 2 | B33: =B32 -> North Carolina Wilmington | C33: 199218 | D33: =IF(D32=2023,2017,D32+1) -> 2020 | E33: 0 | F33: =E33/VLOOKUP($D33,CPI!$P$16:$R$22,3,FALSE) -> 0 | G33: 583414 | H33: =G33/VLOOKUP($D33,CPI!$P$16:$R$22,3,FALSE) -> 679705.77 | I33: 103920 | J33: =I33/VLOOKUP($D33,CPI!$P$16:$R$22,3,FALSE) -> 121071.87 | K33: =VLOOKUP(C33,Total!A:O,11,FALSE) -> 44205
A34: =IF(ISBLANK(A$2),"",$A$2) -> 2 | B34: =B33 -> North Carolina Wilmington | C34: 199218 | D34: =IF(D33=2023,2017,D33+1) -> 2021 | E34: 0 | F34: =E34/VLOOKUP($D34,CPI!$P$16:$R$22,3,FALSE) -> 0 | G34: 309314 | H34: =G34/VLOOKUP($D34,CPI!$P$16:$R$22,3,FALSE) -> 352258.2 | I34: 10578 | J34: =I34/VLOOKUP($D34,CPI!$P$16:$R$22,3,FALSE) -> 12046.617 | K34: =VLOOKUP(C34,Total!A:O,12,FALSE) -> 36711
A35: =IF(ISBLANK(A$2),"",$A$2) -> 2 | B35: =B34 -> North Carolina Wilmington | C35: 199218 | D35: =IF(D34=2023,2017,D34+1) -> 2022 | E35: 0 | F35: =E35/VLOOKUP($D35,CPI!$P$16:$R$22,3,FALSE) -> 0 | G35: 514794 | H35: =G35/VLOOKUP($D35,CPI!$P$16:$R$22,3,FALSE) -> 547030.57 | I35: 65710 | J35: =I35/VLOOKUP($D35,CPI!$P$16:$R$22,3,FALSE) -> 69824.782 | K35: =VLOOKUP(C35,Total!A:O,13,FALSE) -> 57240
A36: =IF(ISBLANK(A$2),"",$A$2) -> 2 | B36: =B35 -> North Carolina Wilmington | C36: 199218 | D36: =IF(D35=2023,2017,D35+1) -> 2023 | E36: 0 | F36: =E36/VLOOKUP($D36,CPI!$P$16:$R$22,3,FALSE) -> 0 | G36: 791926 | H36: =G36/VLOOKUP($D36,CPI!$P$16:$R$22,3,FALSE) -> 791926 | I36: 106227 | J36: =I36/VLOOKUP($D36,CPI!$P$16:$R$22,3,FALSE) -> 106227 | K36: =VLOOKUP(C36,Total!A:O,14,FALSE) -> 29648
A37: =IF(ISBLANK(A$2),"",$A$2) -> 2 | B37: Oregon State | C37: 209542 | D37: =IF(D36=2023,2017,D36+1) -> 2017 | E37: 946108 | F37: =E37/VLOOKUP($D37,CPI!$P$16:$R$22,3,FALSE) -> 1168461.8 | G37: 8884197 | H37: =G37/VLOOKUP($D37,CPI!$P$16:$R$22,3,FALSE) -> 10972156 | I37: 3023142 | J37: =I37/VLOOKUP($D37,CPI!$P$16:$R$22,3,FALSE) -> 3733639.2 | K37: =VLOOKUP(C37,Total!A:O,8,FALSE) -> 480132
A38: =IF(ISBLANK(A$2),"",$A$2) -> 2 | B38: =B37 -> Oregon State | C38: 209542 | D38: =IF(D37=2023,2017,D37+1) -> 2018 | E38: 1077705 | F38: =E38/VLOOKUP($D38,CPI!$P$16:$R$22,3,FALSE) -> 1301647.4 | G38: 7695860 | H38: =G38/VLOOKUP($D38,CPI!$P$16:$R$22,3,FALSE) -> 9295026.1 | I38: 1881904 | J38: =I38/VLOOKUP($D38,CPI!$P$16:$R$22,3,FALSE) -> 2272955.4 | K38: =VLOOKUP(C38,Total!A:O,9,FALSE) -> 424599
A39: =IF(ISBLANK(A$2),"",$A$2) -> 2 | B39: =B38 -> Oregon State | C39: 209542 | D39: =IF(D38=2023,2017,D38+1) -> 2019 | E39: 1439503 | F39: =E39/VLOOKUP($D39,CPI!$P$16:$R$22,3,FALSE) -> 1703323.5 | G39: 8203013 | H39: =G39/VLOOKUP($D39,CPI!$P$16:$R$22,3,FALSE) -> 9706394.8 | I39: 1862983 | J39: =I39/VLOOKUP($D39,CPI!$P$16:$R$22,3,FALSE) -> 2204415.4 | K39: =VLOOKUP(C39,Total!A:O,10,FALSE) -> 347403
A40: =IF(ISBLANK(A$2),"",$A$2) -> 2 | B40: =B39 -> Oregon State | C40: 209542 | D40: =IF(D39=2023,2017,D39+1) -> 2020 | E40: 1007113 | F40: =E40/VLOOKUP($D40,CPI!$P$16:$R$22,3,FALSE) -> 1173335.8 | G40: 7501576 | H40: =G40/VLOOKUP($D40,CPI!$P$16:$R$22,3,FALSE) -> 8739702 | I40: 1778519 | J40: =I40/VLOOKUP($D40,CPI!$P$16:$R$22,3,FALSE) -> 2072061.4 | K40: =VLOOKUP(C40,Total!A:O,11,FALSE) -> 324109
A41: =IF(ISBLANK(A$2),"",$A$2) -> 2 | B41: =B40 -> Oregon State | C41: 209542 | D41: =IF(D40=2023,2017,D40+1) -> 2021 | E41: 384877 | F41: =E41/VLOOKUP($D41,CPI!$P$16:$R$22,3,FALSE) -> 438312.13 | G41: 5629884 | H41: =G41/VLOOKUP($D41,CPI!$P$16:$R$22,3,FALSE) -> 6411519.6 | I41: 1268919 | J41: =I41/VLOOKUP($D41,CPI!$P$16:$R$22,3,FALSE) -> 1445091.8 | K41: =VLOOKUP(C41,Total!A:O,12,FALSE) -> 127035
A42: =IF(ISBLANK(A$2),"",$A$2) -> 2 | B42: =B41 -> Oregon State | C42: 209542 | D42: =IF(D41=2023,2017,D41+1) -> 2022 | E42: 529965 | F42: =E42/VLOOKUP($D42,CPI!$P$16:$R$22,3,FALSE) -> 563151.59 | G42: 8222413 | H42: =G42/VLOOKUP($D42,CPI!$P$16:$R$22,3,FALSE) -> 8737303.3 | I42: 1819187 | J42: =I42/VLOOKUP($D42,CPI!$P$16:$R$22,3,FALSE) -> 1933105.1 | K42: =VLOOKUP(C42,Total!A:O,13,FALSE) -> 378012
A43: =IF(ISBLANK(A$2),"",$A$2) -> 2 | B43: =B42 -> Oregon State | C43: 209542 | D43: =IF(D42=2023,2017,D42+1) -> 2023 | E43: 1493441 | F43: =E43/VLOOKUP($D43,CPI!$P$16:$R$22,3,FALSE) -> 1493441 | G43: 10041519 | H43: =G43/VLOOKUP($D43,CPI!$P$16:$R$22,3,FALSE) -> 10041519 | I43: 2093660 | J43: =I43/VLOOKUP($D43,CPI!$P$16:$R$22,3,FALSE) -> 2093660 | K43: =VLOOKUP(C43,Total!A:O,14,FALSE) -> 271417
A44: =IF(ISBLANK(A$2),"",$A$2) -> 2 | B44: Portland State | C44: 209807 | D44: =IF(D43=2023,2017,D43+1) -> 2017 | E44: 2762 | F44: =E44/VLOOKUP($D44,CPI!$P$16:$R$22,3,FALSE) -> 3411.1238 | G44: 186334 | H44: =G44/VLOOKUP($D44,CPI!$P$16:$R$22,3,FALSE) -> 230126.12 | I44: 114646 | J44: =I44/VLOOKUP($D44,CPI!$P$16:$R$22,3,FALSE) -> 141590.04 | K44: =VLOOKUP(C44,Total!A:O,8,FALSE) -> 33613
A45: =IF(ISBLANK(A$2),"",$A$2) -> 2 | B45: =B44 -> Portland State | C45: 209807 | D45: =IF(D44=2023,2017,D44+1) -> 2018 | E45: 6193 | F45: =E45/VLOOKUP($D45,CPI!$P$16:$R$22,3,FALSE) -> 7479.8784 | G45: 105890 | H45: =G45/VLOOKUP($D45,CPI!$P$16:$R$22,3,FALSE) -> 127893.48 | I45: 46036 | J45: =I45/VLOOKUP($D45,CPI!$P$16:$R$22,3,FALSE) -> 55602.08 | K45: =VLOOKUP(C45,Total!A:O,9,FALSE) -> 29273
A46: =IF(ISBLANK(A$2),"",$A$2) -> 2 | B46: =B45 -> Portland State | C46: 209807 | D46: =IF(D45=2023,2017,D45+1) -> 2019 | E46: 0 | F46: =E46/VLOOKUP($D46,CPI!$P$16:$R$22,3,FALSE) -> 0 | G46: 314872 | H46: =G46/VLOOKUP($D46,CPI!$P$16:$R$22,3,FALSE) -> 372579.19 | I46: 138199 | J46: =I46/VLOOKUP($D46,CPI!$P$16:$R$22,3,FALSE) -> 163526.99 | K46: =VLOOKUP(C46,Total!A:O,10,FALSE) -> 34099
A47: =IF(ISBLANK(A$2),"",$A$2) -> 2 | B47: =B46 -> Portland State | C47: 209807 | D47: =IF(D46=2023,2017,D46+1) -> 2020 | E47: 0 | F47: =E47/VLOOKUP($D47,CPI!$P$16:$R$22,3,FALSE) -> 0 | G47: 281762 | H47: =G47/VLOOKUP($D47,CPI!$P$16:$R$22,3,FALSE) -> 328266.48 | I47: 215506 | J47: =I47/VLOOKUP($D47,CPI!$P$16:$R$22,3,FALSE) -> 251075 | K47: =VLOOKUP(C47,Total!A:O,11,FALSE) -> 36118
A48: =IF(ISBLANK(A$2),"",$A$2) -> 2 | B48: =B47 -> Portland State | C48: 209807 | D48: =IF(D47=2023,2017,D47+1) -> 2021 | E48: 0 | F48: =E48/VLOOKUP($D48,CPI!$P$16:$R$22,3,FALSE) -> 0 | G48: 94171 | H48: =G48/VLOOKUP($D48,CPI!$P$16:$R$22,3,FALSE) -> 107245.41 | I48: 87596 | J48: =I48/VLOOKUP($D48,CPI!$P$16:$R$22,3,FALSE) -> 99757.557 | K48: =VLOOKUP(C48,Total!A:O,12,FALSE) -> 1492
A49: =IF(ISBLANK(A$2),"",$A$2) -> 2 | B49: =B48 -> Portland State | C49: 209807 | D49: =IF(D48=2023,2017,D48+1) -> 2022 | E49: 0 | F49: =E49/VLOOKUP($D49,CPI!$P$16:$R$22,3,FALSE) -> 0 | G49: 251416 | H49: =G49/VLOOKUP($D49,CPI!$P$16:$R$22,3,FALSE) -> 267159.75 | I49: 109282 | J49: =I49/VLOOKUP($D49,CPI!$P$16:$R$22,3,FALSE) -> 116125.28 | K49: =VLOOKUP(C49,Total!A:O,13,FALSE) -> 29728
A50: =IF(ISBLANK(A$2),"",$A$2) -> 2 | B50: =B49 -> Portland State | C50: 209807 | D50: =IF(D49=2023,2017,D49+1) -> 2023 | E50: 0 | F50: =E50/VLOOKUP($D50,CPI!$P$16:$R$22,3,FALSE) -> 0 | G50: 451157 | H50: =G50/VLOOKUP($D50,CPI!$P$16:$R$22,3,FALSE) -> 451157 | I50: 318775 | J50: =I50/VLOOKUP($D50,CPI!$P$16:$R$22,3,FALSE) -> 318775 | K50: =VLOOKUP(C50,Total!A:O,14,FALSE) -> 31799
A51: =IF(ISBLANK(A$2),"",$A$2) -> 2 | B51: Weber State | C51: 230782 | D51: =IF(D50=2023,2017,D50+1) -> 2017 | E51: 2323 | F51: =E51/VLOOKUP($D51,CPI!$P$16:$R$22,3,FALSE) -> 2868.9502 | G51: 678551 | H51: =G51/VLOOKUP($D51,CPI!$P$16:$R$22,3,FALSE) -> 838023.69 | I51: 524588 | J51: =I51/VLOOKUP($D51,CPI!$P$16:$R$22,3,FALSE) -> 647876.39 | K51: =VLOOKUP(C51,Total!A:O,8,FALSE) -> 70489
A52: =IF(ISBLANK(A$2),"",$A$2) -> 2 | B52: =B51 -> Weber State | C52: 230782 | D52: =IF(D51=2023,2017,D51+1) -> 2018 | E52: 11215 | F52: =E52/VLOOKUP($D52,CPI!$P$16:$R$22,3,FALSE) -> 13545.428 | G52: 849611 | H52: =G52/VLOOKUP($D52,CPI!$P$16:$R$22,3,FALSE) -> 1026156.5 | I52: 658083 | J52: =I52/VLOOKUP($D52,CPI!$P$16:$R$22,3,FALSE) -> 794829.78 | K52: =VLOOKUP(C52,Total!A:O,9,FALSE) -> 79842
A53: =IF(ISBLANK(A$2),"",$A$2) -> 2 | B53: =B52 -> Weber State | C53: 230782 | D53: =IF(D52=2023,2017,D52+1) -> 2019 | E53: 14023 | F53: =E53/VLOOKUP($D53,CPI!$P$16:$R$22,3,FALSE) -> 16593.022 | G53: 510817 | H53: =G53/VLOOKUP($D53,CPI!$P$16:$R$22,3,FALSE) -> 604435.4 | I53: 344497 | J53: =I53/VLOOKUP($D53,CPI!$P$16:$R$22,3,FALSE) -> 407633.62 | K53: =VLOOKUP(C53,Total!A:O,10,FALSE) -> 80581
A54: =IF(ISBLANK(A$2),"",$A$2) -> 2 | B54: =B53 -> Weber State | C54: 230782 | D54: =IF(D53=2023,2017,D53+1) -> 2020 | E54: 21160 | F54: =E54/VLOOKUP($D54,CPI!$P$16:$R$22,3,FALSE) -> 24652.432 | G54: 476578 | H54: =G54/VLOOKUP($D54,CPI!$P$16:$R$22,3,FALSE) -> 555236.62 | I54: 312828 | J54: =I54/VLOOKUP($D54,CPI!$P$16:$R$22,3,FALSE) -> 364459.88 | K54: =VLOOKUP(C54,Total!A:O,11,FALSE) -> 71817
A55: =IF(ISBLANK(A$2),"",$A$2) -> 2 | B55: =B54 -> Weber State | C55: 230782 | D55: =IF(D54=2023,2017,D54+1) -> 2021 | E55: 9626 | F55: =E55/VLOOKUP($D55,CPI!$P$16:$R$22,3,FALSE) -> 10962.444 | G55: 160023 | H55: =G55/VLOOKUP($D55,CPI!$P$16:$R$22,3,FALSE) -> 182240.1 | I55: 198894 | J55: =I55/VLOOKUP($D55,CPI!$P$16:$R$22,3,FALSE) -> 226507.83 | K55: =VLOOKUP(C55,Total!A:O,12,FALSE) -> 19912
A56: =IF(ISBLANK(A$2),"",$A$2) -> 2 | B56: =B55 -> Weber State | C56: 230782 | D56: =IF(D55=2023,2017,D55+1) -> 2022 | E56: 13481 | F56: =E56/VLOOKUP($D56,CPI!$P$16:$R$22,3,FALSE) -> 14325.185 | G56: 547550 | H56: =G56/VLOOKUP($D56,CPI!$P$16:$R$22,3,FALSE) -> 581837.76 | I56: 381113 | J56: =I56/VLOOKUP($D56,CPI!$P$16:$R$22,3,FALSE) -> 404978.42 | K56: =VLOOKUP(C56,Total!A:O,13,FALSE) -> 52398
A57: =IF(ISBLANK(A$2),"",$A$2) -> 2 | B57: =B56 -> Weber State | C57: 230782 | D57: =IF(D56=2023,2017,D56+1) -> 2023 | E57: 19175 | F57: =E57/VLOOKUP($D57,CPI!$P$16:$R$22,3,FALSE) -> 19175 | G57: 891844 | H57: =G57/VLOOKUP($D57,CPI!$P$16:$R$22,3,FALSE) -> 891844 | I57: 400596 | J57: =I57/VLOOKUP($D57,CPI!$P$16:$R$22,3,FALSE) -> 400596 | K57: =VLOOKUP(C57,Total!A:O,14,FALSE) -> 73458

Sheet Sheet2
A1: RA6 | B1: Sex | C1: Code | D1: FY | E1: unitid | F1: University | G1: Gender | H1: Sport | I1: Concessions | J1: RealConcessions | K1: AdRev | L1: RealAdRev | M1: AdExp | N1: RealAdExp | O1: Attendance
A2: 2 | B2: =IF(ISBLANK(G2),"",IF(MID(G2,1,1)="M",0,1)) -> 0 | C2: =IF(ISBLANK(H2),"",VLOOKUP(H2,Code!B:C,2,FALSE)) -> 1 | D2: 2017 | E2: 104179 | F2: Arizona | G2: Male | H2: Baseball | I2: {=IF(B2=0,INDEX('Category 14'!F:F,MATCH(C2&E2&D2,'Category 14'!B:B&'Category 14'!C:C&'Category 14'!A:A,0)),INDEX('Category 14'!G:G,MATCH(C2&E2&D2,'Category 14'!B:B&'Category 14'!C:C&'Category 14'!A:A,0)))} -> 23795 | J2: =I2/VLOOKUP($D2,CPI!$P$16:$R$22,3,FALSE) -> 29387.288 | K2: {=IF(B2=0,INDEX('Category 15'!F:F,MATCH(C2&E2&D2,'Category 15'!B:B&'Category 15'!C:C&'Category 15'!A:A,0)),INDEX('Category 15'!G:G,MATCH(C2&E2&D2,'Category 15'!B:B&'Category 31'!C:C&'Category 15'!A:A,0)))} -> 0 | L2: =K2/VLOOKUP($D2,CPI!$P$16:$R$22,3,FALSE) -> 0 | M2: {=IF(B2=0,INDEX('Category 31'!F:F,MATCH(C2&E2&D2,'Category 31'!B:B&'Category 31'!C:C&'Category 31'!A:A,0)),INDEX('Category 31'!G:G,MATCH(C2&E2&D2,'Category 31'!B:B&'Category 31'!C:C&'Category 31'!A:A,0)))} -> 0 | N2: =M2/VLOOKUP($D2,CPI!$P$16:$R$22,3,FALSE) -> 0 | O2: =VLOOKUP(E2,MBaseball!C:O,6,FALSE) -> 103896
A3: 2 | B3: =IF(ISBLANK(G3),"",IF(MID(G3,1,1)="M",0,1)) -> 0 | C3: =IF(ISBLANK(H3),"",VLOOKUP(H3,Code!B:C,2,FALSE)) -> 2 | D3: 2017 | E3: 104179 | F3: Arizona | G3: Male | H3: Basketball | I3: {=IF(B3=0,INDEX('Category 14'!F:F,MATCH(C3&E3&D3,'Category 14'!B:B&'Category 14'!C:C&'Category 14'!A:A,0)),INDEX('Category 14'!G:G,MATCH(C3&E3&D3,'Category 14'!B:B&'Category 14'!C:C&'Category 14'!A:A,0)))} -> 353895 | J3: =I3/VLOOKUP($D3,CPI!$P$16:$R$22,3,FALSE) -> 437067.21 | K3: {=IF(B3=0,INDEX('Category 15'!F:F,MATCH(C3&E3&D3,'Category 15'!B:B&'Category 15'!C:C&'Category 15'!A:A,0)),INDEX('Category 15'!G:G,MATCH(C3&E3&D3,'Category 15'!B:B&'Category 31'!C:C&'Category 15'!A:A,0)))} -> 4950066 | L3: =K3/VLOOKUP($D3,CPI!$P$16:$R$22,3,FALSE) -> 6113427.8 | M3: 0 | N3: =M3/VLOOKUP($D3,CPI!$P$16:$R$22,3,FALSE) -> 0 | O3: =VLOOKUP(E3,MBasketball!C:P,6,FALSE) -> 230560
A4: 2 | B4: =IF(ISBLANK(G4),"",IF(MID(G4,1,1)="M",0,1)) -> 0 | C4: =IF(ISBLANK(H4),"",VLOOKUP(H4,Code!B:C,2,FALSE)) -> 8 | D4: 2017 | E4: 104179 | F4: Arizona | G4: Male | H4: Football | I4: {=IF(B4=0,INDEX('Category 14'!F:F,MATCH(C4&E4&D4,'Category 14'!B:B&'Category 14'!C:C&'Category 14'!A:A,0)),INDEX('Category 14'!G:G,MATCH(C4&E4&D4,'Category 14'!B:B&'Category 14'!C:C&'Category 14'!A:A,0)))} -> 659525 | J4: =I4/VLOOKUP($D4,CPI!$P$16:$R$22,3,FALSE) -> 814526.21 | K4: {=IF(B4=0,INDEX('Category 15'!F:F,MATCH(C4&E4&D4,'Category 15'!B:B&'Category 15'!C:C&'Category 15'!A:A,0)),INDEX('Category 15'!G:G,MATCH(C4&E4&D4,'Category 15'!B:B&'Category 31'!C:C&'Category 15'!A:A,0)))} -> 4950066 | L4: =K4/VLOOKUP($D4,CPI!$P$16:$R$22,3,FALSE) -> 6113427.8 | M4: {=IF(B4=0,INDEX('Category 31'!F:F,MATCH(C4&E4&D4,'Category 31'!B:B&'Category 31'!C:C&'Category 31'!A:A,0)),INDEX('Category 31'!G:G,MATCH(C4&E4&D4,'Category 31'!B:B&'Category 31'!C:C&'Category 31'!A:A,0)))} -> 0 | N4: =M4/VLOOKUP($D4,CPI!$P$16:$R$22,3,FALSE) -> 0 | O4: =VLOOKUP(E4,MFootball!C:P,6,FALSE) -> 338017
A5: 2 | B5: =IF(ISBLANK(G5),"",IF(MID(G5,1,1)="M",0,1)) -> 0 | C5: =IF(ISBLANK(H5),"",VLOOKUP(H5,Code!B:C,2,FALSE)) -> 9 | D5: 2017 | E5: 104179 | F5: Arizona | G5: Male | H5: Golf | I5: {=IF(B5=0,INDEX('Category 14'!F:F,MATCH(C5&E5&D5,'Category 14'!B:B&'Category 14'!C:C&'Category 14'!A:A,0)),INDEX('Category 14'!G:G,MATCH(C5&E5&D5,'Category 14'!B:B&'Category 14'!C:C&'Category 14'!A:A,0)))} -> 18513 | J5: =I5/VLOOKUP($D5,CPI!$P$16:$R$22,3,FALSE) -> 22863.915 | K5: {=IF(B5=0,INDEX('Category 15'!F:F,MATCH(C5&E5&D5,'Category 15'!B:B&'Category 15'!C:C&'Category 15'!A:A,0)),INDEX('Category 15'!G:G,MATCH(C5&E5&D5,'Category 15'!B:B&'Category 31'!C:C&'Category 15'!A:A,0)))} -> 0 | L5: =K5/VLOOKUP($D5,CPI!$P$16:$R$22,3,FALSE) -> 0 | M5: {=IF(B5=0,INDEX('Category 31'!F:F,MATCH(C5&E5&D5,'Category 31'!B:B&'Category 31'!C:C&'Category 31'!A:A,0)),INDEX('Category 31'!G:G,MATCH(C5&E5&D5,'Category 31'!B:B&'Category 31'!C:C&'Category 31'!A:A,0)))} -> 0 | N5: =M5/VLOOKUP($D5,CPI!$P$16:$R$22,3,FALSE) -> 0 | O5: 0
A6: 2 | B6: =IF(ISBLANK(G6),"",IF(MID(G6,1,1)="M",0,1)) -> 0 | C6: =IF(ISBLANK(H6),"",VLOOKUP(H6,Code!B:C,2,FALSE)) -> 19 | D6: 2017 | E6: 104179 | F6: Arizona | G6: Male | H6: Swimming and Diving | I6: {=IF(B6=0,INDEX('Category 14'!F:F,MATCH(C6&E6&D6,'Category 14'!B:B&'Category 14'!C:C&'Category 14'!A:A,0)),INDEX('Category 14'!G:G,MATCH(C6&E6&D6,'Category 14'!B:B&'Category 14'!C:C&'Category 14'!A:A,0)))} -> 5787 | J6: =I6/VLOOKUP($D6,CPI!$P$16:$R$22,3,FALSE) -> 7147.0576 | K6: {=IF(B6=0,INDEX('Category 15'!F:F,MATCH(C6&E6&D6,'Category 15'!B:B&'Category 15'!C:C&'Category 15'!A:A,0)),INDEX('Category 15'!G:G,MATCH(C6&E6&D6,'Category 15'!B:B&'Category 31'!C:C&'Category 15'!A:A,0)))} -> 0 | L6: =K6/VLOOKUP($D6,CPI!$P$16:$R$22,3,FALSE) -> 0 | M6: {=IF(B6=0,INDEX('Category 31'!F:F,MATCH(C6&E6&D6,'Category 31'!B:B&'Category 31'!C:C&'Category 31'!A:A,0)),INDEX('Category 31'!G:G,MATCH(C6&E6&D6,'Category 31'!B:B&'Category 31'!C:C&'Category 31'!A:A,0)))} -> 0 | N6: =M6/VLOOKUP($D6,CPI!$P$16:$R$22,3,FALSE) -> 0 | O6: 0
A7: 2 | B7: =IF(ISBLANK(G7),"",IF(MID(G7,1,1)="M",0,1)) -> 0 | C7: =IF(ISBLANK(H7),"",VLOOKUP(H7,Code!B:C,2,FALSE)) -> 20 | D7: 2017 | E7: 104179 | F7: Arizona | G7: Male | H7: Tennis | I7: {=IF(B7=0,INDEX('Category 14'!F:F,MATCH(C7&E7&D7,'Category 14'!B:B&'Category 14'!C:C&'Category 14'!A:A,0)),INDEX('Category 14'!G:G,MATCH(C7&E7&D7,'Category 14'!B:B&'Category 14'!C:C&'Category 14'!A:A,0)))} -> 0 | J7: =I7/VLOOKUP($D7,CPI!$P$16:$R$22,3,FALSE) -> 0 | K7: {=IF(B7=0,INDEX('Category 15'!F:F,MATCH(C7&E7&D7,'Category 15'!B:B&'Category 15'!C:C&'Category 15'!A:A,0)),INDEX('Category 15'!G:G,MATCH(C7&E7&D7,'Category 15'!B:B&'Category 31'!C:C&'Category 15'!A:A,0)))} -> 0 | L7: =K7/VLOOKUP($D7,CPI!$P$16:$R$22,3,FALSE) -> 0 | M7: {=IF(B7=0,INDEX('Category 31'!F:F,MATCH(C7&E7&D7,'Category 31'!B:B&'Category 31'!C:C&'Category 31'!A:A,0)),INDEX('Category 31'!G:G,MATCH(C7&E7&D7,'Category 31'!B:B&'Category 31'!C:C&'Category 31'!A:A,0)))} -> 0 | N7: =M7/VLOOKUP($D7,CPI!$P$16:$R$22,3,FALSE) -> 0 | O7: 0
A8: 2 | B8: =IF(ISBLANK(G8),"",IF(MID(G8,1,1)="M",0,1)) -> 0 | C8: =IF(ISBLANK(H8),"",VLOOKUP(H8,Code!B:C,2,FALSE)) -> 21 | D8: 2017 | E8: 104179 | F8: Arizona | G8: Male | H8: Track and Field, X-Country | I8: {=IF(B8=0,INDEX('Category 14'!F:F,MATCH(C8&E8&D8,'Category 14'!B:B&'Category 14'!C:C&'Category 14'!A:A,0)),INDEX('Category 14'!G:G,MATCH(C8&E8&D8,'Category 14'!B:B&'Category 14'!C:C&'Category 14'!A:A,0)))} -> 15915 | J8: =I8/VLOOKUP($D8,CPI!$P$16:$R$22,3,FALSE) -> 19655.335 | K8: {=IF(B8=0,INDEX('Category 15'!F:F,MATCH(C8&E8&D8,'Category 15'!B:B&'Category 15'!C:C&'Category 15'!A:A,0)),INDEX('Category 15'!G:G,MATCH(C8&E8&D8,'Category 15'!B:B&'Category 31'!C:C&'Category 15'!A:A,0)))} -> 0 | L8: =K8/VLOOKUP($D8,CPI!$P$16:$R$22,3,FALSE) -> 0 | M8: {=IF(B8=0,INDEX('Category 31'!F:F,MATCH(C8&E8&D8,'Category 31'!B:B&'Category 31'!C:C&'Category 31'!A:A,0)),INDEX('Category 31'!G:G,MATCH(C8&E8&D8,'Category 31'!B:B&'Category 31'!C:C&'Category 31'!A:A,0)))} -> 0 | N8: =M8/VLOOKUP($D8,CPI!$P$16:$R$22,3,FALSE) -> 0 | O8: 0
A9: 2 | B9: =IF(ISBLANK(G9),"",IF(MID(G9,1,1)="M",0,1)) -> 1 | C9: =IF(ISBLANK(H9),"",VLOOKUP(H9,Code!B:C,2,FALSE)) -> 2 | D9: 2017 | E9: 104179 | F9: Arizona | G9: Female | H9: Basketball | I9: {=IF(B9=0,INDEX('Category 14'!F:F,MATCH(C9&E9&D9,'Category 14'!B:B&'Category 14'!C:C&'Category 14'!A:A,0)),INDEX('Category 14'!G:G,MATCH(C9&E9&D9,'Category 14'!B:B&'Category 14'!C:C&'Category 14'!A:A,0)))} -> 0 | J9: =I9/VLOOKUP($D9,CPI!$P$16:$R$22,3,FALSE) -> 0 | K9: {=IF(B9=0,INDEX('Category 15'!F:F,MATCH(C9&E9&D9,'Category 15'!B:B&'Category 15'!C:C&'Category 15'!A:A,0)),INDEX('Category 15'!G:G,MATCH(C9&E9&D9,'Category 15'!B:B&'Category 31'!C:C&'Category 15'!A:A,0)))} -> 0 | L9: =K9/VLOOKUP($D9,CPI!$P$16:$R$22,3,FALSE) -> 0 | M9: 0 | N9: =M9/VLOOKUP($D9,CPI!$P$16:$R$22,3,FALSE) -> 0 | O9: =VLOOKUP(E9,WBasketball!C:P,6,FALSE) -> 29422
A10: 2 | B10: =IF(ISBLANK(G10),"",IF(MID(G10,1,1)="M",0,1)) -> 1 | C10: =IF(ISBLANK(H10),"",VLOOKUP(H10,Code!B:C,2,FALSE)) -> 3 | D10: 2017 | E10: 104179 | F10: Arizona | G10: Female | H10: Beach Volleyball | I10: {=IF(B10=0,INDEX('Category 14'!F:F,MATCH(C10&E10&D10,'Category 14'!B:B&'Category 14'!C:C&'Category 14'!A:A,0)),INDEX('Category 14'!G:G,MATCH(C10&E10&D10,'Category 14'!B:B&'Category 14'!C:C&'Category 14'!A:A,0)))} -> 328 | J10: =I10/VLOOKUP($D10,CPI!$P$16:$R$22,3,FALSE) -> 405.08638 | K10: {=IF(B10=0,INDEX('Category 15'!F:F,MATCH(C10&E10&D10,'Category 15'!B:B&'Category 15'!C:C&'Category 15'!A:A,0)),INDEX('Category 15'!G:G,MATCH(C10&E10&D10,'Category 15'!B:B&'Category 31'!C:C&'Category 15'!A:A,0)))} -> 0 | L10: =K10/VLOOKUP($D10,CPI!$P$16:$R$22,3,FALSE) -> 0 | M10: {=IF(B10=0,INDEX('Category 31'!F:F,MATCH(C10&E10&D10,'Category 31'!B:B&'Category 31'!C:C&'Category 31'!A:A,0)),INDEX('Category 31'!G:G,MATCH(C10&E10&D10,'Category 31'!B:B&'Category 31'!C:C&'Category 31'!A:A,0)))} -> 0 | N10: =M10/VLOOKUP($D10,CPI!$P$16:$R$22,3,FALSE) -> 0 | O10: 0
A11: 2 | B11: =IF(ISBLANK(G11),"",IF(MID(G11,1,1)="M",0,1)) -> 1 | C11: =IF(ISBLANK(H11),"",VLOOKUP(H11,Code!B:C,2,FALSE)) -> 9 | D11: 2017 | E11: 104179 | F11: Arizona | G11: Female | H11: Golf | I11: {=IF(B11=0,INDEX('Category 14'!F:F,MATCH(C11&E11&D11,'Category 14'!B:B&'Category 14'!C:C&'Category 14'!A:A,0)),INDEX('Category 14'!G:G,MATCH(C11&E11&D11,'Category 14'!B:B&'Category 14'!C:C&'Category 14'!A:A,0)))} -> 4680 | J11: =I11/VLOOKUP($D11,CPI!$P$16:$R$22,3,FALSE) -> 5779.8911 | K11: {=IF(B11=0,INDEX('Category 15'!F:F,MATCH(C11&E11&D11,'Category 15'!B:B&'Category 15'!C:C&'Category 15'!A:A,0)),INDEX('Category 15'!G:G,MATCH(C11&E11&D11,'Category 15'!B:B&'Category 31'!C:C&'Category 15'!A:A,0)))} -> 0 | L11: =K11/VLOOKUP($D11,CPI!$P$16:$R$22,3,FALSE) -> 0 | M11: {=IF(B11=0,INDEX('Category 31'!F:F,MATCH(C11&E11&D11,'Category 31'!B:B&'Category 31'!C:C&'Category 31'!A:A,0)),INDEX('Category 31'!G:G,MATCH(C11&E11&D11,'Category 31'!B:B&'Category 31'!C:C&'Category 31'!A:A,0)))} -> 0 | N11: =M11/VLOOKUP($D11,CPI!$P$16:$R$22,3,FALSE) -> 0 | O11: 0
A12: 2 | B12: =IF(ISBLANK(G12),"",IF(MID(G12,1,1)="M",0,1)) -> 1 | C12: =IF(ISBLANK(H12),"",VLOOKUP(H12,Code!B:C,2,FALSE)) -> 10 | D12: 2017 | E12: 104179 | F12: Arizona | G12: Female | H12: Gymnastics | I12: {=IF(B12=0,INDEX('Category 14'!F:F,MATCH(C12&E12&D12,'Category 14'!B:B&'Category 14'!C:C&'Category 14'!A:A,0)),INDEX('Category 14'!G:G,MATCH(C12&E12&D12,'Category 14'!B:B&'Category 14'!C:C&'Category 14'!A:A,0)))} -> 295 | J12: =I12/VLOOKUP($D12,CPI!$P$16:$R$22,3,FALSE) -> 364.33074 | K12: {=IF(B12=0,INDEX('Category 15'!F:F,MATCH(C12&E12&D12,'Category 15'!B:B&'Category 15'!C:C&'Category 15'!A:A,0)),INDEX('Category 15'!G:G,MATCH(C12&E12&D12,'Category 15'!B:B&'Category 31'!C:C&'Category 15'!A:A,0)))} -> 0 | L12: =K12/VLOOKUP($D12,CPI!$P$16:$R$22,3,FALSE) -> 0 | M12: {=IF(B12=0,INDEX('Category 31'!F:F,MATCH(C12&E12&D12,'Category 31'!B:B&'Category 31'!C:C&'Category 31'!A:A,0)),INDEX('Category 31'!G:G,MATCH(C12&E12&D12,'Category 31'!B:B&'Category 31'!C:C&'Category 31'!A:A,0)))} -> 0 | N12: =M12/VLOOKUP($D12,CPI!$P$16:$R$22,3,FALSE) -> 0 | O12: 0
A13: 2 | B13: =IF(ISBLANK(G13),"",IF(MID(G13,1,1)="M",0,1)) -> 1 | C13: =IF(ISBLANK(H13),"",VLOOKUP(H13,Code!B:C,2,FALSE)) -> 17 | D13: 2017 | E13: 104179 | F13: Arizona | G13: Female | H13: Soccer | I13: {=IF(B13=0,INDEX('Category 14'!F:F,MATCH(C13&E13&D13,'Category 14'!B:B&'Category 14'!C:C&'Category 14'!A:A,0)),INDEX('Category 14'!G:G,MATCH(C13&E13&D13,'Category 14'!B:B&'Category 14'!C:C&'Category 14'!A:A,0)))} -> 2346 | J13: =I13/VLOOKUP($D13,CPI!$P$16:$R$22,3,FALSE) -> 2897.3557 | K13: {=IF(B13=0,INDEX('Category 15'!F:F,MATCH(C13&E13&D13,'Category 15'!B:B&'Category 15'!C:C&'Category 15'!A:A,0)),INDEX('Category 15'!G:G,MATCH(C13&E13&D13,'Category 15'!B:B&'Category 31'!C:C&'Category 15'!A:A,0)))} -> 0 | L13: =K13/VLOOKUP($D13,CPI!$P$16:$R$22,3,FALSE) -> 0 | M13: {=IF(B13=0,INDEX('Category 31'!F:F,MATCH(C13&E13&D13,'Category 31'!B:B&'Category 31'!C:C&'Category 31'!A:A,0)),INDEX('Category 31'!G:G,MATCH(C13&E13&D13,'Category 31'!B:B&'Category 31'!C:C&'Category 31'!A:A,0)))} -> 0 | N13: =M13/VLOOKUP($D13,CPI!$P$16:$R$22,3,FALSE) -> 0 | O13: =VLOOKUP(E13,WSoccer!C:P,6,FALSE) -> 5822
A14: 2 | B14: =IF(ISBLANK(G14),"",IF(MID(G14,1,1)="M",0,1)) -> 1 | C14: =IF(ISBLANK(H14),"",VLOOKUP(H14,Code!B:C,2,FALSE)) -> 18 | D14: 2017 | E14: 104179 | F14: Arizona | G14: Female | H14: Softball | I14: {=IF(B14=0,INDEX('Category 14'!F:F,MATCH(C14&E14&D14,'Category 14'!B:B&'Category 14'!C:C&'Category 14'!A:A,0)),INDEX('Category 14'!G:G,MATCH(C14&E14&D14,'Category 14'!B:B&'Category 14'!C:C&'Category 14'!A:A,0)))} -> 30388 | J14: =I14/VLOOKUP($D14,CPI!$P$16:$R$22,3,FALSE) -> 37529.771 | K14: {=IF(B14=0,INDEX('Category 15'!F:F,MATCH(C14&E14&D14,'Category 15'!B:B&'Category 15'!C:C&'Category 15'!A:A,0)),INDEX('Category 15'!G:G,MATCH(C14&E14&D14,'Category 15'!B:B&'Category 31'!C:C&'Category 15'!A:A,0)))} -> 0 | L14: =K14/VLOOKUP($D14,CPI!$P$16:$R$22,3,FALSE) -> 0 | M14: {=IF(B14=0,INDEX('Category 31'!F:F,MATCH(C14&E14&D14,'Category 31'!B:B&'Category 31'!C:C&'Category 31'!A:A,0)),INDEX('Category 31'!G:G,MATCH(C14&E14&D14,'Category 31'!B:B&'Category 31'!C:C&'Category 31'!A:A,0)))} -> 0 | N14: =M14/VLOOKUP($D14,CPI!$P$16:$R$22,3,FALSE) -> 0 | O14: =VLOOKUP(E14,WSoftball!C:P,6,FALSE) -> 66402
A15: 2 | B15: =IF(ISBLANK(G15),"",IF(MID(G15,1,1)="M",0,1)) -> 1 | C15: =IF(ISBLANK(H15),"",VLOOKUP(H15,Code!B:C,2,FALSE)) -> 19 | D15: 2017 | E15: 104179 | F15: Arizona | G15: Female | H15: Swimming and Diving | I15: {=IF(B15=0,INDEX('Category 14'!F:F,MATCH(C15&E15&D15,'Category 14'!B:B&'Category 14'!C:C&'Category 14'!A:A,0)),INDEX('Category 14'!G:G,MATCH(C15&E15&D15,'Category 14'!B:B&'Category 14'!C:C&'Category 14'!A:A,0)))} -> 8180 | J15: =I15/VLOOKUP($D15,CPI!$P$16:$R$22,3,FALSE) -> 10102.459 | K15: {=IF(B15=0,INDEX('Category 15'!F:F,MATCH(C15&E15&D15,'Category 15'!B:B&'Category 15'!C:C&'Category 15'!A:A,0)),INDEX('Category 15'!G:G,MATCH(C15&E15&D15,'Category 15'!B:B&'Category 31'!C:C&'Category 15'!A:A,0)))} -> 0 | L15: =K15/VLOOKUP($D15,CPI!$P$16:$R$22,3,FALSE) -> 0 | M15: {=IF(B15=0,INDEX('Category 31'!F:F,MATCH(C15&E15&D15,'Category 31'!B:B&'Category 31'!C:C&'Category 31'!A:A,0)),INDEX('Category 31'!G:G,MATCH(C15&E15&D15,'Category 31'!B:B&'Category 31'!C:C&'Category 31'!A:A,0)))} -> 0 | N15: =M15/VLOOKUP($D15,CPI!$P$16:$R$22,3,FALSE) -> 0 | O15: 0
A16: 2 | B16: =IF(ISBLANK(G16),"",IF(MID(G16,1,1)="M",0,1)) -> 1 | C16: =IF(ISBLANK(H16),"",VLOOKUP(H16,Code!B:C,2,FALSE)) -> 20 | D16: 2017 | E16: 104179 | F16: Arizona | G16: Female | H16: Tennis | I16: {=IF(B16=0,INDEX('Category 14'!F:F,MATCH(C16&E16&D16,'Category 14'!B:B&'Category 14'!C:C&'Category 14'!A:A,0)),INDEX('Category 14'!G:G,MATCH(C16&E16&D16,'Category 14'!B:B&'Category 14'!C:C&'Category 14'!A:A,0)))} -> 12187 | J16: =I16/VLOOKUP($D16,CPI!$P$16:$R$22,3,FALSE) -> 15051.182 | K16: {=IF(B16=0,INDEX('Category 15'!F:F,MATCH(C16&E16&D16,'Category 15'!B:B&'Category 15'!C:C&'Category 15'!A:A,0)),INDEX('Category 15'!G:G,MATCH(C16&E16&D16,'Category 15'!B:B&'Category 31'!C:C&'Category 15'!A:A,0)))} -> 0 | L16: =K16/VLOOKUP($D16,CPI!$P$16:$R$22,3,FALSE) -> 0 | M16: {=IF(B16=0,INDEX('Category 31'!F:F,MATCH(C16&E16&D16,'Category 31'!B:B&'Category 31'!C:C&'Category 31'!A:A,0)),INDEX('Category 31'!G:G,MATCH(C16&E16&D16,'Category 31'!B:B&'Category 31'!C:C&'Category 31'!A:A,0)))} -> 0 | N16: =M16/VLOOKUP($D16,CPI!$P$16:$R$22,3,FALSE) -> 0 | O16: 0
A17: 2 | B17: =IF(ISBLANK(G17),"",IF(MID(G17,1,1)="M",0,1)) -> 1 | C17: =IF(ISBLANK(H17),"",VLOOKUP(H17,Code!B:C,2,FALSE)) -> 21 | D17: 2017 | E17: 104179 | F17: Arizona | G17: Female | H17: Track and Field, X-Country | I17: {=IF(B17=0,INDEX('Category 14'!F:F,MATCH(C17&E17&D17,'Category 14'!B:B&'Category 14'!C:C&'Category 14'!A:A,0)),INDEX('Category 14'!G:G,MATCH(C17&E17&D17,'Category 14'!B:B&'Category 14'!C:C&'Category 14'!A:A,0)))} -> 9702 | J17: =I17/VLOOKUP($D17,CPI!$P$16:$R$22,3,FALSE) -> 11982.159 | K17: {=IF(B17=0,INDEX('Category 15'!F:F,MATCH(C17&E17&D17,'Category 15'!B:B&'Category 15'!C:C&'Category 15'!A:A,0)),INDEX('Category 15'!G:G,MATCH(C17&E17&D17,'Category 15'!B:B&'Category 31'!C:C&'Category 15'!A:A,0)))} -> 0 | L17: =K17/VLOOKUP($D17,CPI!$P$16:$R$22,3,FALSE) -> 0 | M17: {=IF(B17=0,INDEX('Category 31'!F:F,MATCH(C17&E17&D17,'Category 31'!B:B&'Category 31'!C:C&'Category 31'!A:A,0)),INDEX('Category 31'!G:G,MATCH(C17&E17&D17,'Category 31'!B:B&'Category 31'!C:C&'Category 31'!A:A,0)))} -> 0 | N17: =M17/VLOOKUP($D17,CPI!$P$16:$R$22,3,FALSE) -> 0 | O17: 0
A18: 2 | B18: =IF(ISBLANK(G18),"",IF(MID(G18,1,1)="M",0,1)) -> 1 | C18: =IF(ISBLANK(H18),"",VLOOKUP(H18,Code!B:C,2,FALSE)) -> 23 | D18: 2017 | E18: 104179 | F18: Arizona | G18: Female | H18: Volleyball | I18: {=IF(B18=0,INDEX('Category 14'!F:F,MATCH(C18&E18&D18,'Category 14'!B:B&'Category 14'!C:C&'Category 14'!A:A,0)),INDEX('Category 14'!G:G,MATCH(C18&E18&D18,'Category 14'!B:B&'Category 14'!C:C&'Category 14'!A:A,0)))} -> 19455 | J18: =I18/VLOOKUP($D18,CPI!$P$16:$R$22,3,FALSE) -> 24027.304 | K18: {=IF(B18=0,INDEX('Category 15'!F:F,MATCH(C18&E18&D18,'Category 15'!B:B&'Category 15'!C:C&'Category 15'!A:A,0)),INDEX('Category 15'!G:G,MATCH(C18&E18&D18,'Category 15'!B:B&'Category 31'!C:C&'Category 15'!A:A,0)))} -> 0 | L18: =K18/VLOOKUP($D18,CPI!$P$16:$R$22,3,FALSE) -> 0 | M18: {=IF(B18=0,INDEX('Category 31'!F:F,MATCH(C18&E18&D18,'Category 31'!B:B&'Category 31'!C:C&'Category 31'!A:A,0)),INDEX('Category 31'!G:G,MATCH(C18&E18&D18,'Category 31'!B:B&'Category 31'!C:C&'Category 31'!A:A,0)))} -> 0 | N18: =M18/VLOOKUP($D18,CPI!$P$16:$R$22,3,FALSE) -> 0 | O18: =VLOOKUP(E18,WVolleyball!C:P,6,FALSE) -> 18595
A19: 2 | B19: =IF(ISBLANK(G19),"",IF(MID(G19,1,1)="M",0,1)) -> 0 | C19: =IF(ISBLANK(H19),"",VLOOKUP(H19,Code!B:C,2,FALSE)) -> 1 | D19: 2018 | E19: 104179 | F19: Arizona | G19: Male | H19: Baseball | I19: {=IF(B19=0,INDEX('Category 14'!F:F,MATCH(C19&E19&D19,'Category 14'!B:B&'Category 14'!C:C&'Category 14'!A:A,0)),INDEX('Category 14'!G:G,MATCH(C19&E19&D19,'Category 14'!B:B&'Category 14'!C:C&'Category 14'!A:A,0)))} -> 2150 | J19: =I19/VLOOKUP($D19,CPI!$P$16:$R$22,3,FALSE) -> 2596.7606 | K19: {=IF(B19=0,INDEX('Category 15'!F:F,MATCH(C19&E19&D19,'Category 15'!B:B&'Category 15'!C:C&'Category 15'!A:A,0)),INDEX('Category 15'!G:G,MATCH(C19&E19&D19,'Category 15'!B:B&'Category 31'!C:C&'Category 15'!A:A,0)))} -> 0 | L19: =K19/VLOOKUP($D19,CPI!$P$16:$R$22,3,FALSE) -> 0 | M19: {=IF(B19=0,INDEX('Category 31'!F:F,MATCH(C19&E19&D19,'Category 31'!B:B&'Category 31'!C:C&'Category 31'!A:A,0)),INDEX('Category 31'!G:G,MATCH(C19&E19&D19,'Category 31'!B:B&'Category 31'!C:C&'Category 31'!A:A,0)))} -> 0 | N19: =M19/VLOOKUP($D19,CPI!$P$16:$R$22,3,FALSE) -> 0 | O19: 93511
A20: 2 | B20: =IF(ISBLANK(G20),"",IF(MID(G20,1,1)="M",0,1)) -> 0 | C20: =IF(ISBLANK(H20),"",VLOOKUP(H20,Code!B:C,2,FALSE)) -> 2 | D20: 2018 | E20: 104179 | F20: Arizona | G20: Male | H20: Basketball | I20: {=IF(B20=0,INDEX('Category 14'!F:F,MATCH(C20&E20&D20,'Category 14'!B:B&'Category 14'!C:C&'Category 14'!A:A,0)),INDEX('Category 14'!G:G,MATCH(C20&E20&D20,'Category 14'!B:B&'Category 14'!C:C&'Category 14'!A:A,0)))} -> 166804 | J20: =I20/VLOOKUP($D20,CPI!$P$16:$R$22,3,FALSE) -> 201465.14 | K20: {=IF(B20=0,INDEX('Category 15'!F:F,MATCH(C20&E20&D20,'Category 15'!B:B&'Category 15'!C:C&'Category 15'!A:A,0)),INDEX('Category 15'!G:G,MATCH(C20&E20&D20,'Category 15'!B:B&'Category 31'!C:C&'Category 15'!A:A,0)))} -> 4432881 | L20: =K20/VLOOKUP($D20,CPI!$P$16:$R$22,3,FALSE) -> 5354014.3 | M20: {=IF(B20=0,INDEX('Category 31'!F:F,MATCH(C20&E20&D20,'Category 31'!B:B&'Category 31'!C:C&'Category 31'!A:A,0)),INDEX('Category 31'!G:G,MATCH(C20&E20&D20,'Category 31'!B:B&'Category 31'!C:C&'Category 31'!A:A,0)))} -> 0 | N20: =M20/VLOOKUP($D20,CPI!$P$16:$R$22,3,FALSE) -> 0 | O20: =VLOOKUP(E3,MBasketball!C:P,7,FALSE) -> 230947
A21: 2 | B21: =IF(ISBLANK(G21),"",IF(MID(G21,1,1)="M",0,1)) -> 0 | C21: =IF(ISBLANK(H21),"",VLOOKUP(H21,Code!B:C,2,FALSE)) -> 8 | D21: 2018 | E21: 104179 | F21: Arizona | G21: Male | H21: Football | I21: {=IF(B21=0,INDEX('Category 14'!F:F,MATCH(C21&E21&D21,'Category 14'!B:B&'Category 14'!C:C&'Category 14'!A:A,0)),INDEX('Category 14'!G:G,MATCH(C21&E21&D21,'Category 14'!B:B&'Category 14'!C:C&'Category 14'!A:A,0)))} -> 592731 | J21: =I21/VLOOKUP($D21,CPI!$P$16:$R$22,3,FALSE) -> 715897.92 | K21: {=IF(B21=0,INDEX('Category 15'!F:F,MATCH(C21&E21&D21,'Category 15'!B:B&'Category 15'!C:C&'Category 15'!A:A,0)),INDEX('Category 15'!G:G,MATCH(C21&E21&D21,'Category 15'!B:B&'Category 31'!C:C&'Category 15'!A:A,0)))} -> 4432880 | L21: =K21/VLOOKUP($D21,CPI!$P$16:$R$22,3,FALSE) -> 5354013.1 | M21: {=IF(B21=0,INDEX('Category 31'!F:F,MATCH(C21&E21&D21,'Category 31'!B:B&'Category 31'!C:C&'Category 31'!A:A,0)),INDEX('Category 31'!G:G,MATCH(C21&E21&D21,'Category 31'!B:B&'Category 31'!C:C&'Category 31'!A:A,0)))} -> 0 | N21: =M21/VLOOKUP($D21,CPI!$P$16:$R$22,3,FALSE) -> 0 | O21: =VLOOKUP(E4,MFootball!C:P,7,FALSE) -> 255791
A22: 2 | B22: =IF(ISBLANK(G22),"",IF(MID(G22,1,1)="M",0,1)) -> 0 | C22: =IF(ISBLANK(H22),"",VLOOKUP(H22,Code!B:C,2,FALSE)) -> 9 | D22: 2018 | E22: 104179 | F22: Arizona | G22: Male | H22: Golf | I22: {=IF(B22=0,INDEX('Category 14'!F:F,MATCH(C22&E22&D22,'Category 14'!B:B&'Category 14'!C:C&'Category 14'!A:A,0)),INDEX('Category 14'!G:G,MATCH(C22&E22&D22,'Category 14'!B:B&'Category 14'!C:C&'Category 14'!A:A,0)))} -> 32700 | J22: =I22/VLOOKUP($D22,CPI!$P$16:$R$22,3,FALSE) -> 39494.917 | K22: {=IF(B22=0,INDEX('Category 15'!F:F,MATCH(C22&E22&D22,'Category 15'!B:B&'Category 15'!C:C&'Category 15'!A:A,0)),INDEX('Category 15'!G:G,MATCH(C22&E22&D22,'Category 15'!B:B&'Category 31'!C:C&'Category 15'!A:A,0)))} -> 0 | L22: =K22/VLOOKUP($D22,CPI!$P$16:$R$22,3,FALSE) -> 0 | M22: {=IF(B22=0,INDEX('Category 31'!F:F,MATCH(C22&E22&D22,'Category 31'!B:B&'Category 31'!C:C&'Category 31'!A:A,0)),INDEX('Category 31'!G:G,MATCH(C22&E22&D22,'Category 31'!B:B&'Category 31'!C:C&'Category 31'!A:A,0)))} -> 0 | N22: =M22/VLOOKUP($D22,CPI!$P$16:$R$22,3,FALSE) -> 0 | O22: 0
A23: 2 | B23: =IF(ISBLANK(G23),"",IF(MID(G23,1,1)="M",0,1)) -> 0 | C23: =IF(ISBLANK(H23),"",VLOOKUP(H23,Code!B:C,2,FALSE)) -> 19 | D23: 2018 | E23: 104179 | F23: Arizona | G23: Male | H23: Swimming and Diving | I23: {=IF(B23=0,INDEX('Category 14'!F:F,MATCH(C23&E23&D23,'Category 14'!B:B&'Category 14'!C:C&'Category 14'!A:A,0)),INDEX('Category 14'!G:G,MATCH(C23&E23&D23,'Category 14'!B:B&'Category 14'!C:C&'Category 14'!A:A,0)))} -> 1296 | J23: =I23/VLOOKUP($D23,CPI!$P$16:$R$22,3,FALSE) -> 1565.3031 | K23: {=IF(B23=0,INDEX('Category 15'!F:F,MATCH(C23&E23&D23,'Category 15'!B:B&'Category 15'!C:C&'Category 15'!A:A,0)),INDEX('Category 15'!G:G,MATCH(C23&E23&D23,'Category 15'!B:B&'Category 31'!C:C&'Category 15'!A:A,0)))} -> 0 | L23: =K23/VLOOKUP($D23,CPI!$P$16:$R$22,3,FALSE) -> 0 | M23: {=IF(B23=0,INDEX('Category 31'!F:F,MATCH(C23&E23&D23,'Category 31'!B:B&'Category 31'!C:C&'Category 31'!A:A,0)),INDEX('Category 31'!G:G,MATCH(C23&E23&D23,'Category 31'!B:B&'Category 31'!C:C&'Category 31'!A:A,0)))} -> 0 | N23: =M23/VLOOKUP($D23,CPI!$P$16:$R$22,3,FALSE) -> 0 | O23: 0
A24: 2 | B24: =IF(ISBLANK(G24),"",IF(MID(G24,1,1)="M",0,1)) -> 0 | C24: =IF(ISBLANK(H24),"",VLOOKUP(H24,Code!B:C,2,FALSE)) -> 20 | D24: 2018 | E24: 104179 | F24: Arizona | G24: Male | H24: Tennis | I24: {=IF(B24=0,INDEX('Category 14'!F:F,MATCH(C24&E24&D24,'Category 14'!B:B&'Category 14'!C:C&'Category 14'!A:A,0)),INDEX('Category 14'!G:G,MATCH(C24&E24&D24,'Category 14'!B:B&'Category 14'!C:C&'Category 14'!A:A,0)))} -> 0 | J24: =I24/VLOOKUP($D24,CPI!$P$16:$R$22,3,FALSE) -> 0 | K24: {=IF(B24=0,INDEX('Category 15'!F:F,MATCH(C24&E24&D24,'Category 15'!B:B&'Category 15'!C:C&'Category 15'!A:A,0)),INDEX('Category 15'!G:G,MATCH(C24&E24&D24,'Category 15'!B:B&'Category 31'!C:C&'Category 15'!A:A,0)))} -> 0 | L24: =K24/VLOOKUP($D24,CPI!$P$16:$R$22,3,FALSE) -> 0 | M24: {=IF(B24=0,INDEX('Category 31'!F:F,MATCH(C24&E24&D24,'Category 31'!B:B&'Category 31'!C:C&'Category 31'!A:A,0)),INDEX('Category 31'!G:G,MATCH(C24&E24&D24,'Category 31'!B:B&'Category 31'!C:C&'Category 31'!A:A,0)))} -> 0 | N24: =M24/VLOOKUP($D24,CPI!$P$16:$R$22,3,FALSE) -> 0 | O24: 0
A25: 2 | B25: =IF(ISBLANK(G25),"",IF(MID(G25,1,1)="M",0,1)) -> 0 | C25: =IF(ISBLANK(H25),"",VLOOKUP(H25,Code!B:C,2,FALSE)) -> 21 | D25: 2018 | E25: 104179 | F25: Arizona | G25: Male | H25: Track and Field, X-Country | I25: {=IF(B25=0,INDEX('Category 14'!F:F,MATCH(C25&E25&D25,'Category 14'!B:B&'Category 14'!C:C&'Category 14'!A:A,0)),INDEX('Category 14'!G:G,MATCH(C25&E25&D25,'Category 14'!B:B&'Category 14'!C:C&'Category 14'!A:A,0)))} -> 11082 | J25: =I25/VLOOKUP($D25,CPI!$P$16:$R$22,3,FALSE) -> 13384.791 | K25: {=IF(B25=0,INDEX('Category 15'!F:F,MATCH(C25&E25&D25,'Category 15'!B:B&'Category 15'!C:C&'Category 15'!A:A,0)),INDEX('Category 15'!G:G,MATCH(C25&E25&D25,'Category 15'!B:B&'Category 31'!C:C&'Category 15'!A:A,0)))} -> 0 | L25: =K25/VLOOKUP($D25,CPI!$P$16:$R$22,3,FALSE) -> 0 | M25: {=IF(B25=0,INDEX('Category 31'!F:F,MATCH(C25&E25&D25,'Category 31'!B:B&'Category 31'!C:C&'Category 31'!A:A,0)),INDEX('Category 31'!G:G,MATCH(C25&E25&D25,'Category 31'!B:B&'Category 31'!C:C&'Category 31'!A:A,0)))} -> 0 | N25: =M25/VLOOKUP($D25,CPI!$P$16:$R$22,3,FALSE) -> 0 | O25: 0
A26: 2 | B26: =IF(ISBLANK(G26),"",IF(MID(G26,1,1)="M",0,1)) -> 1 | C26: =IF(ISBLANK(H26),"",VLOOKUP(H26,Code!B:C,2,FALSE)) -> 2 | D26: 2018 | E26: 104179 | F26: Arizona | G26: Female | H26: Basketball | I26: {=IF(B26=0,INDEX('Category 14'!F:F,MATCH(C26&E26&D26,'Category 14'!B:B&'Category 14'!C:C&'Category 14'!A:A,0)),INDEX('Category 14'!G:G,MATCH(C26&E26&D26,'Category 14'!B:B&'Category 14'!C:C&'Category 14'!A:A,0)))} -> 0 | J26: =I26/VLOOKUP($D26,CPI!$P$16:$R$22,3,FALSE) -> 0 | K26: {=IF(B26=0,INDEX('Category 15'!F:F,MATCH(C26&E26&D26,'Category 15'!B:B&'Category 15'!C:C&'Category 15'!A:A,0)),INDEX('Category 15'!G:G,MATCH(C26&E26&D26,'Category 15'!B:B&'Category 31'!C:C&'Category 15'!A:A,0)))} -> 0 | L26: =K26/VLOOKUP($D26,CPI!$P$16:$R$22,3,FALSE) -> 0 | M26: {=IF(B26=0,INDEX('Category 31'!F:F,MATCH(C26&E26&D26,'Category 31'!B:B&'Category 31'!C:C&'Category 31'!A:A,0)),INDEX('Category 31'!G:G,MATCH(C26&E26&D26,'Category 31'!B:B&'Category 31'!C:C&'Category 31'!A:A,0)))} -> 0 | N26: =M26/VLOOKUP($D26,CPI!$P$16:$R$22,3,FALSE) -> 0 | O26: =VLOOKUP(E26,WBasketball!C:P,7,FALSE) -> 28988
A27: 2 | B27: =IF(ISBLANK(G27),"",IF(MID(G27,1,1)="M",0,1)) -> 1 | C27: =IF(ISBLANK(H27),"",VLOOKUP(H27,Code!B:C,2,FALSE)) -> 3 | D27: 2018 | E27: 104179 | F27: Arizona | G27: Female | H27: Beach Volleyball | I27: {=IF(B27=0,INDEX('Category 14'!F:F,MATCH(C27&E27&D27,'Category 14'!B:B&'Category 14'!C:C&'Category 14'!A:A,0)),INDEX('Category 14'!G:G,MATCH(C27&E27&D27,'Category 14'!B:B&'Category 14'!C:C&'Category 14'!A:A,0)))} -> 0 | J27: =I27/VLOOKUP($D27,CPI!$P$16:$R$22,3,FALSE) -> 0 | K27: {=IF(B27=0,INDEX('Category 15'!F:F,MATCH(C27&E27&D27,'Category 15'!B:B&'Category 15'!C:C&'Category 15'!A:A,0)),INDEX('Category 15'!G:G,MATCH(C27&E27&D27,'Category 15'!B:B&'Category 31'!C:C&'Category 15'!A:A,0)))} -> 0 | L27: =K27/VLOOKUP($D27,CPI!$P$16:$R$22,3,FALSE) -> 0 | M27: {=IF(B27=0,INDEX('Category 31'!F:F,MATCH(C27&E27&D27,'Category 31'!B:B&'Category 31'!C:C&'Category 31'!A:A,0)),INDEX('Category 31'!G:G,MATCH(C27&E27&D27,'Category 31'!B:B&'Category 31'!C:C&'Category 31'!A:A,0)))} -> 0 | N27: =M27/VLOOKUP($D27,CPI!$P$16:$R$22,3,FALSE) -> 0 | O27: 0
A28: 2 | B28: =IF(ISBLANK(G28),"",IF(MID(G28,1,1)="M",0,1)) -> 1 | C28: =IF(ISBLANK(H28),"",VLOOKUP(H28,Code!B:C,2,FALSE)) -> 9 | D28: 2018 | E28: 104179 | F28: Arizona | G28: Female | H28: Golf | I28: {=IF(B28=0,INDEX('Category 14'!F:F,MATCH(C28&E28&D28,'Category 14'!B:B&'Category 14'!C:C&'Category 14'!A:A,0)),INDEX('Category 14'!G:G,MATCH(C28&E28&D28,'Category 14'!B:B&'Category 14'!C:C&'Category 14'!A:A,0)))} -> 11085 | J28: =I28/VLOOKUP($D28,CPI!$P$16:$R$22,3,FALSE) -> 13388.415 | K28: {=IF(B28=0,INDEX('Category 15'!F:F,MATCH(C28&E28&D28,'Category 15'!B:B&'Category 15'!C:C&'Category 15'!A:A,0)),INDEX('Category 15'!G:G,MATCH(C28&E28&D28,'Category 15'!B:B&'Category 31'!C:C&'Category 15'!A:A,0)))} -> 0 | L28: =K28/VLOOKUP($D28,CPI!$P$16:$R$22,3,FALSE) -> 0 | M28: {=IF(B28=0,INDEX('Category 31'!F:F,MATCH(C28&E28&D28,'Category 31'!B:B&'Category 31'!C:C&'Category 31'!A:A,0)),INDEX('Category 31'!G:G,MATCH(C28&E28&D28,'Category 31'!B:B&'Category 31'!C:C&'Category 31'!A:A,0)))} -> 0 | N28: =M28/VLOOKUP($D28,CPI!$P$16:$R$22,3,FALSE) -> 0 | O28: 0
A29: 2 | B29: =IF(ISBLANK(G29),"",IF(MID(G29,1,1)="M",0,1)) -> 1 | C29: =IF(ISBLANK(H29),"",VLOOKUP(H29,Code!B:C,2,FALSE)) -> 10 | D29: 2018 | E29: 104179 | F29: Arizona | G29: Female | H29: Gymnastics | I29: {=IF(B29=0,INDEX('Category 14'!F:F,MATCH(C29&E29&D29,'Category 14'!B:B&'Category 14'!C:C&'Category 14'!A:A,0)),INDEX('Category 14'!G:G,MATCH(C29&E29&D29,'Category 14'!B:B&'Category 14'!C:C&'Category 14'!A:A,0)))} -> 1937 | J29: =I29/VLOOKUP($D29,CPI!$P$16:$R$22,3,FALSE) -> 2339.5001 | K29: {=IF(B29=0,INDEX('Category 15'!F:F,MATCH(C29&E29&D29,'Category 15'!B:B&'Category 15'!C:C&'Category 15'!A:A,0)),INDEX('Category 15'!G:G,MATCH(C29&E29&D29,'Category 15'!B:B&'Category 31'!C:C&'Category 15'!A:A,0)))} -> 0 | L29: =K29/VLOOKUP($D29,CPI!$P$16:$R$22,3,FALSE) -> 0 | M29: {=IF(B29=0,INDEX('Category 31'!F:F,MATCH(C29&E29&D29,'Category 31'!B:B&'Category 31'!C:C&'Category 31'!A:A,0)),INDEX('Category 31'!G:G,MATCH(C29&E29&D29,'Category 31'!B:B&'Category 31'!C:C&'Category 31'!A:A,0)))} -> 0 | N29: =M29/VLOOKUP($D29,CPI!$P$16:$R$22,3,FALSE) -> 0 | O29: 0
A30: 2 | B30: =IF(ISBLANK(G30),"",IF(MID(G30,1,1)="M",0,1)) -> 1 | C30: =IF(ISBLANK(H30),"",VLOOKUP(H30,Code!B:C,2,FALSE)) -> 17 | D30: 2018 | E30: 104179 | F30: Arizona | G30: Female | H30: Soccer | I30: {=IF(B30=0,INDEX('Category 14'!F:F,MATCH(C30&E30&D30,'Category 14'!B:B&'Category 14'!C:C&'Category 14'!A:A,0)),INDEX('Category 14'!G:G,MATCH(C30&E30&D30,'Category 14'!B:B&'Category 14'!C:C&'Category 14'!A:A,0)))} -> 2300 | J30: =I30/VLOOKUP($D30,CPI!$P$16:$R$22,3,FALSE) -> 2777.93 | K30: {=IF(B30=0,INDEX('Category 15'!F:F,MATCH(C30&E30&D30,'Category 15'!B:B&'Category 15'!C:C&'Category 15'!A:A,0)),INDEX('Category 15'!G:G,MATCH(C30&E30&D30,'Category 15'!B:B&'Category 31'!C:C&'Category 15'!A:A,0)))} -> 0 | L30: =K30/VLOOKUP($D30,CPI!$P$16:$R$22,3,FALSE) -> 0 | M30: {=IF(B30=0,INDEX('Category 31'!F:F,MATCH(C30&E30&D30,'Category 31'!B:B&'Category 31'!C:C&'Category 31'!A:A,0)),INDEX('Category 31'!G:G,MATCH(C30&E30&D30,'Category 31'!B:B&'Category 31'!C:C&'Category 31'!A:A,0)))} -> 0 | N30: =M30/VLOOKUP($D30,CPI!$P$16:$R$22,3,FALSE) -> 0 | O30: =VLOOKUP(E30,WSoccer!C:P,7,FALSE) -> 7125
A31: 2 | B31: =IF(ISBLANK(G31),"",IF(MID(G31,1,1)="M",0,1)) -> 1 | C31: =IF(ISBLANK(H31),"",VLOOKUP(H31,Code!B:C,2,FALSE)) -> 18 | D31: 2018 | E31: 104179 | F31: Arizona | G31: Female | H31: Softball | I31: {=IF(B31=0,INDEX('Category 14'!F:F,MATCH(C31&E31&D31,'Category 14'!B:B&'Category 14'!C:C&'Category 14'!A:A,0)),INDEX('Category 14'!G:G,MATCH(C31&E31&D31,'Category 14'!B:B&'Category 14'!C:C&'Category 14'!A:A,0)))} -> 0 | J31: =I31/VLOOKUP($D31,CPI!$P$16:$R$22,3,FALSE) -> 0 | K31: {=IF(B31=0,INDEX('Category 15'!F:F,MATCH(C31&E31&D31,'Category 15'!B:B&'Category 15'!C:C&'Category 15'!A:A,0)),INDEX('Category 15'!G:G,MATCH(C31&E31&D31,'Category 15'!B:B&'Category 31'!C:C&'Category 15'!A:A,0)))} -> 0 | L31: =K31/VLOOKUP($D31,CPI!$P$16:$R$22,3,FALSE) -> 0 | M31: {=IF(B31=0,INDEX('Category 31'!F:F,MATCH(C31&E31&D31,'Category 31'!B:B&'Category 31'!C:C&'Category 31'!A:A,0)),INDEX('Category 31'!G:G,MATCH(C31&E31&D31,'Category 31'!B:B&'Category 31'!C:C&'Category 31'!A:A,0)))} -> 0 | N31: =M31/VLOOKUP($D31,CPI!$P$16:$R$22,3,FALSE) -> 0 | O31: =VLOOKUP(E31,WSoftball!C:P,7,FALSE) -> 57769
A32: 2 | B32: =IF(ISBLANK(G32),"",IF(MID(G32,1,1)="M",0,1)) -> 1 | C32: =IF(ISBLANK(H32),"",VLOOKUP(H32,Code!B:C,2,FALSE)) -> 19 | D32: 2018 | E32: 104179 | F32: Arizona | G32: Female | H32: Swimming and Diving | I32: {=IF(B32=0,INDEX('Category 14'!F:F,MATCH(C32&E32&D32,'Category 14'!B:B&'Category 14'!C:C&'Category 14'!A:A,0)),INDEX('Category 14'!G:G,MATCH(C32&E32&D32,'Category 14'!B:B&'Category 14'!C:C&'Category 14'!A:A,0)))} -> 1121 | J32: =I32/VLOOKUP($D32,CPI!$P$16:$R$22,3,FALSE) -> 1353.9389 | K32: {=IF(B32=0,INDEX('Category 15'!F:F,MATCH(C32&E32&D32,'Category 15'!B:B&'Category 15'!C:C&'Category 15'!A:A,0)),INDEX('Category 15'!G:G,MATCH(C32&E32&D32,'Category 15'!B:B&'Category 31'!C:C&'Category 15'!A:A,0)))} -> 0 | L32: =K32/VLOOKUP($D32,CPI!$P$16:$R$22,3,FALSE) -> 0 | M32: {=IF(B32=0,INDEX('Category 31'!F:F,MATCH(C32&E32&D32,'Category 31'!B:B&'Category 31'!C:C&'Category 31'!A:A,0)),INDEX('Category 31'!G:G,MATCH(C32&E32&D32,'Category 31'!B:B&'Category 31'!C:C&'Category 31'!A:A,0)))} -> 0 | N32: =M32/VLOOKUP($D32,CPI!$P$16:$R$22,3,FALSE) -> 0 | O32: 0
A33: 2 | B33: =IF(ISBLANK(G33),"",IF(MID(G33,1,1)="M",0,1)) -> 1 | C33: =IF(ISBLANK(H33),"",VLOOKUP(H33,Code!B:C,2,FALSE)) -> 20 | D33: 2018 | E33: 104179 | F33: Arizona | G33: Female | H33: Tennis | I33: {=IF(B33=0,INDEX('Category 14'!F:F,MATCH(C33&E33&D33,'Category 14'!B:B&'Category 14'!C:C&'Category 14'!A:A,0)),INDEX('Category 14'!G:G,MATCH(C33&E33&D33,'Category 14'!B:B&'Category 14'!C:C&'Category 14'!A:A,0)))} -> 870 | J33: =I33/VLOOKUP($D33,CPI!$P$16:$R$22,3,FALSE) -> 1050.7822 | K33: {=IF(B33=0,INDEX('Category 15'!F:F,MATCH(C33&E33&D33,'Category 15'!B:B&'Category 15'!C:C&'Category 15'!A:A,0)),INDEX('Category 15'!G:G,MATCH(C33&E33&D33,'Category 15'!B:B&'Category 31'!C:C&'Category 15'!A:A,0)))} -> 0 | L33: =K33/VLOOKUP($D33,CPI!$P$16:$R$22,3,FALSE) -> 0 | M33: {=IF(B33=0,INDEX('Category 31'!F:F,MATCH(C33&E33&D33,'Category 31'!B:B&'Category 31'!C:C&'Category 31'!A:A,0)),INDEX('Category 31'!G:G,MATCH(C33&E33&D33,'Category 31'!B:B&'Category 31'!C:C&'Category 31'!A:A,0)))} -> 0 | N33: =M33/VLOOKUP($D33,CPI!$P$16:$R$22,3,FALSE) -> 0 | O33: 0
A34: 2 | B34: =IF(ISBLANK(G34),"",IF(MID(G34,1,1)="M",0,1)) -> 1 | C34: =IF(ISBLANK(H34),"",VLOOKUP(H34,Code!B:C,2,FALSE)) -> 21 | D34: 2018 | E34: 104179 | F34: Arizona | G34: Female | H34: Track and Field, X-Country | I34: {=IF(B34=0,INDEX('Category 14'!F:F,MATCH(C34&E34&D34,'Category 14'!B:B&'Category 14'!C:C&'Category 14'!A:A,0)),INDEX('Category 14'!G:G,MATCH(C34&E34&D34,'Category 14'!B:B&'Category 14'!C:C&'Category 14'!A:A,0)))} -> 10223 | J34: =I34/VLOOKUP($D34,CPI!$P$16:$R$22,3,FALSE) -> 12347.295 | K34: {=IF(B34=0,INDEX('Category 15'!F:F,MATCH(C34&E34&D34,'Category 15'!B:B&'Category 15'!C:C&'Category 15'!A:A,0)),INDEX('Category 15'!G:G,MATCH(C34&E34&D34,'Category 15'!B:B&'Category 31'!C:C&'Category 15'!A:A,0)))} -> 0 | L34: =K34/VLOOKUP($D34,CPI!$P$16:$R$22,3,FALSE) -> 0 | M34: {=IF(B34=0,INDEX('Category 31'!F:F,MATCH(C34&E34&D34,'Category 31'!B:B&'Category 31'!C:C&'Category 31'!A:A,0)),INDEX('Category 31'!G:G,MATCH(C34&E34&D34,'Category 31'!B:B&'Category 31'!C:C&'Category 31'!A:A,0)))} -> 0 | N34: =M34/VLOOKUP($D34,CPI!$P$16:$R$22,3,FALSE) -> 0 | O34: 0
A35: 2 | B35: =IF(ISBLANK(G35),"",IF(MID(G35,1,1)="M",0,1)) -> 1 | C35: =IF(ISBLANK(H35),"",VLOOKUP(H35,Code!B:C,2,FALSE)) -> 23 | D35: 2018 | E35: 104179 | F35: Arizona | G35: Female | H35: Volleyball | I35: {=IF(B35=0,INDEX('Category 14'!F:F,MATCH(C35&E35&D35,'Category 14'!B:B&'Category 14'!C:C&'Category 14'!A:A,0)),INDEX('Category 14'!G:G,MATCH(C35&E35&D35,'Category 14'!B:B&'Category 14'!C:C&'Category 14'!A:A,0)))} -> 0 | J35: =I35/VLOOKUP($D35,CPI!$P$16:$R$22,3,FALSE) -> 0 | K35: {=IF(B35=0,INDEX('Category 15'!F:F,MATCH(C35&E35&D35,'Category 15'!B:B&'Category 15'!C:C&'Category 15'!A:A,0)),INDEX('Category 15'!G:G,MATCH(C35&E35&D35,'Category 15'!B:B&'Category 31'!C:C&'Category 15'!A:A,0)))} -> 0 | L35: =K35/VLOOKUP($D35,CPI!$P$16:$R$22,3,FALSE) -> 0 | M35: {=IF(B35=0,INDEX('Category 31'!F:F,MATCH(C35&E35&D35,'Category 31'!B:B&'Category 31'!C:C&'Category 31'!A:A,0)),INDEX('Category 31'!G:G,MATCH(C35&E35&D35,'Category 31'!B:B&'Category 31'!C:C&'Category 31'!A:A,0)))} -> 0 | N35: =M35/VLOOKUP($D35,CPI!$P$16:$R$22,3,FALSE) -> 0 | O35: =VLOOKUP(E35,WVolleyball!C:P,7,FALSE) -> 24356
A36: 2 | B36: =IF(ISBLANK(G36),"",IF(MID(G36,1,1)="M",0,1)) -> 0 | C36: =IF(ISBLANK(H36),"",VLOOKUP(H36,Code!B:C,2,FALSE)) -> 1 | D36: 2019 | E36: 104179 | F36: Arizona | G36: Male | H36: Baseball | I36: {=IF(B36=0,INDEX('Category 14'!F:F,MATCH(C36&E36&D36,'Category 14'!B:B&'Category 14'!C:C&'Category 14'!A:A,0)),INDEX('Category 14'!G:G,MATCH(C36&E36&D36,'Category 14'!B:B&'Category 14'!C:C&'Category 14'!A:A,0)))} -> 3435 | J36: =I36/VLOOKUP($D36,CPI!$P$16:$R$22,3,FALSE) -> 4064.539 | K36: {=IF(B36=0,INDEX('Category 15'!F:F,MATCH(C36&E36&D36,'Category 15'!B:B&'Category 15'!C:C&'Category 15'!A:A,0)),INDEX('Category 15'!G:G,MATCH(C36&E36&D36,'Category 15'!B:B&'Category 31'!C:C&'Category 15'!A:A,0)))} -> 0 | L36: =K36/VLOOKUP($D36,CPI!$P$16:$R$22,3,FALSE) -> 0 | M36: {=IF(B36=0,INDEX('Category 31'!F:F,MATCH(C36&E36&D36,'Category 31'!B:B&'Category 31'!C:C&'Category 31'!A:A,0)),INDEX('Category 31'!G:G,MATCH(C36&E36&D36,'Category 31'!B:B&'Category 31'!C:C&'Category 31'!A:A,0)))} -> 0 | N36: =M36/VLOOKUP($D36,CPI!$P$16:$R$22,3,FALSE) -> 0 | O36: 81394
A37: 2 | B37: =IF(ISBLANK(G37),"",IF(MID(G37,1,1)="M",0,1)) -> 0 | C37: =IF(ISBLANK(H37),"",VLOOKUP(H37,Code!B:C,2,FALSE)) -> 2 | D37: 2019 | E37: 104179 | F37: Arizona | G37: Male | H37: Basketball | I37: {=IF(B37=0,INDEX('Category 14'!F:F,MATCH(C37&E37&D37,'Category 14'!B:B&'Category 14'!C:C&'Category 14'!A:A,0)),INDEX('Category 14'!G:G,MATCH(C37&E37&D37,'Category 14'!B:B&'Category 14'!C:C&'Category 14'!A:A,0)))} -> 45770 | J37: =I37/VLOOKUP($D37,CPI!$P$16:$R$22,3,FALSE) -> 54158.355 | K37: {=IF(B37=0,INDEX('Category 15'!F:F,MATCH(C37&E37&D37,'Category 15'!B:B&'Category 15'!C:C&'Category 15'!A:A,0)),INDEX('Category 15'!G:G,MATCH(C37&E37&D37,'Category 15'!B:B&'Category 31'!C:C&'Category 15'!A:A,0)))} -> 4381518 | L37: =K37/VLOOKUP($D37,CPI!$P$16:$R$22,3,FALSE) -> 5184527.1 | M37: {=IF(B37=0,INDEX('Category 31'!F:F,MATCH(C37&E37&D37,'Category 31'!B:B&'Category 31'!C:C&'Category 31'!A:A,0)),INDEX('Category 31'!G:G,MATCH(C37&E37&D37,'Category 31'!B:B&'Category 31'!C:C&'Category 31'!A:A,0)))} -> 0 | N37: =M37/VLOOKUP($D37,CPI!$P$16:$R$22,3,FALSE) -> 0 | O37: =VLOOKUP(E37,MBasketball!C:P,8,FALSE) -> 233645
A38: 2 | B38: =IF(ISBLANK(G38),"",IF(MID(G38,1,1)="M",0,1)) -> 0 | C38: =IF(ISBLANK(H38),"",VLOOKUP(H38,Code!B:C,2,FALSE)) -> 8 | D38: 2019 | E38: 104179 | F38: Arizona | G38: Male | H38: Football | I38: {=IF(B38=0,INDEX('Category 14'!F:F,MATCH(C38&E38&D38,'Category 14'!B:B&'Category 14'!C:C&'Category 14'!A:A,0)),INDEX('Category 14'!G:G,MATCH(C38&E38&D38,'Category 14'!B:B&'Category 14'!C:C&'Category 14'!A:A,0)))} -> 471041 | J38: =I38/VLOOKUP($D38,CPI!$P$16:$R$22,3,FALSE) -> 557369.58 | K38: {=IF(B38=0,INDEX('Category 15'!F:F,MATCH(C38&E38&D38,'Category 15'!B:B&'Category 15'!C:C&'Category 15'!A:A,0)),INDEX('Category 15'!G:G,MATCH(C38&E38&D38,'Category 15'!B:B&'Category 31'!C:C&'Category 15'!A:A,0)))} -> 4381518 | L38: =K38/VLOOKUP($D38,CPI!$P$16:$R$22,3,FALSE) -> 5184527.1 | M38: {=IF(B38=0,INDEX('Category 31'!F:F,MATCH(C38&E38&D38,'Category 31'!B:B&'Category 31'!C:C&'Category 31'!A:A,0)),INDEX('Category 31'!G:G,MATCH(C38&E38&D38,'Category 31'!B:B&'Category 31'!C:C&'Category 31'!A:A,0)))} -> 0 | N38: =M38/VLOOKUP($D38,CPI!$P$16:$R$22,3,FALSE) -> 0 | O38: =VLOOKUP(E38,MFootball!C:P,8,FALSE) -> 318051
A39: 2 | B39: =IF(ISBLANK(G39),"",IF(MID(G39,1,1)="M",0,1)) -> 0 | C39: =IF(ISBLANK(H39),"",VLOOKUP(H39,Code!B:C,2,FALSE)) -> 9 | D39: 2019 | E39: 104179 | F39: Arizona | G39: Male | H39: Golf | I39: {=IF(B39=0,INDEX('Category 14'!F:F,MATCH(C39&E39&D39,'Category 14'!B:B&'Category 14'!C:C&'Category 14'!A:A,0)),INDEX('Category 14'!G:G,MATCH(C39&E39&D39,'Category 14'!B:B&'Category 14'!C:C&'Category 14'!A:A,0)))} -> 0 | J39: =I39/VLOOKUP($D39,CPI!$P$16:$R$22,3,FALSE) -> 0 | K39: {=IF(B39=0,INDEX('Category 15'!F:F,MATCH(C39&E39&D39,'Category 15'!B:B&'Category 15'!C:C&'Category 15'!A:A,0)),INDEX('Category 15'!G:G,MATCH(C39&E39&D39,'Category 15'!B:B&'Category 31'!C:C&'Category 15'!A:A,0)))} -> 0 | L39: =K39/VLOOKUP($D39,CPI!$P$16:$R$22,3,FALSE) -> 0 | M39: {=IF(B39=0,INDEX('Category 31'!F:F,MATCH(C39&E39&D39,'Category 31'!B:B&'Category 31'!C:C&'Category 31'!A:A,0)),INDEX('Category 31'!G:G,MATCH(C39&E39&D39,'Category 31'!B:B&'Category 31'!C:C&'Category 31'!A:A,0)))} -> 0 | N39: =M39/VLOOKUP($D39,CPI!$P$16:$R$22,3,FALSE) -> 0 | O39: 0
A40: 2 | B40: =IF(ISBLANK(G40),"",IF(MID(G40,1,1)="M",0,1)) -> 0 | C40: =IF(ISBLANK(H40),"",VLOOKUP(H40,Code!B:C,2,FALSE)) -> 19 | D40: 2019 | E40: 104179 | F40: Arizona | G40: Male | H40: Swimming and Diving | I40: {=IF(B40=0,INDEX('Category 14'!F:F,MATCH(C40&E40&D40,'Category 14'!B:B&'Category 14'!C:C&'Category 14'!A:A,0)),INDEX('Category 14'!G:G,MATCH(C40&E40&D40,'Category 14'!B:B&'Category 14'!C:C&'Category 14'!A:A,0)))} -> 0 | J40: =I40/VLOOKUP($D40,CPI!$P$16:$R$22,3,FALSE) -> 0 | K40: {=IF(B40=0,INDEX('Category 15'!F:F,MATCH(C40&E40&D40,'Category 15'!B:B&'Category 15'!C:C&'Category 15'!A:A,0)),INDEX('Category 15'!G:G,MATCH(C40&E40&D40,'Category 15'!B:B&'Category 31'!C:C&'Category 15'!A:A,0)))} -> 0 | L40: =K40/VLOOKUP($D40,CPI!$P$16:$R$22,3,FALSE) -> 0 | M40: {=IF(B40=0,INDEX('Category 31'!F:F,MATCH(C40&E40&D40,'Category 31'!B:B&'Category 31'!C:C&'Category 31'!A:A,0)),INDEX('Category 31'!G:G,MATCH(C40&E40&D40,'Category 31'!B:B&'Category 31'!C:C&'Category 31'!A:A,0)))} -> 0 | N40: =M40/VLOOKUP($D40,CPI!$P$16:$R$22,3,FALSE) -> 0 | O40: 0
A41: 2 | B41: =IF(ISBLANK(G41),"",IF(MID(G41,1,1)="M",0,1)) -> 0 | C41: =IF(ISBLANK(H41),"",VLOOKUP(H41,Code!B:C,2,FALSE)) -> 20 | D41: 2019 | E41: 104179 | F41: Arizona | G41: Male | H41: Tennis | I41: {=IF(B41=0,INDEX('Category 14'!F:F,MATCH(C41&E41&D41,'Category 14'!B:B&'Category 14'!C:C&'Category 14'!A:A,0)),INDEX('Category 14'!G:G,MATCH(C41&E41&D41,'Category 14'!B:B&'Category 14'!C:C&'Category 14'!A:A,0)))} -> 0 | J41: =I41/VLOOKUP($D41,CPI!$P$16:$R$22,3,FALSE) -> 0 | K41: {=IF(B41=0,INDEX('Category 15'!F:F,MATCH(C41&E41&D41,'Category 15'!B:B&'Category 15'!C:C&'Category 15'!A:A,0)),INDEX('Category 15'!G:G,MATCH(C41&E41&D41,'Category 15'!B:B&'Category 31'!C:C&'Category 15'!A:A,0)))} -> 0 | L41: =K41/VLOOKUP($D41,CPI!$P$16:$R$22,3,FALSE) -> 0 | M41: {=IF(B41=0,INDEX('Category 31'!F:F,MATCH(C41&E41&D41,'Category 31'!B:B&'Category 31'!C:C&'Category 31'!A:A,0)),INDEX('Category 31'!G:G,MATCH(C41&E41&D41,'Category 31'!B:B&'Category 31'!C:C&'Category 31'!A:A,0)))} -> 0 | N41: =M41/VLOOKUP($D41,CPI!$P$16:$R$22,3,FALSE) -> 0 | O41: 0
A42: 2 | B42: =IF(ISBLANK(G42),"",IF(MID(G42,1,1)="M",0,1)) -> 0 | C42: =IF(ISBLANK(H42),"",VLOOKUP(H42,Code!B:C,2,FALSE)) -> 21 | D42: 2019 | E42: 104179 | F42: Arizona | G42: Male | H42: Track and Field, X-Country | I42: {=IF(B42=0,INDEX('Category 14'!F:F,MATCH(C42&E42&D42,'Category 14'!B:B&'Category 14'!C:C&'Category 14'!A:A,0)),INDEX('Category 14'!G:G,MATCH(C42&E42&D42,'Category 14'!B:B&'Category 14'!C:C&'Category 14'!A:A,0)))} -> 0 | J42: =I42/VLOOKUP($D42,CPI!$P$16:$R$22,3,FALSE) -> 0 | K42: {=IF(B42=0,INDEX('Category 15'!F:F,MATCH(C42&E42&D42,'Category 15'!B:B&'Category 15'!C:C&'Category 15'!A:A,0)),INDEX('Category 15'!G:G,MATCH(C42&E42&D42,'Category 15'!B:B&'Category 31'!C:C&'Category 15'!A:A,0)))} -> 0 | L42: =K42/VLOOKUP($D42,CPI!$P$16:$R$22,3,FALSE) -> 0 | M42: {=IF(B42=0,INDEX('Category 31'!F:F,MATCH(C42&E42&D42,'Category 31'!B:B&'Category 31'!C:C&'Category 31'!A:A,0)),INDEX('Category 31'!G:G,MATCH(C42&E42&D42,'Category 31'!B:B&'Category 31'!C:C&'Category 31'!A:A,0)))} -> 0 | N42: =M42/VLOOKUP($D42,CPI!$P$16:$R$22,3,FALSE) -> 0 | O42: 0
A43: 2 | B43: =IF(ISBLANK(G43),"",IF(MID(G43,1,1)="M",0,1)) -> 1 | C43: =IF(ISBLANK(H43),"",VLOOKUP(H43,Code!B:C,2,FALSE)) -> 2 | D43: 2019 | E43: 104179 | F43: Arizona | G43: Female | H43: Basketball | I43: {=IF(B43=0,INDEX('Category 14'!F:F,MATCH(C43&E43&D43,'Category 14'!B:B&'Category 14'!C:C&'Category 14'!A:A,0)),INDEX('Category 14'!G:G,MATCH(C43&E43&D43,'Category 14'!B:B&'Category 14'!C:C&'Category 14'!A:A,0)))} -> 0 | J43: =I43/VLOOKUP($D43,CPI!$P$16:$R$22,3,FALSE) -> 0 | K43: {=IF(B43=0,INDEX('Category 15'!F:F,MATCH(C43&E43&D43,'Category 15'!B:B&'Category 15'!C:C&'Category 15'!A:A,0)),INDEX('Category 15'!G:G,MATCH(C43&E43&D43,'Category 15'!B:B&'Category 31'!C:C&'Category 15'!A:A,0)))} -> 0 | L43: =K43/VLOOKUP($D43,CPI!$P$16:$R$22,3,FALSE) -> 0 | M43: {=IF(B43=0,INDEX('Category 31'!F:F,MATCH(C43&E43&D43,'Category 31'!B:B&'Category 31'!C:C&'Category 31'!A:A,0)),INDEX('Category 31'!G:G,MATCH(C43&E43&D43,'Category 31'!B:B&'Category 31'!C:C&'Category 31'!A:A,0)))} -> 0 | N43: =M43/VLOOKUP($D43,CPI!$P$16:$R$22,3,FALSE) -> 0 | O43: =VLOOKUP(E43,WBasketball!C:P,8,FALSE) -> 80850
A44: 2 | B44: =IF(ISBLANK(G44),"",IF(MID(G44,1,1)="M",0,1)) -> 1 | C44: =IF(ISBLANK(H44),"",VLOOKUP(H44,Code!B:C,2,FALSE)) -> 3 | D44: 2019 | E44: 104179 | F44: Arizona | G44: Female | H44: Beach Volleyball | I44: {=IF(B44=0,INDEX('Category 14'!F:F,MATCH(C44&E44&D44,'Category 14'!B:B&'Category 14'!C:C&'Category 14'!A:A,0)),INDEX('Category 14'!G:G,MATCH(C44&E44&D44,'Category 14'!B:B&'Category 14'!C:C&'Category 14'!A:A,0)))} -> 590 | J44: =I44/VLOOKUP($D44,CPI!$P$16:$R$22,3,FALSE) -> 698.13042 | K44: {=IF(B44=0,INDEX('Category 15'!F:F,MATCH(C44&E44&D44,'Category 15'!B:B&'Category 15'!C:C&'Category 15'!A:A,0)),INDEX('Category 15'!G:G,MATCH(C44&E44&D44,'Category 15'!B:B&'Category 31'!C:C&'Category 15'!A:A,0)))} -> 0 | L44: =K44/VLOOKUP($D44,CPI!$P$16:$R$22,3,FALSE) -> 0 | M44: {=IF(B44=0,INDEX('Category 31'!F:F,MATCH(C44&E44&D44,'Category 31'!B:B&'Category 31'!C:C&'Category 31'!A:A,0)),INDEX('Category 31'!G:G,MATCH(C44&E44&D44,'Category 31'!B:B&'Category 31'!C:C&'Category 31'!A:A,0)))} -> 0 | N44: =M44/VLOOKUP($D44,CPI!$P$16:$R$22,3,FALSE) -> 0 | O44: 0
A45: 2 | B45: =IF(ISBLANK(G45),"",IF(MID(G45,1,1)="M",0,1)) -> 1 | C45: =IF(ISBLANK(H45),"",VLOOKUP(H45,Code!B:C,2,FALSE)) -> 9 | D45: 2019 | E45: 104179 | F45: Arizona | G45: Female | H45: Golf | I45: {=IF(B45=0,INDEX('Category 14'!F:F,MATCH(C45&E45&D45,'Category 14'!B:B&'Category 14'!C:C&'Category 14'!A:A,0)),INDEX('Category 14'!G:G,MATCH(C45&E45&D45,'Category 14'!B:B&'Category 14'!C:C&'Category 14'!A:A,0)))} -> 0 | J45: =I45/VLOOKUP($D45,CPI!$P$16:$R$22,3,FALSE) -> 0 | K45: {=IF(B45=0,INDEX('Category 15'!F:F,MATCH(C45&E45&D45,'Category 15'!B:B&'Category 15'!C:C&'Category 15'!A:A,0)),INDEX('Category 15'!G:G,MATCH(C45&E45&D45,'Category 15'!B:B&'Category 31'!C:C&'Category 15'!A:A,0)))} -> 0 | L45: =K45/VLOOKUP($D45,CPI!$P$16:$R$22,3,FALSE) -> 0 | M45: {=IF(B45=0,INDEX('Category 31'!F:F,MATCH(C45&E45&D45,'Category 31'!B:B&'Category 31'!C:C&'Category 31'!A:A,0)),INDEX('Category 31'!G:G,MATCH(C45&E45&D45,'Category 31'!B:B&'Category 31'!C:C&'Category 31'!A:A,0)))} -> 0 | N45: =M45/VLOOKUP($D45,CPI!$P$16:$R$22,3,FALSE) -> 0 | O45: 0
A46: 2 | B46: =IF(ISBLANK(G46),"",IF(MID(G46,1,1)="M",0,1)) -> 1 | C46: =IF(ISBLANK(H46),"",VLOOKUP(H46,Code!B:C,2,FALSE)) -> 10 | D46: 2019 | E46: 104179 | F46: Arizona | G46: Female | H46: Gymnastics | I46: {=IF(B46=0,INDEX('Category 14'!F:F,MATCH(C46&E46&D46,'Category 14'!B:B&'Category 14'!C:C&'Category 14'!A:A,0)),INDEX('Category 14'!G:G,MATCH(C46&E46&D46,'Category 14'!B:B&'Category 14'!C:C&'Category 14'!A:A,0)))} -> 0 | J46: =I46/VLOOKUP($D46,CPI!$P$16:$R$22,3,FALSE) -> 0 | K46: {=IF(B46=0,INDEX('Category 15'!F:F,MATCH(C46&E46&D46,'Category 15'!B:B&'Category 15'!C:C&'Category 15'!A:A,0)),INDEX('Category 15'!G:G,MATCH(C46&E46&D46,'Category 15'!B:B&'Category 31'!C:C&'Category 15'!A:A,0)))} -> 0 | L46: =K46/VLOOKUP($D46,CPI!$P$16:$R$22,3,FALSE) -> 0 | M46: {=IF(B46=0,INDEX('Category 31'!F:F,MATCH(C46&E46&D46,'Category 31'!B:B&'Category 31'!C:C&'Category 31'!A:A,0)),INDEX('Category 31'!G:G,MATCH(C46&E46&D46,'Category 31'!B:B&'Category 31'!C:C&'Category 31'!A:A,0)))} -> 0 | N46: =M46/VLOOKUP($D46,CPI!$P$16:$R$22,3,FALSE) -> 0 | O46: 0
A47: 2 | B47: =IF(ISBLANK(G47),"",IF(MID(G47,1,1)="M",0,1)) -> 1 | C47: =IF(ISBLANK(H47),"",VLOOKUP(H47,Code!B:C,2,FALSE)) -> 17 | D47: 2019 | E47: 104179 | F47: Arizona | G47: Female | H47: Soccer | I47: {=IF(B47=0,INDEX('Category 14'!F:F,MATCH(C47&E47&D47,'Category 14'!B:B&'Category 14'!C:C&'Category 14'!A:A,0)),INDEX('Category 14'!G:G,MATCH(C47&E47&D47,'Category 14'!B:B&'Category 14'!C:C&'Category 14'!A:A,0)))} -> 14756 | J47: =I47/VLOOKUP($D47,CPI!$P$16:$R$22,3,FALSE) -> 17460.36 | K47: {=IF(B47=0,INDEX('Category 15'!F:F,MATCH(C47&E47&D47,'Category 15'!B:B&'Category 15'!C:C&'Category 15'!A:A,0)),INDEX('Category 15'!G:G,MATCH(C47&E47&D47,'Category 15'!B:B&'Category 31'!C:C&'Category 15'!A:A,0)))} -> 0 | L47: =K47/VLOOKUP($D47,CPI!$P$16:$R$22,3,FALSE) -> 0 | M47: {=IF(B47=0,INDEX('Category 31'!F:F,MATCH(C47&E47&D47,'Category 31'!B:B&'Category 31'!C:C&'Category 31'!A:A,0)),INDEX('Category 31'!G:G,MATCH(C47&E47&D47,'Category 31'!B:B&'Category 31'!C:C&'Category 31'!A:A,0)))} -> 0 | N47: =M47/VLOOKUP($D47,CPI!$P$16:$R$22,3,FALSE) -> 0 | O47: =VLOOKUP(E47,WSoccer!C:P,8,FALSE) -> 9314
A48: 2 | B48: =IF(ISBLANK(G48),"",IF(MID(G48,1,1)="M",0,1)) -> 1 | C48: =IF(ISBLANK(H48),"",VLOOKUP(H48,Code!B:C,2,FALSE)) -> 18 | D48: 2019 | E48: 104179 | F48: Arizona | G48: Female | H48: Softball | I48: {=IF(B48=0,INDEX('Category 14'!F:F,MATCH(C48&E48&D48,'Category 14'!B:B&'Category 14'!C:C&'Category 14'!A:A,0)),INDEX('Category 14'!G:G,MATCH(C48&E48&D48,'Category 14'!B:B&'Category 14'!C:C&'Category 14'!A:A,0)))} -> 0 | J48: =I48/VLOOKUP($D48,CPI!$P$16:$R$22,3,FALSE) -> 0 | K48: {=IF(B48=0,INDEX('Category 15'!F:F,MATCH(C48&E48&D48,'Category 15'!B:B&'Category 15'!C:C&'Category 15'!A:A,0)),INDEX('Category 15'!G:G,MATCH(C48&E48&D48,'Category 15'!B:B&'Category 31'!C:C&'Category 15'!A:A,0)))} -> 0 | L48: =K48/VLOOKUP($D48,CPI!$P$16:$R$22,3,FALSE) -> 0 | M48: {=IF(B48=0,INDEX('Category 31'!F:F,MATCH(C48&E48&D48,'Category 31'!B:B&'Category 31'!C:C&'Category 31'!A:A,0)),INDEX('Category 31'!G:G,MATCH(C48&E48&D48,'Category 31'!B:B&'Category 31'!C:C&'Category 31'!A:A,0)))} -> 0 | N48: =M48/VLOOKUP($D48,CPI!$P$16:$R$22,3,FALSE) -> 0 | O48: =VLOOKUP(E48,WSoftball!C:P,8,FALSE) -> 72405
A49: 2 | B49: =IF(ISBLANK(G49),"",IF(MID(G49,1,1)="M",0,1)) -> 1 | C49: =IF(ISBLANK(H49),"",VLOOKUP(H49,Code!B:C,2,FALSE)) -> 19 | D49: 2019 | E49: 104179 | F49: Arizona | G49: Female | H49: Swimming and Diving | I49: {=IF(B49=0,INDEX('Category 14'!F:F,MATCH(C49&E49&D49,'Category 14'!B:B&'Category 14'!C:C&'Category 14'!A:A,0)),INDEX('Category 14'!G:G,MATCH(C49&E49&D49,'Category 14'!B:B&'Category 14'!C:C&'Category 14'!A:A,0)))} -> 0 | J49: =I49/VLOOKUP($D49,CPI!$P$16:$R$22,3,FALSE) -> 0 | K49: {=IF(B49=0,INDEX('Category 15'!F:F,MATCH(C49&E49&D49,'Category 15'!B:B&'Category 15'!C:C&'Category 15'!A:A,0)),INDEX('Category 15'!G:G,MATCH(C49&E49&D49,'Category 15'!B:B&'Category 31'!C:C&'Category 15'!A:A,0)))} -> 0 | L49: =K49/VLOOKUP($D49,CPI!$P$16:$R$22,3,FALSE) -> 0 | M49: {=IF(B49=0,INDEX('Category 31'!F:F,MATCH(C49&E49&D49,'Category 31'!B:B&'Category 31'!C:C&'Category 31'!A:A,0)),INDEX('Category 31'!G:G,MATCH(C49&E49&D49,'Category 31'!B:B&'Category 31'!C:C&'Category 31'!A:A,0)))} -> 0 | N49: =M49/VLOOKUP($D49,CPI!$P$16:$R$22,3,FALSE) -> 0 | O49: 0
A50: 2 | B50: =IF(ISBLANK(G50),"",IF(MID(G50,1,1)="M",0,1)) -> 1 | C50: =IF(ISBLANK(H50),"",VLOOKUP(H50,Code!B:C,2,FALSE)) -> 20 | D50: 2019 | E50: 104179 | F50: Arizona | G50: Female | H50: Tennis | I50: {=IF(B50=0,INDEX('Category 14'!F:F,MATCH(C50&E50&D50,'Category 14'!B:B&'Category 14'!C:C&'Category 14'!A:A,0)),INDEX('Category 14'!G:G,MATCH(C50&E50&D50,'Category 14'!B:B&'Category 14'!C:C&'Category 14'!A:A,0)))} -> 0 | J50: =I50/VLOOKUP($D50,CPI!$P$16:$R$22,3,FALSE) -> 0 | K50: {=IF(B50=0,INDEX('Category 15'!F:F,MATCH(C50&E50&D50,'Category 15'!B:B&'Category 15'!C:C&'Category 15'!A:A,0)),INDEX('Category 15'!G:G,MATCH(C50&E50&D50,'Category 15'!B:B&'Category 31'!C:C&'Category 15'!A:A,0)))} -> 0 | L50: =K50/VLOOKUP($D50,CPI!$P$16:$R$22,3,FALSE) -> 0 | M50: {=IF(B50=0,INDEX('Category 31'!F:F,MATCH(C50&E50&D50,'Category 31'!B:B&'Category 31'!C:C&'Category 31'!A:A,0)),INDEX('Category 31'!G:G,MATCH(C50&E50&D50,'Category 31'!B:B&'Category 31'!C:C&'Category 31'!A:A,0)))} -> 0 | N50: =M50/VLOOKUP($D50,CPI!$P$16:$R$22,3,FALSE) -> 0 | O50: 0
A51: 2 | B51: =IF(ISBLANK(G51),"",IF(MID(G51,1,1)="M",0,1)) -> 1 | C51: =IF(ISBLANK(H51),"",VLOOKUP(H51,Code!B:C,2,FALSE)) -> 21 | D51: 2019 | E51: 104179 | F51: Arizona | G51: Female | H51: Track and Field, X-Country | I51: {=IF(B51=0,INDEX('Category 14'!F:F,MATCH(C51&E51&D51,'Category 14'!B:B&'Category 14'!C:C&'Category 14'!A:A,0)),INDEX('Category 14'!G:G,MATCH(C51&E51&D51,'Category 14'!B:B&'Category 14'!C:C&'Category 14'!A:A,0)))} -> 0 | J51: =I51/VLOOKUP($D51,CPI!$P$16:$R$22,3,FALSE) -> 0 | K51: {=IF(B51=0,INDEX('Category 15'!F:F,MATCH(C51&E51&D51,'Category 15'!B:B&'Category 15'!C:C&'Category 15'!A:A,0)),INDEX('Category 15'!G:G,MATCH(C51&E51&D51,'Category 15'!B:B&'Category 31'!C:C&'Category 15'!A:A,0)))} -> 0 | L51: =K51/VLOOKUP($D51,CPI!$P$16:$R$22,3,FALSE) -> 0 | M51: {=IF(B51=0,INDEX('Category 31'!F:F,MATCH(C51&E51&D51,'Category 31'!B:B&'Category 31'!C:C&'Category 31'!A:A,0)),INDEX('Category 31'!G:G,MATCH(C51&E51&D51,'Category 31'!B:B&'Category 31'!C:C&'Category 31'!A:A,0)))} -> 0 | N51: =M51/VLOOKUP($D51,CPI!$P$16:$R$22,3,FALSE) -> 0 | O51: 0
A52: 2 | B52: =IF(ISBLANK(G52),"",IF(MID(G52,1,1)="M",0,1)) -> 1 | C52: =IF(ISBLANK(H52),"",VLOOKUP(H52,Code!B:C,2,FALSE)) -> 23 | D52: 2019 | E52: 104179 | F52: Arizona | G52: Female | H52: Volleyball | I52: {=IF(B52=0,INDEX('Category 14'!F:F,MATCH(C52&E52&D52,'Category 14'!B:B&'Category 14'!C:C&'Category 14'!A:A,0)),INDEX('Category 14'!G:G,MATCH(C52&E52&D52,'Category 14'!B:B&'Category 14'!C:C&'Category 14'!A:A,0)))} -> 0 | J52: =I52/VLOOKUP($D52,CPI!$P$16:$R$22,3,FALSE) -> 0 | K52: {=IF(B52=0,INDEX('Category 15'!F:F,MATCH(C52&E52&D52,'Category 15'!B:B&'Category 15'!C:C&'Category 15'!A:A,0)),INDEX('Category 15'!G:G,MATCH(C52&E52&D52,'Category 15'!B:B&'Category 31'!C:C&'Category 15'!A:A,0)))} -> 0 | L52: =K52/VLOOKUP($D52,CPI!$P$16:$R$22,3,FALSE) -> 0 | M52: {=IF(B52=0,INDEX('Category 31'!F:F,MATCH(C52&E52&D52,'Category 31'!B:B&'Category 31'!C:C&'Category 31'!A:A,0)),INDEX('Category 31'!G:G,MATCH(C52&E52&D52,'Category 31'!B:B&'Category 31'!C:C&'Category 31'!A:A,0)))} -> 0 | N52: =M52/VLOOKUP($D52,CPI!$P$16:$R$22,3,FALSE) -> 0 | O52: =VLOOKUP(E52,WVolleyball!C:P,8,FALSE) -> 20066
A53: 2 | B53: =IF(ISBLANK(G53),"",IF(MID(G53,1,1)="M",0,1)) -> 0 | C53: =IF(ISBLANK(H53),"",VLOOKUP(H53,Code!B:C,2,FALSE)) -> 1 | D53: 2020 | E53: 104179 | F53: Arizona | G53: Male | H53: Baseball | I53: {=IF(B53=0,INDEX('Category 14'!F:F,MATCH(C53&E53&D53,'Category 14'!B:B&'Category 14'!C:C&'Category 14'!A:A,0)),INDEX('Category 14'!G:G,MATCH(C53&E53&D53,'Category 14'!B:B&'Category 14'!C:C&'Category 14'!A:A,0)))} -> 55 | J53: =I53/VLOOKUP($D53,CPI!$P$16:$R$22,3,FALSE) -> 64.077683 | K53: {=IF(B53=0,INDEX('Category 15'!F:F,MATCH(C53&E53&D53,'Category 15'!B:B&'Category 15'!C:C&'Category 15'!A:A,0)),INDEX('Category 15'!G:G,MATCH(C53&E53&D53,'Category 15'!B:B&'Category 31'!C:C&'Category 15'!A:A,0)))} -> 0 | L53: =K53/VLOOKUP($D53,CPI!$P$16:$R$22,3,FALSE) -> 0 | M53: {=IF(B53=0,INDEX('Category 31'!F:F,MATCH(C53&E53&D53,'Category 31'!B:B&'Category 31'!C:C&'Category 31'!A:A,0)),INDEX('Category 31'!G:G,MATCH(C53&E53&D53,'Category 31'!B:B&'Category 31'!C:C&'Category 31'!A:A,0)))} -> 0 | N53: =M53/VLOOKUP($D53,CPI!$P$16:$R$22,3,FALSE) -> 0 | O53: 21831
A54: 2 | B54: =IF(ISBLANK(G54),"",IF(MID(G54,1,1)="M",0,1)) -> 0 | C54: =IF(ISBLANK(H54),"",VLOOKUP(H54,Code!B:C,2,FALSE)) -> 2 | D54: 2020 | E54: 104179 | F54: Arizona | G54: Male | H54: Basketball | I54: {=IF(B54=0,INDEX('Category 14'!F:F,MATCH(C54&E54&D54,'Category 14'!B:B&'Category 14'!C:C&'Category 14'!A:A,0)),INDEX('Category 14'!G:G,MATCH(C54&E54&D54,'Category 14'!B:B&'Category 14'!C:C&'Category 14'!A:A,0)))} -> 111966 | J54: =I54/VLOOKUP($D54,CPI!$P$16:$R$22,3,FALSE) -> 130445.85 | K54: {=IF(B54=0,INDEX('Category 15'!F:F,MATCH(C54&E54&D54,'Category 15'!B:B&'Category 15'!C:C&'Category 15'!A:A,0)),INDEX('Category 15'!G:G,MATCH(C54&E54&D54,'Category 15'!B:B&'Category 31'!C:C&'Category 15'!A:A,0)))} -> 4185479 | L54: =K54/VLOOKUP($D54,CPI!$P$16:$R$22,3,FALSE) -> 4876287.2 | M54: {=IF(B54=0,INDEX('Category 31'!F:F,MATCH(C54&E54&D54,'Category 31'!B:B&'Category 31'!C:C&'Category 31'!A:A,0)),INDEX('Category 31'!G:G,MATCH(C54&E54&D54,'Category 31'!B:B&'Category 31'!C:C&'Category 31'!A:A,0)))} -> 0 | N54: =M54/VLOOKUP($D54,CPI!$P$16:$R$22,3,FALSE) -> 0 | O54: =VLOOKUP(E37,MBasketball!C:P,9,FALSE) -> 232114
A55: 2 | B55: =IF(ISBLANK(G55),"",IF(MID(G55,1,1)="M",0,1)) -> 0 | C55: =IF(ISBLANK(H55),"",VLOOKUP(H55,Code!B:C,2,FALSE)) -> 8 | D55: 2020 | E55: 104179 | F55: Arizona | G55: Male | H55: Football | I55: {=IF(B55=0,INDEX('Category 14'!F:F,MATCH(C55&E55&D55,'Category 14'!B:B&'Category 14'!C:C&'Category 14'!A:A,0)),INDEX('Category 14'!G:G,MATCH(C55&E55&D55,'Category 14'!B:B&'Category 14'!C:C&'Category 14'!A:A,0)))} -> 448366 | J55: =I55/VLOOKUP($D55,CPI!$P$16:$R$22,3,FALSE) -> 522368.27 | K55: {=IF(B55=0,INDEX('Category 15'!F:F,MATCH(C55&E55&D55,'Category 15'!B:B&'Category 15'!C:C&'Category 15'!A:A,0)),INDEX('Category 15'!G:G,MATCH(C55&E55&D55,'Category 15'!B:B&'Category 31'!C:C&'Category 15'!A:A,0)))} -> 4185478 | L55: =K55/VLOOKUP($D55,CPI!$P$16:$R$22,3,FALSE) -> 4876286.1 | M55: {=IF(B55=0,INDEX('Category 31'!F:F,MATCH(C55&E55&D55,'Category 31'!B:B&'Category 31'!C:C&'Category 31'!A:A,0)),INDEX('Category 31'!G:G,MATCH(C55&E55&D55,'Category 31'!B:B&'Category 31'!C:C&'Category 31'!A:A,0)))} -> 0 | N55: =M55/VLOOKUP($D55,CPI!$P$16:$R$22,3,FALSE) -> 0 | O55: =VLOOKUP(E38,MFootball!C:P,9,FALSE) -> 237194
A56: 2 | B56: =IF(ISBLANK(G56),"",IF(MID(G56,1,1)="M",0,1)) -> 0 | C56: =IF(ISBLANK(H56),"",VLOOKUP(H56,Code!B:C,2,FALSE)) -> 9 | D56: 2020 | E56: 104179 | F56: Arizona | G56: Male | H56: Golf | I56: {=IF(B56=0,INDEX('Category 14'!F:F,MATCH(C56&E56&D56,'Category 14'!B:B&'Category 14'!C:C&'Category 14'!A:A,0)),INDEX('Category 14'!G:G,MATCH(C56&E56&D56,'Category 14'!B:B&'Category 14'!C:C&'Category 14'!A:A,0)))} -> 0 | J56: =I56/VLOOKUP($D56,CPI!$P$16:$R$22,3,FALSE) -> 0 | K56: {=IF(B56=0,INDEX('Category 15'!F:F,MATCH(C56&E56&D56,'Category 15'!B:B&'Category 15'!C:C&'Category 15'!A:A,0)),INDEX('Category 15'!G:G,MATCH(C56&E56&D56,'Category 15'!B:B&'Category 31'!C:C&'Category 15'!A:A,0)))} -> 0 | L56: =K56/VLOOKUP($D56,CPI!$P$16:$R$22,3,FALSE) -> 0 | M56: {=IF(B56=0,INDEX('Category 31'!F:F,MATCH(C56&E56&D56,'Category 31'!B:B&'Category 31'!C:C&'Category 31'!A:A,0)),INDEX('Category 31'!G:G,MATCH(C56&E56&D56,'Category 31'!B:B&'Category 31'!C:C&'Category 31'!A:A,0)))} -> 0 | N56: =M56/VLOOKUP($D56,CPI!$P$16:$R$22,3,FALSE) -> 0 | O56: 0
A57: 2 | B57: =IF(ISBLANK(G57),"",IF(MID(G57,1,1)="M",0,1)) -> 0 | C57: =IF(ISBLANK(H57),"",VLOOKUP(H57,Code!B:C,2,FALSE)) -> 19 | D57: 2020 | E57: 104179 | F57: Arizona | G57: Male | H57: Swimming and Diving | I57: {=IF(B57=0,INDEX('Category 14'!F:F,MATCH(C57&E57&D57,'Category 14'!B:B&'Category 14'!C:C&'Category 14'!A:A,0)),INDEX('Category 14'!G:G,MATCH(C57&E57&D57,'Category 14'!B:B&'Category 14'!C:C&'Category 14'!A:A,0)))} -> 0 | J57: =I57/VLOOKUP($D57,CPI!$P$16:$R$22,3,FALSE) -> 0 | K57: {=IF(B57=0,INDEX('Category 15'!F:F,MATCH(C57&E57&D57,'Category 15'!B:B&'Category 15'!C:C&'Category 15'!A:A,0)),INDEX('Category 15'!G:G,MATCH(C57&E57&D57,'Category 15'!B:B&'Category 31'!C:C&'Category 15'!A:A,0)))} -> 0 | L57: =K57/VLOOKUP($D57,CPI!$P$16:$R$22,3,FALSE) -> 0 | M57: {=IF(B57=0,INDEX('Category 31'!F:F,MATCH(C57&E57&D57,'Category 31'!B:B&'Category 31'!C:C&'Category 31'!A:A,0)),INDEX('Category 31'!G:G,MATCH(C57&E57&D57,'Category 31'!B:B&'Category 31'!C:C&'Category 31'!A:A,0)))} -> 0 | N57: =M57/VLOOKUP($D57,CPI!$P$16:$R$22,3,FALSE) -> 0 | O57: 0
A58: 2 | B58: =IF(ISBLANK(G58),"",IF(MID(G58,1,1)="M",0,1)) -> 0 | C58: =IF(ISBLANK(H58),"",VLOOKUP(H58,Code!B:C,2,FALSE)) -> 20 | D58: 2020 | E58: 104179 | F58: Arizona | G58: Male | H58: Tennis | I58: {=IF(B58=0,INDEX('Category 14'!F:F,MATCH(C58&E58&D58,'Category 14'!B:B&'Category 14'!C:C&'Category 14'!A:A,0)),INDEX('Category 14'!G:G,MATCH(C58&E58&D58,'Category 14'!B:B&'Category 14'!C:C&'Category 14'!A:A,0)))} -> 0 | J58: =I58/VLOOKUP($D58,CPI!$P$16:$R$22,3,FALSE) -> 0 | K58: {=IF(B58=0,INDEX('Category 15'!F:F,MATCH(C58&E58&D58,'Category 15'!B:B&'Category 15'!C:C&'Category 15'!A:A,0)),INDEX('Category 15'!G:G,MATCH(C58&E58&D58,'Category 15'!B:B&'Category 31'!C:C&'Category 15'!A:A,0)))} -> 0 | L58: =K58/VLOOKUP($D58,CPI!$P$16:$R$22,3,FALSE) -> 0 | M58: {=IF(B58=0,INDEX('Category 31'!F:F,MATCH(C58&E58&D58,'Category 31'!B:B&'Category 31'!C:C&'Category 31'!A:A,0)),INDEX('Category 31'!G:G,MATCH(C58&E58&D58,'Category 31'!B:B&'Category 31'!C:C&'Category 31'!A:A,0)))} -> 0 | N58: =M58/VLOOKUP($D58,CPI!$P$16:$R$22,3,FALSE) -> 0 | O58: 0
A59: 2 | B59: =IF(ISBLANK(G59),"",IF(MID(G59,1,1)="M",0,1)) -> 0 | C59: =IF(ISBLANK(H59),"",VLOOKUP(H59,Code!B:C,2,FALSE)) -> 21 | D59: 2020 | E59: 104179 | F59: Arizona | G59: Male | H59: Track and Field, X-Country | I59: {=IF(B59=0,INDEX('Category 14'!F:F,MATCH(C59&E59&D59,'Category 14'!B:B&'Category 14'!C:C&'Category 14'!A:A,0)),INDEX('Category 14'!G:G,MATCH(C59&E59&D59,'Category 14'!B:B&'Category 14'!C:C&'Category 14'!A:A,0)))} -> 0 | J59: =I59/VLOOKUP($D59,CPI!$P$16:$R$22,3,FALSE) -> 0 | K59: {=IF(B59=0,INDEX('Category 15'!F:F,MATCH(C59&E59&D59,'Category 15'!B:B&'Category 15'!C:C&'Category 15'!A:A,0)),INDEX('Category 15'!G:G,MATCH(C59&E59&D59,'Category 15'!B:B&'Category 31'!C:C&'Category 15'!A:A,0)))} -> 0 | L59: =K59/VLOOKUP($D59,CPI!$P$16:$R$22,3,FALSE) -> 0 | M59: {=IF(B59=0,INDEX('Category 31'!F:F,MATCH(C59&E59&D59,'Category 31'!B:B&'Category 31'!C:C&'Category 31'!A:A,0)),INDEX('Category 31'!G:G,MATCH(C59&E59&D59,'Category 31'!B:B&'Category 31'!C:C&'Category 31'!A:A,0)))} -> 0 | N59: =M59/VLOOKUP($D59,CPI!$P$16:$R$22,3,FALSE) -> 0 | O59: 0
A60: 2 | B60: =IF(ISBLANK(G60),"",IF(MID(G60,1,1)="M",0,1)) -> 1 | C60: =IF(ISBLANK(H60),"",VLOOKUP(H60,Code!B:C,2,FALSE)) -> 2 | D60: 2020 | E60: 104179 | F60: Arizona | G60: Female | H60: Basketball | I60: {=IF(B60=0,INDEX('Category 14'!F:F,MATCH(C60&E60&D60,'Category 14'!B:B&'Category 14'!C:C&'Category 14'!A:A,0)),INDEX('Category 14'!G:G,MATCH(C60&E60&D60,'Category 14'!B:B&'Category 14'!C:C&'Category 14'!A:A,0)))} -> 0 | J60: =I60/VLOOKUP($D60,CPI!$P$16:$R$22,3,FALSE) -> 0 | K60: {=IF(B60=0,INDEX('Category 15'!F:F,MATCH(C60&E60&D60,'Category 15'!B:B&'Category 15'!C:C&'Category 15'!A:A,0)),INDEX('Category 15'!G:G,MATCH(C60&E60&D60,'Category 15'!B:B&'Category 31'!C:C&'Category 15'!A:A,0)))} -> 0 | L60: =K60/VLOOKUP($D60,CPI!$P$16:$R$22,3,FALSE) -> 0 | M60: {=IF(B60=0,INDEX('Category 31'!F:F,MATCH(C60&E60&D60,'Category 31'!B:B&'Category 31'!C:C&'Category 31'!A:A,0)),INDEX('Category 31'!G:G,MATCH(C60&E60&D60,'Category 31'!B:B&'Category 31'!C:C&'Category 31'!A:A,0)))} -> 0 | N60: =M60/VLOOKUP($D60,CPI!$P$16:$R$22,3,FALSE) -> 0 | O60: =VLOOKUP(E43,WBasketball!C:P,9,FALSE) -> 95098
A61: 2 | B61: =IF(ISBLANK(G61),"",IF(MID(G61,1,1)="M",0,1)) -> 1 | C61: =IF(ISBLANK(H61),"",VLOOKUP(H61,Code!B:C,2,FALSE)) -> 3 | D61: 2020 | E61: 104179 | F61: Arizona | G61: Female | H61: Beach Volleyball | I61: {=IF(B61=0,INDEX('Category 14'!F:F,MATCH(C61&E61&D61,'Category 14'!B:B&'Category 14'!C:C&'Category 14'!A:A,0)),INDEX('Category 14'!G:G,MATCH(C61&E61&D61,'Category 14'!B:B&'Category 14'!C:C&'Category 14'!A:A,0)))} -> 0 | J61: =I61/VLOOKUP($D61,CPI!$P$16:$R$22,3,FALSE) -> 0 | K61: {=IF(B61=0,INDEX('Category 15'!F:F,MATCH(C61&E61&D61,'Category 15'!B:B&'Category 15'!C:C&'Category 15'!A:A,0)),INDEX('Category 15'!G:G,MATCH(C61&E61&D61,'Category 15'!B:B&'Category 31'!C:C&'Category 15'!A:A,0)))} -> 0 | L61: =K61/VLOOKUP($D61,CPI!$P$16:$R$22,3,FALSE) -> 0 | M61: {=IF(B61=0,INDEX('Category 31'!F:F,MATCH(C61&E61&D61,'Category 31'!B:B&'Category 31'!C:C&'Category 31'!A:A,0)),INDEX('Category 31'!G:G,MATCH(C61&E61&D61,'Category 31'!B:B&'Category 31'!C:C&'Category 31'!A:A,0)))} -> 0 | N61: =M61/VLOOKUP($D61,CPI!$P$16:$R$22,3,FALSE) -> 0 | O61: 0
A62: 2 | B62: =IF(ISBLANK(G62),"",IF(MID(G62,1,1)="M",0,1)) -> 1 | C62: =IF(ISBLANK(H62),"",VLOOKUP(H62,Code!B:C,2,FALSE)) -> 9 | D62: 2020 | E62: 104179 | F62: Arizona | G62: Female | H62: Golf | I62: {=IF(B62=0,INDEX('Category 14'!F:F,MATCH(C62&E62&D62,'Category 14'!B:B&'Category 14'!C:C&'Category 14'!A:A,0)),INDEX('Category 14'!G:G,MATCH(C62&E62&D62,'Category 14'!B:B&'Category 14'!C:C&'Category 14'!A:A,0)))} -> 0 | J62: =I62/VLOOKUP($D62,CPI!$P$16:$R$22,3,FALSE) -> 0 | K62: {=IF(B62=0,INDEX('Category 15'!F:F,MATCH(C62&E62&D62,'Category 15'!B:B&'Category 15'!C:C&'Category 15'!A:A,0)),INDEX('Category 15'!G:G,MATCH(C62&E62&D62,'Category 15'!B:B&'Category 31'!C:C&'Category 15'!A:A,0)))} -> 0 | L62: =K62/VLOOKUP($D62,CPI!$P$16:$R$22,3,FALSE) -> 0 | M62: {=IF(B62=0,INDEX('Category 31'!F:F,MATCH(C62&E62&D62,'Category 31'!B:B&'Category 31'!C:C&'Category 31'!A:A,0)),INDEX('Category 31'!G:G,MATCH(C62&E62&D62,'Category 31'!B:B&'Category 31'!C:C&'Category 31'!A:A,0)))} -> 0 | N62: =M62/VLOOKUP($D62,CPI!$P$16:$R$22,3,FALSE) -> 0 | O62: 0
A63: 2 | B63: =IF(ISBLANK(G63),"",IF(MID(G63,1,1)="M",0,1)) -> 1 | C63: =IF(ISBLANK(H63),"",VLOOKUP(H63,Code!B:C,2,FALSE)) -> 10 | D63: 2020 | E63: 104179 | F63: Arizona | G63: Female | H63: Gymnastics | I63: {=IF(B63=0,INDEX('Category 14'!F:F,MATCH(C63&E63&D63,'Category 14'!B:B&'Category 14'!C:C&'Category 14'!A:A,0)),INDEX('Category 14'!G:G,MATCH(C63&E63&D63,'Category 14'!B:B&'Category 14'!C:C&'Category 14'!A:A,0)))} -> 0 | J63: =I63/VLOOKUP($D63,CPI!$P$16:$R$22,3,FALSE) -> 0 | K63: {=IF(B63=0,INDEX('Category 15'!F:F,MATCH(C63&E63&D63,'Category 15'!B:B&'Category 15'!C:C&'Category 15'!A:A,0)),INDEX('Category 15'!G:G,MATCH(C63&E63&D63,'Category 15'!B:B&'Category 31'!C:C&'Category 15'!A:A,0)))} -> 0 | L63: =K63/VLOOKUP($D63,CPI!$P$16:$R$22,3,FALSE) -> 0 | M63: {=IF(B63=0,INDEX('Category 31'!F:F,MATCH(C63&E63&D63,'Category 31'!B:B&'Category 31'!C:C&'Category 31'!A:A,0)),INDEX('Category 31'!G:G,MATCH(C63&E63&D63,'Category 31'!B:B&'Category 31'!C:C&'Category 31'!A:A,0)))} -> 0 | N63: =M63/VLOOKUP($D63,CPI!$P$16:$R$22,3,FALSE) -> 0 | O63: 0
A64: 2 | B64: =IF(ISBLANK(G64),"",IF(MID(G64,1,1)="M",0,1)) -> 1 | C64: =IF(ISBLANK(H64),"",VLOOKUP(H64,Code!B:C,2,FALSE)) -> 17 | D64: 2020 | E64: 104179 | F64: Arizona | G64: Female | H64: Soccer | I64: {=IF(B64=0,INDEX('Category 14'!F:F,MATCH(C64&E64&D64,'Category 14'!B:B&'Category 14'!C:C&'Category 14'!A:A,0)),INDEX('Category 14'!G:G,MATCH(C64&E64&D64,'Category 14'!B:B&'Category 14'!C:C&'Category 14'!A:A,0)))} -> 20490 | J64: =I64/VLOOKUP($D64,CPI!$P$16:$R$22,3,FALSE) -> 23871.85 | K64: {=IF(B64=0,INDEX('Category 15'!F:F,MATCH(C64&E64&D64,'Category 15'!B:B&'Category 15'!C:C&'Category 15'!A:A,0)),INDEX('Category 15'!G:G,MATCH(C64&E64&D64,'Category 15'!B:B&'Category 31'!C:C&'Category 15'!A:A,0)))} -> 0 | L64: =K64/VLOOKUP($D64,CPI!$P$16:$R$22,3,FALSE) -> 0 | M64: {=IF(B64=0,INDEX('Category 31'!F:F,MATCH(C64&E64&D64,'Category 31'!B:B&'Category 31'!C:C&'Category 31'!A:A,0)),INDEX('Category 31'!G:G,MATCH(C64&E64&D64,'Category 31'!B:B&'Category 31'!C:C&'Category 31'!A:A,0)))} -> 0 | N64: =M64/VLOOKUP($D64,CPI!$P$16:$R$22,3,FALSE) -> 0 | O64: =VLOOKUP(E47,WSoccer!C:S,9,FALSE) -> 9594
A65: 2 | B65: =IF(ISBLANK(G65),"",IF(MID(G65,1,1)="M",0,1)) -> 1 | C65: =IF(ISBLANK(H65),"",VLOOKUP(H65,Code!B:C,2,FALSE)) -> 18 | D65: 2020 | E65: 104179 | F65: Arizona | G65: Female | H65: Softball | I65: {=IF(B65=0,INDEX('Category 14'!F:F,MATCH(C65&E65&D65,'Category 14'!B:B&'Category 14'!C:C&'Category 14'!A:A,0)),INDEX('Category 14'!G:G,MATCH(C65&E65&D65,'Category 14'!B:B&'Category 14'!C:C&'Category 14'!A:A,0)))} -> 0 | J65: =I65/VLOOKUP($D65,CPI!$P$16:$R$22,3,FALSE) -> 0 | K65: {=IF(B65=0,INDEX('Category 15'!F:F,MATCH(C65&E65&D65,'Category 15'!B:B&'Category 15'!C:C&'Category 15'!A:A,0)),INDEX('Category 15'!G:G,MATCH(C65&E65&D65,'Category 15'!B:B&'Category 31'!C:C&'Category 15'!A:A,0)))} -> 0 | L65: =K65/VLOOKUP($D65,CPI!$P$16:$R$22,3,FALSE) -> 0 | M65: {=IF(B65=0,INDEX('Category 31'!F:F,MATCH(C65&E65&D65,'Category 31'!B:B&'Category 31'!C:C&'Category 31'!A:A,0)),INDEX('Category 31'!G:G,MATCH(C65&E65&D65,'Category 31'!B:B&'Category 31'!C:C&'Category 31'!A:A,0)))} -> 0 | N65: =M65/VLOOKUP($D65,CPI!$P$16:$R$22,3,FALSE) -> 0 | O65: =VLOOKUP(E48,WSoftball!C:S,9,FALSE) -> 18456
A66: 2 | B66: =IF(ISBLANK(G66),"",IF(MID(G66,1,1)="M",0,1)) -> 1 | C66: =IF(ISBLANK(H66),"",VLOOKUP(H66,Code!B:C,2,FALSE)) -> 19 | D66: 2020 | E66: 104179 | F66: Arizona | G66: Female | H66: Swimming and Diving | I66: {=IF(B66=0,INDEX('Category 14'!F:F,MATCH(C66&E66&D66,'Category 14'!B:B&'Category 14'!C:C&'Category 14'!A:A,0)),INDEX('Category 14'!G:G,MATCH(C66&E66&D66,'Category 14'!B:B&'Category 14'!C:C&'Category 14'!A:A,0)))} -> 0 | J66: =I66/VLOOKUP($D66,CPI!$P$16:$R$22,3,FALSE) -> 0 | K66: {=IF(B66=0,INDEX('Category 15'!F:F,MATCH(C66&E66&D66,'Category 15'!B:B&'Category 15'!C:C&'Category 15'!A:A,0)),INDEX('Category 15'!G:G,MATCH(C66&E66&D66,'Category 15'!B:B&'Category 31'!C:C&'Category 15'!A:A,0)))} -> 0 | L66: =K66/VLOOKUP($D66,CPI!$P$16:$R$22,3,FALSE) -> 0 | M66: {=IF(B66=0,INDEX('Category 31'!F:F,MATCH(C66&E66&D66,'Category 31'!B:B&'Category 31'!C:C&'Category 31'!A:A,0)),INDEX('Category 31'!G:G,MATCH(C66&E66&D66,'Category 31'!B:B&'Category 31'!C:C&'Category 31'!A:A,0)))} -> 0 | N66: =M66/VLOOKUP($D66,CPI!$P$16:$R$22,3,FALSE) -> 0 | O66: 0
A67: 2 | B67: =IF(ISBLANK(G67),"",IF(MID(G67,1,1)="M",0,1)) -> 1 | C67: =IF(ISBLANK(H67),"",VLOOKUP(H67,Code!B:C,2,FALSE)) -> 20 | D67: 2020 | E67: 104179 | F67: Arizona | G67: Female | H67: Tennis | I67: {=IF(B67=0,INDEX('Category 14'!F:F,MATCH(C67&E67&D67,'Category 14'!B:B&'Category 14'!C:C&'Category 14'!A:A,0)),INDEX('Category 14'!G:G,MATCH(C67&E67&D67,'Category 14'!B:B&'Category 14'!C:C&'Category 14'!A:A,0)))} -> 0 | J67: =I67/VLOOKUP($D67,CPI!$P$16:$R$22,3,FALSE) -> 0 | K67: {=IF(B67=0,INDEX('Category 15'!F:F,MATCH(C67&E67&D67,'Category 15'!B:B&'Category 15'!C:C&'Category 15'!A:A,0)),INDEX('Category 15'!G:G,MATCH(C67&E67&D67,'Category 15'!B:B&'Category 31'!C:C&'Category 15'!A:A,0)))} -> 0 | L67: =K67/VLOOKUP($D67,CPI!$P$16:$R$22,3,FALSE) -> 0 | M67: {=IF(B67=0,INDEX('Category 31'!F:F,MATCH(C67&E67&D67,'Category 31'!B:B&'Category 31'!C:C&'Category 31'!A:A,0)),INDEX('Category 31'!G:G,MATCH(C67&E67&D67,'Category 31'!B:B&'Category 31'!C:C&'Category 31'!A:A,0)))} -> 0 | N67: =M67/VLOOKUP($D67,CPI!$P$16:$R$22,3,FALSE) -> 0 | O67: 0
A68: 2 | B68: =IF(ISBLANK(G68),"",IF(MID(G68,1,1)="M",0,1)) -> 1 | C68: =IF(ISBLANK(H68),"",VLOOKUP(H68,Code!B:C,2,FALSE)) -> 21 | D68: 2020 | E68: 104179 | F68: Arizona | G68: Female | H68: Track and Field, X-Country | I68: {=IF(B68=0,INDEX('Category 14'!F:F,MATCH(C68&E68&D68,'Category 14'!B:B&'Category 14'!C:C&'Category 14'!A:A,0)),INDEX('Category 14'!G:G,MATCH(C68&E68&D68,'Category 14'!B:B&'Category 14'!C:C&'Category 14'!A:A,0)))} -> 0 | J68: =I68/VLOOKUP($D68,CPI!$P$16:$R$22,3,FALSE) -> 0 | K68: {=IF(B68=0,INDEX('Category 15'!F:F,MATCH(C68&E68&D68,'Category 15'!B:B&'Category 15'!C:C&'Category 15'!A:A,0)),INDEX('Category 15'!G:G,MATCH(C68&E68&D68,'Category 15'!B:B&'Category 31'!C:C&'Category 15'!A:A,0)))} -> 0 | L68: =K68/VLOOKUP($D68,CPI!$P$16:$R$22,3,FALSE) -> 0 | M68: {=IF(B68=0,INDEX('Category 31'!F:F,MATCH(C68&E68&D68,'Category 31'!B:B&'Category 31'!C:C&'Category 31'!A:A,0)),INDEX('Category 31'!G:G,MATCH(C68&E68&D68,'Category 31'!B:B&'Category 31'!C:C&'Category 31'!A:A,0)))} -> 0 | N68: =M68/VLOOKUP($D68,CPI!$P$16:$R$22,3,FALSE) -> 0 | O68: 0
A69: 2 | B69: =IF(ISBLANK(G69),"",IF(MID(G69,1,1)="M",0,1)) -> 1 | C69: =IF(ISBLANK(H69),"",VLOOKUP(H69,Code!B:C,2,FALSE)) -> 23 | D69: 2020 | E69: 104179 | F69: Arizona | G69: Female | H69: Volleyball | I69: {=IF(B69=0,INDEX('Category 14'!F:F,MATCH(C69&E69&D69,'Category 14'!B:B&'Category 14'!C:C&'Category 14'!A:A,0)),INDEX('Category 14'!G:G,MATCH(C69&E69&D69,'Category 14'!B:B&'Category 14'!C:C&'Category 14'!A:A,0)))} -> 0 | J69: =I69/VLOOKUP($D69,CPI!$P$16:$R$22,3,FALSE) -> 0 | K69: {=IF(B69=0,INDEX('Category 15'!F:F,MATCH(C69&E69&D69,'Category 15'!B:B&'Category 15'!C:C&'Category 15'!A:A,0)),INDEX('Category 15'!G:G,MATCH(C69&E69&D69,'Category 15'!B:B&'Category 31'!C:C&'Category 15'!A:A,0)))} -> 0 | L69: =K69/VLOOKUP($D69,CPI!$P$16:$R$22,3,FALSE) -> 0 | M69: {=IF(B69=0,INDEX('Category 31'!F:F,MATCH(C69&E69&D69,'Category 31'!B:B&'Category 31'!C:C&'Category 31'!A:A,0)),INDEX('Category 31'!G:G,MATCH(C69&E69&D69,'Category 31'!B:B&'Category 31'!C:C&'Category 31'!A:A,0)))} -> 0 | N69: =M69/VLOOKUP($D69,CPI!$P$16:$R$22,3,FALSE) -> 0 | O69: =VLOOKUP(E52,WVolleyball!C:S,9,FALSE) -> 20759
A70: 2 | B70: =IF(ISBLANK(G70),"",IF(MID(G70,1,1)="M",0,1)) -> 0 | C70: =IF(ISBLANK(H70),"",VLOOKUP(H70,Code!B:C,2,FALSE)) -> 1 | D70: 2021 | E70: 104179 | F70: Arizona | G70: Male | H70: Baseball | I70: {=IF(B70=0,INDEX('Category 14'!F:F,MATCH(C70&E70&D70,'Category 14'!B:B&'Category 14'!C:C&'Category 14'!A:A,0)),INDEX('Category 14'!G:G,MATCH(C70&E70&D70,'Category 14'!B:B&'Category 14'!C:C&'Category 14'!A:A,0)))} -> 0 | J70: =I70/VLOOKUP($D70,CPI!$P$16:$R$22,3,FALSE) -> 0 | K70: {=IF(B70=0,INDEX('Category 15'!F:F,MATCH(C70&E70&D70,'Category 15'!B:B&'Category 15'!C:C&'Category 15'!A:A,0)),INDEX('Category 15'!G:G,MATCH(C70&E70&D70,'Category 15'!B:B&'Category 31'!C:C&'Category 15'!A:A,0)))} -> 0 | L70: =K70/VLOOKUP($D70,CPI!$P$16:$R$22,3,FALSE) -> 0 | M70: {=IF(B70=0,INDEX('Category 31'!F:F,MATCH(C70&E70&D70,'Category 31'!B:B&'Category 31'!C:C&'Category 31'!A:A,0)),INDEX('Category 31'!G:G,MATCH(C70&E70&D70,'Category 31'!B:B&'Category 31'!C:C&'Category 31'!A:A,0)))} -> 0 | N70: =M70/VLOOKUP($D70,CPI!$P$16:$R$22,3,FALSE) -> 0 | O70: 60554
A71: 2 | B71: =IF(ISBLANK(G71),"",IF(MID(G71,1,1)="M",0,1)) -> 0 | C71: =IF(ISBLANK(H71),"",VLOOKUP(H71,Code!B:C,2,FALSE)) -> 2 | D71: 2021 | E71: 104179 | F71: Arizona | G71: Male | H71: Basketball | I71: {=IF(B71=0,INDEX('Category 14'!F:F,MATCH(C71&E71&D71,'Category 14'!B:B&'Category 14'!C:C&'Category 14'!A:A,0)),INDEX('Category 14'!G:G,MATCH(C71&E71&D71,'Category 14'!B:B&'Category 14'!C:C&'Category 14'!A:A,0)))} -> 29555 | J71: =I71/VLOOKUP($D71,CPI!$P$16:$R$22,3,FALSE) -> 33658.325 | K71: {=IF(B71=0,INDEX('Category 15'!F:F,MATCH(C71&E71&D71,'Category 15'!B:B&'Category 15'!C:C&'Category 15'!A:A,0)),INDEX('Category 15'!G:G,MATCH(C71&E71&D71,'Category 15'!B:B&'Category 31'!C:C&'Category 15'!A:A,0)))} -> 3437220 | L71: =K71/VLOOKUP($D71,CPI!$P$16:$R$22,3,FALSE) -> 3914433 | M71: {=IF(B71=0,INDEX('Category 31'!F:F,MATCH(C71&E71&D71,'Category 31'!B:B&'Category 31'!C:C&'Category 31'!A:A,0)),INDEX('Category 31'!G:G,MATCH(C71&E71&D71,'Category 31'!B:B&'Category 31'!C:C&'Category 31'!A:A,0)))} -> 0 | N71: =M71/VLOOKUP($D71,CPI!$P$16:$R$22,3,FALSE) -> 0 | O71: =VLOOKUP(E37,MBasketball!C:N,10,FALSE) -> 0
A72: 2 | B72: =IF(ISBLANK(G72),"",IF(MID(G72,1,1)="M",0,1)) -> 0 | C72: =IF(ISBLANK(H72),"",VLOOKUP(H72,Code!B:C,2,FALSE)) -> 8 | D72: 2021 | E72: 104179 | F72: Arizona | G72: Male | H72: Football | I72: {=IF(B72=0,INDEX('Category 14'!F:F,MATCH(C72&E72&D72,'Category 14'!B:B&'Category 14'!C:C&'Category 14'!A:A,0)),INDEX('Category 14'!G:G,MATCH(C72&E72&D72,'Category 14'!B:B&'Category 14'!C:C&'Category 14'!A:A,0)))} -> 305983 | J72: =I72/VLOOKUP($D72,CPI!$P$16:$R$22,3,FALSE) -> 348464.73 | K72: {=IF(B72=0,INDEX('Category 15'!F:F,MATCH(C72&E72&D72,'Category 15'!B:B&'Category 15'!C:C&'Category 15'!A:A,0)),INDEX('Category 15'!G:G,MATCH(C72&E72&D72,'Category 15'!B:B&'Category 31'!C:C&'Category 15'!A:A,0)))} -> 3437220 | L72: =K72/VLOOKUP($D72,CPI!$P$16:$R$22,3,FALSE) -> 3914433 | M72: {=IF(B72=0,INDEX('Category 31'!F:F,MATCH(C72&E72&D72,'Category 31'!B:B&'Category 31'!C:C&'Category 31'!A:A,0)),INDEX('Category 31'!G:G,MATCH(C72&E72&D72,'Category 31'!B:B&'Category 31'!C:C&'Category 31'!A:A,0)))} -> 0 | N72: =M72/VLOOKUP($D72,CPI!$P$16:$R$22,3,FALSE) -> 0 | O72: =VLOOKUP(E38,MFootball!C:S,10,FALSE) -> 0
A73: 2 | B73: =IF(ISBLANK(G73),"",IF(MID(G73,1,1)="M",0,1)) -> 0 | C73: 9 | D73: 2021 | E73: 104179 | F73: Arizona | G73: Male | H73: Golf | I73: {=IF(B73=0,INDEX('Category 14'!F:F,MATCH(C73&E73&D73,'Category 14'!B:B&'Category 14'!C:C&'Category 14'!A:A,0)),INDEX('Category 14'!G:G,MATCH(C73&E73&D73,'Category 14'!B:B&'Category 14'!C:C&'Category 14'!A:A,0)))} -> 0 | J73: =I73/VLOOKUP($D73,CPI!$P$16:$R$22,3,FALSE) -> 0 | K73: {=IF(B73=0,INDEX('Category 15'!F:F,MATCH(C73&E73&D73,'Category 15'!B:B&'Category 15'!C:C&'Category 15'!A:A,0)),INDEX('Category 15'!G:G,MATCH(C73&E73&D73,'Category 15'!B:B&'Category 31'!C:C&'Category 15'!A:A,0)))} -> 0 | L73: =K73/VLOOKUP($D73,CPI!$P$16:$R$22,3,FALSE) -> 0 | M73: {=IF(B73=0,INDEX('Category 31'!F:F,MATCH(C73&E73&D73,'Category 31'!B:B&'Category 31'!C:C&'Category 31'!A:A,0)),INDEX('Category 31'!G:G,MATCH(C73&E73&D73,'Category 31'!B:B&'Category 31'!C:C&'Category 31'!A:A,0)))} -> 0 | N73: =M73/VLOOKUP($D73,CPI!$P$16:$R$22,3,FALSE) -> 0 | O73: 0
A74: 2 | B74: =IF(ISBLANK(G74),"",IF(MID(G74,1,1)="M",0,1)) -> 0 | C74: 19 | D74: 2021 | E74: 104179 | F74: Arizona | G74: Male | H74: Swimming and diving | I74: {=IF(B74=0,INDEX('Category 14'!F:F,MATCH(C74&E74&D74,'Category 14'!B:B&'Category 14'!C:C&'Category 14'!A:A,0)),INDEX('Category 14'!G:G,MATCH(C74&E74&D74,'Category 14'!B:B&'Category 14'!C:C&'Category 14'!A:A,0)))} -> 0 | J74: =I74/VLOOKUP($D74,CPI!$P$16:$R$22,3,FALSE) -> 0 | K74: {=IF(B74=0,INDEX('Category 15'!F:F,MATCH(C74&E74&D74,'Category 15'!B:B&'Category 15'!C:C&'Category 15'!A:A,0)),INDEX('Category 15'!G:G,MATCH(C74&E74&D74,'Category 15'!B:B&'Category 31'!C:C&'Category 15'!A:A,0)))} -> 0 | L74: =K74/VLOOKUP($D74,CPI!$P$16:$R$22,3,FALSE) -> 0 | M74: {=IF(B74=0,INDEX('Category 31'!F:F,MATCH(C74&E74&D74,'Category 31'!B:B&'Category 31'!C:C&'Category 31'!A:A,0)),INDEX('Category 31'!G:G,MATCH(C74&E74&D74,'Category 31'!B:B&'Category 31'!C:C&'Category 31'!A:A,0)))} -> 0 | N74: =M74/VLOOKUP($D74,CPI!$P$16:$R$22,3,FALSE) -> 0 | O74: 0
A75: 2 | B75: =IF(ISBLANK(G75),"",IF(MID(G75,1,1)="M",0,1)) -> 0 | C75: =IF(ISBLANK(H75),"",VLOOKUP(H75,Code!B:C,2,FALSE)) -> 20 | D75: 2021 | E75: 104179 | F75: Arizona | G75: Male | H75: Tennis | I75: {=IF(B75=0,INDEX('Category 14'!F:F,MATCH(C75&E75&D75,'Category 14'!B:B&'Category 14'!C:C&'Category 14'!A:A,0)),INDEX('Category 14'!G:G,MATCH(C75&E75&D75,'Category 14'!B:B&'Category 14'!C:C&'Category 14'!A:A,0)))} -> 0 | J75: =I75/VLOOKUP($D75,CPI!$P$16:$R$22,3,FALSE) -> 0 | K75: {=IF(B75=0,INDEX('Category 15'!F:F,MATCH(C75&E75&D75,'Category 15'!B:B&'Category 15'!C:C&'Category 15'!A:A,0)),INDEX('Category 15'!G:G,MATCH(C75&E75&D75,'Category 15'!B:B&'Category 31'!C:C&'Category 15'!A:A,0)))} -> 0 | L75: =K75/VLOOKUP($D75,CPI!$P$16:$R$22,3,FALSE) -> 0 | M75: {=IF(B75=0,INDEX('Category 31'!F:F,MATCH(C75&E75&D75,'Category 31'!B:B&'Category 31'!C:C&'Category 31'!A:A,0)),INDEX('Category 31'!G:G,MATCH(C75&E75&D75,'Category 31'!B:B&'Category 31'!C:C&'Category 31'!A:A,0)))} -> 0 | N75: =M75/VLOOKUP($D75,CPI!$P$16:$R$22,3,FALSE) -> 0 | O75: 0
A76: 2 | B76: =IF(ISBLANK(G76),"",IF(MID(G76,1,1)="M",0,1)) -> 0 | C76: 21 | D76: 2021 | E76: 104179 | F76: Arizona | G76: Male | H76: Track and Field , X country | I76: {=IF(B76=0,INDEX('Category 14'!F:F,MATCH(C76&E76&D76,'Category 14'!B:B&'Category 14'!C:C&'Category 14'!A:A,0)),INDEX('Category 14'!G:G,MATCH(C76&E76&D76,'Category 14'!B:B&'Category 14'!C:C&'Category 14'!A:A,0)))} -> 0 | J76: =I76/VLOOKUP($D76,CPI!$P$16:$R$22,3,FALSE) -> 0 | K76: {=IF(B76=0,INDEX('Category 15'!F:F,MATCH(C76&E76&D76,'Category 15'!B:B&'Category 15'!C:C&'Category 15'!A:A,0)),INDEX('Category 15'!G:G,MATCH(C76&E76&D76,'Category 15'!B:B&'Category 31'!C:C&'Category 15'!A:A,0)))} -> 0 | L76: =K76/VLOOKUP($D76,CPI!$P$16:$R$22,3,FALSE) -> 0 | M76: {=IF(B76=0,INDEX('Category 31'!F:F,MATCH(C76&E76&D76,'Category 31'!B:B&'Category 31'!C:C&'Category 31'!A:A,0)),INDEX('Category 31'!G:G,MATCH(C76&E76&D76,'Category 31'!B:B&'Category 31'!C:C&'Category 31'!A:A,0)))} -> 0 | N76: =M76/VLOOKUP($D76,CPI!$P$16:$R$22,3,FALSE) -> 0 | O76: 0
A77: 2 | B77: =IF(ISBLANK(G77),"",IF(MID(G77,1,1)="M",0,1)) -> 1 | C77: =IF(ISBLANK(H77),"",VLOOKUP(H77,Code!B:C,2,FALSE)) -> 2 | D77: 2021 | E77: 104179 | F77: Arizona | G77: Women | H77: Basketball | I77: {=IF(B77=0,INDEX('Category 14'!F:F,MATCH(C77&E77&D77,'Category 14'!B:B&'Category 14'!C:C&'Category 14'!A:A,0)),INDEX('Category 14'!G:G,MATCH(C77&E77&D77,'Category 14'!B:B&'Category 14'!C:C&'Category 14'!A:A,0)))} -> 0 | J77: =I77/VLOOKUP($D77,CPI!$P$16:$R$22,3,FALSE) -> 0 | K77: {=IF(B77=0,INDEX('Category 15'!F:F,MATCH(C77&E77&D77,'Category 15'!B:B&'Category 15'!C:C&'Category 15'!A:A,0)),INDEX('Category 15'!G:G,MATCH(C77&E77&D77,'Category 15'!B:B&'Category 31'!C:C&'Category 15'!A:A,0)))} -> 0 | L77: =K77/VLOOKUP($D77,CPI!$P$16:$R$22,3,FALSE) -> 0 | M77: {=IF(B77=0,INDEX('Category 31'!F:F,MATCH(C77&E77&D77,'Category 31'!B:B&'Category 31'!C:C&'Category 31'!A:A,0)),INDEX('Category 31'!G:G,MATCH(C77&E77&D77,'Category 31'!B:B&'Category 31'!C:C&'Category 31'!A:A,0)))} -> 0 | N77: =M77/VLOOKUP($D77,CPI!$P$16:$R$22,3,FALSE) -> 0 | O77: =VLOOKUP(E43,WBasketball!C:S,10,FALSE) -> 0
A78: 2 | B78: =IF(ISBLANK(G78),"",IF(MID(G78,1,1)="M",0,1)) -> 1 | C78: 3 | D78: 2021 | E78: 104179 | F78: Arizona | G78: Women | H78: Beach Volleyball | I78: {=IF(B78=0,INDEX('Category 14'!F:F,MATCH(C78&E78&D78,'Category 14'!B:B&'Category 14'!C:C&'Category 14'!A:A,0)),INDEX('Category 14'!G:G,MATCH(C78&E78&D78,'Category 14'!B:B&'Category 14'!C:C&'Category 14'!A:A,0)))} -> 0 | J78: =I78/VLOOKUP($D78,CPI!$P$16:$R$22,3,FALSE) -> 0 | K78: {=IF(B78=0,INDEX('Category 15'!F:F,MATCH(C78&E78&D78,'Category 15'!B:B&'Category 15'!C:C&'Category 15'!A:A,0)),INDEX('Category 15'!G:G,MATCH(C78&E78&D78,'Category 15'!B:B&'Category 31'!C:C&'Category 15'!A:A,0)))} -> 0 | L78: =K78/VLOOKUP($D78,CPI!$P$16:$R$22,3,FALSE) -> 0 | M78: {=IF(B78=0,INDEX('Category 31'!F:F,MATCH(C78&E78&D78,'Category 31'!B:B&'Category 31'!C:C&'Category 31'!A:A,0)),INDEX('Category 31'!G:G,MATCH(C78&E78&D78,'Category 31'!B:B&'Category 31'!C:C&'Category 31'!A:A,0)))} -> 0 | N78: =M78/VLOOKUP($D78,CPI!$P$16:$R$22,3,FALSE) -> 0 | O78: 0
A79: 2 | B79: =IF(ISBLANK(G79),"",IF(MID(G79,1,1)="M",0,1)) -> 1 | C79: 9 | D79: 2021 | E79: 104179 | F79: Arizona | G79: Women | H79: Golf | I79: {=IF(B79=0,INDEX('Category 14'!F:F,MATCH(C79&E79&D79,'Category 14'!B:B&'Category 14'!C:C&'Category 14'!A:A,0)),INDEX('Category 14'!G:G,MATCH(C79&E79&D79,'Category 14'!B:B&'Category 14'!C:C&'Category 14'!A:A,0)))} -> 0 | J79: =I79/VLOOKUP($D79,CPI!$P$16:$R$22,3,FALSE) -> 0 | K79: {=IF(B79=0,INDEX('Category 15'!F:F,MATCH(C79&E79&D79,'Category 15'!B:B&'Category 15'!C:C&'Category 15'!A:A,0)),INDEX('Category 15'!G:G,MATCH(C79&E79&D79,'Category 15'!B:B&'Category 31'!C:C&'Category 15'!A:A,0)))} -> 0 | L79: =K79/VLOOKUP($D79,CPI!$P$16:$R$22,3,FALSE) -> 0 | M79: {=IF(B79=0,INDEX('Category 31'!F:F,MATCH(C79&E79&D79,'Category 31'!B:B&'Category 31'!C:C&'Category 31'!A:A,0)),INDEX('Category 31'!G:G,MATCH(C79&E79&D79,'Category 31'!B:B&'Category 31'!C:C&'Category 31'!A:A,0)))} -> 0 | N79: =M79/VLOOKUP($D79,CPI!$P$16:$R$22,3,FALSE) -> 0 | O79: 0
A80: 2 | B80: =IF(ISBLANK(G80),"",IF(MID(G80,1,1)="M",0,1)) -> 1 | C80: =IF(ISBLANK(H80),"",VLOOKUP(H80,Code!B:C,2,FALSE)) -> 10 | D80: 2021 | E80: 104179 | F80: Arizona | G80: Women | H80: Gymnastics | I80: {=IF(B80=0,INDEX('Category 14'!F:F,MATCH(C80&E80&D80,'Category 14'!B:B&'Category 14'!C:C&'Category 14'!A:A,0)),INDEX('Category 14'!G:G,MATCH(C80&E80&D80,'Category 14'!B:B&'Category 14'!C:C&'Category 14'!A:A,0)))} -> 0 | J80: =I80/VLOOKUP($D80,CPI!$P$16:$R$22,3,FALSE) -> 0 | K80: {=IF(B80=0,INDEX('Category 15'!F:F,MATCH(C80&E80&D80,'Category 15'!B:B&'Category 15'!C:C&'Category 15'!A:A,0)),INDEX('Category 15'!G:G,MATCH(C80&E80&D80,'Category 15'!B:B&'Category 31'!C:C&'Category 15'!A:A,0)))} -> 0 | L80: =K80/VLOOKUP($D80,CPI!$P$16:$R$22,3,FALSE) -> 0 | M80: {=IF(B80=0,INDEX('Category 31'!F:F,MATCH(C80&E80&D80,'Category 31'!B:B&'Category 31'!C:C&'Category 31'!A:A,0)),INDEX('Category 31'!G:G,MATCH(C80&E80&D80,'Category 31'!B:B&'Category 31'!C:C&'Category 31'!A:A,0)))} -> 0 | N80: =M80/VLOOKUP($D80,CPI!$P$16:$R$22,3,FALSE) -> 0 | O80: 0
A81: 2 | B81: =IF(ISBLANK(G81),"",IF(MID(G81,1,1)="M",0,1)) -> 1 | C81: =IF(ISBLANK(H81),"",VLOOKUP(H81,Code!B:C,2,FALSE)) -> 17 | D81: 2021 | E81: 104179 | F81: Arizona | G81: Women | H81: Soccer | I81: {=IF(B81=0,INDEX('Category 14'!F:F,MATCH(C81&E81&D81,'Category 14'!B:B&'Category 14'!C:C&'Category 14'!A:A,0)),INDEX('Category 14'!G:G,MATCH(C81&E81&D81,'Category 14'!B:B&'Category 14'!C:C&'Category 14'!A:A,0)))} -> 0 | J81: =I81/VLOOKUP($D81,CPI!$P$16:$R$22,3,FALSE) -> 0 | K81: {=IF(B81=0,INDEX('Category 15'!F:F,MATCH(C81&E81&D81,'Category 15'!B:B&'Category 15'!C:C&'Category 15'!A:A,0)),INDEX('Category 15'!G:G,MATCH(C81&E81&D81,'Category 15'!B:B&'Category 31'!C:C&'Category 15'!A:A,0)))} -> 0 | L81: =K81/VLOOKUP($D81,CPI!$P$16:$R$22,3,FALSE) -> 0 | M81: {=IF(B81=0,INDEX('Category 31'!F:F,MATCH(C81&E81&D81,'Category 31'!B:B&'Category 31'!C:C&'Category 31'!A:A,0)),INDEX('Category 31'!G:G,MATCH(C81&E81&D81,'Category 31'!B:B&'Category 31'!C:C&'Category 31'!A:A,0)))} -> 0 | N81: =M81/VLOOKUP($D81,CPI!$P$16:$R$22,3,FALSE) -> 0 | O81: =VLOOKUP(E47,WSoccer!C:S,10,FALSE) -> 0
A82: 2 | B82: =IF(ISBLANK(G82),"",IF(MID(G82,1,1)="M",0,1)) -> 1 | C82: =IF(ISBLANK(H82),"",VLOOKUP(H82,Code!B:C,2,FALSE)) -> 18 | D82: 2021 | E82: 104179 | F82: Arizona | G82: Women | H82: Softball | I82: {=IF(B82=0,INDEX('Category 14'!F:F,MATCH(C82&E82&D82,'Category 14'!B:B&'Category 14'!C:C&'Category 14'!A:A,0)),INDEX('Category 14'!G:G,MATCH(C82&E82&D82,'Category 14'!B:B&'Category 14'!C:C&'Category 14'!A:A,0)))} -> 0 | J82: =I82/VLOOKUP($D82,CPI!$P$16:$R$22,3,FALSE) -> 0 | K82: {=IF(B82=0,INDEX('Category 15'!F:F,MATCH(C82&E82&D82,'Category 15'!B:B&'Category 15'!C:C&'Category 15'!A:A,0)),INDEX('Category 15'!G:G,MATCH(C82&E82&D82,'Category 15'!B:B&'Category 31'!C:C&'Category 15'!A:A,0)))} -> 0 | L82: =K82/VLOOKUP($D82,CPI!$P$16:$R$22,3,FALSE) -> 0 | M82: {=IF(B82=0,INDEX('Category 31'!F:F,MATCH(C82&E82&D82,'Category 31'!B:B&'Category 31'!C:C&'Category 31'!A:A,0)),INDEX('Category 31'!G:G,MATCH(C82&E82&D82,'Category 31'!B:B&'Category 31'!C:C&'Category 31'!A:A,0)))} -> 0 | N82: =M82/VLOOKUP($D82,CPI!$P$16:$R$22,3,FALSE) -> 0 | O82: =VLOOKUP(E48,WSoftball!C:S,10,FALSE) -> 6217
A83: 2 | B83: =IF(ISBLANK(G83),"",IF(MID(G83,1,1)="M",0,1)) -> 1 | C83: 19 | D83: 2021 | E83: 104179 | F83: Arizona | G83: Women | H83: Swimming and diving | I83: {=IF(B83=0,INDEX('Category 14'!F:F,MATCH(C83&E83&D83,'Category 14'!B:B&'Category 14'!C:C&'Category 14'!A:A,0)),INDEX('Category 14'!G:G,MATCH(C83&E83&D83,'Category 14'!B:B&'Category 14'!C:C&'Category 14'!A:A,0)))} -> 0 | J83: =I83/VLOOKUP($D83,CPI!$P$16:$R$22,3,FALSE) -> 0 | K83: {=IF(B83=0,INDEX('Category 15'!F:F,MATCH(C83&E83&D83,'Category 15'!B:B&'Category 15'!C:C&'Category 15'!A:A,0)),INDEX('Category 15'!G:G,MATCH(C83&E83&D83,'Category 15'!B:B&'Category 31'!C:C&'Category 15'!A:A,0)))} -> 0 | L83: =K83/VLOOKUP($D83,CPI!$P$16:$R$22,3,FALSE) -> 0 | M83: {=IF(B83=0,INDEX('Category 31'!F:F,MATCH(C83&E83&D83,'Category 31'!B:B&'Category 31'!C:C&'Category 31'!A:A,0)),INDEX('Category 31'!G:G,MATCH(C83&E83&D83,'Category 31'!B:B&'Category 31'!C:C&'Category 31'!A:A,0)))} -> 0 | N83: =M83/VLOOKUP($D83,CPI!$P$16:$R$22,3,FALSE) -> 0 | O83: 0
A84: 2 | B84: =IF(ISBLANK(G84),"",IF(MID(G84,1,1)="M",0,1)) -> 1 | C84: =IF(ISBLANK(H84),"",VLOOKUP(H84,Code!B:C,2,FALSE)) -> 20 | D84: 2021 | E84: 104179 | F84: Arizona | G84: Women | H84: Tennis | I84: {=IF(B84=0,INDEX('Category 14'!F:F,MATCH(C84&E84&D84,'Category 14'!B:B&'Category 14'!C:C&'Category 14'!A:A,0)),INDEX('Category 14'!G:G,MATCH(C84&E84&D84,'Category 14'!B:B&'Category 14'!C:C&'Category 14'!A:A,0)))} -> 0 | J84: =I84/VLOOKUP($D84,CPI!$P$16:$R$22,3,FALSE) -> 0 | K84: {=IF(B84=0,INDEX('Category 15'!F:F,MATCH(C84&E84&D84,'Category 15'!B:B&'Category 15'!C:C&'Category 15'!A:A,0)),INDEX('Category 15'!G:G,MATCH(C84&E84&D84,'Category 15'!B:B&'Category 31'!C:C&'Category 15'!A:A,0)))} -> 0 | L84: =K84/VLOOKUP($D84,CPI!$P$16:$R$22,3,FALSE) -> 0 | M84: {=IF(B84=0,INDEX('Category 31'!F:F,MATCH(C84&E84&D84,'Category 31'!B:B&'Category 31'!C:C&'Category 31'!A:A,0)),INDEX('Category 31'!G:G,MATCH(C84&E84&D84,'Category 31'!B:B&'Category 31'!C:C&'Category 31'!A:A,0)))} -> 0 | N84: =M84/VLOOKUP($D84,CPI!$P$16:$R$22,3,FALSE) -> 0 | O84: 0
A85: 2 | B85: =IF(ISBLANK(G85),"",IF(MID(G85,1,1)="M",0,1)) -> 1 | C85: 21 | D85: 2021 | E85: 104179 | F85: Arizona | G85: Women | H85: Track and Field , X country | I85: {=IF(B85=0,INDEX('Category 14'!F:F,MATCH(C85&E85&D85,'Category 14'!B:B&'Category 14'!C:C&'Category 14'!A:A,0)),INDEX('Category 14'!G:G,MATCH(C85&E85&D85,'Category 14'!B:B&'Category 14'!C:C&'Category 14'!A:A,0)))} -> 0 | J85: =I85/VLOOKUP($D85,CPI!$P$16:$R$22,3,FALSE) -> 0 | K85: {=IF(B85=0,INDEX('Category 15'!F:F,MATCH(C85&E85&D85,'Category 15'!B:B&'Category 15'!C:C&'Category 15'!A:A,0)),INDEX('Category 15'!G:G,MATCH(C85&E85&D85,'Category 15'!B:B&'Category 31'!C:C&'Category 15'!A:A,0)))} -> 0 | L85: =K85/VLOOKUP($D85,CPI!$P$16:$R$22,3,FALSE) -> 0 | M85: {=IF(B85=0,INDEX('Category 31'!F:F,MATCH(C85&E85&D85,'Category 31'!B:B&'Category 31'!C:C&'Category 31'!A:A,0)),INDEX('Category 31'!G:G,MATCH(C85&E85&D85,'Category 31'!B:B&'Category 31'!C:C&'Category 31'!A:A,0)))} -> 0 | N85: =M85/VLOOKUP($D85,CPI!$P$16:$R$22,3,FALSE) -> 0 | O85: 0
A86: 2 | B86: =IF(ISBLANK(G86),"",IF(MID(G86,1,1)="M",0,1)) -> 1 | C86: =IF(ISBLANK(H86),"",VLOOKUP(H86,Code!B:C,2,FALSE)) -> 23 | D86: 2021 | E86: 104179 | F86: Arizona | G86: Women | H86: Volleyball | I86: {=IF(B86=0,INDEX('Category 14'!F:F,MATCH(C86&E86&D86,'Category 14'!B:B&'Category 14'!C:C&'Category 14'!A:A,0)),INDEX('Category 14'!G:G,MATCH(C86&E86&D86,'Category 14'!B:B&'Category 14'!C:C&'Category 14'!A:A,0)))} -> 0 | J86: =I86/VLOOKUP($D86,CPI!$P$16:$R$22,3,FALSE) -> 0 | K86: {=IF(B86=0,INDEX('Category 15'!F:F,MATCH(C86&E86&D86,'Category 15'!B:B&'Category 15'!C:C&'Category 15'!A:A,0)),INDEX('Category 15'!G:G,MATCH(C86&E86&D86,'Category 15'!B:B&'Category 31'!C:C&'Category 15'!A:A,0)))} -> 0 | L86: =K86/VLOOKUP($D86,CPI!$P$16:$R$22,3,FALSE) -> 0 | M86: {=IF(B86=0,INDEX('Category 31'!F:F,MATCH(C86&E86&D86,'Category 31'!B:B&'Category 31'!C:C&'Category 31'!A:A,0)),INDEX('Category 31'!G:G,MATCH(C86&E86&D86,'Category 31'!B:B&'Category 31'!C:C&'Category 31'!A:A,0)))} -> 0 | N86: =M86/VLOOKUP($D86,CPI!$P$16:$R$22,3,FALSE) -> 0 | O86: =VLOOKUP(E52,WVolleyball!C:S,10,FALSE) -> 0
A87: 2 | B87: =IF(ISBLANK(G87),"",IF(MID(G87,1,1)="M",0,1)) -> 0 | C87: =IF(ISBLANK(H87),"",VLOOKUP(H87,Code!B:C,2,FALSE)) -> 1 | D87: 2022 | E87: 104179 | F87: Arizona | G87: Male | H87: Baseball | I87: {=IF(B87=0,INDEX('Category 14'!F:F,MATCH(C87&E87&D87,'Category 14'!B:B&'Category 14'!C:C&'Category 14'!A:A,0)),INDEX('Category 14'!G:G,MATCH(C87&E87&D87,'Category 14'!B:B&'Category 14'!C:C&'Category 14'!A:A,0)))} -> 986 | J87: =I87/VLOOKUP($D87,CPI!$P$16:$R$22,3,FALSE) -> 1047.7437 | K87: {=IF(B87=0,INDEX('Category 15'!F:F,MATCH(C87&E87&D87,'Category 15'!B:B&'Category 15'!C:C&'Category 15'!A:A,0)),INDEX('Category 15'!G:G,MATCH(C87&E87&D87,'Category 15'!B:B&'Category 31'!C:C&'Category 15'!A:A,0)))} -> 0 | L87: =K87/VLOOKUP($D87,CPI!$P$16:$R$22,3,FALSE) -> 0 | M87: {=IF(B87=0,INDEX('Category 31'!F:F,MATCH(C87&E87&D87,'Category 31'!B:B&'Category 31'!C:C&'Category 31'!A:A,0)),INDEX('Category 31'!G:G,MATCH(C87&E87&D87,'Category 31'!B:B&'Category 31'!C:C&'Category 31'!A:A,0)))} -> 0 | N87: =M87/VLOOKUP($D87,CPI!$P$16:$R$22,3,FALSE) -> 0 | O87: 100226
A88: 2 | B88: =IF(ISBLANK(G88),"",IF(MID(G88,1,1)="M",0,1)) -> 0 | C88: =IF(ISBLANK(H88),"",VLOOKUP(H88,Code!B:C,2,FALSE)) -> 2 | D88: 2022 | E88: 104179 | F88: Arizona | G88: Male | H88: Basketball | I88: {=IF(B88=0,INDEX('Category 14'!F:F,MATCH(C88&E88&D88,'Category 14'!B:B&'Category 14'!C:C&'Category 14'!A:A,0)),INDEX('Category 14'!G:G,MATCH(C88&E88&D88,'Category 14'!B:B&'Category 14'!C:C&'Category 14'!A:A,0)))} -> 29403 | J88: =I88/VLOOKUP($D88,CPI!$P$16:$R$22,3,FALSE) -> 31244.226 | K88: {=IF(B88=0,INDEX('Category 15'!F:F,MATCH(C88&E88&D88,'Category 15'!B:B&'Category 15'!C:C&'Category 15'!A:A,0)),INDEX('Category 15'!G:G,MATCH(C88&E88&D88,'Category 15'!B:B&'Category 31'!C:C&'Category 15'!A:A,0)))} -> 4756131 | L88: =K88/VLOOKUP($D88,CPI!$P$16:$R$22,3,FALSE) -> 5053961.5 | M88: {=IF(B88=0,INDEX('Category 31'!F:F,MATCH(C88&E88&D88,'Category 31'!B:B&'Category 31'!C:C&'Category 31'!A:A,0)),INDEX('Category 31'!G:G,MATCH(C88&E88&D88,'Category 31'!B:B&'Category 31'!C:C&'Category 31'!A:A,0)))} -> 0 | N88: =M88/VLOOKUP($D88,CPI!$P$16:$R$22,3,FALSE) -> 0 | O88: =VLOOKUP(E37,MBasketball!C:N,11,FALSE) -> 228040
A89: 2 | B89: =IF(ISBLANK(G89),"",IF(MID(G89,1,1)="M",0,1)) -> 0 | C89: =IF(ISBLANK(H89),"",VLOOKUP(H89,Code!B:C,2,FALSE)) -> 8 | D89: 2022 | E89: 104179 | F89: Arizona | G89: Male | H89: Football | I89: {=IF(B89=0,INDEX('Category 14'!F:F,MATCH(C89&E89&D89,'Category 14'!B:B&'Category 14'!C:C&'Category 14'!A:A,0)),INDEX('Category 14'!G:G,MATCH(C89&E89&D89,'Category 14'!B:B&'Category 14'!C:C&'Category 14'!A:A,0)))} -> 497067 | J89: =I89/VLOOKUP($D89,CPI!$P$16:$R$22,3,FALSE) -> 528193.5 | K89: {=IF(B89=0,INDEX('Category 15'!F:F,MATCH(C89&E89&D89,'Category 15'!B:B&'Category 15'!C:C&'Category 15'!A:A,0)),INDEX('Category 15'!G:G,MATCH(C89&E89&D89,'Category 15'!B:B&'Category 31'!C:C&'Category 15'!A:A,0)))} -> 4756130 | L89: =K89/VLOOKUP($D89,CPI!$P$16:$R$22,3,FALSE) -> 5053960.5 | M89: {=IF(B89=0,INDEX('Category 31'!F:F,MATCH(C89&E89&D89,'Category 31'!B:B&'Category 31'!C:C&'Category 31'!A:A,0)),INDEX('Category 31'!G:G,MATCH(C89&E89&D89,'Category 31'!B:B&'Category 31'!C:C&'Category 31'!A:A,0)))} -> 0 | N89: =M89/VLOOKUP($D89,CPI!$P$16:$R$22,3,FALSE) -> 0 | O89: =VLOOKUP(E38,MFootball!C:S,11,FALSE) -> 209401
A90: 2 | B90: =IF(ISBLANK(G90),"",IF(MID(G90,1,1)="M",0,1)) -> 0 | C90: =IF(ISBLANK(H90),"",VLOOKUP(H90,Code!B:C,2,FALSE)) -> 9 | D90: 2022 | E90: 104179 | F90: Arizona | G90: Male | H90: Golf | I90: {=IF(B90=0,INDEX('Category 14'!F:F,MATCH(C90&E90&D90,'Category 14'!B:B&'Category 14'!C:C&'Category 14'!A:A,0)),INDEX('Category 14'!G:G,MATCH(C90&E90&D90,'Category 14'!B:B&'Category 14'!C:C&'Category 14'!A:A,0)))} -> 0 | J90: =I90/VLOOKUP($D90,CPI!$P$16:$R$22,3,FALSE) -> 0 | K90: {=IF(B90=0,INDEX('Category 15'!F:F,MATCH(C90&E90&D90,'Category 15'!B:B&'Category 15'!C:C&'Category 15'!A:A,0)),INDEX('Category 15'!G:G,MATCH(C90&E90&D90,'Category 15'!B:B&'Category 31'!C:C&'Category 15'!A:A,0)))} -> 0 | L90: =K90/VLOOKUP($D90,CPI!$P$16:$R$22,3,FALSE) -> 0 | M90: {=IF(B90=0,INDEX('Category 31'!F:F,MATCH(C90&E90&D90,'Category 31'!B:B&'Category 31'!C:C&'Category 31'!A:A,0)),INDEX('Category 31'!G:G,MATCH(C90&E90&D90,'Category 31'!B:B&'Category 31'!C:C&'Category 31'!A:A,0)))} -> 0 | N90: =M90/VLOOKUP($D90,CPI!$P$16:$R$22,3,FALSE) -> 0 | O90: 0
A91: 2 | B91: =IF(ISBLANK(G91),"",IF(MID(G91,1,1)="M",0,1)) -> 0 | C91: =IF(ISBLANK(H91),"",VLOOKUP(H91,Code!B:C,2,FALSE)) -> 19 | D91: 2022 | E91: 104179 | F91: Arizona | G91: Male | H91: Swimming and Diving | I91: {=IF(B91=0,INDEX('Category 14'!F:F,MATCH(C91&E91&D91,'Category 14'!B:B&'Category 14'!C:C&'Category 14'!A:A,0)),INDEX('Category 14'!G:G,MATCH(C91&E91&D91,'Category 14'!B:B&'Category 14'!C:C&'Category 14'!A:A,0)))} -> 0 | J91: =I91/VLOOKUP($D91,CPI!$P$16:$R$22,3,FALSE) -> 0 | K91: {=IF(B91=0,INDEX('Category 15'!F:F,MATCH(C91&E91&D91,'Category 15'!B:B&'Category 15'!C:C&'Category 15'!A:A,0)),INDEX('Category 15'!G:G,MATCH(C91&E91&D91,'Category 15'!B:B&'Category 31'!C:C&'Category 15'!A:A,0)))} -> 0 | L91: =K91/VLOOKUP($D91,CPI!$P$16:$R$22,3,FALSE) -> 0 | M91: {=IF(B91=0,INDEX('Category 31'!F:F,MATCH(C91&E91&D91,'Category 31'!B:B&'Category 31'!C:C&'Category 31'!A:A,0)),INDEX('Category 31'!G:G,MATCH(C91&E91&D91,'Category 31'!B:B&'Category 31'!C:C&'Category 31'!A:A,0)))} -> 0 | N91: =M91/VLOOKUP($D91,CPI!$P$16:$R$22,3,FALSE) -> 0 | O91: 0
A92: 2 | B92: =IF(ISBLANK(G92),"",IF(MID(G92,1,1)="M",0,1)) -> 0 | C92: =IF(ISBLANK(H92),"",VLOOKUP(H92,Code!B:C,2,FALSE)) -> 20 | D92: 2022 | E92: 104179 | F92: Arizona | G92: Male | H92: Tennis | I92: {=IF(B92=0,INDEX('Category 14'!F:F,MATCH(C92&E92&D92,'Category 14'!B:B&'Category 14'!C:C&'Category 14'!A:A,0)),INDEX('Category 14'!G:G,MATCH(C92&E92&D92,'Category 14'!B:B&'Category 14'!C:C&'Category 14'!A:A,0)))} -> 1155 | J92: =I92/VLOOKUP($D92,CPI!$P$16:$R$22,3,FALSE) -> 1227.3265 | K92: {=IF(B92=0,INDEX('Category 15'!F:F,MATCH(C92&E92&D92,'Category 15'!B:B&'Category 15'!C:C&'Category 15'!A:A,0)),INDEX('Category 15'!G:G,MATCH(C92&E92&D92,'Category 15'!B:B&'Category 31'!C:C&'Category 15'!A:A,0)))} -> 0 | L92: =K92/VLOOKUP($D92,CPI!$P$16:$R$22,3,FALSE) -> 0 | M92: {=IF(B92=0,INDEX('Category 31'!F:F,MATCH(C92&E92&D92,'Category 31'!B:B&'Category 31'!C:C&'Category 31'!A:A,0)),INDEX('Category 31'!G:G,MATCH(C92&E92&D92,'Category 31'!B:B&'Category 31'!C:C&'Category 31'!A:A,0)))} -> 0 | N92: =M92/VLOOKUP($D92,CPI!$P$16:$R$22,3,FALSE) -> 0 | O92: 0
A93: 2 | B93: =IF(ISBLANK(G93),"",IF(MID(G93,1,1)="M",0,1)) -> 0 | C93: =IF(ISBLANK(H93),"",VLOOKUP(H93,Code!B:C,2,FALSE)) -> 21 | D93: 2022 | E93: 104179 | F93: Arizona | G93: Male | H93: Track and Field, X-Country | I93: {=IF(B93=0,INDEX('Category 14'!F:F,MATCH(C93&E93&D93,'Category 14'!B:B&'Category 14'!C:C&'Category 14'!A:A,0)),INDEX('Category 14'!G:G,MATCH(C93&E93&D93,'Category 14'!B:B&'Category 14'!C:C&'Category 14'!A:A,0)))} -> 0 | J93: =I93/VLOOKUP($D93,CPI!$P$16:$R$22,3,FALSE) -> 0 | K93: {=IF(B93=0,INDEX('Category 15'!F:F,MATCH(C93&E93&D93,'Category 15'!B:B&'Category 15'!C:C&'Category 15'!A:A,0)),INDEX('Category 15'!G:G,MATCH(C93&E93&D93,'Category 15'!B:B&'Category 31'!C:C&'Category 15'!A:A,0)))} -> 0 | L93: =K93/VLOOKUP($D93,CPI!$P$16:$R$22,3,FALSE) -> 0 | M93: {=IF(B93=0,INDEX('Category 31'!F:F,MATCH(C93&E93&D93,'Category 31'!B:B&'Category 31'!C:C&'Category 31'!A:A,0)),INDEX('Category 31'!G:G,MATCH(C93&E93&D93,'Category 31'!B:B&'Category 31'!C:C&'Category 31'!A:A,0)))} -> 0 | N93: =M93/VLOOKUP($D93,CPI!$P$16:$R$22,3,FALSE) -> 0 | O93: 0
A94: 2 | B94: =IF(ISBLANK(G94),"",IF(MID(G94,1,1)="M",0,1)) -> 1 | C94: =IF(ISBLANK(H94),"",VLOOKUP(H94,Code!B:C,2,FALSE)) -> 2 | D94: 2022 | E94: 104179 | F94: Arizona | G94: Female | H94: Basketball | I94: {=IF(B94=0,INDEX('Category 14'!F:F,MATCH(C94&E94&D94,'Category 14'!B:B&'Category 14'!C:C&'Category 14'!A:A,0)),INDEX('Category 14'!G:G,MATCH(C94&E94&D94,'Category 14'!B:B&'Category 14'!C:C&'Category 14'!A:A,0)))} -> 40615 | J94: =I94/VLOOKUP($D94,CPI!$P$16:$R$22,3,FALSE) -> 43158.325 | K94: {=IF(B94=0,INDEX('Category 15'!F:F,MATCH(C94&E94&D94,'Category 15'!B:B&'Category 15'!C:C&'Category 15'!A:A,0)),INDEX('Category 15'!G:G,MATCH(C94&E94&D94,'Category 15'!B:B&'Category 31'!C:C&'Category 15'!A:A,0)))} -> 0 | L94: =K94/VLOOKUP($D94,CPI!$P$16:$R$22,3,FALSE) -> 0 | M94: {=IF(B94=0,INDEX('Category 31'!F:F,MATCH(C94&E94&D94,'Category 31'!B:B&'Category 31'!C:C&'Category 31'!A:A,0)),INDEX('Category 31'!G:G,MATCH(C94&E94&D94,'Category 31'!B:B&'Category 31'!C:C&'Category 31'!A:A,0)))} -> 0 | N94: =M94/VLOOKUP($D94,CPI!$P$16:$R$22,3,FALSE) -> 0 | O94: =VLOOKUP(E43,WBasketball!C:S,11,FALSE) -> 117330
A95: 2 | B95: =IF(ISBLANK(G95),"",IF(MID(G95,1,1)="M",0,1)) -> 1 | C95: =IF(ISBLANK(H95),"",VLOOKUP(H95,Code!B:C,2,FALSE)) -> 3 | D95: 2022 | E95: 104179 | F95: Arizona | G95: Female | H95: Beach Volleyball | I95: {=IF(B95=0,INDEX('Category 14'!F:F,MATCH(C95&E95&D95,'Category 14'!B:B&'Category 14'!C:C&'Category 14'!A:A,0)),INDEX('Category 14'!G:G,MATCH(C95&E95&D95,'Category 14'!B:B&'Category 14'!C:C&'Category 14'!A:A,0)))} -> 0 | J95: =I95/VLOOKUP($D95,CPI!$P$16:$R$22,3,FALSE) -> 0 | K95: {=IF(B95=0,INDEX('Category 15'!F:F,MATCH(C95&E95&D95,'Category 15'!B:B&'Category 15'!C:C&'Category 15'!A:A,0)),INDEX('Category 15'!G:G,MATCH(C95&E95&D95,'Category 15'!B:B&'Category 31'!C:C&'Category 15'!A:A,0)))} -> 0 | L95: =K95/VLOOKUP($D95,CPI!$P$16:$R$22,3,FALSE) -> 0 | M95: {=IF(B95=0,INDEX('Category 31'!F:F,MATCH(C95&E95&D95,'Category 31'!B:B&'Category 31'!C:C&'Category 31'!A:A,0)),INDEX('Category 31'!G:G,MATCH(C95&E95&D95,'Category 31'!B:B&'Category 31'!C:C&'Category 31'!A:A,0)))} -> 0 | N95: =M95/VLOOKUP($D95,CPI!$P$16:$R$22,3,FALSE) -> 0 | O95: 0
A96: 2 | B96: =IF(ISBLANK(G96),"",IF(MID(G96,1,1)="M",0,1)) -> 1 | C96: =IF(ISBLANK(H96),"",VLOOKUP(H96,Code!B:C,2,FALSE)) -> 9 | D96: 2022 | E96: 104179 | F96: Arizona | G96: Female | H96: Golf | I96: {=IF(B96=0,INDEX('Category 14'!F:F,MATCH(C96&E96&D96,'Category 14'!B:B&'Category 14'!C:C&'Category 14'!A:A,0)),INDEX('Category 14'!G:G,MATCH(C96&E96&D96,'Category 14'!B:B&'Category 14'!C:C&'Category 14'!A:A,0)))} -> 0 | J96: =I96/VLOOKUP($D96,CPI!$P$16:$R$22,3,FALSE) -> 0 | K96: {=IF(B96=0,INDEX('Category 15'!F:F,MATCH(C96&E96&D96,'Category 15'!B:B&'Category 15'!C:C&'Category 15'!A:A,0)),INDEX('Category 15'!G:G,MATCH(C96&E96&D96,'Category 15'!B:B&'Category 31'!C:C&'Category 15'!A:A,0)))} -> 0 | L96: =K96/VLOOKUP($D96,CPI!$P$16:$R$22,3,FALSE) -> 0 | M96: {=IF(B96=0,INDEX('Category 31'!F:F,MATCH(C96&E96&D96,'Category 31'!B:B&'Category 31'!C:C&'Category 31'!A:A,0)),INDEX('Category 31'!G:G,MATCH(C96&E96&D96,'Category 31'!B:B&'Category 31'!C:C&'Category 31'!A:A,0)))} -> 0 | N96: =M96/VLOOKUP($D96,CPI!$P$16:$R$22,3,FALSE) -> 0 | O96: 0
A97: 2 | B97: =IF(ISBLANK(G97),"",IF(MID(G97,1,1)="M",0,1)) -> 1 | C97: =IF(ISBLANK(H97),"",VLOOKUP(H97,Code!B:C,2,FALSE)) -> 10 | D97: 2022 | E97: 104179 | F97: Arizona | G97: Female | H97: Gymnastics | I97: {=IF(B97=0,INDEX('Category 14'!F:F,MATCH(C97&E97&D97,'Category 14'!B:B&'Category 14'!C:C&'Category 14'!A:A,0)),INDEX('Category 14'!G:G,MATCH(C97&E97&D97,'Category 14'!B:B&'Category 14'!C:C&'Category 14'!A:A,0)))} -> 0 | J97: =I97/VLOOKUP($D97,CPI!$P$16:$R$22,3,FALSE) -> 0 | K97: {=IF(B97=0,INDEX('Category 15'!F:F,MATCH(C97&E97&D97,'Category 15'!B:B&'Category 15'!C:C&'Category 15'!A:A,0)),INDEX('Category 15'!G:G,MATCH(C97&E97&D97,'Category 15'!B:B&'Category 31'!C:C&'Category 15'!A:A,0)))} -> 0 | L97: =K97/VLOOKUP($D97,CPI!$P$16:$R$22,3,FALSE) -> 0 | M97: {=IF(B97=0,INDEX('Category 31'!F:F,MATCH(C97&E97&D97,'Category 31'!B:B&'Category 31'!C:C&'Category 31'!A:A,0)),INDEX('Category 31'!G:G,MATCH(C97&E97&D97,'Category 31'!B:B&'Category 31'!C:C&'Category 31'!A:A,0)))} -> 0 | N97: =M97/VLOOKUP($D97,CPI!$P$16:$R$22,3,FALSE) -> 0 | O97: 0
A98: 2 | B98: =IF(ISBLANK(G98),"",IF(MID(G98,1,1)="M",0,1)) -> 1 | C98: =IF(ISBLANK(H98),"",VLOOKUP(H98,Code!B:C,2,FALSE)) -> 17 | D98: 2022 | E98: 104179 | F98: Arizona | G98: Female | H98: Soccer | I98: {=IF(B98=0,INDEX('Category 14'!F:F,MATCH(C98&E98&D98,'Category 14'!B:B&'Category 14'!C:C&'Category 14'!A:A,0)),INDEX('Category 14'!G:G,MATCH(C98&E98&D98,'Category 14'!B:B&'Category 14'!C:C&'Category 14'!A:A,0)))} -> 0 | J98: =I98/VLOOKUP($D98,CPI!$P$16:$R$22,3,FALSE) -> 0 | K98: {=IF(B98=0,INDEX('Category 15'!F:F,MATCH(C98&E98&D98,'Category 15'!B:B&'Category 15'!C:C&'Category 15'!A:A,0)),INDEX('Category 15'!G:G,MATCH(C98&E98&D98,'Category 15'!B:B&'Category 31'!C:C&'Category 15'!A:A,0)))} -> 0 | L98: =K98/VLOOKUP($D98,CPI!$P$16:$R$22,3,FALSE) -> 0 | M98: {=IF(B98=0,INDEX('Category 31'!F:F,MATCH(C98&E98&D98,'Category 31'!B:B&'Category 31'!C:C&'Category 31'!A:A,0)),INDEX('Category 31'!G:G,MATCH(C98&E98&D98,'Category 31'!B:B&'Category 31'!C:C&'Category 31'!A:A,0)))} -> 0 | N98: =M98/VLOOKUP($D98,CPI!$P$16:$R$22,3,FALSE) -> 0 | O98: =VLOOKUP(E47,WSoccer!C:S,11,FALSE) -> 5547
A99: 2 | B99: =IF(ISBLANK(G99),"",IF(MID(G99,1,1)="M",0,1)) -> 1 | C99: =IF(ISBLANK(H99),"",VLOOKUP(H99,Code!B:C,2,FALSE)) -> 18 | D99: 2022 | E99: 104179 | F99: Arizona | G99: Female | H99: Softball | I99: {=IF(B99=0,INDEX('Category 14'!F:F,MATCH(C99&E99&D99,'Category 14'!B:B&'Category 14'!C:C&'Category 14'!A:A,0)),INDEX('Category 14'!G:G,MATCH(C99&E99&D99,'Category 14'!B:B&'Category 14'!C:C&'Category 14'!A:A,0)))} -> 0 | J99: =I99/VLOOKUP($D99,CPI!$P$16:$R$22,3,FALSE) -> 0 | K99: {=IF(B99=0,INDEX('Category 15'!F:F,MATCH(C99&E99&D99,'Category 15'!B:B&'Category 15'!C:C&'Category 15'!A:A,0)),INDEX('Category 15'!G:G,MATCH(C99&E99&D99,'Category 15'!B:B&'Category 31'!C:C&'Category 15'!A:A,0)))} -> 0 | L99: =K99/VLOOKUP($D99,CPI!$P$16:$R$22,3,FALSE) -> 0 | M99: {=IF(B99=0,INDEX('Category 31'!F:F,MATCH(C99&E99&D99,'Category 31'!B:B&'Category 31'!C:C&'Category 31'!A:A,0)),INDEX('Category 31'!G:G,MATCH(C99&E99&D99,'Category 31'!B:B&'Category 31'!C:C&'Category 31'!A:A,0)))} -> 0 | N99: =M99/VLOOKUP($D99,CPI!$P$16:$R$22,3,FALSE) -> 0 | O99: =VLOOKUP(E48,WSoftball!C:S,11,FALSE) -> 74028
A100: 2 | B100: =IF(ISBLANK(G100),"",IF(MID(G100,1,1)="M",0,1)) -> 1 | C100: =IF(ISBLANK(H100),"",VLOOKUP(H100,Code!B:C,2,FALSE)) -> 19 | D100: 2022 | E100: 104179 | F100: Arizona | G100: Female | H100: Swimming and Diving | I100: {=IF(B100=0,INDEX('Category 14'!F:F,MATCH(C100&E100&D100,'Category 14'!B:B&'Category 14'!C:C&'Category 14'!A:A,0)),INDEX('Category 14'!G:G,MATCH(C100&E100&D100,'Category 14'!B:B&'Category 14'!C:C&'Category 14'!A:A,0)))} -> 0 | J100: =I100/VLOOKUP($D100,CPI!$P$16:$R$22,3,FALSE) -> 0 | K100: {=IF(B100=0,INDEX('Category 15'!F:F,MATCH(C100&E100&D100,'Category 15'!B:B&'Category 15'!C:C&'Category 15'!A:A,0)),INDEX('Category 15'!G:G,MATCH(C100&E100&D100,'Category 15'!B:B&'Category 31'!C:C&'Category 15'!A:A,0)))} -> 0 | L100: =K100/VLOOKUP($D100,CPI!$P$16:$R$22,3,FALSE) -> 0 | M100: {=IF(B100=0,INDEX('Category 31'!F:F,MATCH(C100&E100&D100,'Category 31'!B:B&'Category 31'!C:C&'Category 31'!A:A,0)),INDEX('Category 31'!G:G,MATCH(C100&E100&D100,'Category 31'!B:B&'Category 31'!C:C&'Category 31'!A:A,0)))} -> 0 | N100: =M100/VLOOKUP($D100,CPI!$P$16:$R$22,3,FALSE) -> 0 | O100: 0
...

Sheet Category 14
A1: FY | B1: Code | C1: unitid | D1: University | E1: Sport | F1: Mens | G1: Womens | H1: NAG
A2: 2017 | B2: =IF(ISBLANK(E2),"",VLOOKUP(E2,Code!B:C,2,FALSE)) -> 1 | C2: 104179 | D2: Arizona | E2: Baseball | F2: 23795
A3: 2017 | B3: =IF(ISBLANK(E3),"",VLOOKUP(E3,Code!B:C,2,FALSE)) -> 2 | C3: 104179 | D3: Arizona | E3: Basketball | F3: 353895
A4: 2017 | B4: =IF(ISBLANK(E4),"",VLOOKUP(E4,Code!B:C,2,FALSE)) -> 3 | C4: 104179 | D4: Arizona | E4: Beach Volleyball | G4: 328
A5: 2017 | B5: 8 | C5: 104179 | D5: Arizona | E5: Football | F5: 659525
A6: 2017 | B6: =IF(ISBLANK(E6),"",VLOOKUP(E6,Code!B:C,2,FALSE)) -> 9 | C6: 104179 | D6: Arizona | E6: Golf | F6: 18513 | G6: 4680
A7: 2017 | B7: =IF(ISBLANK(E7),"",VLOOKUP(E7,Code!B:C,2,FALSE)) -> 10 | C7: 104179 | D7: Arizona | E7: Gymnastics | G7: 295
A8: 2017 | B8: =IF(ISBLANK(E8),"",VLOOKUP(E8,Code!B:C,2,FALSE)) -> 17 | C8: 104179 | D8: Arizona | E8: Soccer | G8: 2346
A9: 2017 | B9: =IF(ISBLANK(E9),"",VLOOKUP(E9,Code!B:C,2,FALSE)) -> 18 | C9: 104179 | D9: Arizona | E9: Softball | G9: 30388
A10: 2017 | B10: =IF(ISBLANK(E10),"",VLOOKUP(E10,Code!B:C,2,FALSE)) -> 19 | C10: 104179 | D10: Arizona | E10: Swimming and Diving | F10: 5787 | G10: 8180
A11: 2017 | B11: =IF(ISBLANK(E11),"",VLOOKUP(E11,Code!B:C,2,FALSE)) -> 20 | C11: 104179 | D11: Arizona | E11: Tennis | G11: 12187
A12: 2017 | B12: =IF(ISBLANK(E12),"",VLOOKUP(E12,Code!B:C,2,FALSE)) -> 21 | C12: 104179 | D12: Arizona | E12: Track and Field, X-Country | F12: 15915 | G12: 9702
A13: 2017 | B13: =IF(ISBLANK(E13),"",VLOOKUP(E13,Code!B:C,2,FALSE)) -> 23 | C13: 104179 | D13: Arizona | E13: Volleyball | G13: 19455
A14: 2018 | B14: =IF(ISBLANK(E14),"",VLOOKUP(E14,Code!B:C,2,FALSE)) -> 1 | C14: 104179 | D14: Arizona | E14: Baseball | F14: 2150
A15: 2018 | B15: =IF(ISBLANK(E15),"",VLOOKUP(E15,Code!B:C,2,FALSE)) -> 2 | C15: 104179 | D15: Arizona | E15: Basketball | F15: 166804
A16: 2018 | B16: =IF(ISBLANK(E16),"",VLOOKUP(E16,Code!B:C,2,FALSE)) -> 8 | C16: 104179 | D16: Arizona | E16: Football | F16: 592731
A17: 2018 | B17: =IF(ISBLANK(E17),"",VLOOKUP(E17,Code!B:C,2,FALSE)) -> 21 | C17: 104179 | D17: Arizona | E17: Track and Field, X-Country | F17: 11082 | G17: 10223
A18: 2018 | B18: =IF(ISBLANK(E18),"",VLOOKUP(E18,Code!B:C,2,FALSE)) -> 3 | C18: 104179 | D18: Arizona | E18: Beach Volleyball
A19: 2018 | B19: =IF(ISBLANK(E19),"",VLOOKUP(E19,Code!B:C,2,FALSE)) -> 9 | C19: 104179 | D19: Arizona | E19: Golf | F19: 32700 | G19: 11085
A20: 2018 | B20: =IF(ISBLANK(E20),"",VLOOKUP(E20,Code!B:C,2,FALSE)) -> 10 | C20: 104179 | D20: Arizona | E20: Gymnastics | G20: 1937
A21: 2018 | B21: =IF(ISBLANK(E21),"",VLOOKUP(E21,Code!B:C,2,FALSE)) -> 17 | C21: 104179 | D21: Arizona | E21: Soccer | G21: 2300
A22: 2018 | B22: =IF(ISBLANK(E22),"",VLOOKUP(E22,Code!B:C,2,FALSE)) -> 18 | C22: 104179 | D22: Arizona | E22: Softball
A23: 2018 | B23: =IF(ISBLANK(E23),"",VLOOKUP(E23,Code!B:C,2,FALSE)) -> 19 | C23: 104179 | D23: Arizona | E23: Swimming and Diving | F23: 1296 | G23: 1121
A24: 2018 | B24: =IF(ISBLANK(E24),"",VLOOKUP(E24,Code!B:C,2,FALSE)) -> 20 | C24: 104179 | D24: Arizona | E24: Tennis | G24: 870
A25: 2018 | B25: =IF(ISBLANK(E25),"",VLOOKUP(E25,Code!B:C,2,FALSE)) -> 23 | C25: 104179 | D25: Arizona | E25: Volleyball
A26: 2019 | B26: =IF(ISBLANK(E26),"",VLOOKUP(E26,Code!B:C,2,FALSE)) -> 1 | C26: 104179 | D26: Arizona | E26: Baseball | F26: 3435
A27: 2019 | B27: =IF(ISBLANK(E27),"",VLOOKUP(E27,Code!B:C,2,FALSE)) -> 2 | C27: 104179 | D27: Arizona | E27: Basketball | F27: 45770
A28: 2019 | B28: =IF(ISBLANK(E28),"",VLOOKUP(E28,Code!B:C,2,FALSE)) -> 8 | C28: 104179 | D28: Arizona | E28: Football | F28: 471041
A29: 2019 | B29: =IF(ISBLANK(E29),"",VLOOKUP(E29,Code!B:C,2,FALSE)) -> 9 | C29: 104179 | D29: Arizona | E29: Golf
A30: 2019 | B30: =IF(ISBLANK(E30),"",VLOOKUP(E30,Code!B:C,2,FALSE)) -> 20 | C30: 104179 | D30: Arizona | E30: Tennis
A31: 2019 | B31: =IF(ISBLANK(E31),"",VLOOKUP(E31,Code!B:C,2,FALSE)) -> 21 | C31: 104179 | D31: Arizona | E31: Track and Field, X-Country
A32: 2019 | B32: =IF(ISBLANK(E32),"",VLOOKUP(E32,Code!B:C,2,FALSE)) -> 3 | C32: 104179 | D32: Arizona | E32: Beach Volleyball | G32: 590
A33: 2019 | B33: =IF(ISBLANK(E33),"",VLOOKUP(E33,Code!B:C,2,FALSE)) -> 10 | C33: 104179 | D33: Arizona | E33: Gymnastics
A34: 2019 | B34: =IF(ISBLANK(E34),"",VLOOKUP(E34,Code!B:C,2,FALSE)) -> 17 | C34: 104179 | D34: Arizona | E34: Soccer | G34: 14756
A35: 2019 | B35: =IF(ISBLANK(E35),"",VLOOKUP(E35,Code!B:C,2,FALSE)) -> 18 | C35: 104179 | D35: Arizona | E35: Softball
A36: 2019 | B36: =IF(ISBLANK(E36),"",VLOOKUP(E36,Code!B:C,2,FALSE)) -> 19 | C36: 104179 | D36: Arizona | E36: Swimming and Diving
A37: 2019 | B37: =IF(ISBLANK(E37),"",VLOOKUP(E37,Code!B:C,2,FALSE)) -> 23 | C37: 104179 | D37: Arizona | E37: Volleyball
A38: 2020 | B38: =IF(ISBLANK(E38),"",VLOOKUP(E38,Code!B:C,2,FALSE)) -> 1 | C38: 104179 | D38: Arizona | E38: Baseball | F38: 55
A39: 2020 | B39: =IF(ISBLANK(E39),"",VLOOKUP(E39,Code!B:C,2,FALSE)) -> 2 | C39: 104179 | D39: Arizona | E39: Basketball | F39: 111966
A40: 2020 | B40: =IF(ISBLANK(E40),"",VLOOKUP(E40,Code!B:C,2,FALSE)) -> 8 | C40: 104179 | D40: Arizona | E40: Football | F40: 448366
A41: 2020 | B41: =IF(ISBLANK(E41),"",VLOOKUP(E41,Code!B:C,2,FALSE)) -> 3 | C41: 104179 | D41: Arizona | E41: Beach Volleyball
A42: 2020 | B42: =IF(ISBLANK(E42),"",VLOOKUP(E42,Code!B:C,2,FALSE)) -> 9 | C42: 104179 | D42: Arizona | E42: Golf
A43: 2020 | B43: =IF(ISBLANK(E43),"",VLOOKUP(E43,Code!B:C,2,FALSE)) -> 10 | C43: 104179 | D43: Arizona | E43: Gymnastics
A44: 2020 | B44: =IF(ISBLANK(E44),"",VLOOKUP(E44,Code!B:C,2,FALSE)) -> 17 | C44: 104179 | D44: Arizona | E44: Soccer | G44: 20490
A45: 2020 | B45: =IF(ISBLANK(E45),"",VLOOKUP(E45,Code!B:C,2,FALSE)) -> 18 | C45: 104179 | D45: Arizona | E45: Softball
A46: 2020 | B46: =IF(ISBLANK(E46),"",VLOOKUP(E46,Code!B:C,2,FALSE)) -> 19 | C46: 104179 | D46: Arizona | E46: Swimming and Diving
A47: 2020 | B47: =IF(ISBLANK(E47),"",VLOOKUP(E47,Code!B:C,2,FALSE)) -> 20 | C47: 104179 | D47: Arizona | E47: Tennis
A48: 2020 | B48: =IF(ISBLANK(E48),"",VLOOKUP(E48,Code!B:C,2,FALSE)) -> 21 | C48: 104179 | D48: Arizona | E48: Track and Field, X-Country
A49: 2020 | B49: =IF(ISBLANK(E49),"",VLOOKUP(E49,Code!B:C,2,FALSE)) -> 23 | C49: 104179 | D49: Arizona | E49: Volleyball
A50: 2021 | B50: =IF(ISBLANK(E50),"",VLOOKUP(E50,Code!B:C,2,FALSE)) -> 1 | C50: 104179 | D50: Arizona | E50: Baseball
A51: 2021 | B51: =IF(ISBLANK(E51),"",VLOOKUP(E51,Code!B:C,2,FALSE)) -> 2 | C51: 104179 | D51: Arizona | E51: Basketball | F51: 29555
A52: 2021 | B52: =IF(ISBLANK(E52),"",VLOOKUP(E52,Code!B:C,2,FALSE)) -> 8 | C52: 104179 | D52: Arizona | E52: Football | F52: 305983
A53: 2021 | B53: 3 | C53: 104179 | D53: Arizona | E53: Beach Volleyball
A54: 2021 | B54: 9 | C54: 104179 | D54: Arizona | E54: Golf
A55: 2021 | B55: =IF(ISBLANK(E55),"",VLOOKUP(E55,Code!B:C,2,FALSE)) -> 10 | C55: 104179 | D55: Arizona | E55: Gymnastics
A56: 2021 | B56: =IF(ISBLANK(E56),"",VLOOKUP(E56,Code!B:C,2,FALSE)) -> 17 | C56: 104179 | D56: Arizona | E56: Soccer
A57: 2021 | B57: =IF(ISBLANK(E57),"",VLOOKUP(E57,Code!B:C,2,FALSE)) -> 18 | C57: 104179 | D57: Arizona | E57: Softball
A58: 2021 | B58: 19 | C58: 104179 | D58: Arizona | E58: Swimming and diving
A59: 2021 | B59: =IF(ISBLANK(E59),"",VLOOKUP(E59,Code!B:C,2,FALSE)) -> 20 | C59: 104179 | D59: Arizona | E59: Tennis
A60: 2021 | B60: 21 | C60: 104179 | D60: Arizona | E60: Track and Field , X country
A61: 2021 | B61: =IF(ISBLANK(E61),"",VLOOKUP(E61,Code!B:C,2,FALSE)) -> 23 | C61: 104179 | D61: Arizona | E61: Volleyball
A62: 2022 | B62: =IF(ISBLANK(E62),"",VLOOKUP(E62,Code!B:C,2,FALSE)) -> 1 | C62: 104179 | D62: Arizona | E62: Baseball | F62: 986
A63: 2022 | B63: =IF(ISBLANK(E63),"",VLOOKUP(E63,Code!B:C,2,FALSE)) -> 2 | C63: 104179 | D63: Arizona | E63: Basketball | F63: 29403 | G63: 40615
A64: 2022 | B64: =IF(ISBLANK(E64),"",VLOOKUP(E64,Code!B:C,2,FALSE)) -> 8 | C64: 104179 | D64: Arizona | E64: Football | F64: 497067
A65: 2022 | B65: =IF(ISBLANK(E65),"",VLOOKUP(E65,Code!B:C,2,FALSE)) -> 3 | C65: 104179 | D65: Arizona | E65: Beach Volleyball
A66: 2022 | B66: =IF(ISBLANK(E66),"",VLOOKUP(E66,Code!B:C,2,FALSE)) -> 9 | C66: 104179 | D66: Arizona | E66: Golf
A67: 2022 | B67: =IF(ISBLANK(E67),"",VLOOKUP(E67,Code!B:C,2,FALSE)) -> 10 | C67: 104179 | D67: Arizona | E67: Gymnastics
A68: 2022 | B68: =IF(ISBLANK(E68),"",VLOOKUP(E68,Code!B:C,2,FALSE)) -> 17 | C68: 104179 | D68: Arizona | E68: Soccer
A69: 2022 | B69: =IF(ISBLANK(E69),"",VLOOKUP(E69,Code!B:C,2,FALSE)) -> 18 | C69: 104179 | D69: Arizona | E69: Softball
A70: 2022 | B70: =IF(ISBLANK(E70),"",VLOOKUP(E70,Code!B:C,2,FALSE)) -> 19 | C70: 104179 | D70: Arizona | E70: Swimming and Diving
A71: 2022 | B71: =IF(ISBLANK(E71),"",VLOOKUP(E71,Code!B:C,2,FALSE)) -> 20 | C71: 104179 | D71: Arizona | E71: Tennis | F71: 1155
A72: 2022 | B72: =IF(ISBLANK(E72),"",VLOOKUP(E72,Code!B:C,2,FALSE)) -> 21 | C72: 104179 | D72: Arizona | E72: Track and Field, X-Country
A73: 2022 | B73: =IF(ISBLANK(E73),"",VLOOKUP(E73,Code!B:C,2,FALSE)) -> 23 | C73: 104179 | D73: Arizona | E73: Volleyball
A74: 2023 | B74: =IF(ISBLANK(E74),"",VLOOKUP(E74,Code!B:C,2,FALSE)) -> 1 | C74: 104179 | D74: Arizona | E74: Baseball | F74: 11162
A75: 2023 | B75: =IF(ISBLANK(E75),"",VLOOKUP(E75,Code!B:C,2,FALSE)) -> 2 | C75: 104179 | D75: Arizona | E75: Basketball | F75: 86490 | G75: 65747
A76: 2023 | B76: =IF(ISBLANK(E76),"",VLOOKUP(E76,Code!B:C,2,FALSE)) -> 8 | C76: 104179 | D76: Arizona | E76: Football | F76: 564856
A77: 2023 | B77: =IF(ISBLANK(E77),"",VLOOKUP(E77,Code!B:C,2,FALSE)) -> 3 | C77: 104179 | D77: Arizona | E77: Beach Volleyball
A78: 2023 | B78: =IF(ISBLANK(E78),"",VLOOKUP(E78,Code!B:C,2,FALSE)) -> 9 | C78: 104179 | D78: Arizona | E78: Golf
A79: 2023 | B79: =IF(ISBLANK(E79),"",VLOOKUP(E79,Code!B:C,2,FALSE)) -> 10 | C79: 104179 | D79: Arizona | E79: Gymnastics
A80: 2023 | B80: =IF(ISBLANK(E80),"",VLOOKUP(E80,Code!B:C,2,FALSE)) -> 17 | C80: 104179 | D80: Arizona | E80: Soccer
A81: 2023 | B81: =IF(ISBLANK(E81),"",VLOOKUP(E81,Code!B:C,2,FALSE)) -> 18 | C81: 104179 | D81: Arizona | E81: Softball
A82: 2023 | B82: =IF(ISBLANK(E82),"",VLOOKUP(E82,Code!B:C,2,FALSE)) -> 19 | C82: 104179 | D82: Arizona | E82: Swimming and Diving
A83: 2023 | B83: =IF(ISBLANK(E83),"",VLOOKUP(E83,Code!B:C,2,FALSE)) -> 20 | C83: 104179 | D83: Arizona | E83: Tennis
A84: 2023 | B84: =IF(ISBLANK(E84),"",VLOOKUP(E84,Code!B:C,2,FALSE)) -> 21 | C84: 104179 | D84: Arizona | E84: Track and Field, X- Country | F84: 1579
A85: 2023 | B85: =IF(ISBLANK(E85),"",VLOOKUP(E85,Code!B:C,2,FALSE)) -> 23 | C85: 104179 | D85: Arizona | E85: Volleyball
A86: 2017 | B86: =IF(ISBLANK(E86),"",VLOOKUP(E86,Code!B:C,2,FALSE)) -> 1 | C86: 110635 | D86: California | E86: Baseball | F86: 7729
A87: 2017 | B87: =IF(ISBLANK(E87),"",VLOOKUP(E87,Code!B:C,2,FALSE)) -> 2 | C87: 110635 | D87: California | E87: Basketball | F87: 1499 | G87: 671
A88: 2017 | B88: =IF(ISBLANK(E88),"",VLOOKUP(E88,Code!B:C,2,FALSE)) -> 8 | C88: 110635 | D88: California | E88: Football | F88: 522852
A89: 2017 | B89: =IF(ISBLANK(E89),"",VLOOKUP(E89,Code!B:C,2,FALSE)) -> 3 | C89: 110635 | D89: California | E89: Beach Volleyball
A90: 2017 | B90: =IF(ISBLANK(E90),"",VLOOKUP(E90,Code!B:C,2,FALSE)) -> 7 | C90: 110635 | D90: California | E90: Field Hockey
A91: 2017 | B91: =IF(ISBLANK(E91),"",VLOOKUP(E91,Code!B:C,2,FALSE)) -> 9 | C91: 110635 | D91: California | E91: Golf
A92: 2017 | B92: =IF(ISBLANK(E92),"",VLOOKUP(E92,Code!B:C,2,FALSE)) -> 10 | C92: 110635 | D92: California | E92: Gymnastics
A93: 2017 | B93: =IF(ISBLANK(E93),"",VLOOKUP(E93,Code!B:C,2,FALSE)) -> 12 | C93: 110635 | D93: California | E93: Lacrosse
A94: 2017 | B94: =IF(ISBLANK(E94),"",VLOOKUP(E94,Code!B:C,2,FALSE)) -> 14 | C94: 110635 | D94: California | E94: Rowing
A95: 2017 | B95: =IF(ISBLANK(E95),"",VLOOKUP(E95,Code!B:C,2,FALSE)) -> 17 | C95: 110635 | D95: California | E95: Soccer | F95: 260 | G95: 255
A96: 2017 | B96: =IF(ISBLANK(E96),"",VLOOKUP(E96,Code!B:C,2,FALSE)) -> 18 | C96: 110635 | D96: California | E96: Softball
A97: 2017 | B97: =IF(ISBLANK(E97),"",VLOOKUP(E97,Code!B:C,2,FALSE)) -> 19 | C97: 110635 | D97: California | E97: Swimming and Diving
A98: 2017 | B98: =IF(ISBLANK(E98),"",VLOOKUP(E98,Code!B:C,2,FALSE)) -> 20 | C98: 110635 | D98: California | E98: Tennis
A99: 2017 | B99: =IF(ISBLANK(E99),"",VLOOKUP(E99,Code!B:C,2,FALSE)) -> 21 | C99: 110635 | D99: California | E99: Track and Field, X-Country
A100: 2017 | B100: =IF(ISBLANK(E100),"",VLOOKUP(E100,Code!B:C,2,FALSE)) -> 23 | C100: 110635 | D100: California | E100: Volleyball | G100: 203
...

Sheet Category 15
A1: FY | B1: Code | C1: unitid | D1: University | E1: Sport | F1: Mens | G1: Womens | H1: NAG
A2: 2017 | B2: =IF(ISBLANK(E2),"",VLOOKUP(E2,Code!B:C,2,FALSE)) -> 1 | C2: 104179 | D2: Arizona | E2: Baseball
A3: 2017 | B3: =IF(ISBLANK(E3),"",VLOOKUP(E3,Code!B:C,2,FALSE)) -> 2 | C3: 104179 | D3: Arizona | E3: Basketball | F3: 4950066
A4: 2017 | B4: =IF(ISBLANK(E4),"",VLOOKUP(E4,Code!B:C,2,FALSE)) -> 3 | C4: 104179 | D4: Arizona | E4: Beach Volleyball
A5: 2017 | B5: 8 | C5: 104179 | D5: Arizona | E5: Football | F5: 4950066
A6: 2017 | B6: =IF(ISBLANK(E6),"",VLOOKUP(E6,Code!B:C,2,FALSE)) -> 9 | C6: 104179 | D6: Arizona | E6: Golf
A7: 2017 | B7: =IF(ISBLANK(E7),"",VLOOKUP(E7,Code!B:C,2,FALSE)) -> 10 | C7: 104179 | D7: Arizona | E7: Gymnastics
A8: 2017 | B8: =IF(ISBLANK(E8),"",VLOOKUP(E8,Code!B:C,2,FALSE)) -> 17 | C8: 104179 | D8: Arizona | E8: Soccer
A9: 2017 | B9: =IF(ISBLANK(E9),"",VLOOKUP(E9,Code!B:C,2,FALSE)) -> 18 | C9: 104179 | D9: Arizona | E9: Softball
A10: 2017 | B10: =IF(ISBLANK(E10),"",VLOOKUP(E10,Code!B:C,2,FALSE)) -> 19 | C10: 104179 | D10: Arizona | E10: Swimming and Diving
A11: 2017 | B11: =IF(ISBLANK(E11),"",VLOOKUP(E11,Code!B:C,2,FALSE)) -> 20 | C11: 104179 | D11: Arizona | E11: Tennis
A12: 2017 | B12: =IF(ISBLANK(E12),"",VLOOKUP(E12,Code!B:C,2,FALSE)) -> 21 | C12: 104179 | D12: Arizona | E12: Track and Field, X-Country
A13: 2017 | B13: =IF(ISBLANK(E13),"",VLOOKUP(E13,Code!B:C,2,FALSE)) -> 23 | C13: 104179 | D13: Arizona | E13: Volleyball
A14: 2018 | B14: =IF(ISBLANK(E14),"",VLOOKUP(E14,Code!B:C,2,FALSE)) -> 1 | C14: 104179 | D14: Arizona | E14: Baseball
A15: 2018 | B15: =IF(ISBLANK(E15),"",VLOOKUP(E15,Code!B:C,2,FALSE)) -> 2 | C15: 104179 | D15: Arizona | E15: Basketball | F15: 4432881
A16: 2018 | B16: =IF(ISBLANK(E16),"",VLOOKUP(E16,Code!B:C,2,FALSE)) -> 8 | C16: 104179 | D16: Arizona | E16: Football | F16: 4432880
A17: 2018 | B17: =IF(ISBLANK(E17),"",VLOOKUP(E17,Code!B:C,2,FALSE)) -> 21 | C17: 104179 | D17: Arizona | E17: Track and Field, X-Country
A18: 2018 | B18: =IF(ISBLANK(E18),"",VLOOKUP(E18,Code!B:C,2,FALSE)) -> 3 | C18: 104179 | D18: Arizona | E18: Beach Volleyball
A19: 2018 | B19: =IF(ISBLANK(E19),"",VLOOKUP(E19,Code!B:C,2,FALSE)) -> 9 | C19: 104179 | D19: Arizona | E19: Golf
A20: 2018 | B20: =IF(ISBLANK(E20),"",VLOOKUP(E20,Code!B:C,2,FALSE)) -> 10 | C20: 104179 | D20: Arizona | E20: Gymnastics
A21: 2018 | B21: =IF(ISBLANK(E21),"",VLOOKUP(E21,Code!B:C,2,FALSE)) -> 17 | C21: 104179 | D21: Arizona | E21: Soccer
A22: 2018 | B22: =IF(ISBLANK(E22),"",VLOOKUP(E22,Code!B:C,2,FALSE)) -> 18 | C22: 104179 | D22: Arizona | E22: Softball
A23: 2018 | B23: =IF(ISBLANK(E23),"",VLOOKUP(E23,Code!B:C,2,FALSE)) -> 19 | C23: 104179 | D23: Arizona | E23: Swimming and Diving
A24: 2018 | B24: =IF(ISBLANK(E24),"",VLOOKUP(E24,Code!B:C,2,FALSE)) -> 20 | C24: 104179 | D24: Arizona | E24: Tennis
A25: 2018 | B25: =IF(ISBLANK(E25),"",VLOOKUP(E25,Code!B:C,2,FALSE)) -> 23 | C25: 104179 | D25: Arizona | E25: Volleyball
A26: 2019 | B26: =IF(ISBLANK(E26),"",VLOOKUP(E26,Code!B:C,2,FALSE)) -> 1 | C26: 104179 | D26: Arizona | E26: Baseball
A27: 2019 | B27: =IF(ISBLANK(E27),"",VLOOKUP(E27,Code!B:C,2,FALSE)) -> 2 | C27: 104179 | D27: Arizona | E27: Basketball | F27: 4381518
A28: 2019 | B28: =IF(ISBLANK(E28),"",VLOOKUP(E28,Code!B:C,2,FALSE)) -> 8 | C28: 104179 | D28: Arizona | E28: Football | F28: 4381518
A29: 2019 | B29: =IF(ISBLANK(E29),"",VLOOKUP(E29,Code!B:C,2,FALSE)) -> 9 | C29: 104179 | D29: Arizona | E29: Golf
A30: 2019 | B30: =IF(ISBLANK(E30),"",VLOOKUP(E30,Code!B:C,2,FALSE)) -> 20 | C30: 104179 | D30: Arizona | E30: Tennis
A31: 2019 | B31: =IF(ISBLANK(E31),"",VLOOKUP(E31,Code!B:C,2,FALSE)) -> 21 | C31: 104179 | D31: Arizona | E31: Track and Field, X-Country
A32: 2019 | B32: =IF(ISBLANK(E32),"",VLOOKUP(E32,Code!B:C,2,FALSE)) -> 3 | C32: 104179 | D32: Arizona | E32: Beach Volleyball
A33: 2019 | B33: =IF(ISBLANK(E33),"",VLOOKUP(E33,Code!B:C,2,FALSE)) -> 10 | C33: 104179 | D33: Arizona | E33: Gymnastics
A34: 2019 | B34: =IF(ISBLANK(E34),"",VLOOKUP(E34,Code!B:C,2,FALSE)) -> 17 | C34: 104179 | D34: Arizona | E34: Soccer
A35: 2019 | B35: =IF(ISBLANK(E35),"",VLOOKUP(E35,Code!B:C,2,FALSE)) -> 18 | C35: 104179 | D35: Arizona | E35: Softball
A36: 2019 | B36: =IF(ISBLANK(E36),"",VLOOKUP(E36,Code!B:C,2,FALSE)) -> 19 | C36: 104179 | D36: Arizona | E36: Swimming and Diving
A37: 2019 | B37: =IF(ISBLANK(E37),"",VLOOKUP(E37,Code!B:C,2,FALSE)) -> 23 | C37: 104179 | D37: Arizona | E37: Volleyball
A38: 2020 | B38: =IF(ISBLANK(E38),"",VLOOKUP(E38,Code!B:C,2,FALSE)) -> 1 | C38: 104179 | D38: Arizona | E38: Baseball
A39: 2020 | B39: =IF(ISBLANK(E39),"",VLOOKUP(E39,Code!B:C,2,FALSE)) -> 2 | C39: 104179 | D39: Arizona | E39: Basketball | F39: 4185479
A40: 2020 | B40: =IF(ISBLANK(E40),"",VLOOKUP(E40,Code!B:C,2,FALSE)) -> 8 | C40: 104179 | D40: Arizona | E40: Football | F40: 4185478
A41: 2020 | B41: =IF(ISBLANK(E41),"",VLOOKUP(E41,Code!B:C,2,FALSE)) -> 3 | C41: 104179 | D41: Arizona | E41: Beach Volleyball
A42: 2020 | B42: =IF(ISBLANK(E42),"",VLOOKUP(E42,Code!B:C,2,FALSE)) -> 9 | C42: 104179 | D42: Arizona | E42: Golf
A43: 2020 | B43: =IF(ISBLANK(E43),"",VLOOKUP(E43,Code!B:C,2,FALSE)) -> 10 | C43: 104179 | D43: Arizona | E43: Gymnastics
A44: 2020 | B44: =IF(ISBLANK(E44),"",VLOOKUP(E44,Code!B:C,2,FALSE)) -> 17 | C44: 104179 | D44: Arizona | E44: Soccer
A45: 2020 | B45: =IF(ISBLANK(E45),"",VLOOKUP(E45,Code!B:C,2,FALSE)) -> 18 | C45: 104179 | D45: Arizona | E45: Softball
A46: 2020 | B46: =IF(ISBLANK(E46),"",VLOOKUP(E46,Code!B:C,2,FALSE)) -> 19 | C46: 104179 | D46: Arizona | E46: Swimming and Diving
A47: 2020 | B47: =IF(ISBLANK(E47),"",VLOOKUP(E47,Code!B:C,2,FALSE)) -> 20 | C47: 104179 | D47: Arizona | E47: Tennis
A48: 2020 | B48: =IF(ISBLANK(E48),"",VLOOKUP(E48,Code!B:C,2,FALSE)) -> 21 | C48: 104179 | D48: Arizona | E48: Track and Field, X-Country
A49: 2020 | B49: =IF(ISBLANK(E49),"",VLOOKUP(E49,Code!B:C,2,FALSE)) -> 23 | C49: 104179 | D49: Arizona | E49: Volleyball
A50: 2021 | B50: =IF(ISBLANK(E50),"",VLOOKUP(E50,Code!B:C,2,FALSE)) -> 1 | C50: 104179 | D50: Arizona | E50: Baseball
A51: 2021 | B51: =IF(ISBLANK(E51),"",VLOOKUP(E51,Code!B:C,2,FALSE)) -> 2 | C51: 104179 | D51: Arizona | E51: Basketball | F51: 3437220
A52: 2021 | B52: =IF(ISBLANK(E52),"",VLOOKUP(E52,Code!B:C,2,FALSE)) -> 8 | C52: 104179 | D52: Arizona | E52: Football | F52: 3437220
A53: 2021 | B53: 3 | C53: 104179 | D53: Arizona | E53: Beach Volleyball
A54: 2021 | B54: 9 | C54: 104179 | D54: Arizona | E54: Golf
A55: 2021 | B55: =IF(ISBLANK(E55),"",VLOOKUP(E55,Code!B:C,2,FALSE)) -> 10 | C55: 104179 | D55: Arizona | E55: Gymnastics
A56: 2021 | B56: =IF(ISBLANK(E56),"",VLOOKUP(E56,Code!B:C,2,FALSE)) -> 17 | C56: 104179 | D56: Arizona | E56: Soccer
A57: 2021 | B57: =IF(ISBLANK(E57),"",VLOOKUP(E57,Code!B:C,2,FALSE)) -> 18 | C57: 104179 | D57: Arizona | E57: Softball
A58: 2021 | B58: 19 | C58: 104179 | D58: Arizona | E58: Swimming and diving
A59: 2021 | B59: =IF(ISBLANK(E59),"",VLOOKUP(E59,Code!B:C,2,FALSE)) -> 20 | C59: 104179 | D59: Arizona | E59: Tennis
A60: 2021 | B60: 21 | C60: 104179 | D60: Arizona | E60: Track and Field , X country
A61: 2021 | B61: =IF(ISBLANK(E61),"",VLOOKUP(E61,Code!B:C,2,FALSE)) -> 23 | C61: 104179 | D61: Arizona | E61: Volleyball
A62: 2022 | B62: =IF(ISBLANK(E62),"",VLOOKUP(E62,Code!B:C,2,FALSE)) -> 1 | C62: 104179 | D62: Arizona | E62: Baseball
A63: 2022 | B63: =IF(ISBLANK(E63),"",VLOOKUP(E63,Code!B:C,2,FALSE)) -> 2 | C63: 104179 | D63: Arizona | E63: Basketball | F63: 4756131
A64: 2022 | B64: =IF(ISBLANK(E64),"",VLOOKUP(E64,Code!B:C,2,FALSE)) -> 8 | C64: 104179 | D64: Arizona | E64: Football | F64: 4756130
A65: 2022 | B65: =IF(ISBLANK(E65),"",VLOOKUP(E65,Code!B:C,2,FALSE)) -> 3 | C65: 104179 | D65: Arizona | E65: Beach Volleyball
A66: 2022 | B66: =IF(ISBLANK(E66),"",VLOOKUP(E66,Code!B:C,2,FALSE)) -> 9 | C66: 104179 | D66: Arizona | E66: Golf
A67: 2022 | B67: =IF(ISBLANK(E67),"",VLOOKUP(E67,Code!B:C,2,FALSE)) -> 10 | C67: 104179 | D67: Arizona | E67: Gymnastics
A68: 2022 | B68: =IF(ISBLANK(E68),"",VLOOKUP(E68,Code!B:C,2,FALSE)) -> 17 | C68: 104179 | D68: Arizona | E68: Soccer
A69: 2022 | B69: =IF(ISBLANK(E69),"",VLOOKUP(E69,Code!B:C,2,FALSE)) -> 18 | C69: 104179 | D69: Arizona | E69: Softball
A70: 2022 | B70: =IF(ISBLANK(E70),"",VLOOKUP(E70,Code!B:C,2,FALSE)) -> 19 | C70: 104179 | D70: Arizona | E70: Swimming and Diving
A71: 2022 | B71: =IF(ISBLANK(E71),"",VLOOKUP(E71,Code!B:C,2,FALSE)) -> 20 | C71: 104179 | D71: Arizona | E71: Tennis
A72: 2022 | B72: =IF(ISBLANK(E72),"",VLOOKUP(E72,Code!B:C,2,FALSE)) -> 21 | C72: 104179 | D72: Arizona | E72: Track and Field, X-Country
A73: 2022 | B73: =IF(ISBLANK(E73),"",VLOOKUP(E73,Code!B:C,2,FALSE)) -> 23 | C73: 104179 | D73: Arizona | E73: Volleyball
A74: 2023 | B74: =IF(ISBLANK(E74),"",VLOOKUP(E74,Code!B:C,2,FALSE)) -> 1 | C74: 104179 | D74: Arizona | E74: Baseball
A75: 2023 | B75: =IF(ISBLANK(E75),"",VLOOKUP(E75,Code!B:C,2,FALSE)) -> 2 | C75: 104179 | D75: Arizona | E75: Basketball | F75: 6234414
A76: 2023 | B76: =IF(ISBLANK(E76),"",VLOOKUP(E76,Code!B:C,2,FALSE)) -> 8 | C76: 104179 | D76: Arizona | E76: Football | F76: 6234414
A77: 2023 | B77: =IF(ISBLANK(E77),"",VLOOKUP(E77,Code!B:C,2,FALSE)) -> 3 | C77: 104179 | D77: Arizona | E77: Beach Volleyball
A78: 2023 | B78: =IF(ISBLANK(E78),"",VLOOKUP(E78,Code!B:C,2,FALSE)) -> 9 | C78: 104179 | D78: Arizona | E78: Golf
A79: 2023 | B79: =IF(ISBLANK(E79),"",VLOOKUP(E79,Code!B:C,2,FALSE)) -> 10 | C79: 104179 | D79: Arizona | E79: Gymnastics
A80: 2023 | B80: =IF(ISBLANK(E80),"",VLOOKUP(E80,Code!B:C,2,FALSE)) -> 17 | C80: 104179 | D80: Arizona | E80: Soccer
A81: 2023 | B81: =IF(ISBLANK(E81),"",VLOOKUP(E81,Code!B:C,2,FALSE)) -> 18 | C81: 104179 | D81: Arizona | E81: Softball
A82: 2023 | B82: =IF(ISBLANK(E82),"",VLOOKUP(E82,Code!B:C,2,FALSE)) -> 19 | C82: 104179 | D82: Arizona | E82: Swimming and Diving
A83: 2023 | B83: =IF(ISBLANK(E83),"",VLOOKUP(E83,Code!B:C,2,FALSE)) -> 20 | C83: 104179 | D83: Arizona | E83: Tennis
A84: 2023 | B84: =IF(ISBLANK(E84),"",VLOOKUP(E84,Code!B:C,2,FALSE)) -> 21 | C84: 104179 | D84: Arizona | E84: Track and Field, X- Country
A85: 2023 | B85: =IF(ISBLANK(E85),"",VLOOKUP(E85,Code!B:C,2,FALSE)) -> 23 | C85: 104179 | D85: Arizona | E85: Volleyball
A86: 2017 | B86: =IF(ISBLANK(E86),"",VLOOKUP(E86,Code!B:C,2,FALSE)) -> 1 | C86: 110635 | D86: California | E86: Baseball | F86: 55000
A87: 2017 | B87: =IF(ISBLANK(E87),"",VLOOKUP(E87,Code!B:C,2,FALSE)) -> 2 | C87: 110635 | D87: California | E87: Basketball | F87: 465
A88: 2017 | B88: =IF(ISBLANK(E88),"",VLOOKUP(E88,Code!B:C,2,FALSE)) -> 8 | C88: 110635 | D88: California | E88: Football | F88: 4501086
A89: 2017 | B89: =IF(ISBLANK(E89),"",VLOOKUP(E89,Code!B:C,2,FALSE)) -> 3 | C89: 110635 | D89: California | E89: Beach Volleyball
A90: 2017 | B90: =IF(ISBLANK(E90),"",VLOOKUP(E90,Code!B:C,2,FALSE)) -> 7 | C90: 110635 | D90: California | E90: Field Hockey
A91: 2017 | B91: =IF(ISBLANK(E91),"",VLOOKUP(E91,Code!B:C,2,FALSE)) -> 9 | C91: 110635 | D91: California | E91: Golf
A92: 2017 | B92: =IF(ISBLANK(E92),"",VLOOKUP(E92,Code!B:C,2,FALSE)) -> 10 | C92: 110635 | D92: California | E92: Gymnastics
A93: 2017 | B93: =IF(ISBLANK(E93),"",VLOOKUP(E93,Code!B:C,2,FALSE)) -> 12 | C93: 110635 | D93: California | E93: Lacrosse
A94: 2017 | B94: =IF(ISBLANK(E94),"",VLOOKUP(E94,Code!B:C,2,FALSE)) -> 14 | C94: 110635 | D94: California | E94: Rowing
A95: 2017 | B95: =IF(ISBLANK(E95),"",VLOOKUP(E95,Code!B:C,2,FALSE)) -> 17 | C95: 110635 | D95: California | E95: Soccer
A96: 2017 | B96: =IF(ISBLANK(E96),"",VLOOKUP(E96,Code!B:C,2,FALSE)) -> 18 | C96: 110635 | D96: California | E96: Softball | G96: 30000
A97: 2017 | B97: =IF(ISBLANK(E97),"",VLOOKUP(E97,Code!B:C,2,FALSE)) -> 19 | C97: 110635 | D97: California | E97: Swimming and Diving | F97: 24920
A98: 2017 | B98: =IF(ISBLANK(E98),"",VLOOKUP(E98,Code!B:C,2,FALSE)) -> 20 | C98: 110635 | D98: California | E98: Tennis
A99: 2017 | B99: =IF(ISBLANK(E99),"",VLOOKUP(E99,Code!B:C,2,FALSE)) -> 21 | C99: 110635 | D99: California | E99: Track and Field, X-Country
A100: 2017 | B100: =IF(ISBLANK(E100),"",VLOOKUP(E100,Code!B:C,2,FALSE)) -> 23 | C100: 110635 | D100: California | E100: Volleyball
...

Sheet Category 31
A1: FY | B1: Code | C1: unitid | D1: University | E1: Sport | F1: Mens | G1: Womens | H1: NAG
A2: 2017 | B2: =IF(ISBLANK(E2),"",VLOOKUP(E2,Code!B:C,2,FALSE)) -> 1 | C2: 104179 | D2: Arizona | E2: Baseball
A3: 2017 | B3: =IF(ISBLANK(E3),"",VLOOKUP(E3,Code!B:C,2,FALSE)) -> 3 | C3: 104179 | D3: Arizona | E3: Beach Volleyball
A4: 2017 | B4: 8 | C4: 104179 | D4: Arizona | E4: Football
A5: 2017 | B5: =IF(ISBLANK(E5),"",VLOOKUP(E5,Code!B:C,2,FALSE)) -> 9 | C5: 104179 | D5: Arizona | E5: Golf
A6: 2017 | B6: =IF(ISBLANK(E6),"",VLOOKUP(E6,Code!B:C,2,FALSE)) -> 10 | C6: 104179 | D6: Arizona | E6: Gymnastics
A7: 2017 | B7: =IF(ISBLANK(E7),"",VLOOKUP(E7,Code!B:C,2,FALSE)) -> 17 | C7: 104179 | D7: Arizona | E7: Soccer
A8: 2017 | B8: =IF(ISBLANK(E8),"",VLOOKUP(E8,Code!B:C,2,FALSE)) -> 18 | C8: 104179 | D8: Arizona | E8: Softball
A9: 2017 | B9: =IF(ISBLANK(E9),"",VLOOKUP(E9,Code!B:C,2,FALSE)) -> 19 | C9: 104179 | D9: Arizona | E9: Swimming and Diving
A10: 2017 | B10: =IF(ISBLANK(E10),"",VLOOKUP(E10,Code!B:C,2,FALSE)) -> 20 | C10: 104179 | D10: Arizona | E10: Tennis
A11: 2017 | B11: =IF(ISBLANK(E11),"",VLOOKUP(E11,Code!B:C,2,FALSE)) -> 21 | C11: 104179 | D11: Arizona | E11: Track and Field, X-Country
A12: 2017 | B12: =IF(ISBLANK(E12),"",VLOOKUP(E12,Code!B:C,2,FALSE)) -> 23 | C12: 104179 | D12: Arizona | E12: Volleyball
A13: 2018 | B13: =IF(ISBLANK(E13),"",VLOOKUP(E13,Code!B:C,2,FALSE)) -> 1 | C13: 104179 | D13: Arizona | E13: Baseball
A14: 2018 | B14: =IF(ISBLANK(E14),"",VLOOKUP(E14,Code!B:C,2,FALSE)) -> 2 | C14: 104179 | D14: Arizona | E14: Basketball
A15: 2018 | B15: =IF(ISBLANK(E15),"",VLOOKUP(E15,Code!B:C,2,FALSE)) -> 8 | C15: 104179 | D15: Arizona | E15: Football
A16: 2018 | B16: =IF(ISBLANK(E16),"",VLOOKUP(E16,Code!B:C,2,FALSE)) -> 21 | C16: 104179 | D16: Arizona | E16: Track and Field, X-Country
... A51: 2021 | B51: =IF(ISBLANK(E51),"",VLOOKUP(E51,Code!B:C,2,FALSE)) -> 8 | C51: 104179 | D51: Arizona | E51: Football
A52: 2021 | B52: 3 | C52: 104179 | D52: Arizona | E52: Beach Volleyball
A53: 2021 | B53: 9 | C53: 104179 | D53: Arizona | E53: Golf
A54: 2021 | B54: =IF(ISBLANK(E54),"",VLOOKUP(E54,Code!B:C,2,FALSE)) -> 10 | C54: 104179 | D54: Arizona | E54: Gymnastics
A55: 2021 | B55: =IF(ISBLANK(E55),"",VLOOKUP(E55,Code!B:C,2,FALSE)) -> 17 | C55: 104179 | D55: Arizona | E55: Soccer
A56: 2021 | B56: =IF(ISBLANK(E56),"",VLOOKUP(E56,Code!B:C,2,FALSE)) -> 18 | C56: 104179 | D56: Arizona | E56: Softball
A57: 2021 | B57: 19 | C57: 104179 | D57: Arizona | E57: Swimming and diving
A58: 2021 | B58: =IF(ISBLANK(E58),"",VLOOKUP(E58,Code!B:C,2,FALSE)) -> 20 | C58: 104179 | D58: Arizona | E58: Tennis
A59: 2021 | B59: 21 | C59: 104179 | D59: Arizona | E59: Track and Field , X country
A60: 2021 | B60: =IF(ISBLANK(E60),"",VLOOKUP(E60,Code!B:C,2,FALSE)) -> 23 | C60: 104179 | D60: Arizona | E60: Volleyball
A61: 2022 | B61: =IF(ISBLANK(E61),"",VLOOKUP(E61,Code!B:C,2,FALSE)) -> 1 | C61: 104179 | D61: Arizona | E61: Baseball
A62: 2022 | B62: =IF(ISBLANK(E62),"",VLOOKUP(E62,Code!B:C,2,FALSE)) -> 2 | C62: 104179 | D62: Arizona | E62: Basketball
A63: 2022 | B63: =IF(ISBLANK(E63),"",VLOOKUP(E63,Code!B:C,2,FALSE)) -> 8 | C63: 104179 | D63: Arizona | E63: Football
A64: 2022 | B64: =IF(ISBLANK(E64),"",VLOOKUP(E64,Code!B:C,2,FALSE)) -> 3 | C64: 104179 | D64: Arizona | E64: Beach Volleyball
A65: 2022 | B65: =IF(ISBLANK(E65),"",VLOOKUP(E65,Code!B:C,2,FALSE)) -> 9 | C65: 104179 | D65: Arizona | E65: Golf
A66: 2022 | B66: =IF(ISBLANK(E66),"",VLOOKUP(E66,Code!B:C,2,FALSE)) -> 10 | C66: 104179 | D66: Arizona | E66: Gymnastics
A67: 2022 | B67: =IF(ISBLANK(E67),"",VLOOKUP(E67,Code!B:C,2,FALSE)) -> 17 | C67: 104179 | D67: Arizona | E67: Soccer
A68: 2022 | B68: =IF(ISBLANK(E68),"",VLOOKUP(E68,Code!B:C,2,FALSE)) -> 18 | C68: 104179 | D68: Arizona | E68: Softball
A69: 2022 | B69: =IF(ISBLANK(E69),"",VLOOKUP(E69,Code!B:C,2,FALSE)) -> 19 | C69: 104179 | D69: Arizona | E69: Swimming and Diving
A70: 2022 | B70: =IF(ISBLANK(E70),"",VLOOKUP(E70,Code!B:C,2,FALSE)) -> 20 | C70: 104179 | D70: Arizona | E70: Tennis
A71: 2022 | B71: =IF(ISBLANK(E71),"",VLOOKUP(E71,Code!B:C,2,FALSE)) -> 21 | C71: 104179 | D71: Arizona | E71: Track and Field, X-Country
... A84: 2023 | B84: =IF(ISBLANK(E84),"",VLOOKUP(E84,Code!B:C,2,FALSE)) -> 23 | C84: 104179 | D84: Arizona | E84: Volleyball
A85: 2017 | B85: =IF(ISBLANK(E85),"",VLOOKUP(E85,Code!B:C,2,FALSE)) -> 1 | C85: 110635 | D85: California | E85: Baseball | F85: 10253
A86: 2017 | B86: =IF(ISBLANK(E86),"",VLOOKUP(E86,Code!B:C,2,FALSE)) -> 2 | C86: 110635 | D86: California | E86: Basketball | F86: 368417 | G86: 101742
A87: 2017 | B87: =IF(ISBLANK(E87),"",VLOOKUP(E87,Code!B:C,2,FALSE)) -> 8 | C87: 110635 | D87: California | E87: Football | F87: 924701
A88: 2017 | B88: =IF(ISBLANK(E88),"",VLOOKUP(E88,Code!B:C,2,FALSE)) -> 3 | C88: 110635 | D88: California | E88: Beach Volleyball | G88: 1735
A89: 2017 | B89: =IF(ISBLANK(E89),"",VLOOKUP(E89,Code!B:C,2,FALSE)) -> 7 | C89: 110635 | D89: California | E89: Field Hockey | G89: 9448
A90: 2017 | B90: =IF(ISBLANK(E90),"",VLOOKUP(E90,Code!B:C,2,FALSE)) -> 9 | C90: 110635 | D90: California | E90: Golf | F90: 84044 | G90: 6661
A91: 2017 | B91: =IF(ISBLANK(E91),"",VLOOKUP(E91,Code!B:C,2,FALSE)) -> 10 | C91: 110635 | D91: California | E91: Gymnastics | F91: 2419 | G91: 4814
A92: 2017 | B92: =IF(ISBLANK(E92),"",VLOOKUP(E92,Code!B:C,2,FALSE)) -> 12 | C92: 110635 | D92: California | E92: Lacrosse | G92: 2364
A93: 2017 | B93: =IF(ISBLANK(E93),"",VLOOKUP(E93,Code!B:C,2,FALSE)) -> 14 | C93: 110635 | D93: California | E93: Rowing | G93: 12452
A94: 2017 | B94: =IF(ISBLANK(E94),"",VLOOKUP(E94,Code!B:C,2,FALSE)) -> 17 | C94: 110635 | D94: California | E94: Soccer | F94: 14360 | G94: 16976
A95: 2017 | B95: =IF(ISBLANK(E95),"",VLOOKUP(E95,Code!B:C,2,FALSE)) -> 18 | C95: 110635 | D95: California | E95: Softball | G95: 8643
A96: 2017 | B96: =IF(ISBLANK(E96),"",VLOOKUP(E96,Code!B:C,2,FALSE)) -> 19 | C96: 110635 | D96: California | E96: Swimming and Diving | F96: 26761 | G96: 24725
A97: 2017 | B97: =IF(ISBLANK(E97),"",VLOOKUP(E97,Code!B:C,2,FALSE)) -> 20 | C97: 110635 | D97: California | E97: Tennis | F97: 13666 | G97: 10364
A98: 2017 | B98: =IF(ISBLANK(E98),"",VLOOKUP(E98,Code!B:C,2,FALSE)) -> 21 | C98: 110635 | D98: California | E98: Track and Field, X-Country | F98: 3093 | G98: 3183
A99: 2017 | B99: =IF(ISBLANK(E99),"",VLOOKUP(E99,Code!B:C,2,FALSE)) -> 23 | C99: 110635 | D99: California | E99: Volleyball | G99: 18691
A100: 2017 | B100: =IF(ISBLANK(E100),"",VLOOKUP(E100,Code!B:C,2,FALSE)) -> 24 | C100: 110635 | D100: California | E100: Water Polo | F100: 19151 | G100: 16268
A101: 2018 | B101: =IF(ISBLANK(E101),"",VLOOKUP(E101,Code!B:C,2,FALSE)) -> 1 | C101: 110635 | D101: California | E101: Baseball | F101: 9036
A102: 2018 | B102: =IF(ISBLANK(E102),"",VLOOKUP(E102,Code!B:C,2,FALSE)) -> 2 | C102: 110635 | D102: California | E102: Basketball | F102: 253154 | G102: 54470
A103: 2018 | B103: =IF(ISBLANK(E103),"",VLOOKUP(E103,Code!B:C,2,FALSE)) -> 8 | C103: 110635 | D103: California | E103: Football | F103: 896192
A104: 2018 | B104: =IF(ISBLANK(E104),"",VLOOKUP(E104,Code!B:C,2,FALSE)) -> 10 | C104: 110635 | D104: California | E104: Gymnastics | F104: 1827 | G104: 1864
A105: 2018 | B105: =IF(ISBLANK(E105),"",VLOOKUP(E105,Code!B:C,2,FALSE)) -> 3 | C105: 110635 | D105: California | E105: Beach Volleyball | G105: 5756
A106: 2018 | B106: =IF(ISBLANK(E106),"",VLOOKUP(E106,Code!B:C,2,FALSE)) -> 7 | C106: 110635 | D106: California | E106: Field Hockey | G106: 10539
A107: 2018 | B107: =IF(ISBLANK(E107),"",VLOOKUP(E107,Code!B:C,2,FALSE)) -> 9 | C107: 110635 | D107: California | E107: Golf | F107: 118733 | G107: 13441
A108: 2018 | B108: =IF(ISBLANK(E108),"",VLOOKUP(E108,Code!B:C,2,FALSE)) -> 12 | C108: 110635 | D108: California | E108: Lacrosse | G108: 11881
A109: 2018 | B109: =IF(ISBLANK(E109),"",VLOOKUP(E109,Code!B:C,2,FALSE)) -> 14 | C109: 110635 | D109: California | E109: Rowing | G109: 8032
A110: 2018 | B110: =IF(ISBLANK(E110),"",VLOOKUP(E110,Code!B:C,2,FALSE)) -> 17 | C110: 110635 | D110: California | E110: Soccer | F110: 12020 | G110: 9093
A111: 2018 | B111: =IF(ISBLANK(E111),"",VLOOKUP(E111,Code!B:C,2,FALSE)) -> 18 | C111: 110635 | D111: California | E111: Softball | G111: 14459
A112: 2018 | B112: =IF(ISBLANK(E112),"",VLOOKUP(E112,Code!B:C,2,FALSE)) -> 19 | C112: 110635 | D112: California | E112: Swimming and Diving | F112: 12770 | G112: 16581
A113: 2018 | B113: =IF(ISBLANK(E113),"",VLOOKUP(E113,Code!B:C,2,FALSE)) -> 20 | C113: 110635 | D113: California | E113: Tennis | F113: 10206 | G113: 3390
A114: 2018 | B114: =IF(ISBLANK(E114),"",VLOOKUP(E114,Code!B:C,2,FALSE)) -> 21 | C114: 110635 | D114: California | E114: Track and Field, X-Country | F114: 3692 | G114: 3692
A115: 2018 | B115: =IF(ISBLANK(E115),"",VLOOKUP(E115,Code!B:C,2,FALSE)) -> 23 | C115: 110635 | D115: California | E115: Volleyball | G115: 9334
A116: 2018 | B116: =IF(ISBLANK(E116),"",VLOOKUP(E116,Code!B:C,2,FALSE)) -> 24 | C116: 110635 | D116: California | E116: Water Polo | F116: 5216 | G116: 3919
A117: 2019 | B117: =IF(ISBLANK(E117),"",VLOOKUP(E117,Code!B:C,2,FALSE)) -> 1 | C117: 110635 | D117: California | E117: Baseball | F117: 7440
A118: 2019 | B118: =IF(ISBLANK(E118),"",VLOOKUP(E118,Code!B:C,2,FALSE)) -> 2 | C118: 110635 | D118: California | E118: Basketball | F118: 160129 | G118: 82801
A119: 2019 | B119: =IF(ISBLANK(E119),"",VLOOKUP(E119,Code!B:C,2,FALSE)) -> 8 | C119: 110635 | D119: California | E119: Football | F119: 973548
A120: 2019 | B120: =IF(ISBLANK(E120),"",VLOOKUP(E120,Code!B:C,2,FALSE)) -> 3 | C120: 110635 | D120: California | E120: Beach Volleyball | G120: 2118
A121: 2019 | B121: =IF(ISBLANK(E121),"",VLOOKUP(E121,Code!B:C,2,FALSE)) -> 7 | C121: 110635 | D121: California | E121: Field Hockey | G121: 8261
A122: 2019 | B122: =IF(ISBLANK(E122),"",VLOOKUP(E122,Code!B:C,2,FALSE)) -> 9 | C122: 110635 | D122: California | E122: Golf | F122: 83627 | G122: 7919
A123: 2019 | B123: =IF(ISBLANK(E123),"",VLOOKUP(E123,Code!B:C,2,FALSE)) -> 10 | C123: 110635 | D123: California | E123: Gymnastics | F123: 5602 | G123: 40391
A124: 2019 | B124: =IF(ISBLANK(E124),"",VLOOKUP(E124,Code!B:C,2,FALSE)) -> 12 | C124: 110635 | D124: California | E124: Lacrosse | G124: 13034
A125: 2019 | B125: =IF(ISBLANK(E125),"",VLOOKUP(E125,Code!B:C,2,FALSE)) -> 14 | C125: 110635 | D125: California | E125: Rowing | G125: 5914
A126: 2019 | B126: =IF(ISBLANK(E126),"",VLOOKUP(E126,Code!B:C,2,FALSE)) -> 17 | C126: 110635 | D126: California | E126: Soccer | F126: 26627 | G126: 4327
A127: 2019 | B127: =IF(ISBLANK(E127),"",VLOOKUP(E127,Code!B:C,2,FALSE)) -> 18 | C127: 110635 | D127: California | E127: Softball | G127: 18746
A128: 2019 | B128: =IF(ISBLANK(E128),"",VLOOKUP(E128,Code!B:C,2,FALSE)) -> 19 | C128: 110635 | D128: California | E128: Swimming and Diving | F128: 120970 | G128: 11789
A129: 2019 | B129: =IF(ISBLANK(E129),"",VLOOKUP(E129,Code!B:C,2,FALSE)) -> 20 | C129: 110635 | D129: California | E129: Tennis | F129: 30702 | G129: 2510
A130: 2019 | B130: =IF(ISBLANK(E130),"",VLOOKUP(E130,Code!B:C,2,FALSE)) -> 21 | C130: 110635 | D130: California | E130: Track and Field, X-Country | F130: 4995 | G130: 4995
A131: 2019 | B131: =IF(ISBLANK(E131),"",VLOOKUP(E131,Code!B:C,2,FALSE)) -> 23 | C131: 110635 | D131: California | E131: Volleyball | G131: 15549
A132: 2019 | B132: =IF(ISBLANK(E132),"",VLOOKUP(E132,Code!B:C,2,FALSE)) -> 24 | C132: 110635 | D132: California | E132: Water Polo | F132: 5250 | G132: 4212
A133: 2020 | B133: =IF(ISBLANK(E133),"",VLOOKUP(E133,Code!B:C,2,FALSE)) -> 1 | C133: 110635 | D133: California | E133: Baseball | F133: 5990
A134: 2020 | B134: =IF(ISBLANK(E134),"",VLOOKUP(E134,Code!B:C,2,FALSE)) -> 2 | C134: 110635 | D134: California | E134: Basketball | F134: 122682 | G134: 44667
A135: 2020 | B135: =IF(ISBLANK(E135),"",VLOOKUP(E135,Code!B:C,2,FALSE)) -> 8 | C135: 110635 | D135: California | E135: Football | F135: 752901
A136: 2020 | B136: =IF(ISBLANK(E136),"",VLOOKUP(E136,Code!B:C,2,FALSE)) -> 10 | C136: 110635 | D136: California | E136: Gymnastics | F136: 3859 | G136: 24600
A137: 2020 | B137: =IF(ISBLANK(E137),"",VLOOKUP(E137,Code!B:C,2,FALSE)) -> 3 | C137: 110635 | D137: California | E137: Beach Volleyball | G137: 1481
A138: 2020 | B138: =IF(ISBLANK(E138),"",VLOOKUP(E138,Code!B:C,2,FALSE)) -> 7 | C138: 110635 | D138: California | E138: Field Hockey | G138: 7240
A139: 2020 | B139: =IF(ISBLANK(E139),"",VLOOKUP(E139,Code!B:C,2,FALSE)) -> 9 | C139: 110635 | D139: California | E139: Golf | F139: 68775 | G139: 6620
A140: 2020 | B140: =IF(ISBLANK(E140),"",VLOOKUP(E140,Code!B:C,2,FALSE)) -> 12 | C140: 110635 | D140: California | E140: Lacrosse | G140: 17333
A141: 2020 | B141: =IF(ISBLANK(E141),"",VLOOKUP(E141,Code!B:C,2,FALSE)) -> 14 | C141: 110635 | D141: California | E141: Rowing | G141: 1204
A142: 2020 | B142: =IF(ISBLANK(E142),"",VLOOKUP(E142,Code!B:C,2,FALSE)) -> 17 | C142: 110635 | D142: California | E142: Soccer | F142: 11076 | G142: 5749
A143: 2020 | B143: =IF(ISBLANK(E143),"",VLOOKUP(E143,Code!B:C,2,FALSE)) -> 18 | C143: 110635 | D143: California | E143: Softball | G143: 1810
A144: 2020 | B144: =IF(ISBLANK(E144),"",VLOOKUP(E144,Code!B:C,2,FALSE)) -> 19 | C144: 110635 | D144: California | E144: Swimming and Diving | F144: 42179 | G144: 5973
A145: 2020 | B145: =IF(ISBLANK(E145),"",VLOOKUP(E145,Code!B:C,2,FALSE)) -> 20 | C145: 110635 | D145: California | E145: Tennis | F145: 18021
A146: 2020 | B146: =IF(ISBLANK(E146),"",VLOOKUP(E146,Code!B:C,2,FALSE)) -> 21 | C146: 110635 | D146: California | E146: Track and Field, X-Country | F146: 1566 | G146: 2253
...

Sheet Code
A1: Sport Code | B1: Sport | C1: Sport Code
A2: 1 | B2: Baseball | C2: 1
A3: 2 | B3: Basketball | C3: 2
A4: 3 | B4: Beach Volleyball | C4: 3
A5: 4 | B5: Bowling | C5: 4
A6: 5 | B6: Equestrian | C6: 5
A7: 6 | B7: Fencing | C7: 6
A8: 7 | B8: Field Hockey | C8: 7
A9: 8 | B9: Football | C9: 8
A10: 9 | B10: Golf | C10: 9
A11: 10 | B11: Gymnastics | C11: 10
A12: 11 | B12: Ice Hockey | C12: 11
A13: 12 | B13: Lacrosse | C13: 12
... A40: 71 | B40: Unduplicated Count of Participants | C40: 71

Sheet unitid
A1: unitid | B1: Univeristy | C1: unitid
A2: 500002 | B2: Air Force | C2: 500002
A3: 200800 | B3: Akron | C3: 200800
A4: 100751 | B4: Alabama | C4: 100751
A5: 100724 | B5: Alabama State | C5: 100724
A6: 196060 | B6: Albany | C6: 196060
A7: 175342 | B7: Alcorn State | C7: 175342
A8: 197869 | B8: Appalachian State | C8: 197869
A9: 104179 | B9: Arizona | C9: 104179
A10: 104151 | B10: Arizona State | C10: 104151
A11: 106397 | B11: Arkansas | C11: 106397
A12: 106245 | B12: Arkansas Little Rock | C12: 106245
A13: 106412 | B13: Arkansas Pine Bluff | C13: 106412
... A224: 206695 | B224: Youngstown State | C224: 206695

Sheet CPI
A1: Consumer Price Index for All Urban Consumers (CPI-U)
A2: Original Data Value
A4: Series Id: | B4: CUUR0000SA0
A5: Not Seasonally Adjusted
A6: Series Title: | B6: All items in U.S. city average, all urban consumers, not seasonally adjusted
A7: Area: | B7: U.S. city average
A8: Item: | B8: All items
A9: Base Period: | B9: 1982-84=100
A10: Years: | B10: 2014 to 2024
A12: Year | B12: Jan | C12: Feb | D12: Mar | E12: Apr | F12: May | G12: Jun | H12: Jul | I12: Aug | J12: Sep | K12: Oct | L12: Nov | M12: Dec | N12: HALF1 | O12: HALF2
A13: 2014 | B13: 233.916 | C13: 234.781 | D13: 236.293 | E13: 237.072 | F13: 237.9 | G13: 238.343 | H13: 238.25 | I13: 237.852 | J13: 238.031 | K13: 237.433 | L13: 236.151 | M13: 234.812 | N13: 236.384 | O13: 237.088
A14: 2015 | B14: 233.707 | C14: 234.722 | D14: 236.119 | E14: 236.599 | F14: 237.805 | G14: 238.638 | H14: 238.654 | I14: 238.316 | J14: 237.945 | K14: 237.838 | L14: 237.336 | M14: 236.525 | N14: 236.265 | O14: 237.769
A15: 2016 | B15: 236.916 | C15: 237.111 | D15: 238.132 | E15: 239.261 | F15: 240.229 | G15: 241.018 | H15: 240.628 | I15: 240.849 | J15: 241.428 | K15: 241.729 | L15: 241.353 | M15: 241.432 | N15: 238.778 | O15: 241.237
A16: 2017 | B16: 242.839 | C16: 243.603 | D16: 243.801 | E16: 244.524 | F16: 244.733 | G16: 244.955 | H16: 244.786 | I16: 245.519 | J16: 246.819 | K16: 246.663 | L16: 246.669 | M16: 246.524 | N16: 244.076 | O16: 246.163 | P16: 2017 | Q16: =AVERAGE(N16,O15) -> 242.6565 | R16: =Q16/Q$22 -> 0.80970384
A17: 2018 | B17: 247.867 | C17: 248.991 | D17: 249.554 | E17: 250.546 | F17: 251.588 | G17: 251.989 | H17: 252.006 | I17: 252.146 | J17: 252.439 | K17: 252.885 | L17: 252.038 | M17: 251.233 | N17: 250.089 | O17: 252.125 | P17: =P16+1 -> 2018 | Q17: =AVERAGE(N17,O16) -> 248.126 | R17: =Q17/Q$22 -> 0.82795464
A18: 2019 | B18: 251.712 | C18: 252.776 | D18: 254.202 | E18: 255.548 | F18: 256.092 | G18: 256.143 | H18: 256.571 | I18: 256.558 | J18: 256.759 | K18: 257.346 | L18: 257.208 | M18: 256.974 | N18: 254.412 | O18: 256.903 | P18: =P17+1 -> 2019 | Q18: =AVERAGE(N18,O17) -> 253.2685 | R18: =Q18/Q$22 -> 0.84511429
A19: 2020 | B19: 257.971 | C19: 258.678 | D19: 258.115 | E19: 256.389 | F19: 256.394 | G19: 257.797 | H19: 259.101 | I19: 259.918 | J19: 260.28 | K19: 260.388 | L19: 260.229 | M19: 260.474 | N19: 257.557 | O19: 260.065 | P19: =P18+1 -> 2020 | Q19: =AVERAGE(N19,O18) -> 257.23 | R19: =Q19/Q$22 -> 0.85833315
A20: 2021 | B20: 261.582 | C20: 263.014 | D20: 264.877 | E20: 267.054 | F20: 269.195 | G20: 271.696 | H20: 273.003 | I20: 273.567 | J20: 274.31 | K20: 276.589 | L20: 277.948 | M20: 278.802 | N20: 266.236 | O20: 275.703 | P20: =P19+1 -> 2021 | Q20: =AVERAGE(N20,O19) -> 263.1505 | R20: =Q20/Q$22 -> 0.87808886
A21: 2022 | B21: 281.148 | C21: 283.716 | D21: 287.504 | E21: 289.109 | F21: 292.296 | G21: 296.311 | H21: 296.276 | I21: 296.171 | J21: 296.808 | K21: 298.012 | L21: 297.711 | M21: 296.797 | N21: 288.347 | O21: 296.963 | P21: =P20+1 -> 2022 | Q21: =AVERAGE(N21,O20) -> 282.025 | R21: =Q21/Q$22 -> 0.94106989
A22: 2023 | B22: 299.17 | C22: 300.84 | D22: 301.836 | E22: 303.363 | F22: 304.127 | G22: 305.109 | H22: 305.691 | I22: 307.026 | J22: 307.789 | K22: 307.671 | L22: 307.051 | M22: 306.746 | N22: 302.408 | O22: 306.996 | P22: =P21+1 -> 2023 | Q22: =AVERAGE(N22,O21) -> 299.6855 | R22: =Q22/Q$22 -> 1
A23: 2024 | B23: 308.417 | C23: 310.326 | D23: 312.332 | E23: 313.548 | F23: 314.069 | G23: 314.175 | H23: 314.54 | I23: 314.796 | J23: 315.301 | N23: 312.145

Sheet Total
A1: unitid | B1: GeoFips | C1: University | D1: panel | E1: 2014 | F1: 2015 | G1: 2016 | H1: 2017 | I1: 2018 | J1: 2019 | K1: 2020 | L1: 2021 | M1: 2022 | N1: 2023 | O1: 2024
A2: 200800 | B2: 10420 | C2: Akron | D2: 1 | E2: =IFERROR(VLOOKUP($A2,MBaseball!$C:$N,E$1-2010,FALSE),0)+IFERROR(VLOOKUP($A2,MBasketball!$C:$J,E$1-2006,FALSE),0)+IFERROR(VLOOKUP($A2,MFootball!$C:$O,E$1-2011,FALSE),0)+IFERROR(VLOOKUP($A2,MIceHockey!$C:$P,E$1-2011,FALSE),0)+IFERROR(VLOOKUP($A2,MLacrosse!$C:$O,E$1-2011,FALSE),0)+IFERROR(VLOOKUP($A2,MSoccer!$C:$O,E$1-2011,FALSE),0)+IFERROR(VLOOKUP($A2,MVolleyball!$C:$O,E$1-2011,FALSE),0)+IFERROR(VLOOKUP($A2,WBasketball!$C:$O,E$1-2011,FALSE),0)+IFERROR(VLOOKUP($A2,WFieldHockey!$C:$O,E$1-2011,FALSE),0)+IFERROR(VLOOKUP($A2,WIceHockey!$C:$O,E$1-2011,FALSE),0)+IFERROR(VLOOKUP($A2,WLacrosse!$C:$O,E$1-2011,FALSE),0)+IFERROR(VLOOKUP($A2,WSoccer!$C:$O,E$1-2011,FALSE),0)+IFERROR(VLOOKUP($A2,WSoftball!$C:$O,E$1-2011,FALSE),0)+IFERROR(VLOOKUP($A2,WVolleyball!$C:$O,E$1-2011,FALSE),0) -> 89199 | F2: =IFERROR(VLOOKUP($A2,MBaseball!$C:$N,F$1-2010,FALSE),0)+IFERROR(VLOOKUP($A2,MBasketball!$C:$J,F$1-2006,FALSE),0)+IFERROR(VLOOKUP($A2,MFootball!$C:$O,F$1-2011,FALSE),0)+IFERROR(VLOOKUP($A2,MIceHockey!$C:$P,F$1-2011,FALSE),0)+IFERROR(VLOOKUP($A2,MLacrosse!$C:$O,F$1-2011,FALSE),0)+IFERROR(VLOOKUP($A2,MSoccer!$C:$O,F$1-2011,FALSE),0)+IFERROR(VLOOKUP($A2,MVolleyball!$C:$O,F$1-2011,FALSE),0)+IFERROR(VLOOKUP($A2,WBasketball!$C:$O,F$1-2011,FALSE),0)+IFERROR(VLOOKUP($A2,WFieldHockey!$C:$O,F$1-2011,FALSE),0)+IFERROR(VLOOKUP($A2,WIceHockey!$C:$O,F$1-2011,FALSE),0)+IFERROR(VLOOKUP($A2,WLacrosse!$C:$O,F$1-2011,FALSE),0)+IFERROR(VLOOKUP($A2,WSoccer!$C:$O,F$1-2011,FALSE),0)+IFERROR(VLOOKUP($A2,WSoftball!$C:$O,F$1-2011,FALSE),0)+IFERROR(VLOOKUP($A2,WVolleyball!$C:$O,F$1-2011,FALSE),0) -> 93700 | G2: =IFERROR(VLOOKUP($A2,MBaseball!$C:$N,G$1-2010,FALSE),0)+IFERROR(VLOOKUP($A2,MBasketball!$C:$J,G$1-2006,FALSE),0)+IFERROR(VLOOKUP($A2,MFootball!$C:$O,G$1-2011,FALSE),0)+IFERROR(VLOOKUP($A2,MIceHockey!$C:$P,G$1-2011,FALSE),0)+IFERROR(VLOOKUP($A2,MLacrosse!$C:$O,G$1-2011,FALSE),0)+IFERROR(VLOOKUP($A2,MSoccer!$C:$O,G$1-2011,FALSE),0)+IFERROR(VLOOKUP($A2,MVolleyball!$C:$O,G$1-2011,FALSE),0)+IFERROR(VLOOKUP($A2,WBasketball!$C:$O,G$1-2011,FALSE),0)+IFERROR(VLOOKUP($A2,WFieldHockey!$C:$O,G$1-2011,FALSE),0)+IFERROR(VLOOKUP($A2,WIceHockey!$C:$O,G$1-2011,FALSE),0)+IFERROR(VLOOKUP($A2,WLacrosse!$C:$O,G$1-2011,FALSE),0)+IFERROR(VLOOKUP($A2,WSoccer!$C:$O,G$1-2011,FALSE),0)+IFERROR(VLOOKUP($A2,WSoftball!$C:$O,G$1-2011,FALSE),0)+IFERROR(VLOOKUP($A2,WVolleyball!$C:$O,G$1-2011,FALSE),0) -> 164186 | H2: =IFERROR(VLOOKUP($A2,MBaseball!$C:$N,H$1-2010,FALSE),0)+IFERROR(VLOOKUP($A2,MBasketball!$C:$J,H$1-2006,FALSE),0)+IFERROR(VLOOKUP($A2,MFootball!$C:$O,H$1-2011,FALSE),0)+IFERROR(VLOOKUP($A2,MIceHockey!$C:$P,H$1-2011,FALSE),0)+IFERROR(VLOOKUP($A2,MLacrosse!$C:$O,H$1-2011,FALSE),0)+IFERROR(VLOOKUP($A2,MSoccer!$C:$O,H$1-2011,FALSE),0)+IFERROR(VLOOKUP($A2,MVolleyball!$C:$O,H$1-2011,FALSE),0)+IFERROR(VLOOKUP($A2,WBasketball!$C:$O,H$1-2011,FALSE),0)+IFERROR(VLOOKUP($A2,WFieldHockey!$C:$O,H$1-2011,FALSE),0)+IFERROR(VLOOKUP($A2,WIceHockey!$C:$O,H$1-2011,FALSE),0)+IFERROR(VLOOKUP($A2,WLacrosse!$C:$O,H$1-2011,FALSE),0)+IFERROR(VLOOKUP($A2,WSoccer!$C:$O,H$1-2011,FALSE),0)+IFERROR(VLOOKUP($A2,WSoftball!$C:$O,H$1-2011,FALSE),0)+IFERROR(VLOOKUP($A2,WVolleyball!$C:$O,H$1-2011,FALSE),0) -> 108854 | I2: =IFERROR(VLOOKUP($A2,MBaseball!$C:$N,I$1-2010,FALSE),0)+IFERROR(VLOOKUP($A2,MBasketball!$C:$J,I$1-2006,FALSE),0)+IFERROR(VLOOKUP($A2,MFootball!$C:$O,I$1-2011,FALSE),0)+IFERROR(VLOOKUP($A2,MIceHockey!$C:$P,I$1-2011,FALSE),0)+IFERROR(VLOOKUP($A2,MLacrosse!$C:$O,I$1-2011,FALSE),0)+IFERROR(VLOOKUP($A2,MSoccer!$C:$O,I$1-2011,FALSE),0)+IFERROR(VLOOKUP($A2,MVolleyball!$C:$O,I$1-2011,FALSE),0)+IFERROR(VLOOKUP($A2,WBasketball!$C:$O,I$1-2011,FALSE),0)+IFERROR(VLOOKUP($A2,WFieldHockey!$C:$O,I$1-2011,FALSE),0)+IFERROR(VLOOKUP($A2,WIceHockey!$C:$O,I$1-2011,FALSE),0)+IFERROR(VLOOKUP($A2,WLacrosse!$C:$O,I$1-2011,FALSE),0)+IFERROR(VLOOKUP($A2,WSoccer!$C:$O,I$1-2011,FALSE),0)+IFERROR(VLOOKUP($A2,WSoftball!$C:$O,I$1-2011,FALSE),0)+IFERROR(VLOOKUP($A2,WVolleyball!$C:$O,I$1-2011,FALSE),0) -> 159073 | J2: =IFERROR(VLOOKUP($A2,MBaseball!$C:$N,J$1-2010,FALSE),0)+IFERROR(VLOOKUP($A2,MBasketball!$C:$J,J$1-2006,FALSE),0)+IFERROR(VLOOKUP($A2,MFootball!$C:$O,J$1-2011,FALSE),0)+IFERROR(VLOOKUP($A2,MIceHockey!$C:$P,J$1-2011,FALSE),0)+IFERROR(VLOOKUP($A2,MLacrosse!$C:$O,J$1-2011,FALSE),0)+IFERROR(VLOOKUP($A2,MSoccer!$C:$O,J$1-2011,FALSE),0)+IFERROR(VLOOKUP($A2,MVolleyball!$C:$O,J$1-2011,FALSE),0)+IFERROR(VLOOKUP($A2,WBasketball!$C:$O,J$1-2011,FALSE),0)+IFERROR(VLOOKUP($A2,WFieldHockey!$C:$O,J$1-2011,FALSE),0)+IFERROR(VLOOKUP($A2,WIceHockey!$C:$O,J$1-2011,FALSE),0)+IFERROR(VLOOKUP($A2,WLacrosse!$C:$O,J$1-2011,FALSE),0)+IFERROR(VLOOKUP($A2,WSoccer!$C:$O,J$1-2011,FALSE),0)+IFERROR(VLOOKUP($A2,WSoftball!$C:$O,J$1-2011,FALSE),0)+IFERROR(VLOOKUP($A2,WVolleyball!$C:$O,J$1-2011,FALSE),0) -> 124475 | K2: =IFERROR(VLOOKUP($A2,MBaseball!$C:$N,K$1-2010,FALSE),0)+IFERROR(VLOOKUP($A2,MBasketball!$C:$J,K$1-2006,FALSE),0)+IFERROR(VLOOKUP($A2,MFootball!$C:$O,K$1-2011,FALSE),0)+IFERROR(VLOOKUP($A2,MIceHockey!$C:$P,K$1-2011,FALSE),0)+IFERROR(VLOOKUP($A2,MLacrosse!$C:$O,K$1-2011,FALSE),0)+IFERROR(VLOOKUP($A2,MSoccer!$C:$O,K$1-2011,FALSE),0)+IFERROR(VLOOKUP($A2,MVolleyball!$C:$O,K$1-2011,FALSE),0)+IFERROR(VLOOKUP($A2,WBasketball!$C:$O,K$1-2011,FALSE),0)+IFERROR(VLOOKUP($A2,WFieldHockey!$C:$O,K$1-2011,FALSE),0)+IFERROR(VLOOKUP($A2,WIceHockey!$C:$O,K$1-2011,FALSE),0)+IFERROR(VLOOKUP($A2,WLacrosse!$C:$O,K$1-2011,FALSE),0)+IFERROR(VLOOKUP($A2,WSoccer!$C:$O,K$1-2011,FALSE),0)+IFERROR(VLOOKUP($A2,WSoftball!$C:$O,K$1-2011,FALSE),0)+IFERROR(VLOOKUP($A2,WVolleyball!$C:$O,K$1-2011,FALSE),0) -> 130999 | L2: =IFERROR(VLOOKUP($A2,MBaseball!$C:$N,L$1-2010,FALSE),0)+IFERROR(VLOOKUP($A2,MBasketball!$C:$J,L$1-2006,FALSE),0)+IFERROR(VLOOKUP($A2,MFootball!$C:$O,L$1-2011,FALSE),0)+IFERROR(VLOOKUP($A2,MIceHockey!$C:$P,L$1-2011,FALSE),0)+IFERROR(VLOOKUP($A2,MLacrosse!$C:$O,L$1-2011,FALSE),0)+IFERROR(VLOOKUP($A2,MSoccer!$C:$O,L$1-2011,FALSE),0)+IFERROR(VLOOKUP($A2,MVolleyball!$C:$O,L$1-2011,FALSE),0)+IFERROR(VLOOKUP($A2,WBasketball!$C:$O,L$1-2011,FALSE),0)+IFERROR(VLOOKUP($A2,WFieldHockey!$C:$O,L$1-2011,FALSE),0)+IFERROR(VLOOKUP($A2,WIceHockey!$C:$O,L$1-2011,FALSE),0)+IFERROR(VLOOKUP($A2,WLacrosse!$C:$O,L$1-2011,FALSE),0)+IFERROR(VLOOKUP($A2,WSoccer!$C:$O,L$1-2011,FALSE),0)+IFERROR(VLOOKUP($A2,WSoftball!$C:$O,L$1-2011,FALSE),0)+IFERROR(VLOOKUP($A2,WVolleyball!$C:$O,L$1-2011,FALSE),0) -> 8344 | ... N2: =IFERROR(VLOOKUP($A2,MBaseball!$C:$N,N$1-2010,FALSE),0)+IFERROR(VLOOKUP($A2,MBasketball!$C:$J,N$1-2006,FALSE),0)+IFERROR(VLOOKUP($A2,MFootball!$C:$O,N$1-2011,FALSE),0)+IFERROR(VLOOKUP($A2,MIceHockey!$C:$P,N$1-2011,FALSE),0)+IFERROR(VLOOKUP($A2,MLacrosse!$C:$O,N$1-2011,FALSE),0)+IFERROR(VLOOKUP($A2,MSoccer!$C:$O,N$1-2011,FALSE),0)+IFERROR(VLOOKUP($A2,MVolleyball!$C:$O,N$1-2011,FALSE),0)+IFERROR(VLOOKUP($A2,WBasketball!$C:$O,N$1-2011,FALSE),0)+IFERROR(VLOOKUP($A2,WFieldHockey!$C:$O,N$1-2011,FALSE),0)+IFERROR(VLOOKUP($A2,WIceHockey!$C:$O,N$1-2011,FALSE),0)+IFERROR(VLOOKUP($A2,WLacrosse!$C:$O,N$1-2011,FALSE),0)+IFERROR(VLOOKUP($A2,WSoccer!$C:$O,N$1-2011,FALSE),0)+IFERROR(VLOOKUP($A2,WSoftball!$C:$O,N$1-2011,FALSE),0)+IFERROR(VLOOKUP($A2,WVolleyball!$C:$O,N$1-2011,FALSE),0) -> 87361
A3: 100751 | B3: 46220 | C3: Alabama | D3: 2 | E3: =IFERROR(VLOOKUP($A3,MBaseball!$C:$N,E$1-2010,FALSE),0)+IFERROR(VLOOKUP($A3,MBasketball!$C:$J,E$1-2006,FALSE),0)+IFERROR(VLOOKUP($A3,MFootball!$C:$O,E$1-2011,FALSE),0)+IFERROR(VLOOKUP($A3,MIceHockey!$C:$P,E$1-2011,FALSE),0)+IFERROR(VLOOKUP($A3,MLacrosse!$C:$O,E$1-2011,FALSE),0)+IFERROR(VLOOKUP($A3,MSoccer!$C:$O,E$1-2011,FALSE),0)+IFERROR(VLOOKUP($A3,MVolleyball!$C:$O,E$1-2011,FALSE),0)+IFERROR(VLOOKUP($A3,WBasketball!$C:$O,E$1-2011,FALSE),0)+IFERROR(VLOOKUP($A3,WFieldHockey!$C:$O,E$1-2011,FALSE),0)+IFERROR(VLOOKUP($A3,WIceHockey!$C:$O,E$1-2011,FALSE),0)+IFERROR(VLOOKUP($A3,WLacrosse!$C:$O,E$1-2011,FALSE),0)+IFERROR(VLOOKUP($A3,WSoccer!$C:$O,E$1-2011,FALSE),0)+IFERROR(VLOOKUP($A3,WSoftball!$C:$O,E$1-2011,FALSE),0)+IFERROR(VLOOKUP($A3,WVolleyball!$C:$O,E$1-2011,FALSE),0) -> 304839 | F3: =IFERROR(VLOOKUP($A3,MBaseball!$C:$N,F$1-2010,FALSE),0)+IFERROR(VLOOKUP($A3,MBasketball!$C:$J,F$1-2006,FALSE),0)+IFERROR(VLOOKUP($A3,MFootball!$C:$O,F$1-2011,FALSE),0)+IFERROR(VLOOKUP($A3,MIceHockey!$C:$P,F$1-2011,FALSE),0)+IFERROR(VLOOKUP($A3,MLacrosse!$C:$O,F$1-2011,FALSE),0)+IFERROR(VLOOKUP($A3,MSoccer!$C:$O,F$1-2011,FALSE),0)+IFERROR(VLOOKUP($A3,MVolleyball!$C:$O,F$1-2011,FALSE),0)+IFERROR(VLOOKUP($A3,WBasketball!$C:$O,F$1-2011,FALSE),0)+IFERROR(VLOOKUP($A3,WFieldHockey!$C:$O,F$1-2011,FALSE),0)+IFERROR(VLOOKUP($A3,WIceHockey!$C:$O,F$1-2011,FALSE),0)+IFERROR(VLOOKUP($A3,WLacrosse!$C:$O,F$1-2011,FALSE),0)+IFERROR(VLOOKUP($A3,WSoccer!$C:$O,F$1-2011,FALSE),0)+IFERROR(VLOOKUP($A3,WSoftball!$C:$O,F$1-2011,FALSE),0)+IFERROR(VLOOKUP($A3,WVolleyball!$C:$O,F$1-2011,FALSE),0) -> 911957 | G3: =IFERROR(VLOOKUP($A3,MBaseball!$C:$N,G$1-2010,FALSE),0)+IFERROR(VLOOKUP($A3,MBasketball!$C:$J,G$1-2006,FALSE),0)+IFERROR(VLOOKUP($A3,MFootball!$C:$O,G$1-2011,FALSE),0)+IFERROR(VLOOKUP($A3,MIceHockey!$C:$P,G$1-2011,FALSE),0)+IFERROR(VLOOKUP($A3,MLacrosse!$C:$O,G$1-2011,FALSE),0)+IFERROR(VLOOKUP($A3,MSoccer!$C:$O,G$1-2011,FALSE),0)+IFERROR(VLOOKUP($A3,MVolleyball!$C:$O,G$1-2011,FALSE),0)+IFERROR(VLOOKUP($A3,WBasketball!$C:$O,G$1-2011,FALSE),0)+IFERROR(VLOOKUP($A3,WFieldHockey!$C:$O,G$1-2011,FALSE),0)+IFERROR(VLOOKUP($A3,WIceHockey!$C:$O,G$1-2011,FALSE),0)+IFERROR(VLOOKUP($A3,WLacrosse!$C:$O,G$1-2011,FALSE),0)+IFERROR(VLOOKUP($A3,WSoccer!$C:$O,G$1-2011,FALSE),0)+IFERROR(VLOOKUP($A3,WSoftball!$C:$O,G$1-2011,FALSE),0)+IFERROR(VLOOKUP($A3,WVolleyball!$C:$O,G$1-2011,FALSE),0) -> 988519 | H3: =IFERROR(VLOOKUP($A3,MBaseball!$C:$N,H$1-2010,FALSE),0)+IFERROR(VLOOKUP($A3,MBasketball!$C:$J,H$1-2006,FALSE),0)+IFERROR(VLOOKUP($A3,MFootball!$C:$O,H$1-2011,FALSE),0)+IFERROR(VLOOKUP($A3,MIceHockey!$C:$P,H$1-2011,FALSE),0)+IFERROR(VLOOKUP($A3,MLacrosse!$C:$O,H$1-2011,FALSE),0)+IFERROR(VLOOKUP($A3,MSoccer!$C:$O,H$1-2011,FALSE),0)+IFERROR(VLOOKUP($A3,MVolleyball!$C:$O,H$1-2011,FALSE),0)+IFERROR(VLOOKUP($A3,WBasketball!$C:$O,H$1-2011,FALSE),0)+IFERROR(VLOOKUP($A3,WFieldHockey!$C:$O,H$1-2011,FALSE),0)+IFERROR(VLOOKUP($A3,WIceHockey!$C:$O,H$1-2011,FALSE),0)+IFERROR(VLOOKUP($A3,WLacrosse!$C:$O,H$1-2011,FALSE),0)+IFERROR(VLOOKUP($A3,WSoccer!$C:$O,H$1-2011,FALSE),0)+IFERROR(VLOOKUP($A3,WSoftball!$C:$O,H$1-2011,FALSE),0)+IFERROR(VLOOKUP($A3,WVolleyball!$C:$O,H$1-2011,FALSE),0) -> 969780 | I3: =IFERROR(VLOOKUP($A3,MBaseball!$C:$N,I$1-2010,FALSE),0)+IFERROR(VLOOKUP($A3,MBasketball!$C:$J,I$1-2006,FALSE),0)+IFERROR(VLOOKUP($A3,MFootball!$C:$O,I$1-2011,FALSE),0)+IFERROR(VLOOKUP($A3,MIceHockey!$C:$P,I$1-2011,FALSE),0)+IFERROR(VLOOKUP($A3,MLacrosse!$C:$O,I$1-2011,FALSE),0)+IFERROR(VLOOKUP($A3,MSoccer!$C:$O,I$1-2011,FALSE),0)+IFERROR(VLOOKUP($A3,MVolleyball!$C:$O,I$1-2011,FALSE),0)+IFERROR(VLOOKUP($A3,WBasketball!$C:$O,I$1-2011,FALSE),0)+IFERROR(VLOOKUP($A3,WFieldHockey!$C:$O,I$1-2011,FALSE),0)+IFERROR(VLOOKUP($A3,WIceHockey!$C:$O,I$1-2011,FALSE),0)+IFERROR(VLOOKUP($A3,WLacrosse!$C:$O,I$1-2011,FALSE),0)+IFERROR(VLOOKUP($A3,WSoccer!$C:$O,I$1-2011,FALSE),0)+IFERROR(VLOOKUP($A3,WSoftball!$C:$O,I$1-2011,FALSE),0)+IFERROR(VLOOKUP($A3,WVolleyball!$C:$O,I$1-2011,FALSE),0) -> 936731 | J3: =IFERROR(VLOOKUP($A3,MBaseball!$C:$N,J$1-2010,FALSE),0)+IFERROR(VLOOKUP($A3,MBasketball!$C:$J,J$1-2006,FALSE),0)+IFERROR(VLOOKUP($A3,MFootball!$C:$O,J$1-2011,FALSE),0)+IFERROR(VLOOKUP($A3,MIceHockey!$C:$P,J$1-2011,FALSE),0)+IFERROR(VLOOKUP($A3,MLacrosse!$C:$O,J$1-2011,FALSE),0)+IFERROR(VLOOKUP($A3,MSoccer!$C:$O,J$1-2011,FALSE),0)+IFERROR(VLOOKUP($A3,MVolleyball!$C:$O,J$1-2011,FALSE),0)+IFERROR(VLOOKUP($A3,WBasketball!$C:$O,J$1-2011,FALSE),0)+IFERROR(VLOOKUP($A3,WFieldHockey!$C:$O,J$1-2011,FALSE),0)+IFERROR(VLOOKUP($A3,WIceHockey!$C:$O,J$1-2011,FALSE),0)+IFERROR(VLOOKUP($A3,WLacrosse!$C:$O,J$1-2011,FALSE),0)+IFERROR(VLOOKUP($A3,WSoccer!$C:$O,J$1-2011,FALSE),0)+IFERROR(VLOOKUP($A3,WSoftball!$C:$O,J$1-2011,FALSE),0)+IFERROR(VLOOKUP($A3,WVolleyball!$C:$O,J$1-2011,FALSE),0) -> 879105 | K3: =IFERROR(VLOOKUP($A3,MBaseball!$C:$N,K$1-2010,FALSE),0)+IFERROR(VLOOKUP($A3,MBasketball!$C:$J,K$1-2006,FALSE),0)+IFERROR(VLOOKUP($A3,MFootball!$C:$O,K$1-2011,FALSE),0)+IFERROR(VLOOKUP($A3,MIceHockey!$C:$P,K$1-2011,FALSE),0)+IFERROR(VLOOKUP($A3,MLacrosse!$C:$O,K$1-2011,FALSE),0)+IFERROR(VLOOKUP($A3,MSoccer!$C:$O,K$1-2011,FALSE),0)+IFERROR(VLOOKUP($A3,MVolleyball!$C:$O,K$1-2011,FALSE),0)+IFERROR(VLOOKUP($A3,WBasketball!$C:$O,K$1-2011,FALSE),0)+IFERROR(VLOOKUP($A3,WFieldHockey!$C:$O,K$1-2011,FALSE),0)+IFERROR(VLOOKUP($A3,WIceHockey!$C:$O,K$1-2011,FALSE),0)+IFERROR(VLOOKUP($A3,WLacrosse!$C:$O,K$1-2011,FALSE),0)+IFERROR(VLOOKUP($A3,WSoccer!$C:$O,K$1-2011,FALSE),0)+IFERROR(VLOOKUP($A3,WSoftball!$C:$O,K$1-2011,FALSE),0)+IFERROR(VLOOKUP($A3,WVolleyball!$C:$O,K$1-2011,FALSE),0) -> 859604 | L3: =IFERROR(VLOOKUP($A3,MBaseball!$C:$N,L$1-2010,FALSE),0)+IFERROR(VLOOKUP($A3,MBasketball!$C:$J,L$1-2006,FALSE),0)+IFERROR(VLOOKUP($A3,MFootball!$C:$O,L$1-2011,FALSE),0)+IFERROR(VLOOKUP($A3,MIceHockey!$C:$P,L$1-2011,FALSE),0)+IFERROR(VLOOKUP($A3,MLacrosse!$C:$O,L$1-2011,FALSE),0)+IFERROR(VLOOKUP($A3,MSoccer!$C:$O,L$1-2011,FALSE),0)+IFERROR(VLOOKUP($A3,MVolleyball!$C:$O,L$1-2011,FALSE),0)+IFERROR(VLOOKUP($A3,WBasketball!$C:$O,L$1-2011,FALSE),0)+IFERROR(VLOOKUP($A3,WFieldHockey!$C:$O,L$1-2011,FALSE),0)+IFERROR(VLOOKUP($A3,WIceHockey!$C:$O,L$1-2011,FALSE),0)+IFERROR(VLOOKUP($A3,WLacrosse!$C:$O,L$1-2011,FALSE),0)+IFERROR(VLOOKUP($A3,WSoccer!$C:$O,L$1-2011,FALSE),0)+IFERROR(VLOOKUP($A3,WSoftball!$C:$O,L$1-2011,FALSE),0)+IFERROR(VLOOKUP($A3,WVolleyball!$C:$O,L$1-2011,FALSE),0) -> 271178 | ... N3: =IFERROR(VLOOKUP($A3,MBaseball!$C:$N,N$1-2010,FALSE),0)+IFERROR(VLOOKUP($A3,MBasketball!$C:$J,N$1-2006,FALSE),0)+IFERROR(VLOOKUP($A3,MFootball!$C:$O,N$1-2011,FALSE),0)+IFERROR(VLOOKUP($A3,MIceHockey!$C:$P,N$1-2011,FALSE),0)+IFERROR(VLOOKUP($A3,MLacrosse!$C:$O,N$1-2011,FALSE),0)+IFERROR(VLOOKUP($A3,MSoccer!$C:$O,N$1-2011,FALSE),0)+IFERROR(VLOOKUP($A3,MVolleyball!$C:$O,N$1-2011,FALSE),0)+IFERROR(VLOOKUP($A3,WBasketball!$C:$O,N$1-2011,FALSE),0)+IFERROR(VLOOKUP($A3,WFieldHockey!$C:$O,N$1-2011,FALSE),0)+IFERROR(VLOOKUP($A3,WIceHockey!$C:$O,N$1-2011,FALSE),0)+IFERROR(VLOOKUP($A3,WLacrosse!$C:$O,N$1-2011,FALSE),0)+IFERROR(VLOOKUP($A3,WSoccer!$C:$O,N$1-2011,FALSE),0)+IFERROR(VLOOKUP($A3,WSoftball!$C:$O,N$1-2011,FALSE),0)+IFERROR(VLOOKUP($A3,WVolleyball!$C:$O,N$1-2011,FALSE),0) -> 884874
A4: 197869 | B4: 14380 | C4: Appalachian State | D4: 3 | E4: =IFERROR(VLOOKUP($A4,MBaseball!$C:$N,E$1-2010,FALSE),0)+IFERROR(VLOOKUP($A4,MBasketball!$C:$J,E$1-2006,FALSE),0)+IFERROR(VLOOKUP($A4,MFootball!$C:$O,E$1-2011,FALSE),0)+IFERROR(VLOOKUP($A4,MIceHockey!$C:$P,E$1-2011,FALSE),0)+IFERROR(VLOOKUP($A4,MLacrosse!$C:$O,E$1-2011,FALSE),0)+IFERROR(VLOOKUP($A4,MSoccer!$C:$O,E$1-2011,FALSE),0)+IFERROR(VLOOKUP($A4,MVolleyball!$C:$O,E$1-2011,FALSE),0)+IFERROR(VLOOKUP($A4,WBasketball!$C:$O,E$1-2011,FALSE),0)+IFERROR(VLOOKUP($A4,WFieldHockey!$C:$O,E$1-2011,FALSE),0)+IFERROR(VLOOKUP($A4,WIceHockey!$C:$O,E$1-2011,FALSE),0)+IFERROR(VLOOKUP($A4,WLacrosse!$C:$O,E$1-2011,FALSE),0)+IFERROR(VLOOKUP($A4,WSoccer!$C:$O,E$1-2011,FALSE),0)+IFERROR(VLOOKUP($A4,WSoftball!$C:$O,E$1-2011,FALSE),0)+IFERROR(VLOOKUP($A4,WVolleyball!$C:$O,E$1-2011,FALSE),0) -> 39268 | F4: =IFERROR(VLOOKUP($A4,MBaseball!$C:$N,F$1-2010,FALSE),0)+IFERROR(VLOOKUP($A4,MBasketball!$C:$J,F$1-2006,FALSE),0)+IFERROR(VLOOKUP($A4,MFootball!$C:$O,F$1-2011,FALSE),0)+IFERROR(VLOOKUP($A4,MIceHockey!$C:$P,F$1-2011,FALSE),0)+IFERROR(VLOOKUP($A4,MLacrosse!$C:$O,F$1-2011,FALSE),0)+IFERROR(VLOOKUP($A4,MSoccer!$C:$O,F$1-2011,FALSE),0)+IFERROR(VLOOKUP($A4,MVolleyball!$C:$O,F$1-2011,FALSE),0)+IFERROR(VLOOKUP($A4,WBasketball!$C:$O,F$1-2011,FALSE),0)+IFERROR(VLOOKUP($A4,WFieldHockey!$C:$O,F$1-2011,FALSE),0)+IFERROR(VLOOKUP($A4,WIceHockey!$C:$O,F$1-2011,FALSE),0)+IFERROR(VLOOKUP($A4,WLacrosse!$C:$O,F$1-2011,FALSE),0)+IFERROR(VLOOKUP($A4,WSoccer!$C:$O,F$1-2011,FALSE),0)+IFERROR(VLOOKUP($A4,WSoftball!$C:$O,F$1-2011,FALSE),0)+IFERROR(VLOOKUP($A4,WVolleyball!$C:$O,F$1-2011,FALSE),0) -> 164735 | G4: =IFERROR(VLOOKUP($A4,MBaseball!$C:$N,G$1-2010,FALSE),0)+IFERROR(VLOOKUP($A4,MBasketball!$C:$J,G$1-2006,FALSE),0)+IFERROR(VLOOKUP($A4,MFootball!$C:$O,G$1-2011,FALSE),0)+IFERROR(VLOOKUP($A4,MIceHockey!$C:$P,G$1-2011,FALSE),0)+IFERROR(VLOOKUP($A4,MLacrosse!$C:$O,G$1-2011,FALSE),0)+IFERROR(VLOOKUP($A4,MSoccer!$C:$O,G$1-2011,FALSE),0)+IFERROR(VLOOKUP($A4,MVolleyball!$C:$O,G$1-2011,FALSE),0)+IFERROR(VLOOKUP($A4,WBasketball!$C:$O,G$1-2011,FALSE),0)+IFERROR(VLOOKUP($A4,WFieldHockey!$C:$O,G$1-2011,FALSE),0)+IFERROR(VLOOKUP($A4,WIceHockey!$C:$O,G$1-2011,FALSE),0)+IFERROR(VLOOKUP($A4,WLacrosse!$C:$O,G$1-2011,FALSE),0)+IFERROR(VLOOKUP($A4,WSoccer!$C:$O,G$1-2011,FALSE),0)+IFERROR(VLOOKUP($A4,WSoftball!$C:$O,G$1-2011,FALSE),0)+IFERROR(VLOOKUP($A4,WVolleyball!$C:$O,G$1-2011,FALSE),0) -> 160011 | H4: =IFERROR(VLOOKUP($A4,MBaseball!$C:$N,H$1-2010,FALSE),0)+IFERROR(VLOOKUP($A4,MBasketball!$C:$J,H$1-2006,FALSE),0)+IFERROR(VLOOKUP($A4,MFootball!$C:$O,H$1-2011,FALSE),0)+IFERROR(VLOOKUP($A4,MIceHockey!$C:$P,H$1-2011,FALSE),0)+IFERROR(VLOOKUP($A4,MLacrosse!$C:$O,H$1-2011,FALSE),0)+IFERROR(VLOOKUP($A4,MSoccer!$C:$O,H$1-2011,FALSE),0)+IFERROR(VLOOKUP($A4,MVolleyball!$C:$O,H$1-2011,FALSE),0)+IFERROR(VLOOKUP($A4,WBasketball!$C:$O,H$1-2011,FALSE),0)+IFERROR(VLOOKUP($A4,WFieldHockey!$C:$O,H$1-2011,FALSE),0)+IFERROR(VLOOKUP($A4,WIceHockey!$C:$O,H$1-2011,FALSE),0)+IFERROR(VLOOKUP($A4,WLacrosse!$C:$O,H$1-2011,FALSE),0)+IFERROR(VLOOKUP($A4,WSoccer!$C:$O,H$1-2011,FALSE),0)+IFERROR(VLOOKUP($A4,WSoftball!$C:$O,H$1-2011,FALSE),0)+IFERROR(VLOOKUP($A4,WVolleyball!$C:$O,H$1-2011,FALSE),0) -> 178383 | I4: =IFERROR(VLOOKUP($A4,MBaseball!$C:$N,I$1-2010,FALSE),0)+IFERROR(VLOOKUP($A4,MBasketball!$C:$J,I$1-2006,FALSE),0)+IFERROR(VLOOKUP($A4,MFootball!$C:$O,I$1-2011,FALSE),0)+IFERROR(VLOOKUP($A4,MIceHockey!$C:$P,I$1-2011,FALSE),0)+IFERROR(VLOOKUP($A4,MLacrosse!$C:$O,I$1-2011,FALSE),0)+IFERROR(VLOOKUP($A4,MSoccer!$C:$O,I$1-2011,FALSE),0)+IFERROR(VLOOKUP($A4,MVolleyball!$C:$O,I$1-2011,FALSE),0)+IFERROR(VLOOKUP($A4,WBasketball!$C:$O,I$1-2011,FALSE),0)+IFERROR(VLOOKUP($A4,WFieldHockey!$C:$O,I$1-2011,FALSE),0)+IFERROR(VLOOKUP($A4,WIceHockey!$C:$O,I$1-2011,FALSE),0)+IFERROR(VLOOKUP($A4,WLacrosse!$C:$O,I$1-2011,FALSE),0)+IFERROR(VLOOKUP($A4,WSoccer!$C:$O,I$1-2011,FALSE),0)+IFERROR(VLOOKUP($A4,WSoftball!$C:$O,I$1-2011,FALSE),0)+IFERROR(VLOOKUP($A4,WVolleyball!$C:$O,I$1-2011,FALSE),0) -> 180248 | J4: =IFERROR(VLOOKUP($A4,MBaseball!$C:$N,J$1-2010,FALSE),0)+IFERROR(VLOOKUP($A4,MBasketball!$C:$J,J$1-2006,FALSE),0)+IFERROR(VLOOKUP($A4,MFootball!$C:$O,J$1-2011,FALSE),0)+IFERROR(VLOOKUP($A4,MIceHockey!$C:$P,J$1-2011,FALSE),0)+IFERROR(VLOOKUP($A4,MLacrosse!$C:$O,J$1-2011,FALSE),0)+IFERROR(VLOOKUP($A4,MSoccer!$C:$O,J$1-2011,FALSE),0)+IFERROR(VLOOKUP($A4,MVolleyball!$C:$O,J$1-2011,FALSE),0)+IFERROR(VLOOKUP($A4,WBasketball!$C:$O,J$1-2011,FALSE),0)+IFERROR(VLOOKUP($A4,WFieldHockey!$C:$O,J$1-2011,FALSE),0)+IFERROR(VLOOKUP($A4,WIceHockey!$C:$O,J$1-2011,FALSE),0)+IFERROR(VLOOKUP($A4,WLacrosse!$C:$O,J$1-2011,FALSE),0)+IFERROR(VLOOKUP($A4,WSoccer!$C:$O,J$1-2011,FALSE),0)+IFERROR(VLOOKUP($A4,WSoftball!$C:$O,J$1-2011,FALSE),0)+IFERROR(VLOOKUP($A4,WVolleyball!$C:$O,J$1-2011,FALSE),0) -> 156385 | K4: =IFERROR(VLOOKUP($A4,MBaseball!$C:$N,K$1-2010,FALSE),0)+IFERROR(VLOOKUP($A4,MBasketball!$C:$J,K$1-2006,FALSE),0)+IFERROR(VLOOKUP($A4,MFootball!$C:$O,K$1-2011,FALSE),0)+IFERROR(VLOOKUP($A4,MIceHockey!$C:$P,K$1-2011,FALSE),0)+IFERROR(VLOOKUP($A4,MLacrosse!$C:$O,K$1-2011,FALSE),0)+IFERROR(VLOOKUP($A4,MSoccer!$C:$O,K$1-2011,FALSE),0)+IFERROR(VLOOKUP($A4,MVolleyball!$C:$O,K$1-2011,FALSE),0)+IFERROR(VLOOKUP($A4,WBasketball!$C:$O,K$1-2011,FALSE),0)+IFERROR(VLOOKUP($A4,WFieldHockey!$C:$O,K$1-2011,FALSE),0)+IFERROR(VLOOKUP($A4,WIceHockey!$C:$O,K$1-2011,FALSE),0)+IFERROR(VLOOKUP($A4,WLacrosse!$C:$O,K$1-2011,FALSE),0)+IFERROR(VLOOKUP($A4,WSoccer!$C:$O,K$1-2011,FALSE),0)+IFERROR(VLOOKUP($A4,WSoftball!$C:$O,K$1-2011,FALSE),0)+IFERROR(VLOOKUP($A4,WVolleyball!$C:$O,K$1-2011,FALSE),0) -> 187143 | L4: =IFERROR(VLOOKUP($A4,MBaseball!$C:$N,L$1-2010,FALSE),0)+IFERROR(VLOOKUP($A4,MBasketball!$C:$J,L$1-2006,FALSE),0)+IFERROR(VLOOKUP($A4,MFootball!$C:$O,L$1-2011,FALSE),0)+IFERROR(VLOOKUP($A4,MIceHockey!$C:$P,L$1-2011,FALSE),0)+IFERROR(VLOOKUP($A4,MLacrosse!$C:$O,L$1-2011,FALSE),0)+IFERROR(VLOOKUP($A4,MSoccer!$C:$O,L$1-2011,FALSE),0)+IFERROR(VLOOKUP($A4,MVolleyball!$C:$O,L$1-2011,FALSE),0)+IFERROR(VLOOKUP($A4,WBasketball!$C:$O,L$1-2011,FALSE),0)+IFERROR(VLOOKUP($A4,WFieldHockey!$C:$O,L$1-2011,FALSE),0)+IFERROR(VLOOKUP($A4,WIceHockey!$C:$O,L$1-2011,FALSE),0)+IFERROR(VLOOKUP($A4,WLacrosse!$C:$O,L$1-2011,FALSE),0)+IFERROR(VLOOKUP($A4,WSoccer!$C:$O,L$1-2011,FALSE),0)+IFERROR(VLOOKUP($A4,WSoftball!$C:$O,L$1-2011,FALSE),0)+IFERROR(VLOOKUP($A4,WVolleyball!$C:$O,L$1-2011,FALSE),0) -> 21420 | ... N4: =IFERROR(VLOOKUP($A4,MBaseball!$C:$N,N$1-2010,FALSE),0)+IFERROR(VLOOKUP($A4,MBasketball!$C:$J,N$1-2006,FALSE),0)+IFERROR(VLOOKUP($A4,MFootball!$C:$O,N$1-2011,FALSE),0)+IFERROR(VLOOKUP($A4,MIceHockey!$C:$P,N$1-2011,FALSE),0)+IFERROR(VLOOKUP($A4,MLacrosse!$C:$O,N$1-2011,FALSE),0)+IFERROR(VLOOKUP($A4,MSoccer!$C:$O,N$1-2011,FALSE),0)+IFERROR(VLOOKUP($A4,MVolleyball!$C:$O,N$1-2011,FALSE),0)+IFERROR(VLOOKUP($A4,WBasketball!$C:$O,N$1-2011,FALSE),0)+IFERROR(VLOOKUP($A4,WFieldHockey!$C:$O,N$1-2011,FALSE),0)+IFERROR(VLOOKUP($A4,WIceHockey!$C:$O,N$1-2011,FALSE),0)+IFERROR(VLOOKUP($A4,WLacrosse!$C:$O,N$1-2011,FALSE),0)+IFERROR(VLOOKUP($A4,WSoccer!$C:$O,N$1-2011,FALSE),0)+IFERROR(VLOOKUP($A4,WSoftball!$C:$O,N$1-2011,FALSE),0)+IFERROR(VLOOKUP($A4,WVolleyball!$C:$O,N$1-2011,FALSE),0) -> 254408
A5: 104179 | B5: 46060 | C5: Arizona | D5: 4 | E5: =IFERROR(VLOOKUP($A5,MBaseball!$C:$N,E$1-2010,FALSE),0)+IFERROR(VLOOKUP($A5,MBasketball!$C:$J,E$1-2006,FALSE),0)+IFERROR(VLOOKUP($A5,MFootball!$C:$O,E$1-2011,FALSE),0)+IFERROR(VLOOKUP($A5,MIceHockey!$C:$P,E$1-2011,FALSE),0)+IFERROR(VLOOKUP($A5,MLacrosse!$C:$O,E$1-2011,FALSE),0)+IFERROR(VLOOKUP($A5,MSoccer!$C:$O,E$1-2011,FALSE),0)+IFERROR(VLOOKUP($A5,MVolleyball!$C:$O,E$1-2011,FALSE),0)+IFERROR(VLOOKUP($A5,WBasketball!$C:$O,E$1-2011,FALSE),0)+IFERROR(VLOOKUP($A5,WFieldHockey!$C:$O,E$1-2011,FALSE),0)+IFERROR(VLOOKUP($A5,WIceHockey!$C:$O,E$1-2011,FALSE),0)+IFERROR(VLOOKUP($A5,WLacrosse!$C:$O,E$1-2011,FALSE),0)+IFERROR(VLOOKUP($A5,WSoccer!$C:$O,E$1-2011,FALSE),0)+IFERROR(VLOOKUP($A5,WSoftball!$C:$O,E$1-2011,FALSE),0)+IFERROR(VLOOKUP($A5,WVolleyball!$C:$O,E$1-2011,FALSE),0) -> 374331 | F5: =IFERROR(VLOOKUP($A5,MBaseball!$C:$N,F$1-2010,FALSE),0)+IFERROR(VLOOKUP($A5,MBasketball!$C:$J,F$1-2006,FALSE),0)+IFERROR(VLOOKUP($A5,MFootball!$C:$O,F$1-2011,FALSE),0)+IFERROR(VLOOKUP($A5,MIceHockey!$C:$P,F$1-2011,FALSE),0)+IFERROR(VLOOKUP($A5,MLacrosse!$C:$O,F$1-2011,FALSE),0)+IFERROR(VLOOKUP($A5,MSoccer!$C:$O,F$1-2011,FALSE),0)+IFERROR(VLOOKUP($A5,MVolleyball!$C:$O,F$1-2011,FALSE),0)+IFERROR(VLOOKUP($A5,WBasketball!$C:$O,F$1-2011,FALSE),0)+IFERROR(VLOOKUP($A5,WFieldHockey!$C:$O,F$1-2011,FALSE),0)+IFERROR(VLOOKUP($A5,WIceHockey!$C:$O,F$1-2011,FALSE),0)+IFERROR(VLOOKUP($A5,WLacrosse!$C:$O,F$1-2011,FALSE),0)+IFERROR(VLOOKUP($A5,WSoccer!$C:$O,F$1-2011,FALSE),0)+IFERROR(VLOOKUP($A5,WSoftball!$C:$O,F$1-2011,FALSE),0)+IFERROR(VLOOKUP($A5,WVolleyball!$C:$O,F$1-2011,FALSE),0) -> 502148 | G5: =IFERROR(VLOOKUP($A5,MBaseball!$C:$N,G$1-2010,FALSE),0)+IFERROR(VLOOKUP($A5,MBasketball!$C:$J,G$1-2006,FALSE),0)+IFERROR(VLOOKUP($A5,MFootball!$C:$O,G$1-2011,FALSE),0)+IFERROR(VLOOKUP($A5,MIceHockey!$C:$P,G$1-2011,FALSE),0)+IFERROR(VLOOKUP($A5,MLacrosse!$C:$O,G$1-2011,FALSE),0)+IFERROR(VLOOKUP($A5,MSoccer!$C:$O,G$1-2011,FALSE),0)+IFERROR(VLOOKUP($A5,MVolleyball!$C:$O,G$1-2011,FALSE),0)+IFERROR(VLOOKUP($A5,WBasketball!$C:$O,G$1-2011,FALSE),0)+IFERROR(VLOOKUP($A5,WFieldHockey!$C:$O,G$1-2011,FALSE),0)+IFERROR(VLOOKUP($A5,WIceHockey!$C:$O,G$1-2011,FALSE),0)+IFERROR(VLOOKUP($A5,WLacrosse!$C:$O,G$1-2011,FALSE),0)+IFERROR(VLOOKUP($A5,WSoccer!$C:$O,G$1-2011,FALSE),0)+IFERROR(VLOOKUP($A5,WSoftball!$C:$O,G$1-2011,FALSE),0)+IFERROR(VLOOKUP($A5,WVolleyball!$C:$O,G$1-2011,FALSE),0) -> 516628 | H5: =IFERROR(VLOOKUP($A5,MBaseball!$C:$N,H$1-2010,FALSE),0)+IFERROR(VLOOKUP($A5,MBasketball!$C:$J,H$1-2006,FALSE),0)+IFERROR(VLOOKUP($A5,MFootball!$C:$O,H$1-2011,FALSE),0)+IFERROR(VLOOKUP($A5,MIceHockey!$C:$P,H$1-2011,FALSE),0)+IFERROR(VLOOKUP($A5,MLacrosse!$C:$O,H$1-2011,FALSE),0)+IFERROR(VLOOKUP($A5,MSoccer!$C:$O,H$1-2011,FALSE),0)+IFERROR(VLOOKUP($A5,MVolleyball!$C:$O,H$1-2011,FALSE),0)+IFERROR(VLOOKUP($A5,WBasketball!$C:$O,H$1-2011,FALSE),0)+IFERROR(VLOOKUP($A5,WFieldHockey!$C:$O,H$1-2011,FALSE),0)+IFERROR(VLOOKUP($A5,WIceHockey!$C:$O,H$1-2011,FALSE),0)+IFERROR(VLOOKUP($A5,WLacrosse!$C:$O,H$1-2011,FALSE),0)+IFERROR(VLOOKUP($A5,WSoccer!$C:$O,H$1-2011,FALSE),0)+IFERROR(VLOOKUP($A5,WSoftball!$C:$O,H$1-2011,FALSE),0)+IFERROR(VLOOKUP($A5,WVolleyball!$C:$O,H$1-2011,FALSE),0) -> 551769 | I5: =IFERROR(VLOOKUP($A5,MBaseball!$C:$N,I$1-2010,FALSE),0)+IFERROR(VLOOKUP($A5,MBasketball!$C:$J,I$1-2006,FALSE),0)+IFERROR(VLOOKUP($A5,MFootball!$C:$O,I$1-2011,FALSE),0)+IFERROR(VLOOKUP($A5,MIceHockey!$C:$P,I$1-2011,FALSE),0)+IFERROR(VLOOKUP($A5,MLacrosse!$C:$O,I$1-2011,FALSE),0)+IFERROR(VLOOKUP($A5,MSoccer!$C:$O,I$1-2011,FALSE),0)+IFERROR(VLOOKUP($A5,MVolleyball!$C:$O,I$1-2011,FALSE),0)+IFERROR(VLOOKUP($A5,WBasketball!$C:$O,I$1-2011,FALSE),0)+IFERROR(VLOOKUP($A5,WFieldHockey!$C:$O,I$1-2011,FALSE),0)+IFERROR(VLOOKUP($A5,WIceHockey!$C:$O,I$1-2011,FALSE),0)+IFERROR(VLOOKUP($A5,WLacrosse!$C:$O,I$1-2011,FALSE),0)+IFERROR(VLOOKUP($A5,WSoccer!$C:$O,I$1-2011,FALSE),0)+IFERROR(VLOOKUP($A5,WSoftball!$C:$O,I$1-2011,FALSE),0)+IFERROR(VLOOKUP($A5,WVolleyball!$C:$O,I$1-2011,FALSE),0) -> 455423 | J5: =IFERROR(VLOOKUP($A5,MBaseball!$C:$N,J$1-2010,FALSE),0)+IFERROR(VLOOKUP($A5,MBasketball!$C:$J,J$1-2006,FALSE),0)+IFERROR(VLOOKUP($A5,MFootball!$C:$O,J$1-2011,FALSE),0)+IFERROR(VLOOKUP($A5,MIceHockey!$C:$P,J$1-2011,FALSE),0)+IFERROR(VLOOKUP($A5,MLacrosse!$C:$O,J$1-2011,FALSE),0)+IFERROR(VLOOKUP($A5,MSoccer!$C:$O,J$1-2011,FALSE),0)+IFERROR(VLOOKUP($A5,MVolleyball!$C:$O,J$1-2011,FALSE),0)+IFERROR(VLOOKUP($A5,WBasketball!$C:$O,J$1-2011,FALSE),0)+IFERROR(VLOOKUP($A5,WFieldHockey!$C:$O,J$1-2011,FALSE),0)+IFERROR(VLOOKUP($A5,WIceHockey!$C:$O,J$1-2011,FALSE),0)+IFERROR(VLOOKUP($A5,WLacrosse!$C:$O,J$1-2011,FALSE),0)+IFERROR(VLOOKUP($A5,WSoccer!$C:$O,J$1-2011,FALSE),0)+IFERROR(VLOOKUP($A5,WSoftball!$C:$O,J$1-2011,FALSE),0)+IFERROR(VLOOKUP($A5,WVolleyball!$C:$O,J$1-2011,FALSE),0) -> 522517 | K5: =IFERROR(VLOOKUP($A5,MBaseball!$C:$N,K$1-2010,FALSE),0)+IFERROR(VLOOKUP($A5,MBasketball!$C:$J,K$1-2006,FALSE),0)+IFERROR(VLOOKUP($A5,MFootball!$C:$O,K$1-2011,FALSE),0)+IFERROR(VLOOKUP($A5,MIceHockey!$C:$P,K$1-2011,FALSE),0)+IFERROR(VLOOKUP($A5,MLacrosse!$C:$O,K$1-2011,FALSE),0)+IFERROR(VLOOKUP($A5,MSoccer!$C:$O,K$1-2011,FALSE),0)+IFERROR(VLOOKUP($A5,MVolleyball!$C:$O,K$1-2011,FALSE),0)+IFERROR(VLOOKUP($A5,WBasketball!$C:$O,K$1-2011,FALSE),0)+IFERROR(VLOOKUP($A5,WFieldHockey!$C:$O,K$1-2011,FALSE),0)+IFERROR(VLOOKUP($A5,WIceHockey!$C:$O,K$1-2011,FALSE),0)+IFERROR(VLOOKUP($A5,WLacrosse!$C:$O,K$1-2011,FALSE),0)+IFERROR(VLOOKUP($A5,WSoccer!$C:$O,K$1-2011,FALSE),0)+IFERROR(VLOOKUP($A5,WSoftball!$C:$O,K$1-2011,FALSE),0)+IFERROR(VLOOKUP($A5,WVolleyball!$C:$O,K$1-2011,FALSE),0) -> 441655 | L5: =IFERROR(VLOOKUP($A5,MBaseball!$C:$N,L$1-2010,FALSE),0)+IFERROR(VLOOKUP($A5,MBasketball!$C:$J,L$1-2006,FALSE),0)+IFERROR(VLOOKUP($A5,MFootball!$C:$O,L$1-2011,FALSE),0)+IFERROR(VLOOKUP($A5,MIceHockey!$C:$P,L$1-2011,FALSE),0)+IFERROR(VLOOKUP($A5,MLacrosse!$C:$O,L$1-2011,FALSE),0)+IFERROR(VLOOKUP($A5,MSoccer!$C:$O,L$1-2011,FALSE),0)+IFERROR(VLOOKUP($A5,MVolleyball!$C:$O,L$1-2011,FALSE),0)+IFERROR(VLOOKUP($A5,WBasketball!$C:$O,L$1-2011,FALSE),0)+IFERROR(VLOOKUP($A5,WFieldHockey!$C:$O,L$1-2011,FALSE),0)+IFERROR(VLOOKUP($A5,WIceHockey!$C:$O,L$1-2011,FALSE),0)+IFERROR(VLOOKUP($A5,WLacrosse!$C:$O,L$1-2011,FALSE),0)+IFERROR(VLOOKUP($A5,WSoccer!$C:$O,L$1-2011,FALSE),0)+IFERROR(VLOOKUP($A5,WSoftball!$C:$O,L$1-2011,FALSE),0)+IFERROR(VLOOKUP($A5,WVolleyball!$C:$O,L$1-2011,FALSE),0) -> 106443 | ... N5: =IFERROR(VLOOKUP($A5,MBaseball!$C:$N,N$1-2010,FALSE),0)+IFERROR(VLOOKUP($A5,MBasketball!$C:$J,N$1-2006,FALSE),0)+IFERROR(VLOOKUP($A5,MFootball!$C:$O,N$1-2011,FALSE),0)+IFERROR(VLOOKUP($A5,MIceHockey!$C:$P,N$1-2011,FALSE),0)+IFERROR(VLOOKUP($A5,MLacrosse!$C:$O,N$1-2011,FALSE),0)+IFERROR(VLOOKUP($A5,MSoccer!$C:$O,N$1-2011,FALSE),0)+IFERROR(VLOOKUP($A5,MVolleyball!$C:$O,N$1-2011,FALSE),0)+IFERROR(VLOOKUP($A5,WBasketball!$C:$O,N$1-2011,FALSE),0)+IFERROR(VLOOKUP($A5,WFieldHockey!$C:$O,N$1-2011,FALSE),0)+IFERROR(VLOOKUP($A5,WIceHockey!$C:$O,N$1-2011,FALSE),0)+IFERROR(VLOOKUP($A5,WLacrosse!$C:$O,N$1-2011,FALSE),0)+IFERROR(VLOOKUP($A5,WSoccer!$C:$O,N$1-2011,FALSE),0)+IFERROR(VLOOKUP($A5,WSoftball!$C:$O,N$1-2011,FALSE),0)+IFERROR(VLOOKUP($A5,WVolleyball!$C:$O,N$1-2011,FALSE),0) -> 515674
