Workbook

Sheet Title
A1: STRYKER DCF
A2: TYLER BERRY
A3: 46235

Sheet Assumptions
A1: Assumption | B1: Value
A2: Revenue Growth | B2: 0.10074775
A3: Operating Margin | B3: 0.195
A4: Tax Rate | B4: 0.16181271
A5: CapEx % Revenue | B5: =ABS(AVERAGE('Historical Financials'!U19:U23))/AVERAGE('Historical Financials'!B3:B7) -> 0.030877166
A6: D&A % Revenue | B6: =AVERAGE('Historical Financials'!G3:G7)/AVERAGE('Historical Financials'!B3:B7) -> 0.031185552
A7: Working Capital % Revenue | B7: =AVERAGE('Historical Financials'!AN11:AN15)/AVERAGE('Historical Financials'!B3:B7) -> 0.27204479

Sheet Historical Financials
A1: Income Statement
A2: YEAR | B2: Revenue | C2: COGS | D2: GROSS PROF | E2: SG&A | F2: R&D | G2: AOIA | H2: GAOI | I2: TOE | J2: OP INCOME | K2: INTREST EXP | L2: Other INC | M2: PRETAX INC | N2: TAXES | O2: NET INC | P2: EBIT MARGIN
A3: 2025 | B3: 25116 | C3: 9051 | D3: 16065 | E3: 8651 | F3: 1623 | G3: 732 | H3: 170 | I3: =SUM(E3:H3) -> 11176 | J3: 4889 | K3: -607 | L3: 232 | M3: 4514 | N3: -1268 | O3: =SUM(M3:N3) -> 3246 | P3: =J3/B3 -> 0.19465679
A4: 2024 | B4: 22595 | C4: 8155 | D4: 14440 | E4: 7685 | F4: 1466 | G4: 623 | H4: 977 | I4: =SUM(E4:H4) -> 10751 | J4: 3689 | K4: -409 | L4: 212 | M4: 3492 | N4: -499 | O4: =SUM(M4:N4) -> 2993 | P4: =J4/B4 -> 0.16326621
A5: 2023 | B5: 20498 | C5: 7440 | D5: 13058 | E5: 7111 | F5: 1388 | G5: 635 | H5: 36 | I5: =SUM(E5:H5) -> 9170 | J5: 3888 | K5: -363 | L5: 148 | M5: 3673 | N5: -508 | O5: =SUM(M5:N5) -> 3165 | P5: =J5/B5 -> 0.18967704
A6: 2022 | B6: 18449 | C6: 6871 | D6: 11578 | E6: 6455 | F6: 1454 | G6: 627 | H6: 201 | I6: =SUM(E6:H6) -> 8737 | J6: 2841 | K6: -158 | L6: 0 | M6: 2683 | N6: -325 | O6: =SUM(M6:N6) -> 2358 | P6: =J6/B6 -> 0.15399209
A7: 2021 | B7: 17108 | C7: 6140 | D7: 10968 | E7: 6427 | F7: 1235 | G7: 619 | H7: 103 | I7: =SUM(E7:H7) -> 8384 | J7: 2584 | K7: -303 | L7: 0 | M7: 2281 | N7: -287 | O7: =SUM(M7:N7) -> 1994 | P7: =J7/B7 -> 0.15104045
A8: 2020 | B8: 14351 | D8: 9057
A9: Balance Sheets
A10: YEAR | B10: CACE | C10: STI | D10: MS | E10: ARLAO | F10: M&S | G10: WIP | H10: Finished gds | I10: Total INV | J10: PREPAID EXP | K10: TOTAL CURRENT AST | L10: LBI | M10: M&E | N10: TP-P&E | O10: LEFD | P10: PPE NET | Q10: GOODWILL | R10: OTHER INT | S10: NDITA | T10: OTHER NCA | U10: TOTAL ASSETS | V10: ACCOUNT P | W10: AC COMP | X10: INC TAX | Y10: DIVIDEND | Z10: Accured PL | AA10: AE&OE | AB10: CMOD | AC10: TOTAL CLIB | AD10: Long Term Debt | AE10: IT | AF10: OTHER NL | AG10: TOTAL LIB | AH10: Common STK | AI10: ADIC | AJ10: RE | AK10: AOCL | AL10: TOTAL SHE | AM10: TL&SE | AN10: Net Working Cap
A11: =2025 -> 2025 | B11: 4011 | C11: 0 | D11: 89 | E11: 4039 | F11: 1349 | G11: 415 | H11: 3546 | I11: =SUM(F11:H11) -> 5310 | J11: 1306 | K11: 14755 | L11: 1793 | M11: 5744 | N11: 7537 | O11: 3661 | P11: 3876 | Q11: 19261 | R11: 5681 | S11: 1098 | T11: 3143 | U11: 47844 | V11: 1799 | W11: 1595 | X11: 418 | Y11: 337 | Z11: 0 | AA11: 2645 | AB11: 1000 | AC11: 7794 | AD11: 14859 | AE11: 402 | AF11: 2369 | AG11: 25424 | AH11: 38 | AI11: 2597 | AJ11: 20472 | AK11: -687 | AL11: 22420 | AM11: 47844 | AN11: =K11-AC11 -> 6961
A12: 2024 | B12: 3625 | C12: 759 | D12: 91 | E12: 3987 | F12: 1147 | G12: 336 | H12: 3291 | I12: =SUM(F12:H12) -> 4774 | J12: 1593 | K12: 14847 | L12: 1627 | M12: 5056 | N12: 6683 | O12: 3235 | P12: 3448 | Q12: 15855 | R12: 4395 | S12: 1742 | T12: 2684 | U12: 42971 | V12: 1679 | W12: 1403 | X12: 539 | Y12: 320 | Z12: 0 | AA12: 2266 | AB12: 1409 | AC12: 7616 | AD12: 12188 | AE12: 349 | AF12: 2184 | AG12: 22337 | AH12: 38 | AI12: 2361 | AJ12: 18528 | AK12: -293 | AL12: 20634 | AM12: 42971 | AN12: =K12-AC12 -> 7231
A13: 2023 | B13: 2971 | C13: 0 | D13: 82 | E13: 2765 | F13: 1242 | G13: 330 | H13: 3271 | I13: =SUM(F13:H13) -> 4843 | J13: 857 | K13: 12518 | L13: 1692 | M13: 4652 | N13: 6344 | O13: 3129 | P13: 3215 | Q13: 15243 | R13: 4593 | S13: 1670 | T13: 2673 | U13: 39912 | V13: 1517 | W13: 1478 | X13: 391 | Y13: 304 | Z13: 209 | AA13: 1928 | AB13: 2094 | AC13: 7921 | AD13: 10901 | AE13: 567 | AF13: 1930 | AG13: 21319 | AH13: 38 | AI13: 2200 | AJ13: 16771 | AK13: -416 | AL13: 18593 | AM13: 39912 | AN13: =K13-AC13 -> 4597
A14: 2022 | B14: 1844 | C14: 0 | D14: 84 | E14: 3565 | F14: 1006 | G14: 348 | H14: 2641 | I14: =SUM(F14:H14) -> 3995 | J14: 787 | K14: 10275 | L14: 1739 | M14: 4066 | N14: 5805 | O14: 2835 | P14: 2970 | Q14: 14880 | R14: 4885 | S14: 1410 | T14: 2464 | U14: 36884 | V14: 1413 | W14: 1149 | X14: 292 | Y14: 284 | Z14: 230 | AA14: 1744 | AB14: 1191 | AC14: 6303 | AD14: 11857 | AE14: 641 | AF14: 1467 | AG14: 20268 | AH14: 38 | AI14: 2034 | AJ14: 14765 | AK14: -221 | AL14: 16616 | AM14: 36884 | AN14: =K14-AC14 -> 3972
A15: 2021 | B15: 2944 | C15: 0 | D15: 75 | E15: 3022 | F15: 691 | G15: 264 | H15: 2359 | I15: =SUM(F15:H15) -> 3314 | J15: 662 | K15: 10017 | L15: 1656 | M15: 3842 | N15: 5498 | O15: 2665 | P15: 2833 | Q15: 12918 | R15: 4840 | S15: 1760 | T15: 2263 | U15: 34631 | V15: 1129 | W15: 1092 | X15: 192 | Y15: 263 | Z15: 401 | AA15: 1465 | AB15: 7 | AC15: 4549 | AD15: 12472 | AE15: 913 | AF15: 1820 | AG15: 19754 | AH15: 38 | AI15: 1890 | AJ15: 13480 | AK15: -531 | AL15: 14877 | AM15: 34631 | AN15: =K15-AC15 -> 5468
A16: 2020 | B16: 2943 | C16: 0 | D16: 81 | E16: 2701 | F16: 678 | G16: 251 | H16: 2565 | I16: =SUM(F16:H16) -> 3494 | J16: 488 | K16: 9707 | L16: 1546 | M16: 3636 | N16: 5182 | O16: 2430 | P16: 2752 | Q16: 12778 | R16: 5554 | S16: 1530 | AL16: 13084
A17: CASH FLOW
A18: YEAR | B18: NET EARN | C18: DEPREC | D18: AOIA | E18: GAOI | F18: SBC | G18: Recall Charge | H18: SOISUTFVAA | I18: Def INC TAX | J18: Acc recive | K18: Inventoires | L18: ACC Payable | M18: AE&OL | N18: Recall Related EXP | O18: INC TAX | P18: Other | Q18: NET Cash | R18: Acquisitions | S18: Proceeds MS | T18: Purchases MS | U18: POP, P&E | V18: Proceeds F/S | W18: Other invest | X18: Net Invest | Y18: Proceeds STB | Z18: Proceeds LTD | AA18: Payments of Dividends | AB18: Cash paid for taxes | AC18: Payments on LTD | AD18: Other Finance | AE18: Net Cash finace | AF18: Effect of EX | AG18: change in cash | AH18: CIC EQ | AI18: C&CEAEOY
A19: 2025 | B19: 3246 | C19: 461 | D19: 732 | E19: 170 | F19: 243 | G19: 0 | H19: 173 | I19: 392 | J19: 127 | K19: -297 | L19: 94 | M19: 318 | N19: 0 | O19: -145 | P19: -470 | Q19: 5044 | R19: -4960 | S19: 0 | T19: 750 | U19: -761 | V19: 165 | W19: -60 | X19: -4866 | Y19: 0 | Z19: 2979 | AA19: -1400 | AB19: -1284 | AC19: -149 | AD19: -33 | AE19: 113 | AF19: 68 | AG19: 359 | AH19: 3652 | AI19: 4011
A20: 2024 | B20: 2993 | C20: 427 | D20: 632 | E20: 977 | F20: 229 | G20: 0 | H20: 46 | I20: -370 | J20: -321 | K20: -206 | L20: 192 | M20: 74 | N20: 0 | O20: -116 | P20: -306 | Q20: 4242 | R20: -1628 | S20: 0 | T20: -750 | U20: -755 | V20: 0 | W20: 133 | X20: -3000 | Y20: -32 | Z20: 3011 | AA20: -2039 | AB20: -1219 | AC20: -195 | AD20: -51 | AE20: -525 | AF20: -36 | AG20: 681 | AH20: 2971 | AI20: 3652
A21: 2023 | B21: 3165 | C21: 393 | D21: 635 | E21: 36 | F21: 205 | G21: 18 | H21: 0 | I21: -206 | J21: -175 | K21: -797 | L21: 77 | M21: 533 | N21: -35 | O21: -4 | P21: -134 | Q21: 3711 | R21: -390 | S21: -52 | T21: 54 | U21: -575 | V21: 0 | W21: 1 | X21: -962 | Y21: 540 | Z21: 1241 | AA21: -2085 | AB21: -1139 | AC21: -155 | AD21: -23 | AE21: -1594 | AF21: -28 | AG21: 1127 | AH21: 1844 | AI21: 2971
A22: 2022 | B22: 2358 | C22: 371 | D22: 627 | E22: =216+54 -> 270 | F22: 168 | G22: -15 | H22: 12 | I22: 58 | J22: -597 | K22: -762 | L22: 290 | M22: 328 | N22: -157 | O22: -238 | P22: -107 | Q22: 2624 | R22: -2563 | S22: -52 | T22: 43 | U22: -588 | V22: 197 | W22: 39 | X22: -2924 | Y22: -375 | Z22: 1500 | AA22: -653 | AB22: -1051 | AC22: -122 | AD22: -48 | AE22: -749 | AF22: -51 | AG22: -1100 | AH22: 2944 | AI22: 1844
A23: 2021 | B23: 1994 | C23: 371 | D23: 619 | E23: 264 | F23: 171 | G23: 103 | H23: 266 | I23: -237 | J23: -377 | K23: -189 | L23: 329 | M23: 315 | N23: 221 | O23: -90 | P23: -47 | Q23: 3263 | R23: -339 | S23: -49 | T23: 55 | U23: -525 | V23: 0 | W23: -1 | X23: -859 | Y23: -7 | Z23: 5 | AA23: -1151 | AB23: -950 | AC23: -114 | AD23: -148 | AE23: -2365 | AF23: -38 | AG23: 1 | AH23: 2943 | AI23: 2944

Sheet Financial Ratios
A1: Metric | B1: 2021 | C1: 2022 | D1: 2023 | E1: 2024 | F1: 2025
A2: Revenue Growth | B2: =('Historical Financials'!B7-'Historical Financials'!B8)/'Historical Financials'!B8 -> 0.19211205 | C2: =('Historical Financials'!B6-'Historical Financials'!B7)/'Historical Financials'!B7 -> 0.078384382 | D2: =('Historical Financials'!B5-'Historical Financials'!B6)/'Historical Financials'!B6 -> 0.11106293 | E2: =('Historical Financials'!B4-'Historical Financials'!B5)/'Historical Financials'!B5 -> 0.10230266 | F2: =('Historical Financials'!B3-'Historical Financials'!B4)/'Historical Financials'!B4 -> 0.11157336
A3: Gross Margin | B3: =('Historical Financials'!D7/'Historical Financials'!B7) -> 0.64110358 | C3: =('Historical Financials'!D6/'Historical Financials'!B6) -> 0.62756789 | D3: =('Historical Financials'!D5/'Historical Financials'!B5) -> 0.63703776 | E3: =('Historical Financials'!D4/'Historical Financials'!B4) -> 0.63907944 | F3: =('Historical Financials'!D3/'Historical Financials'!B3) -> 0.63963211
A4: Operating Margin | B4: ='Historical Financials'!J7/'Historical Financials'!B7 -> 0.15104045 | C4: ='Historical Financials'!J6/'Historical Financials'!B6 -> 0.15399209 | D4: ='Historical Financials'!J5/'Historical Financials'!B5 -> 0.18967704 | E4: ='Historical Financials'!J4/'Historical Financials'!B4 -> 0.16326621 | F4: ='Historical Financials'!J3/'Historical Financials'!B3 -> 0.19465679
A5: Net Margin | B5: ='Historical Financials'!O7/'Historical Financials'!B7 -> 0.11655366 | C5: ='Historical Financials'!O6/'Historical Financials'!B6 -> 0.12781181 | D5: ='Historical Financials'!O5/'Historical Financials'!B5 -> 0.15440531 | E5: ='Historical Financials'!O4/'Historical Financials'!B4 -> 0.13246293 | F5: ='Historical Financials'!O3/'Historical Financials'!B3 -> 0.12924032
A6: Return on Assets | B6: =('Historical Financials'!O7)/(('Historical Financials'!AL16+'Historical Financials'!AL15)/2) -> 0.14262723 | C6: =('Historical Financials'!O6)/(('Historical Financials'!AL15+'Historical Financials'!AL14)/2) -> 0.14974756 | D6: =('Historical Financials'!O5)/(('Historical Financials'!AL14+'Historical Financials'!AL13)/2) -> 0.17978358 | E6: =('Historical Financials'!O4)/(('Historical Financials'!AL13+'Historical Financials'!AL12)/2) -> 0.15259898 | F6: =('Historical Financials'!O3)/(('Historical Financials'!AL12+'Historical Financials'!AL11)/2) -> 0.15078738
A7: Effective Tax rate | B7: =ABS('Historical Financials'!N7)/'Historical Financials'!M7 -> 0.12582201 | C7: =ABS('Historical Financials'!N6)/'Historical Financials'!M6 -> 0.12113306 | D7: =ABS('Historical Financials'!N5)/'Historical Financials'!M5 -> 0.13830656 | E7: =ABS('Historical Financials'!N4)/'Historical Financials'!M4 -> 0.14289805 | F7: =ABS('Historical Financials'!N3)/'Historical Financials'!M3 -> 0.28090385
A8: Return on invested Capital | B8: ='Historical Financials'!J7*(1-'Financial Ratios'!B7)/('Historical Financials'!AD15+'Historical Financials'!AL15-'Historical Financials'!B15) -> 0.092557916 | C8: ='Historical Financials'!J6*(1-'Financial Ratios'!C7)/('Historical Financials'!AD14+'Historical Financials'!AL14-'Historical Financials'!B14) -> 0.093764729 | D8: ='Historical Financials'!J5*(1-'Financial Ratios'!D7)/('Historical Financials'!AD13+'Historical Financials'!AL13-'Historical Financials'!B13) -> 0.12631543 | E8: ='Historical Financials'!J4*(1-'Financial Ratios'!E7)/('Historical Financials'!AD12+'Historical Financials'!AL12-'Historical Financials'!B12) -> 0.10829363 | F8: ='Historical Financials'!J3*(1-'Financial Ratios'!F7)/('Historical Financials'!AD11+'Historical Financials'!AL11-'Historical Financials'!B11) -> 0.10567696
A9: Current Ratio | B9: ='Historical Financials'!K15/'Historical Financials'!AC15 -> 2.2020224 | C9: ='Historical Financials'!K14/'Historical Financials'!AC14 -> 1.6301761 | D9: ='Historical Financials'!K13/'Historical Financials'!AC13 -> 1.580356 | E9: ='Historical Financials'!K12/'Historical Financials'!AC12 -> 1.9494485 | F9: ='Historical Financials'!K11/'Historical Financials'!AC11 -> 1.8931229
A10: Quick Ratio | B10: =('Historical Financials'!K15-'Historical Financials'!I15)/'Historical Financials'!AC15 -> 1.4735107 | C10: =('Historical Financials'!K14-'Historical Financials'!I14)/'Historical Financials'!AC14 -> 0.99635094 | D10: =('Historical Financials'!K13-'Historical Financials'!I13)/'Historical Financials'!AC13 -> 0.96894332 | E10: =('Historical Financials'!K12-'Historical Financials'!I12)/'Historical Financials'!AC12 -> 1.3226103 | F10: =('Historical Financials'!K11-'Historical Financials'!I11)/'Historical Financials'!AC11 -> 1.2118296
A11: Debt-to-equity | B11: ='Historical Financials'!$AD15/'Historical Financials'!$AL15 -> 0.83834106 | C11: ='Historical Financials'!$AD14/'Historical Financials'!$AL14 -> 0.71358931 | D11: ='Historical Financials'!$AD13/'Historical Financials'!$AL13 -> 0.58629592 | E11: ='Historical Financials'!$AD12/'Historical Financials'!$AL12 -> 0.59067558 | F11: ='Historical Financials'!$AD11/'Historical Financials'!$AL11 -> 0.66275647
A12: Intrest Coverage | B12: ='Historical Financials'!$J7/ABS('Historical Financials'!$K7) -> 8.5280528 | C12: ='Historical Financials'!$J6/ABS('Historical Financials'!$K6) -> 17.981013 | D12: ='Historical Financials'!$J5/ABS('Historical Financials'!$K5) -> 10.710744 | E12: ='Historical Financials'!$J4/ABS('Historical Financials'!$K4) -> 9.0195599 | F12: ='Historical Financials'!$J4/ABS('Historical Financials'!$K4) -> 9.0195599
A13: Asset Turnover | B13: ='Historical Financials'!$B7/(('Historical Financials'!$K15+'Historical Financials'!$K16)/2) -> 1.7347394 | C13: ='Historical Financials'!$B6/(('Historical Financials'!$K14+'Historical Financials'!$K15)/2) -> 1.8183521 | D13: ='Historical Financials'!$B5/(('Historical Financials'!$K13+'Historical Financials'!$K14)/2) -> 1.7986224 | E13: ='Historical Financials'!$B4/(('Historical Financials'!$K12+'Historical Financials'!$K13)/2) -> 1.6513795 | F13: ='Historical Financials'!$B4/(('Historical Financials'!$K12+'Historical Financials'!$K13)/2) -> 1.6513795
A14: Free Cash Flow | B14: ='Historical Financials'!$Q23+'Historical Financials'!$U23 -> 2738 | C14: ='Historical Financials'!$Q22+'Historical Financials'!$U22 -> 2036 | D14: ='Historical Financials'!$Q21+'Historical Financials'!$U21 -> 3136 | E14: ='Historical Financials'!$Q20+'Historical Financials'!$U20 -> 3487 | F14: ='Historical Financials'!$Q23+'Historical Financials'!$U19 -> 2502
A15: FCF Margin | B15: =B14/'Historical Financials'!$B7 -> 0.16004209 | C15: =C14/'Historical Financials'!$B6 -> 0.11035829 | D15: =D14/'Historical Financials'!$B5 -> 0.15299054 | E15: =E14/'Historical Financials'!$B4 -> 0.15432618 | F15: =F14/'Historical Financials'!$B3 -> 0.099617774

Sheet Trend Analysis
A1: Metric | B1: 2021 | C1: 2022 | D1: 2023 | E1: 2024 | F1: 2025 | G1: AVGS | I1: CAGR | J1: Revenue | K1: EBIT | L1: NET INCOME | M1: Op CF | N1: FCF
A2: Revnue | B2: 17108 | C2: 18449 | D2: 20498 | E2: 22595 | F2: 25116 | G2: =AVERAGE(B2:F2) -> 20753.2 | J2: =(F2/B2)^(1/4)-1 -> 0.10074775 | K2: =(F3/B3)^(1/4)-1 -> 0.1728214 | L2: =(F4/B4)^(1/4)-1 -> 0.12955099 | M2: =(F5/B5)^(1/4)-1 -> 0.11503757 | N2: =(F6/B6)^(1/4)-1 -> -0.022282327
A3: EBIT | B3: 2584 | C3: 2841 | D3: 3888 | E3: 3689 | F3: 4889 | G3: =AVERAGE(B3:F3) -> 3578.2
A4: Net Income | B4: 1994 | C4: 2358 | D4: 3165 | E4: 2993 | F4: 3246 | G4: =AVERAGE(B4:F4) -> 2751.2
A5: Op Cash Flow | B5: 3263 | C5: 2624 | D5: 3711 | E5: 4242 | F5: 5044 | G5: =AVERAGE(B5:F5) -> 3776.8
A6: FCF | B6: 2738 | C6: 2036 | D6: 3136 | E6: 3487 | F6: 2502 | G6: =AVERAGE(B6:F6) -> 2779.8
A7: RIOC | B7: 0.092557916 | C7: 0.093764729 | D7: 0.12631543 | E7: 0.10829363 | F7: 0.10567696 | G7: =AVERAGE(B7:F7) -> 0.10532173
A8: Debt To equity | B8: 0.83834106 | C8: 0.71358931 | D8: 0.58629592 | E8: 0.59067558 | F8: 0.66275647 | G8: =AVERAGE(B8:F8) -> 0.67833167
A9: Operating Margin | B9: 0.15104045 | C9: 0.15399209 | D9: 0.18967704 | E9: 0.16326621 | F9: 0.19465679 | G9: =AVERAGE(B9:F9) -> 0.17052652

Sheet Forcast
A1: Metric | B1: 2025A | C1: 2026E | D1: 2027E | E1: 2028E | F1: 2029E | G1: 2030E
A2: Revenue | B2: 25116 | C2: =B2*(1+Assumptions!B2) -> 27646.381 | D2: =C2*(1+Assumptions!B2) -> 30431.691 | E2: =D2*(1+Assumptions!B2) -> 33497.616 | F2: =E2*(1+Assumptions!B2) -> 36872.426 | G2: =F2*(1+Assumptions!B2) -> 40587.24
A3: EBIT | B3: 4889 | C3: =B2*Assumptions!B3 -> 4897.62 | D3: =C2*Assumptions!B3 -> 5391.0442 | E3: =D2*Assumptions!B3 -> 5934.1798 | F3: =E2*Assumptions!B3 -> 6532.0351 | G3: =F2*Assumptions!B3 -> 7190.123
A4: NOPAT | B4: =B3*(1-Assumptions!B4) -> 4097.8977 | C4: =C3*(1-Assumptions!$B4) -> 4105.1228 | D4: =D3*(1-Assumptions!$B4) -> 4518.7048 | E4: =E3*(1-Assumptions!$B4) -> 4973.9541 | F4: =F3*(1-Assumptions!$B4) -> 5475.0688 | G4: =G3*(1-Assumptions!$B4) -> 6026.6697
A5: D&A | B5: 732 | C5: =C2*Assumptions!$B6 -> 862.16764 | D5: =D2*Assumptions!$B6 -> 949.0291 | E5: =E2*Assumptions!$B6 -> 1044.6416 | F5: =F2*Assumptions!$B6 -> 1149.8869 | G5: =G2*Assumptions!$B6 -> 1265.7355
A6: (CapEx) | B6: 761 | C6: =C2*(Assumptions!$B5) -> 853.64188 | D6: =D2*(Assumptions!$B5) -> 939.64438 | E6: =E2*(Assumptions!$B5) -> 1034.3114 | F6: =F2*(Assumptions!$B5) -> 1138.516 | G6: =G2*(Assumptions!$B5) -> 1253.2189
A7: OP NWC | B7: 6961 | C7: =C2*(Assumptions!$B7) -> 7521.0539 | D7: =D2*(Assumptions!$B7) -> 8278.7832 | E7: =E2*(Assumptions!$B7) -> 9112.852 | F7: =F2*(Assumptions!$B7) -> 10030.951 | G7: =G2*(Assumptions!$B7) -> 11041.547
A8: ΔNWC | C8: =C7-B7 -> 560.05389 | D8: =D7-C7 -> 757.72929 | E8: =E7-D7 -> 834.06882 | F8: =F7-E7 -> 918.09938 | G8: =G7-F7 -> 1010.5958
A9: FCF | B9: 2502 | C9: =C4+C5-C6-C8 -> 3553.5947 | D9: =D4+D5-D6-D8 -> 3770.3602 | E9: =E4+E5-E6-E8 -> 4150.2155 | F9: =F4+F5-F6-F8 -> 4568.3404 | G9: =G4+G5-G6-G8 -> 5028.5904
A10: EBITDA | B10: =B3+B5 -> 5621

Sheet DCF
A1: DCF
A2: Year | B2: FCF | C2: Discount Factor | D2: PV | E2: Sum of PV | F2: Terminal Value | G2: Discount TV | H2: Enterprise Value | I2: Equity Value | J2: Intrinsic SP
A3: 2026 | B3: 3553.5947 | C3: =1/(1+$B$26)^1 -> 0.91932 | D3: =B3*C3 -> 3266.8907 | E3: =SUM(D3:D7) -> 16242.665 | F3: =(B7*(1+B27))/(B26-B27) -> 82116.916 | G3: =F3/(1+B26)^5 -> 53922.023 | H3: =E3+G3 -> 70164.688 | I3: =H3+(15859-4011) -> 82012.688 | J3: =I3/B21 -> 212.19324
A4: 2027 | B4: 3770.3602 | C4: =1/(1+$B$26)^2 -> 0.84514927 | D4: =B4*C4 -> 3186.5171
A5: 2028 | B5: 4150.2155 | C5: =1/(1+$B$26)^3 -> 0.77696263 | D5: =B5*C5 -> 3224.5623
A6: 2029 | B6: 4568.3404 | C6: =1/(1+$B$26)^4 -> 0.71427728 | D6: =B6*C6 -> 3263.0618
A7: 2030 | B7: 5028 | C7: =1/(1+$B$26)^5 -> 0.65664939 | D7: =B7*C7 -> 3301.6331
A10: WACC
A11: total equity | B11: 22420
A12: Cost of Debt | B12: =ABS(B17)/B18 -> 0.041214014 | E12: =J3 -> 212.19324 | F12: 0.015 | G12: 0.02 | H12: 0.025 | I12: 0.03 | J12: 0.035
A13: Capm | B13: =B14+(B15*B16) -> 9.04 | E13: 0.075 | F13: 227.49626 | G13: 242.25564 | H13: 259.96689 | I13: 281.61397 | J13: 308.67283
A14: Risk Free rate | B14: 4.75 | E14: 0.08 | F14: 211.85167 | G14: 224.1107 | H14: 238.59864 | I14: 255.98418 | J14: 277.23317
A15: Beta | B15: 0.78 | E15: 0.085 | F15: 198.45081 | G15: 208.7662 | H15: 220.80081 | I15: 235.02354 | J15: 252.09081
A16: Market Risk Premium | B16: 5.5 | E16: 0.0877 | F16: 191.98425 | G16: 201.42608 | H16: 212.37378 | I16: 225.21884 | J16: 240.50128
A17: Intrest Expense | B17: -607 | E17: 0.09 | F17: 186.84475 | G17: 195.62184 | H17: 205.74925 | I17: 217.56456 | J17: 231.52811
A18: Total Debt | B18: 14728 | E18: 0.095 | F18: 176.69678 | G18: 184.23742 | H18: 192.85529 | I18: 202.79899 | J18: 214.39997
A19: Tax rate | B19: 0.16181271
A20: share price | B20: 325
A21: shares outstanding | B21: 386.5
A22: AT COD | B22: =B12*(1-B19) -> 0.034545063
A23: Market Value of equity | B23: =B20*B21 -> 125612.5
A24: E% | B24: =B23/(B23+B18) -> 0.89505524
A25: D% | B25: =B18/(B23+B18) -> 0.10494476
A26: WACC CALC | B26: =B24*(0.094)+B25*(B22) -> 0.087760516
A27: Terminal Growth | B27: 0.025
